Workbook
Name Macrobond_Object1: Sheet1!$B$4:$CY$72
Name Macrobond_Object1: Sheet3!$A$3:$B$53

Sheet Sheet1
C1: =_xlfn.TEXTBEFORE(C5,",") -> Austria | D1: =_xlfn.TEXTBEFORE(D5,",") -> Austria | E1: =_xlfn.TEXTBEFORE(E5,",") -> France | F1: =_xlfn.TEXTBEFORE(F5,",") -> France | G1: =_xlfn.TEXTBEFORE(G5,",") -> Italy | H1: =_xlfn.TEXTBEFORE(H5,",") -> Italy | I1: =_xlfn.TEXTBEFORE(I5,",") -> Netherlands | J1: =_xlfn.TEXTBEFORE(J5,",") -> Netherlands | ... CY1: =_xlfn.TEXTBEFORE(CY5,",") -> Netherlands
C2: =_xlfn.TEXTAFTER(C5,", ") -> Capital Formation & Saving, Gross Fixed Capital Formation, Private Sector, Current Prices, EUR | D2: =_xlfn.TEXTAFTER(D5,", ") -> Capital Formation & Saving, Gross Fixed Capital Formation, General Government, Current Prices, EUR | E2: =_xlfn.TEXTAFTER(E5,", ") -> Capital Formation & Saving, Gross Fixed Capital Formation, Private Sector, Current Prices, EUR | F2: =_xlfn.TEXTAFTER(F5,", ") -> Capital Formation & Saving, Gross Fixed Capital Formation, General Government, Current Prices, EUR | G2: =_xlfn.TEXTAFTER(G5,", ") -> Capital Formation & Saving, Gross Fixed Capital Formation, Private Sector, Current Prices, EUR | H2: =_xlfn.TEXTAFTER(H5,", ") -> Capital Formation & Saving, Gross Fixed Capital Formation, General Government, Current Prices, EUR | I2: =_xlfn.TEXTAFTER(I5,", ") -> Capital Formation & Saving, Gross Fixed Capital Formation, Private Sector, Current Prices, EUR | J2: =_xlfn.TEXTAFTER(J5,", ") -> Capital Formation & Saving, Gross Fixed Capital Formation, General Government, Current Prices, EUR | ... CY2: =_xlfn.TEXTAFTER(CY5,", ") -> Monetary Variables, Interest Rates, Nominal, Short-Term, Current Prices
C3: =_xlfn.XLOOKUP(C2,Sheet2!$D:$D,Sheet2!$E:$E) -> I_M_NOM | D3: =_xlfn.XLOOKUP(D2,Sheet2!$D:$D,Sheet2!$E:$E) -> I_G | E3: =_xlfn.XLOOKUP(E2,Sheet2!$D:$D,Sheet2!$E:$E) -> I_M_NOM | F3: =_xlfn.XLOOKUP(F2,Sheet2!$D:$D,Sheet2!$E:$E) -> I_G | G3: =_xlfn.XLOOKUP(G2,Sheet2!$D:$D,Sheet2!$E:$E) -> I_M_NOM | H3: =_xlfn.XLOOKUP(H2,Sheet2!$D:$D,Sheet2!$E:$E) -> I_G | I3: =_xlfn.XLOOKUP(I2,Sheet2!$D:$D,Sheet2!$E:$E) -> I_M_NOM | J3: =_xlfn.XLOOKUP(J2,Sheet2!$D:$D,Sheet2!$E:$E) -> I_G | ... CY3: =_xlfn.XLOOKUP(CY2,Sheet2!$D:$D,Sheet2!$E:$E) -> I_RATE
B4: DG ECFIN AMECO, Estimate
C5: Austria, Capital Formation & Saving, Gross Fixed Capital Formation, Private Sector, Current Prices, EUR | D5: Austria, Capital Formation & Saving, Gross Fixed Capital Formation, General Government, Current Prices, EUR | E5: France, Capital Formation & Saving, Gross Fixed Capital Formation, Private Sector, Current Prices, EUR | F5: France, Capital Formation & Saving, Gross Fixed Capital Formation, General Government, Current Prices, EUR | G5: Italy, Capital Formation & Saving, Gross Fixed Capital Formation, Private Sector, Current Prices, EUR | H5: Italy, Capital Formation & Saving, Gross Fixed Capital Formation, General Government, Current Prices, EUR | I5: Netherlands, Capital Formation & Saving, Gross Fixed Capital Formation, Private Sector, Current Prices, EUR | J5: Netherlands, Capital Formation & Saving, Gross Fixed Capital Formation, General Government, Current Prices, EUR | K5: Finland, Capital Formation & Saving, Gross Fixed Capital Formation, Private Sector, Current Prices, EUR | L5: Finland, Capital Formation & Saving, Gross Fixed Capital Formation, General Government, Current Prices, EUR | M5: Austria, Capital Formation & Saving, Consumption of Fixed Capital, Total, Current Prices, EUR | N5: Austria, Capital Formation & Saving, Consumption of Fixed Capital, General Government, Current Prices, EUR | O5: France, Capital Formation & Saving, Consumption of Fixed Capital, Total, Current Prices, EUR | P5: France, Capital Formation & Saving, Consumption of Fixed Capital, General Government, Current Prices, EUR | Q5: Italy, Capital Formation & Saving, Consumption of Fixed Capital, General Government, Current Prices, EUR | R5: Italy, Capital Formation & Saving, Consumption of Fixed Capital, Total, Current Prices, EUR | S5: Netherlands, Capital Formation & Saving, Consumption of Fixed Capital, Total, Current Prices, EUR | T5: Netherlands, Capital Formation & Saving, Consumption of Fixed Capital, General Government, Current Prices, EUR | U5: Finland, Capital Formation & Saving, Consumption of Fixed Capital, General Government, Current Prices, EUR | V5: Finland, Capital Formation & Saving, Consumption of Fixed Capital, Total, Current Prices, EUR | W5: Austria, General Government, Net Lending(ESA2010), Net Lending (+) or Net Borrowing (-) Excluding Interest, Percent of GDP (Excessive Deficit Procedure), Market Prices | X5: Finland, General Government, Net Lending(ESA2010), Net Lending (+) or Net Borrowing (-) Excluding Interest, Percent of GDP (Excessive Deficit Procedure), Market Prices | Y5: France, General Government, Net Lending(ESA2010), Net Lending (+) or Net Borrowing (-) Excluding Interest, Percent of GDP (Excessive Deficit Procedure), Market Prices | Z5: Italy, General Government, Net Lending(ESA2010), Net Lending (+) or Net Borrowing (-) Excluding Interest, Percent of GDP (Excessive Deficit Procedure), Market Prices | AA5: Netherlands, General Government, Net Lending(ESA2010), Net Lending (+) or Net Borrowing (-) Excluding Interest, Percent of GDP (Excessive Deficit Procedure), Market Prices | AB5: Austria, General Government, Revenue(ESA2010), Total Revenue, EUR | AC5: Finland, General Government, Revenue(ESA2010), Total Revenue, EUR | AD5: France, General Government, Revenue(ESA2010), Total Revenue, EUR | AE5: Italy, General Government, Revenue(ESA2010), Total Revenue, EUR | AF5: Netherlands, General Government, Revenue(ESA2010), Total Revenue, EUR | AG5: Austria, General Government, Revenue(ESA2010), Current Taxes on Income & Wealth, Direct Taxes, EUR | AH5: Finland, General Government, Revenue(ESA2010), Current Taxes on Income & Wealth, Direct Taxes, EUR | AI5: France, General Government, Revenue(ESA2010), Current Taxes on Income & Wealth, Direct Taxes, EUR | AJ5: Italy, General Government, Revenue(ESA2010), Current Taxes on Income & Wealth, Direct Taxes, EUR | AK5: Netherlands, General Government, Revenue(ESA2010), Current Taxes on Income & Wealth, Direct Taxes, EUR | AL5: Austria, General Government, Revenue(ESA2010), Taxes Linked to Imports & Production, Indirect Taxes, EUR | AM5: Finland, General Government, Revenue(ESA2010), Taxes Linked to Imports & Production, Indirect Taxes, EUR | AN5: France, General Government, Revenue(ESA2010), Taxes Linked to Imports & Production, Indirect Taxes, EUR | AO5: Italy, General Government, Revenue(ESA2010), Taxes Linked to Imports & Production, Indirect Taxes, EUR | AP5: Netherlands, General Government, Revenue(ESA2010), Taxes Linked to Imports & Production, Indirect Taxes, EUR | AQ5: Austria, General Government, Revenue(ESA2010), Actual Social Contributions Received, EUR | AR5: Finland, General Government, Revenue(ESA2010), Actual Social Contributions Received, EUR | AS5: France, General Government, Revenue(ESA2010), Actual Social Contributions Received, EUR | AT5: Italy, General Government, Revenue(ESA2010), Actual Social Contributions Received, EUR | AU5: Netherlands, General Government, Revenue(ESA2010), Actual Social Contributions Received, EUR | AV5: Austria, General Government, Revenue(ESA2010), Imputed Social Contributions, EUR | AW5: France, General Government, Revenue(ESA2010), Imputed Social Contributions, EUR | AX5: Finland, General Government, Revenue(ESA2010), Imputed Social Contributions, EUR | AY5: Italy, General Government, Revenue(ESA2010), Imputed Social Contributions, EUR | AZ5: Netherlands, General Government, Revenue(ESA2010), Imputed Social Contributions, EUR | BA5: Austria, General Government, Expenditure(ESA2010), Total Expenditure, EUR | BB5: Finland, General Government, Expenditure(ESA2010), Total Expenditure, EUR | BC5: France, General Government, Expenditure(ESA2010), Total Expenditure, EUR | BD5: Netherlands, General Government, Expenditure(ESA2010), Total Expenditure, EUR | BE5: Italy, General Government, Expenditure(ESA2010), Total Expenditure, EUR | BF5: Austria, General Government, Expenditure(ESA2010), Final Consumption Expenditure, EUR | BG5: Finland, General Government, Expenditure(ESA2010), Final Consumption Expenditure, EUR | BH5: France, General Government, Expenditure(ESA2010), Final Consumption Expenditure, EUR | BI5: Italy, General Government, Expenditure(ESA2010), Final Consumption Expenditure, EUR | BJ5: Netherlands, General Government, Expenditure(ESA2010), Final Consumption Expenditure, EUR | BK5: Austria, General Government, Expenditure(ESA2010), Subsidies, EUR | BL5: Finland, General Government, Expenditure(ESA2010), Subsidies, EUR | BM5: France, General Government, Expenditure(ESA2010), Subsidies, EUR | BN5: Italy, General Government, Expenditure(ESA2010), Subsidies, EUR | BO5: Netherlands, General Government, Expenditure(ESA2010), Subsidies, EUR | BP5: Austria, General Government, Expenditure(ESA2010), Social Benefits Other than Social Transfers in Kind, EUR | BQ5: France, General Government, Expenditure(ESA2010), Social Benefits Other than Social Transfers in Kind, EUR | BR5: Finland, General Government, Expenditure(ESA2010), Social Benefits Other than Social Transfers in Kind, EUR | BS5: Italy, General Government, Expenditure(ESA2010), Social Benefits Other than Social Transfers in Kind, EUR | BT5: Netherlands, General Government, Expenditure(ESA2010), Social Benefits Other than Social Transfers in Kind, EUR | BU5: Austria, General Government, Expenditure(ESA2010), Interest, EUR | BV5: Finland, General Government, Expenditure(ESA2010), Interest, EUR | BW5: France, General Government, Expenditure(ESA2010), Interest, EUR | BX5: Italy, General Government, Expenditure(ESA2010), Interest, EUR | BY5: Netherlands, General Government, Expenditure(ESA2010), Interest, EUR | BZ5: Austria, Gross Public Debt, Based on ESA2010, Total, Percent of GDP (Excessive Deficit Procedure), Market Prices | CA5: Finland, Gross Public Debt, Based on ESA2010, Total, Percent of GDP (Excessive Deficit Procedure), Market Prices | CB5: France, Gross Public Debt, Based on ESA2010, Total, Percent of GDP (Excessive Deficit Procedure), Market Prices | CC5: Italy, Gross Public Debt, Based on ESA2010, Total, Percent of GDP (Excessive Deficit Procedure), Market Prices | CD5: Netherlands, Gross Public Debt, Based on ESA2010, Total, Percent of GDP (Excessive Deficit Procedure), Market Prices | CE5: United States, Monetary Variables, Exchange Rates & Purchasing Power Parities, National Currency per ECU/EUR (Annual Averages), Average of Period | CF5: Austria, Gross Public Debt, Based on ESA2010, Stock-Flow Adjustment on Gross Public Debt, EUR | CG5: Finland, Gross Public Debt, Based on ESA2010, Stock-Flow Adjustment on Gross Public Debt, EUR | CH5: France, Gross Public Debt, Based on ESA2010, Stock-Flow Adjustment on Gross Public Debt, EUR | CI5: Italy, Gross Public Debt, Based on ESA2010, Stock-Flow Adjustment on Gross Public Debt, EUR | CJ5: Netherlands, Gross Public Debt, Based on ESA2010, Stock-Flow Adjustment on Gross Public Debt, EUR | CK5: Austria, General Government, Expenditure(ESA2010), Implicit Interest Rate, Percentage of Gross Public Debt | CL5: Finland, General Government, Expenditure(ESA2010), Implicit Interest Rate, Percentage of Gross Public Debt | CM5: France, General Government, Expenditure(ESA2010), Implicit Interest Rate, Percentage of Gross Public Debt | CN5: Italy, General Government, Expenditure(ESA2010), Implicit Interest Rate, Percentage of Gross Public Debt | CO5: Netherlands, General Government, Expenditure(ESA2010), Implicit Interest Rate, Percentage of Gross Public Debt | CP5: Austria, Monetary Variables, Interest Rates, Nominal, Long-Term, Current Prices | CQ5: Finland, Monetary Variables, Interest Rates, Nominal, Long-Term, Current Prices | CR5: France, Monetary Variables, Interest Rates, Nominal, Long-Term, Current Prices | CS5: Italy, Monetary Variables, Interest Rates, Nominal, Long-Term, Current Prices | CT5: Netherlands, Monetary Variables, Interest Rates, Nominal, Long-Term, Current Prices | CU5: Austria, Monetary Variables, Interest Rates, Nominal, Short-Term, Current Prices | CV5: Finland, Monetary Variables, Interest Rates, Nominal, Short-Term, Current Prices | CW5: Finland, Monetary Variables, Interest Rates, Nominal, Short-Term, Current Prices | CX5: Italy, Monetary Variables, Interest Rates, Nominal, Short-Term, Current Prices | CY5: Netherlands, Monetary Variables, Interest Rates, Nominal, Short-Term, Current Prices
A6: 1960 | B6: 21916 | C6: 1342600000 | D6: 351380000 | E6: 10962500000 | F6: 2417600000 | K6: 1229120000 | L6: 244770000 | M6: 1002100000 | N6: 217340000 | O6: 7292700000 | R6: 5185000000 | S6: 1687600000 | U6: 66100000 | V6: 568970000 | CC6: 31.7222 | CE6: 1.05621 | CR6: 5.7 | CS6: 5.26 | CT6: 4.2 | CX6: 3.5 | CY6: 2.1
A7: =A6+1 -> 1961 | B7: 22282 | C7: 1557500000 | D7: 391750000 | E7: 12425400000 | F7: 2783500000 | K7: 1386240000 | L7: 243560000 | M7: 1088700000 | N7: 233560000 | O7: 7863300000 | R7: 5620500000 | S7: 1869400000 | U7: 73860000 | V7: 642730000 | CC7: 29.8648 | CE7: 1.06734 | CQ7: 6.58 | CR7: 5.52 | CS7: 4.97 | CT7: 3.91 | CX7: 3.5 | CY7: 1.14
A8: =A7+1 -> 1962 | B8: 22647 | C8: 1619400000 | D8: 418620000 | E8: 13563800000 | F8: 3286400000 | K8: 1451490000 | L8: 2.6569e+08 | M8: 1181000000 | N8: 248100000 | O8: 8596400000 | R8: 6274100000 | S8: 2.0336e+09 | U8: 79320000 | V8: 705830000 | CC8: 28.7243 | CE8: 1.06981 | CQ8: 7.09 | CR8: 5.43 | CS8: 5.05 | CT8: 4.21 | CX8: 3.5 | CY8: 1.88
A9: =A8+1 -> 1963 | B9: 23012 | C9: 1758600000 | D9: 458510000 | E9: 15700400000 | F9: 3858000000 | K9: 1431710000 | L9: 300740000 | M9: 1307400000 | N9: 268220000 | O9: 9711600000 | R9: 7256400000 | S9: 2210300000 | U9: 86630000 | V9: 774670000 | CC9: 26.7858 | CE9: 1.06981 | CQ9: 7.95 | CR9: 5.34 | CS9: 5.19 | CT9: 4.22 | CX9: 3.5 | CY9: 1.98
A10: =A9+1 -> 1964 | B10: 23377 | C10: 1938300000 | D10: 5.3072e+08 | E10: 17883000000 | F10: 4616000000 | K10: 1547250000 | L10: 380510000 | M10: 1410600000 | N10: 283310000 | O10: 10614600000 | R10: 8.2548e+09 | S10: 2442500000 | U10: 95070000 | V10: 850220000 | CC10: 26.6171 | CE10: 1.06981 | CQ10: 8.41 | CR10: 5.45 | CS10: 5.74 | CT10: 4.92 | CX10: 3.5 | CY10: 3.45
A11: =A10+1 -> 1965 | B11: 23743 | C11: 2187000000 | D11: 588290000 | E11: 19441100000 | F11: 5216600000 | K11: 1785440000 | L11: 443980000 | M11: 1566900000 | N11: 316840000 | O11: 11521200000 | R11: 8867400000 | S11: 2689000000 | U11: 106330000 | V11: 930440000 | CC11: 27.6472 | CE11: 1.06981 | CP11: 6.51 | CQ11: 8.62 | CR11: 6.2 | CS11: 5.39 | CT11: 5.21 | CX11: 3.5 | CY11: 3.96
A12: =A11+1 -> 1966 | B12: 24108 | C12: 2440800000 | D12: 633230000 | E12: 21532000000 | F12: 5519300000 | K12: 1940650000 | L12: 459950000 | M12: 1703300000 | N12: 336950000 | O12: 12540800000 | R12: 9336900000 | S12: 2950800000 | U12: 114200000 | V12: 1025690000 | CC12: 32.2993 | CE12: 1.06981 | CP12: 6.91 | CQ12: 8.41 | CR12: 6.58 | CS12: 5.49 | CT12: 6.24 | CX12: 3.5 | CY12: 4.87
A13: =A12+1 -> 1967 | B13: 24473 | C13: 2428600000 | D13: 731070000 | E13: 23701800000 | F13: 6149200000 | K13: 1868740000 | L13: 458790000 | M13: 1853100000 | N13: 378950000 | O13: 13710500000 | R13: 10026000000 | S13: 3221300000 | U13: 121100000 | V13: 1.05916e+09 | CC13: 31.8738 | CE13: 1.064817 | CP13: 7.22 | CQ13: 8.19 | CR13: 6.71 | CS13: 5.59 | CT13: 6 | CU13: 4.75 | CX13: 3.5 | CY13: 4.69
A14: =A13+1 -> 1968 | B14: 24838 | C14: 2604400000 | D14: 788100000 | E14: 26671700000 | F14: 6658500000 | K14: 1660270000 | L14: 427050000 | M14: 2028400000 | N14: 409620000 | O14: 14867900000 | R14: 11130800000 | S14: 3605000000 | U14: 121660000 | V14: 1052200000 | CC14: 34.2302 | CE14: 1.02889 | CP14: 7.74 | CQ14: 8.15 | CR14: 6.95 | CS14: 5.61 | CT14: 6.22 | CU14: 4.14 | CX14: 3.5 | CY14: 4.55
A15: =A14+1 -> 1969 | B15: 25204 | C15: 2808300000 | D15: 821810000 | E15: 29496500000 | F15: 6936900000 | K15: 2031170000 | L15: 440490000 | M15: 2172300000 | N15: 408790000 | O15: 15884500000 | R15: 12429500000 | S15: 4012100000 | U15: 134570000 | V15: 1156990000 | CC15: 34.8413 | CE15: 1.022187 | CP15: 7.52 | CQ15: 7.91 | CR15: 7.87 | CS15: 5.8 | CT15: 7.04 | CU15: 4.49 | CX15: 3.71 | CY15: 5.71
A16: =A15+1 -> 1970 | B16: 25569 | C16: 3270100000 | D16: 926410000 | E16: 30363000000 | F16: 7144300000 | G16: 25621100000 | H16: 3748410000 | I16: 8.1766e+09 | J16: 2414530000 | K16: 2605400000 | L16: 426640000 | M16: 2416300000 | N16: 456150000 | O16: 16419600000 | P16: 2670700000 | Q16: 3497000000 | R16: 14482100000 | S16: 4630400000 | T16: 893110000 | U16: 156550000 | V16: 1338640000 | CC16: 35.7766 | CE16: 1.022227 | CP16: 7.82 | CQ16: 7.83 | CR16: 8.04 | CS16: 7.73 | CT16: 7.83 | CU16: 5.62 | CV16: 10.61 | CW16: 10.61 | CX16: 5.25 | CY16: 6.15
A17: =A16+1 -> 1971 | B17: 25934 | C17: 3996800000 | D17: 1127250000 | E17: 33939600000 | F17: 7556500000 | G17: 27188100000 | H17: 3882060000 | I17: 9422700000 | J17: 2808950000 | K17: 2944820000 | L17: 470440000 | M17: 2770300000 | N17: 537910000 | O17: 18520800000 | P17: 3101100000 | Q17: 3576760000 | R17: 15468700000 | S17: 5464700000 | T17: 1.06632e+09 | U17: 173950000 | V17: 1532160000 | CC17: 40.416 | CE17: 1.04776 | CP17: 7.71 | CQ17: 8.1 | CR17: 7.75 | CS17: 7 | CT17: 7.05 | CU17: 4.39 | CV17: 8.09 | CW17: 8.09 | CX17: 5.69 | CY17: 4.45
A18: =A17+1 -> 1972 | B18: 26299 | C18: 5040000000 | D18: 1361760000 | E18: 39231900000 | F18: 8.2451e+09 | G18: 28674600000 | H18: 4378990000 | I18: 10048100000 | J18: 2806310000 | K18: 3249130000 | L18: 568970000 | M18: 3174200000 | N18: 609600000 | O18: 21783800000 | P18: 3706700000 | Q18: 3648220000 | R18: 16829500000 | S18: 6257900000 | T18: 1246280000 | U18: 189220000 | V18: 1692000000 | CC18: 45.9063 | CE18: 1.12178 | CP18: 7.38 | CQ18: 7.97 | CR18: 7.35 | CS18: 6.59 | CT18: 6.67 | CU18: 5.17 | CV18: 7.77 | CW18: 7.77 | CX18: 5.18 | CY18: 2.74
A19: =A18+1 -> 1973 | B19: 26665 | C19: 5809800000 | D19: 1546830000 | E19: 47375500000 | F19: 9508500000 | G19: 34125600000 | H19: 4353380000 | I19: 11642300000 | J19: 3034010000 | K19: 4101960000 | L19: 631220000 | M19: 3787400000 | N19: 732760000 | O19: 26177600000 | P19: 4605600000 | Q19: 4006330000 | R19: 18949300000 | S19: 7280300000 | T19: 1501540000 | U19: 236090000 | V19: 2.06436e+09 | CC19: 48.8105 | CE19: 1.23173 | CP19: 8.25 | CQ19: 8.26 | CR19: 8.29 | CS19: 6.92 | CT19: 7.31 | CU19: 6.94 | CV19: 9.34 | CW19: 9.34 | CX19: 6.98 | CY19: 7.54
A20: =A19+1 -> 1974 | B20: 27030 | C20: 7184000000 | D20: 2022910000 | E20: 54618100000 | F20: 10781300000 | G20: 40741900000 | H20: 5339450000 | I20: 13059400000 | J20: 3672870000 | K20: 5593020000 | L20: 820640000 | M20: 4779600000 | N20: 958160000 | O20: 31408400000 | P20: 5599900000 | Q20: 4691960000 | R20: 23174600000 | S20: 9166300000 | T20: 1896770000 | U20: 330280000 | V20: 2822060000 | CC20: 48.5119 | CE20: 1.1927 | CP20: 9.74 | CQ20: 8.79 | CR20: 10.45 | CS20: 9.61 | CT20: 10.69 | CU20: 7.26 | CV20: 10.41 | CW20: 10.41 | CX20: 14.88 | CY20: 10.36
A21: =A20+1 -> 1975 | B21: 27395 | C21: 7124700000 | D21: 2231340000 | E21: 60523900000 | F21: 13887000000 | G21: 43125800000 | H21: 6740150000 | I21: 13866500000 | J21: 4519270000 | K21: 6750070000 | L21: 1087290000 | M21: 5262200000 | N21: 1.0712e+09 | O21: 39623800000 | P21: 7388600000 | Q21: 5745980000 | R21: 28792900000 | S21: 10704100000 | T21: 2206170000 | U21: 434390000 | V21: 3447650000 | X21: 5.533027 | AC21: 10333800000 | AH21: 3791760000 | AM21: 2848400000 | AR21: 2.11831e+09 | AX21: 346728000 | BB21: 9157500000 | BG21: 4010270000 | BL21: 779811000 | BR21: 2194200000 | BV21: 136074000 | CA21: 6.5094 | CC21: 54.7423 | CE21: 1.24077 | CP21: 9.61 | CQ21: 9.63 | CR21: 9.52 | CS21: 10.04 | CT21: 9.15 | CU21: 5.49 | CV21: 11.72 | CW21: 11.72 | CX21: 10.44 | CY21: 5.35
A22: =A21+1 -> 1976 | B22: 27760 | C22: 8441400000 | D22: 2364020000 | E22: 68415300000 | F22: 15711700000 | G22: 44755300000 | H22: 7106940000 | I22: 15969000000 | J22: 5273290000 | K22: 7204620000 | L22: 1201230000 | M22: 6031500000 | N22: 1238180000 | O22: 46426000000 | P22: 8917400000 | Q22: 6128090000 | R22: 30634200000 | S22: 12744700000 | T22: 2674690000 | U22: 553030000 | V22: 4284980000 | X22: 8.24907 | AC22: 13482500000 | AH22: 5312440000 | AM22: 3428540000 | AR22: 2730700000 | AX22: 427533000 | BB22: 11310300000 | BG22: 5105570000 | BL22: 906094000 | BR22: 2894810000 | BV22: 169634000 | CA22: 6.1066 | CC22: 54.4349 | CE22: 1.11805 | CG22: 2370000000 | CL22: 10.423729 | CP22: 8.75 | CQ22: 10.17 | CR22: 9.33 | CS22: 12.66 | CT22: 9.2 | CU22: 4.67 | CV22: 12.37 | CW22: 12.37 | CX22: 15.97 | CY22: 7.37
A23: =A22+1 -> 1977 | B23: 28126 | C23: 10345100000 | D23: 2726180000 | E23: 71892800000 | F23: 15154100000 | G23: 50099700000 | H23: 7761990000 | I23: 20021000000 | J23: 5371570000 | K23: 7220140000 | L23: 1263330000 | M23: 7244100000 | N23: 1462370000 | O23: 51049600000 | P23: 9947500000 | Q23: 7248900000 | R23: 34840500000 | S23: 14742000000 | T23: 3157070000 | U23: 616130000 | V23: 4707720000 | X23: 7.006843 | AC23: 14033800000 | AH23: 5084390000 | AM23: 3834000000 | AR23: 2943460000 | AX23: 462099000 | BB23: 12195800000 | BG23: 5422220000 | BL23: 941026000 | BR23: 3353780000 | BV23: 210987000 | CA23: 7.7726 | CC23: 53.4769 | CE23: 1.14112 | CG23: 2190000000 | CL23: 12.967383 | CP23: 8.73 | CQ23: 10.75 | CR23: 9.87 | CS23: 14.71 | CT23: 8.49 | CU23: 7.49 | CV23: 11.76 | CW23: 11.76 | CX23: 13.95 | CY23: 4.75
A24: =A23+1 -> 1978 | B24: 28491 | C24: 10123000000 | D24: 3066920000 | E24: 78951000000 | F24: 15878300000 | G24: 54015600000 | H24: 7904750000 | I24: 22028000000 | J24: 5980610000 | K24: 6149450000 | L24: 1215590000 | M24: 8005900000 | N24: 1637250000 | O24: 56792400000 | P24: 11222500000 | Q24: 7787920000 | R24: 37353100000 | S24: 16369000000 | T24: 3564370000 | U24: 606090000 | V24: 4592230000 | X24: 4.611048 | Y24: -0.772626 | AC24: 12830100000 | AD24: 172906000000 | AH24: 4.25513e+09 | AI24: 26524800000 | AM24: 3787510000 | AN24: 58053900000 | AR24: 2570780000 | AS24: 62802300000 | AW24: 6658050000 | AX24: 442652000 | BB24: 11739300000 | BC24: 180064000000 | BG24: 5149510000 | BH24: 81863300000 | BL24: 862603000 | BM24: 7804290000 | BQ24: 58729300000 | BR24: 3353940000 | BV24: 219056000 | BW24: 4110710000 | CA24: 10.9762 | CC24: 57.5131 | CE24: 1.2741 | CG24: 1990000000 | CL24: 10.990888 | CP24: 8.21 | CQ24: 9.78 | CR24: 9.5 | CS24: 13.05 | CT24: 8.05 | CU24: 6.44 | CV24: 8.58 | CW24: 8.58 | CX24: 11.5 | CY24: 6.97
A25: =A24+1 -> 1979 | B25: 28856 | C25: 11539900000 | D25: 3146990000 | E25: 88235200000 | F25: 18006200000 | G25: 63287400000 | H25: 8962690000 | I25: 22854800000 | J25: 6173950000 | K25: 6871860000 | L25: 1331700000 | M25: 8732900000 | N25: 1805310000 | O25: 64021800000 | P25: 12818000000 | Q25: 10519030000 | R25: 41893500000 | S25: 18059300000 | T25: 3968560000 | U25: 680370000 | V25: 5050840000 | X25: 4.299299 | Y25: 0.657303 | AC25: 14199500000 | AD25: 201579000000 | AH25: 4534690000 | AI25: 30985100000 | AM25: 4.25874e+09 | AN25: 68118200000 | AR25: 2881240000 | AS25: 75096600000 | AW25: 7230390000 | AX25: 506089000 | BB25: 13093500000 | BC25: 203739000000 | BG25: 5737910000 | BH25: 91669300000 | BL25: 1.057983e+09 | BM25: 8841640000 | BQ25: 6.62639e+10 | BR25: 3606300000 | BV25: 288236000 | BW25: 5077930000 | CA25: 11.1341 | CC25: 56.3298 | CE25: 1.37047 | CG25: 1700000000 | CL25: 9.392064 | CP25: 7.96 | CQ25: 9.5 | CR25: 9.89 | CS25: 13.02 | CT25: 9.2 | CU25: 5.6 | CV25: 8.52 | CW25: 8.52 | CX25: 11.95 | CY25: 9.58
A26: =A25+1 -> 1980 | B26: 29221 | C26: 13220800000 | D26: 3231730000 | E26: 103085200000 | F26: 20853500000 | G26: 78572000000 | H26: 12608650000 | I26: 25092500000 | J26: 6851420000 | K26: 8899790000 | L26: 1670290000 | M26: 9812200000 | N26: 2.08083e+09 | O26: 75462600000 | P26: 15169000000 | Q26: 6667620000 | R26: 49597400000 | S26: 19921900000 | T26: 4414600000 | U26: 846070000 | V26: 6142030000 | X26: 4.663259 | Y26: 0.798363 | AC26: 16945500000 | AD26: 232147000000 | AH26: 5412060000 | AI26: 37191600000 | AM26: 5014320000 | AN26: 75403700000 | AR26: 3517610000 | AS26: 86615100000 | AW26: 8.31548e+09 | AX26: 596615000 | BB26: 15513100000 | BC26: 234311000000 | BG26: 6858190000 | BH26: 106268200000 | BL26: 1184033000 | BM26: 9760630000 | BQ26: 76293400000 | BR26: 4.15216e+09 | BV26: 370154000 | BW26: 6156140000 | CA26: 11.221 | CC26: 54.2665 | CE26: 1.39233 | CG26: 2290000000 | CL26: 9.962871 | CP26: 9.32 | CQ26: 11.6 | CR26: 13.13 | CS26: 15.25 | CT26: 10.74 | CU26: 10.28 | CV26: 13.8 | CW26: 13.8 | CX26: 16.93 | CY26: 10.55
A27: =A26+1 -> 1981 | B27: 29587 | C27: 14308300000 | D27: 3399870000 | E27: 109209300000 | F27: 23751600000 | G27: 87468800000 | H27: 16699310000 | I27: 23869300000 | J27: 6956760000 | K27: 10824670000 | L27: 1983570000 | M27: 10935500000 | N27: 2332710000 | O27: 84653100000 | P27: 17269000000 | Q27: 8214710000 | R27: 59476500000 | S27: 21762600000 | T27: 4801170000 | U27: 1056910000 | V27: 7601830000 | X27: 6.1451 | Y27: -0.715065 | AC27: 21789500000 | AD27: 2.57821e+11 | AH27: 7302870000 | AI27: 41629900000 | AM27: 6254640000 | AN27: 83293400000 | AR27: 4385200000 | AS27: 94432800000 | AW27: 9318170000 | AX27: 743064000 | BB27: 19378000000 | BC27: 271156000000 | BG27: 8659990000 | BH27: 120481400000 | BL27: 1458837000 | BM27: 11576040000 | BQ27: 88410800000 | BR27: 5179120000 | BV27: 487520000 | BW27: 9414830000 | CA27: 11.5092 | CC27: 56.5292 | CE27: 1.11645 | CG27: 3460000000 | CL27: 10.416115 | CP27: 10.61 | CQ27: 12.4 | CR27: 15.85 | CS27: 19.36 | CT27: 12.24 | CU27: 11.37 | CV27: 12.7 | CW27: 12.7 | CX27: 19.31 | CY27: 11.77
A28: =A27+1 -> 1982 | B28: 29952 | C28: 14665400000 | D28: 3559160000 | E28: 113063700000 | F28: 26476300000 | G28: 92568300000 | H28: 18664380000 | I28: 25513000000 | J28: 7255830000 | K28: 12439120000 | L28: 2383490000 | M28: 12583100000 | N28: 2655420000 | O28: 92205500000 | P28: 19273300000 | Q28: 9463680000 | R28: 68002100000 | S28: 24502200000 | T28: 5377980000 | U28: 1221430000 | V28: 8686420000 | X28: 4.232756 | Y28: -1.099869 | AC28: 24749400000 | AD28: 283308000000 | AH28: 8249380000 | AI28: 45882100000 | AM28: 7132790000 | AN28: 91442900000 | AR28: 4732880000 | AS28: 104905500000 | AW28: 10271050000 | AX28: 862705000 | BB28: 23098500000 | BC28: 300263000000 | BG28: 9968470000 | BH28: 132695400000 | BL28: 1588994000 | BM28: 12728150000 | BQ28: 99003900000 | BR28: 6450710000 | BV28: 635345000 | BW28: 10457700000 | CA28: 13.8067 | CC28: 61.0334 | CE28: 0.979715 | CG28: 3010000000 | CL28: 11.491889 | CP28: 9.92 | CQ28: 12.38 | CR28: 15.65 | CS28: 20.22 | CT28: 10.45 | CU28: 8.77 | CV28: 13.67 | CW28: 13.67 | CX28: 19.88 | CY28: 8.21
A29: =A28+1 -> 1983 | B29: 30317 | C29: 15785300000 | D29: 3800630000 | E29: 111882200000 | F29: 26509400000 | G29: 100268200000 | H29: 20858270000 | I29: 27568500000 | J29: 7064540000 | K29: 13311290000 | L29: 2636300000 | M29: 13836300000 | N29: 2890950000 | O29: 96781400000 | P29: 20460200000 | Q29: 10871770000 | R29: 76989600000 | S29: 26056800000 | T29: 5661270000 | U29: 1334970000 | V29: 9364050000 | X29: 2.943028 | Y29: -0.337976 | AC29: 26327000000 | AD29: 303788000000 | AH29: 8772860000 | AI29: 48881100000 | AM29: 7565250000 | AN29: 96264400000 | AR29: 4791970000 | AS29: 113093500000 | AW29: 10565790000 | AX29: 936044000 | BB29: 25455800000 | BC29: 319801000000 | BG29: 10765110000 | BH29: 140886600000 | BL29: 1750727000 | BM29: 13497400000 | BQ29: 105269500000 | BR29: 7303310000 | BV29: 815884000 | BW29: 13907210000 | CA29: 15.3063 | CC29: 67.0259 | CE29: 0.89022 | CG29: 3040000000 | CL29: 11.500678 | CP29: 8.17 | CQ29: 13.06 | CR29: 13.59 | CS29: 18.3 | CT29: 8.81 | CU29: 5.38 | CV29: 14.22 | CW29: 14.22 | CX29: 18.31 | CY29: 5.67
A30: =A29+1 -> 1984 | B30: 30682 | C30: 1.64745e+10 | D30: 3957510000 | E30: 115250000000 | F30: 28159200000 | G30: 111056600000 | H30: 22742110000 | I30: 29775300000 | J30: 7916710000 | K30: 14886730000 | L30: 2824300000 | M30: 14730800000 | N30: 3044720000 | O30: 103155900000 | P30: 22276100000 | Q30: 12140720000 | R30: 85404200000 | S30: 27276100000 | T30: 5890410000 | U30: 1587100000 | V30: 10981290000 | X30: 4.808227 | Y30: -0.408719 | AC30: 32016300000 | AD30: 330290000000 | AH30: 10549590000 | AI30: 53907200000 | AM30: 9348890000 | AN30: 105223700000 | AR30: 5780750000 | AS30: 123615600000 | AW30: 11371950000 | AX30: 1098758000 | BB30: 29843900000 | BC30: 348755000000 | BG30: 12729490000 | BH30: 152063200000 | BL30: 2035157000 | BM30: 1.709849e+10 | BQ30: 114005900000 | BR30: 8652880000 | BV30: 1059742000 | BW30: 15736300000 | CA30: 15.1324 | CC30: 72.2966 | CE30: 0.789034 | CG30: 3520000000 | CL30: 11.531087 | CP30: 8.02 | CQ30: 14.01 | CR30: 12.49 | CS30: 15.6 | CT30: 8.56 | CU30: 6.57 | CV30: 15.8 | CW30: 15.8 | CX30: 17.27 | CY30: 6.08
A31: =A30+1 -> 1985 | B31: 31048 | C31: 18164500000 | D31: 4.06549e+09 | E31: 122424600000 | F31: 31600700000 | G31: 115925500000 | H31: 25139170000 | I31: 3.26953e+10 | J31: 7781680000 | K31: 16411390000 | L31: 3251370000 | M31: 15494600000 | N31: 3179630000 | O31: 110776700000 | P31: 24184900000 | Q31: 13264340000 | R31: 92229800000 | S31: 28576800000 | T31: 6109190000 | U31: 1789710000 | V31: 12112530000 | X31: 5.067981 | Y31: -0.45065 | AC31: 36587100000 | AD31: 360884000000 | AH31: 11980810000 | AI31: 57532800000 | AM31: 10353220000 | AN31: 114693000000 | AR31: 6970120000 | AS31: 133630300000 | AW31: 12404720000 | AX31: 1231139000 | BB31: 34126100000 | BC31: 382625000000 | BG31: 14516550000 | BH31: 165187500000 | BL31: 2179825000 | BM31: 17408120000 | BQ31: 125086900000 | BR31: 10030240000 | BV31: 1274204000 | BW31: 18480630000 | CA31: 15.79 | CC31: 78.0334 | CE31: 0.763088 | CG31: 3430000000 | CL31: 12.447414 | CP31: 7.77 | CQ31: 12.7 | CR31: 11.12 | CS31: 13.71 | CT31: 7.34 | CU31: 6.2 | CV31: 12.81 | CW31: 12.81 | CX31: 15.04 | CY31: 6.26
A32: =A31+1 -> 1986 | B32: 31413 | C32: 19628700000 | D32: 4678180000 | E32: 1.321349e+11 | F32: 33630600000 | G32: 123617600000 | H32: 26652290000 | I32: 36904000000 | J32: 7712900000 | K32: 1.630505e+10 | L32: 3257190000 | M32: 17058000000 | N32: 3468500000 | O32: 117222400000 | P32: 25644000000 | Q32: 14182190000 | R32: 98533300000 | S32: 31012200000 | T32: 6466380000 | U32: 1861420000 | V32: 12352960000 | X32: 5.462015 | Y32: -0.648131 | AC32: 37986600000 | AD32: 382727000000 | AH32: 12787570000 | AI32: 61743200000 | AM32: 10743470000 | AN32: 121482700000 | AR32: 7015850000 | AS32: 139939900000 | AW32: 13497760000 | AX32: 1271593000 | BB32: 35119800000 | BC32: 407853000000 | BG32: 14903310000 | BH32: 175285600000 | BL32: 2213646000 | BM32: 19196100000 | BQ32: 132947900000 | BR32: 10443780000 | BV32: 1217864000 | BW32: 20075890000 | CA32: 16.402 | CC32: 81.951 | CE32: 0.984167 | CG32: 3430000000 | CL32: 11.101437 | CP32: 7.44 | CQ32: 11.66 | CR32: 8.54 | CS32: 11.47 | CT32: 6.19 | CU32: 5.32 | CV32: 11.67 | CW32: 11.67 | CX32: 12.83 | CY32: 5.66
A33: =A32+1 -> 1987 | B33: 31778 | C33: 21872700000 | D33: 4561050000 | E33: 140544500000 | F33: 35439500000 | G33: 1.322667e+11 | H33: 28339350000 | I33: 38705900000 | J33: 8261120000 | K33: 17679260000 | L33: 3717560000 | M33: 18311800000 | N33: 3712840000 | O33: 121509400000 | P33: 26511500000 | Q33: 15111600000 | R33: 104617200000 | S33: 3.36566e+10 | T33: 6846770000 | U33: 2062440000 | V33: 13401770000 | X33: 3.226869 | Y33: 0.45241 | AC33: 39227500000 | AD33: 399531000000 | AH33: 12222060000 | AI33: 6.42562e+10 | AM33: 11572930000 | AN33: 126801700000 | AR33: 7465650000 | AS33: 146540700000 | AW33: 13592290000 | AX33: 1366354000 | BB33: 37933900000 | BC33: 415853000000 | BG33: 1.612627e+10 | BH33: 179456400000 | BL33: 2264345000 | BM33: 18747850000 | BQ33: 134981900000 | BR33: 11263030000 | BV33: 1268925000 | BW33: 19957690000 | CA33: 17.6184 | CC33: 85.6825 | CE33: 1.15444 | CG33: 3170000000 | CL33: 10.52273 | CP33: 7.01 | CQ33: 10.41 | CR33: 9.5 | CS33: 10.64 | CT33: 6.41 | CU33: 4.35 | CV33: 10.03 | CW33: 10.03 | CX33: 11.39 | CY33: 5.36
A34: =A33+1 -> 1988 | B34: 32143 | C34: 23946700000 | D34: 4522770000 | E34: 154084300000 | F34: 39623400000 | G34: 146497600000 | H34: 30019010000 | I34: 43405100000 | J34: 8704010000 | K34: 21707670000 | L34: 4.29006e+09 | M34: 19017800000 | N34: 3536540000 | O34: 127498300000 | P34: 27677900000 | Q34: 16327060000 | R34: 111824400000 | S34: 35674400000 | T34: 7117190000 | U34: 2384970000 | V34: 15401880000 | X34: 6.655008 | Y34: -0.195984 | AC34: 47529800000 | AD34: 414690000000 | AH34: 15393460000 | AI34: 6.53679e+10 | AM34: 14430090000 | AN34: 132652400000 | AR34: 9507400000 | AS34: 154134700000 | AW34: 13996480000 | AX34: 698773000 | BB34: 42829600000 | BC34: 436808000000 | BG34: 18082710000 | BH34: 187141100000 | BL34: 2552146000 | BM34: 1.665892e+10 | BQ34: 141224200000 | BR34: 12431190000 | BV34: 1434830000 | BW34: 20440970000 | CA34: 16.5129 | CC34: 87.2344 | CE34: 1.18248 | CG34: 6360000000 | CL34: 10.009229 | CP34: 6.86 | CQ34: 10.56 | CR34: 9.08 | CS34: 10.9 | CT34: 6.42 | CU34: 4.59 | CV34: 9.97 | CW34: 9.97 | CX34: 11.29 | CY34: 4.82
A35: =A34+1 -> 1989 | B35: 32509 | C35: 25941800000 | D35: 4849990000 | E35: 171291100000 | F35: 42625900000 | G35: 163631700000 | H35: 3.291389e+10 | I35: 45388600000 | J35: 8863610000 | K35: 28751690000 | L35: 4289020000 | M35: 20402500000 | N35: 3734630000 | O35: 136981800000 | P35: 29440200000 | Q35: 18322160000 | R35: 124906800000 | S35: 37901700000 | T35: 7473280000 | U35: 2809830000 | V35: 18464080000 | X35: 8.141413 | Y35: 0.676015 | AC35: 55268900000 | AD35: 444100000000 | AH35: 17697420000 | AI35: 70914500000 | AM35: 1.667394e+10 | AN35: 138987200000 | AR35: 11244370000 | AS35: 168059400000 | AW35: 14152270000 | AX35: 785545000 | BB35: 47990000000 | BC35: 460696000000 | BG35: 20984370000 | BH35: 196830900000 | BL35: 2821163000 | BM35: 1.629743e+10 | BQ35: 149741000000 | BR35: 14191420000 | BV35: 1515698000 | BW35: 22839380000 | CA35: 14.2457 | CC35: 89.5424 | CE35: 1.10175 | CG35: 6850000000 | CL35: 9.512523 | CP35: 7.15 | CQ35: 12.09 | CR35: 8.79 | CS35: 12.79 | CT35: 7.21 | CU35: 7.46 | CV35: 12.56 | CW35: 12.56 | CX35: 12.68 | CY35: 7.39
... A40: =A39+1 -> 1994 | B40: 34335 | C40: 38255100000 | D40: 7220180000 | E40: 182767800000 | F40: 52581200000 | G40: 155967700000 | H40: 24839320000 | I40: 54017700000 | J40: 12209310000 | K40: 12618940000 | L40: 3638070000 | M40: 29954400000 | N40: 5317520000 | O40: 179243300000 | P40: 39331600000 | Q40: 22046710000 | R40: 143375800000 | S40: 52047800000 | T40: 9921270000 | U40: 2908150000 | V40: 1.693218e+10 | X40: -2.36484 | Y40: -2.115587 | AC40: 48889100000 | AD40: 578490000000 | AH40: 14548420000 | AI40: 94245800000 | AM40: 12372110000 | AN40: 181072700000 | AR40: 13170220000 | AS40: 214627800000 | AW40: 19864200000 | AX40: 206490000 | BB40: 54451900000 | BC40: 642249000000 | BG40: 19426380000 | BH40: 272609100000 | BL40: 2557594000 | BM40: 17867220000 | BQ40: 208518300000 | BR40: 20026650000 | BV40: 3503607000 | BW40: 39030850000 | CA40: 56.198 | CC40: 116.6175 | CE40: 1.18952 | CG40: 3700000000 | CL40: 7.861391 | CP40: 7.03 | CQ40: 9.04 | CR40: 7.22 | CS40: 10.52 | CT40: 6.86 | CU40: 5.04 | CV40: 5.34 | CW40: 5.34 | CX40: 8.45 | CY40: 5.18
A41: =A40+1 -> 1995 | B41: 34700 | C41: 39947500000 | D41: 7211090000 | E41: 184381600000 | F41: 56574300000 | G41: 156057300000 | H41: 22847390000 | I41: 59346300000 | J41: 13099990000 | K41: 15985680000 | L41: 3802690000 | M41: 31688000000 | N41: 5756000000 | O41: 183772500000 | P41: 44897600000 | Q41: 20982150000 | R41: 137322800000 | S41: 55469900000 | T41: 10982270000 | U41: 3340250000 | V41: 18535390000 | W41: -2.152362 | X41: -1.99484 | Y41: -1.652337 | Z41: 3.884118 | AA41: -3.380884 | AB41: 91559100000 | AC41: 56589400000 | AD41: 621602000000 | AE41: 398399000000 | AF41: 159611500000 | AG41: 22029370000 | AH41: 17266790000 | AI41: 98329500000 | AJ41: 124564000000 | AK41: 39345100000 | AL41: 26897520000 | AM41: 13975490000 | AN41: 192183700000 | AO41: 105195300000 | AP41: 36057800000 | AQ41: 27526260000 | AR41: 14463980000 | AS41: 222810400000 | AT41: 111590900000 | AU41: 52204700000 | AV41: 2258084000 | AW41: 20950320000 | AX41: 234348000 | AY41: 14412900000 | AZ41: 4339363000 | BA41: 102891400000 | BB41: 62570000000 | BC41: 683969000000 | BD41: 189840100000 | BE41: 463213000000 | BF41: 36567300000 | BG41: 22378700000 | BH41: 286309400000 | BI41: 157442000000 | BJ41: 77257000000 | BK41: 4726430000 | BL41: 2740313000 | BM41: 18468660000 | BN41: 15778200000 | BO41: 2847410000 | BP41: 36683000000 | BQ41: 216215800000 | BR41: 21864180000 | BS41: 140078600000 | BT41: 50626600000 | BU41: 7379940000 | BV41: 3934969000 | BW41: 42204640000 | BX41: 99785000000 | BY41: 18513430000 | BZ41: 68.5835 | CA41: 55.2045 | CB41: 57.805 | CC41: 119.0877 | CD41: 73.1623 | CE41: 1.30801 | CG41: -1420000000 | CI41: -4820000000 | CL41: 7.415113 | CN41: 10.265051 | CP41: 7.14 | CQ41: 8.79 | CR41: 7.54 | CS41: 12.21 | CT41: 6.9 | CU41: 4.52 | CV41: 5.75 | CW41: 5.75 | CX41: 10.33 | CY41: 4.37
A42: =A41+1 -> 1996 | B42: 35065 | C42: 41408700000 | D42: 6898250000 | E42: 187564000000 | F42: 57601600000 | G42: 176445300000 | H42: 27238800000 | I42: 62337800000 | J42: 14218810000 | K42: 17181720000 | L42: 4.17046e+09 | M42: 3.22582e+10 | N42: 5831840000 | O42: 189175300000 | P42: 46419200000 | Q42: 23355310000 | R42: 156680100000 | S42: 56271700000 | T42: 11100270000 | U42: 3399210000 | V42: 18682390000 | W42: -0.615015 | X42: 0.918835 | Y42: -0.28153 | Z42: 4.422067 | AA42: 3.088908 | AB42: 95557400000 | AC42: 58586400000 | AD42: 656603000000 | AE42: 463342000000 | AF42: 164351600000 | AG42: 24167680000 | AH42: 19144530000 | AI42: 108196100000 | AJ42: 149571300000 | AK42: 41829400000 | AL42: 27895500000 | AM42: 14285450000 | AN42: 205247100000 | AO42: 119370200000 | AP42: 37926100000 | AQ42: 28049650000 | AR42: 14112030000 | AS42: 230756500000 | AT42: 144181400000 | AU42: 51346700000 | AV42: 2385819000 | AW42: 22778870000 | AX42: 228518000 | AY42: 4.13257e+09 | AZ42: 4445053000 | BA42: 104061900000 | BB42: 61857000000 | BC42: 705685000000 | BD42: 171130400000 | BE42: 531778000000 | BF42: 37040100000 | BG42: 22973230000 | BH42: 299086100000 | BI42: 183063800000 | BJ42: 75625600000 | BK42: 4302200000 | BL42: 2013818000 | BM42: 19311280000 | BN42: 17046250000 | BO42: 3330700000 | BP42: 37054400000 | BQ42: 224349500000 | BR42: 21534790000 | BS42: 163832100000 | BT42: 49785400000 | BU42: 7360851000 | BV42: 4.226568e+09 | BW42: 45535520000 | BX42: 114231400000 | BY42: 17763730000 | BZ42: 68.6324 | CA42: 55.3635 | CB42: 60.5935 | CC42: 118.8963 | CD42: 71.3724 | CE42: 1.26975 | CF42: -8570000000 | CG42: -2080000000 | CH42: -8.46e+09 | CI42: 95320000000 | CJ42: -10540000000 | CK42: 5.956544 | CL42: 7.622675 | CM42: 6.424022 | CN42: 9.79748 | CO42: 7.143242 | CP42: 6.32 | CQ42: 7.08 | CR42: 6.31 | CS42: 9.4 | CT42: 6.15 | CU42: 3.34 | CV42: 3.63 | CW42: 3.63 | CX42: 8.69 | CY42: 2.99
A43: =A42+1 -> 1997 | B43: 35431 | C43: 42147100000 | D43: 5592550000 | E43: 188910000000 | F43: 53678700000 | G43: 186828100000 | H43: 29057600000 | I43: 66094100000 | J43: 13684910000 | K43: 19016180000 | L43: 4915820000 | M43: 32596700000 | N43: 4914780000 | O43: 189803900000 | P43: 46784300000 | Q43: 24469080000 | R43: 166272400000 | S43: 56839900000 | T43: 11138110000 | U43: 3570080000 | V43: 19384210000 | W43: 0.987146 | X43: 2.882706 | Y43: -0.160429 | Z43: 6.139121 | AA43: 3.047395 | AB43: 93563700000 | AC43: 61456800000 | AD43: 663418000000 | AE43: 509346000000 | AF43: 165268500000 | AG43: 25389520000 | AH43: 20003990000 | AI43: 116778300000 | AJ43: 166369900000 | AK43: 41335800000 | AL43: 28522830000 | AM43: 1.601027e+10 | AN43: 208371400000 | AO43: 131685000000 | AP43: 39315300000 | AQ43: 28009980000 | AR43: 14265170000 | AS43: 228006900000 | AT43: 154040500000 | AU43: 52491900000 | AV43: 2334354000 | AW43: 23195880000 | AX43: 227490000 | AY43: 3956240000 | AZ43: 4341014000 | BA43: 98465300000 | BB43: 62774200000 | BC43: 710900000000 | BD43: 171169500000 | BE43: 542101000000 | BF43: 37209800000 | BG43: 23838970000 | BH43: 303192300000 | BI43: 194915600000 | BJ43: 76952100000 | BK43: 4048990000 | BL43: 2000905000 | BM43: 18463040000 | BN43: 14864510000 | BO43: 3869530000 | BP43: 36042600000 | BQ43: 228450700000 | BR43: 21377020000 | BS43: 178410200000 | BT43: 47755100000 | BU43: 6746748000 | BV43: 4545764000 | BW43: 45429030000 | BX43: 100226800000 | BY43: 17129810000 | BZ43: 63.9039 | CA43: 52.2354 | CB43: 61.9832 | CC43: 116.4905 | CD43: 65.8091 | CE43: 1.13404 | CF43: -11300000000 | CG43: -1570000000 | CH43: -9770000000 | CI43: -21270000000 | CJ43: -13810000000 | CK43: 5.43994 | CL43: 7.963442 | CM43: 6.06104 | CN43: 8.016659 | CO43: 6.973045 | CP43: 5.68 | CQ43: 5.96 | CR43: 5.58 | CS43: 6.86 | CT43: 5.58 | CU43: 3.51 | CV43: 3.23 | CW43: 3.23 | CX43: 6.78 | CY43: 3.32
A44: =A43+1 -> 1998 | B44: 35796 | C44: 43905800000 | D44: 5711320000 | E44: 204483300000 | F44: 54305200000 | G44: 195869300000 | H44: 31106600000 | I44: 71426000000 | J44: 14055270000 | K44: 21662990000 | L44: 4929510000 | M44: 33807100000 | N44: 5046740000 | O44: 195250000000 | P44: 47695000000 | Q44: 25230960000 | R44: 172660300000 | S44: 59413000000 | T44: 11448140000 | U44: 3725950000 | V44: 20113580000 | W44: 0.842629 | X44: 5.089221 | Y44: 0.994646 | Z44: 4.846061 | AA44: 3.022751 | AB44: 96767400000 | AC44: 6.46163e+10 | AD44: 690119000000 | AE44: 511826000000 | AF44: 172643400000 | AG44: 26662500000 | AH44: 21853810000 | AI44: 150697300000 | AJ44: 155160400000 | AK44: 42760500000 | AL44: 29414720000 | AM44: 1.672256e+10 | AN44: 216594300000 | AO44: 167913900000 | AP44: 42110200000 | AQ44: 28902660000 | AR44: 14972380000 | AS44: 211371900000 | AT44: 1.338993e+11 | AU44: 55734600000 | AV44: 2382172000 | AW44: 23899360000 | AX44: 121250000 | AY44: 3995790000 | AZ44: 4350512000 | BA44: 102108300000 | BB44: 62610700000 | BC44: 722110000000 | BD44: 177877600000 | BE44: 545774000000 | BF44: 38557800000 | BG44: 24597840000 | BH44: 306121800000 | BI44: 199981800000 | BJ44: 81216200000 | BK44: 4656670000 | BL44: 1961864000 | BM44: 18977650000 | BN44: 15304750000 | BO44: 4651330000 | BP44: 36655800000 | BQ44: 234113000000 | BR44: 21104450000 | BS44: 181261100000 | BT44: 48201100000 | BU44: 6975189000 | BV44: 4085726000 | BW44: 45296880000 | BX44: 89044100000 | BY44: 17083350000 | BZ44: 64.3454 | CA44: 46.8434 | CB44: 62.0997 | CC44: 113.8868 | CD44: 62.7788 | CE44: 1.12109 | CF44: 1530000000 | CG44: 960000000 | CH44: 11050000000 | CI44: -6100000000 | CJ44: 1960000000 | CK44: 5.852548 | CL44: 7.105327 | CM44: 5.702653 | CN44: 7.006706 | CO44: 7.073211 | CP44: 4.71 | CQ44: 4.79 | CR44: 4.64 | CS44: 4.88 | CT44: 4.63 | CU44: 3.58 | CV44: 3.57 | CW44: 3.57 | CX44: 4.91 | CY44: 3.42
A45: =A44+1 -> 1999 | B45: 36161 | C45: 45073900000 | D45: 5853030000 | E45: 223899800000 | F45: 57567200000 | G45: 206358800000 | H45: 3.3526e+10 | I45: 80261000000 | J45: 15810000000 | K45: 23489000000 | L45: 4996000000 | M45: 35405800000 | N45: 5229660000 | O45: 203978800000 | P45: 49244300000 | Q45: 26057000000 | R45: 179479100000 | S45: 63648000000 | T45: 12090000000 | U45: 3854000000 | V45: 21381000000 | W45: 0.823234 | X45: 4.584358 | Y45: 1.533816 | Z45: 4.594201 | AA45: 4.321862 | AB45: 101085000000 | AC45: 66818000000 | AD45: 727045000000 | AE45: 533453000000 | AF45: 187210000000 | AG45: 27016490000 | AH45: 22647000000 | AI45: 164811900000 | AJ45: 168082000000 | AK45: 45492000000 | AL45: 30965230000 | AM45: 17622000000 | AN45: 225153100000 | AO45: 170780000000 | AP45: 47381000000 | AQ45: 30124590000 | AR45: 15798000000 | AS45: 222916300000 | AT45: 138974000000 | AU45: 61842000000 | AV45: 2507970000 | AW45: 24893600000 | AX45: 72000000 | AY45: 3809000000 | AZ45: 4392000000 | BA45: 106429100000 | BB45: 64681000000 | BC45: 748589000000 | BD45: 186022000000 | BE45: 554351000000 | BF45: 40881300000 | BG45: 25692000000 | BH45: 319142100000 | BI45: 207383000000 | BJ45: 86110000000 | BK45: 4530720000 | BL45: 1955000000 | BM45: 19937200000 | BN45: 14946000000 | BO45: 5519000000 | BP45: 38429800000 | BQ45: 242066100000 | BR45: 21633000000 | BS45: 190424000000 | BT45: 48956000000 | BU45: 7015850000 | BV45: 3680000000 | BW45: 42943300000 | BX45: 74997000000 | BY45: 1.697e+10 | BZ45: 67.0801 | CA45: 44.0648 | CB45: 61.4231 | CC45: 113.0586 | CD45: 58.6943 | CE45: 1.065776 | CF45: 5220000000 | CG45: 1640000000 | CH45: -660000000 | CI45: 10680000000 | CJ45: -90000000 | CK45: 5.583636 | CL45: 6.523204 | CM45: 5.136393 | CN45: 5.77015 | CO45: 6.846193 | CP45: 4.68 | CQ45: 4.72 | CR45: 4.61 | CS45: 4.73 | CT45: 4.63 | CU45: 2.96 | CV45: 2.96 | CW45: 2.96 | CX45: 2.96 | CY45: 2.96
A46: =A45+1 -> 2000 | B46: 36526 | C46: 48862200000 | D46: 5739210000 | E46: 244613300000 | F46: 63078300000 | G46: 229601400000 | H46: 34605000000 | I46: 84751000000 | J46: 1.7118e+10 | K46: 26651000000 | L46: 4809000000 | M46: 37239500000 | N46: 5408590000 | O46: 217397300000 | P46: 50377700000 | Q46: 27743000000 | R46: 190691500000 | S46: 69098000000 | T46: 12928000000 | U46: 4139000000 | V46: 23105000000 | W46: 1.176629 | X46: 9.600692 | Y46: 1.646652 | Z46: 3.682443 | AA46: 4.574394 | AB46: 104170500000 | AC46: 74768000000 | AD46: 756007000000 | AE46: 5.47045e+11 | AF46: 200529000000 | AG46: 28046400000 | AH46: 27887000000 | AI46: 174235000000 | AJ46: 171067000000 | AK46: 48522000000 | AL46: 31563930000 | AM46: 18285000000 | AN46: 228692100000 | AO46: 178425000000 | AP46: 50228000000 | AQ46: 30940370000 | AR46: 15992000000 | AS46: 231767600000 | AT46: 141832000000 | AU46: 6.6376e+10 | AV46: 2484540000 | AW46: 25980800000 | AX46: 30000000 | AY46: 4040000000 | AZ46: 4285000000 | BA46: 109281900000 | BB46: 6.5373e+10 | BC46: 775349000000 | BD46: 195393000000 | BE46: 577169000000 | BF46: 41486200000 | BG46: 26886000000 | BH46: 332531200000 | BI46: 221855000000 | BJ46: 92704000000 | BK46: 4454270000 | BL46: 2001000000 | BM46: 19764800000 | BN46: 1.642e+10 | BO46: 5445000000 | BP46: 39876900000 | BQ46: 247651800000 | BR46: 21340000000 | BS46: 195723000000 | BT46: 49862000000 | BU46: 7610630000 | BV46: 3699000000 | BW46: 43605900000 | BX46: 75961000000 | BY46: 15549000000 | BZ46: 66.6378 | CA46: 45.1395 | CB46: 59.7214 | CC46: 108.7427 | CD46: 52.2419 | CE46: 0.923613 | CF46: 220000000 | CG46: 15050000000 | CH46: 3720000000 | CI46: -7880000000 | CJ46: -5230000000 | CK46: 5.587174 | CL46: 6.615635 | CM46: 5.088539 | CN46: 5.705686 | CO46: 6.305353 | CP46: 5.56 | CQ46: 5.48 | CR46: 5.39 | CS46: 5.58 | CT46: 5.4 | CU46: 4.39 | CV46: 4.39 | CW46: 4.39 | CX46: 4.39 | CY46: 4.39
A47: =A46+1 -> 2001 | B47: 36892 | C47: 49276000000 | D47: 5409180000 | E47: 254961000000 | F47: 64216200000 | G47: 238642000000 | H47: 38680000000 | I47: 87747000000 | J47: 18945000000 | K47: 28163000000 | L47: 4921000000 | M47: 38949500000 | N47: 5517590000 | O47: 228792500000 | P47: 52100700000 | Q47: 30129000000 | R47: 201314200000 | S47: 74565000000 | T47: 13824000000 | U47: 4326000000 | V47: 24652000000 | W47: 2.91799 | X47: 7.533209 | Y47: 1.635205 | Z47: 2.862322 | AA47: 2.542754 | AB47: 112105900000 | AC47: 75573000000 | AD47: 786539000000 | AE47: 575153000000 | AF47: 210599000000 | AG47: 3.256023e+10 | AH47: 26447000000 | AI47: 185318600000 | AJ47: 183261000000 | AK47: 49493000000 | AL47: 32470830000 | AM47: 18615000000 | AN47: 231405800000 | AO47: 182701000000 | AP47: 56641000000 | AQ47: 31843730000 | AR47: 1.7016e+10 | AS47: 241101200000 | AT47: 149948000000 | AU47: 6.5016e+10 | AV47: 2599120000 | AW47: 26724800000 | AX47: 0 | AY47: 4.063e+09 | AZ47: 4486000000 | BA47: 113669200000 | BB47: 68372000000 | BC47: 808226000000 | BD47: 212858000000 | BE47: 616778000000 | BF47: 42238800000 | BG47: 28814000000 | BH47: 342288700000 | BI47: 241767000000 | BJ47: 100928000000 | BK47: 4.28302e+09 | BL47: 1995000000 | BM47: 21984400000 | BN47: 19014000000 | BO47: 5979000000 | BP47: 40825400000 | BQ47: 258920700000 | BR47: 22073000000 | BS47: 203108000000 | BT47: 52277000000 | BU47: 7964590000 | BV47: 3693000000 | BW47: 46706400000 | BX47: 79082000000 | BY47: 14539000000 | BZ47: 67.2381 | CA47: 43.4435 | CB47: 59.3223 | CC47: 108.5131 | CD47: 49.4961 | CE47: 0.89563 | CF47: 4400000000 | CG47: 8.46e+09 | CH47: 5980000000 | CI47: 24830000000 | CJ47: 550000000 | CK47: 5.626968 | CL47: 5.998636 | CM47: 5.307517 | CN47: 5.84248 | CO47: 6.154517 | CP47: 5.08 | CQ47: 5.04 | CR47: 4.94 | CS47: 5.19 | CT47: 4.96 | CU47: 4.26 | CV47: 4.26 | CW47: 4.26 | CX47: 4.26 | CY47: 4.26
A48: =A47+1 -> 2002 | B48: 37257 | C48: 47058900000 | D48: 6113810000 | E48: 256286500000 | F48: 64688000000 | G48: 262565700000 | H48: 3.3102e+10 | I48: 84277000000 | J48: 21405000000 | K48: 26589000000 | L48: 5487000000 | M48: 40282200000 | N48: 5621400000 | O48: 238913900000 | P48: 53462700000 | Q48: 31849000000 | R48: 213249800000 | S48: 79464000000 | T48: 14805000000 | U48: 4430000000 | V48: 25409000000 | W48: 2.052216 | X48: 6.113581 | Y48: -0.14746 | Z48: 2.540792 | AA48: 0.463511 | AB48: 112963800000 | AC48: 77995000000 | AD48: 800987000000 | AE48: 591190000000 | AF48: 213990000000 | AG48: 30963810000 | AH48: 27054000000 | AI48: 178105500000 | AJ48: 180544000000 | AK48: 52255000000 | AL48: 33658830000 | AM48: 19608000000 | AN48: 239331100000 | AO48: 190078000000 | AP48: 58432000000 | AQ48: 3.232943e+10 | AR48: 17268000000 | AS48: 250197500000 | AT48: 157811000000 | AU48: 64803000000 | AV48: 2626140000 | AW48: 27915200000 | AX48: 0 | AY48: 3880000000 | AZ48: 4610000000 | BA48: 116171900000 | BB48: 71933000000 | BC48: 851107000000 | BD48: 225205000000 | BE48: 630226000000 | BF48: 42972700000 | BG48: 30593000000 | BH48: 361855000000 | BI48: 252325000000 | BJ48: 110735000000 | BK48: 4.23375e+09 | BL48: 2005000000 | BM48: 25182300000 | BN48: 19072000000 | BO48: 6047000000 | BP48: 42514200000 | BQ48: 271758100000 | BR48: 23409000000 | BS48: 214278000000 | BT48: 54579000000 | BU48: 7827430000 | BV48: 3013000000 | BW48: 47793500000 | BX48: 73477000000 | BY48: 13546000000 | BZ48: 67.4403 | CA48: 42.6428 | CB48: 61.256 | CC48: 105.9475 | CD48: 48.7677 | CE48: 0.945574 | CF48: 1090000000 | CG48: 6540000000 | CH48: 9030000000 | CI48: -22920000000 | CJ48: -5000000000 | CK48: 5.306642 | CL48: 4.795862 | CM48: 5.2655 | CN48: 5.174338 | CO48: 5.666905 | CP48: 4.96 | CQ48: 4.98 | CR48: 4.86 | CS48: 5.03 | CT48: 4.89 | CU48: 3.32 | CV48: 3.32 | CW48: 3.32 | CX48: 3.32 | CY48: 3.32
A49: =A48+1 -> 2003 | B49: 37622 | C49: 49788900000 | D49: 5988640000 | E49: 2.633948e+11 | F49: 69162300000 | G49: 255454600000 | H49: 42394000000 | I49: 83399000000 | J49: 22239000000 | K49: 27189000000 | L49: 5867000000 | M49: 41718000000 | N49: 5842300000 | O49: 248090500000 | P49: 55543400000 | Q49: 33473000000 | R49: 221945900000 | S49: 82835000000 | T49: 15611000000 | U49: 4538000000 | V49: 26150000000 | W49: 1.367374 | X49: 4.256694 | Y49: -1.211782 | Z49: 1.714395 | AA49: -0.71606 | AB49: 115095100000 | AC49: 78551000000 | AD49: 815469000000 | AE49: 612124000000 | AF49: 219143000000 | AG49: 31239400000 | AH49: 25885000000 | AI49: 177645500000 | AJ49: 178472000000 | AK49: 48776000000 | AL49: 3.412024e+10 | AM49: 20693000000 | AN49: 244883100000 | AO49: 190737000000 | AP49: 60002000000 | AQ49: 3.313909e+10 | AR49: 17375000000 | AS49: 260805200000 | AT49: 164873000000 | AU49: 70202000000 | AV49: 2635330000 | AW49: 29380300000 | AX49: 0 | AY49: 3860000000 | AZ49: 4662000000 | BA49: 119334400000 | BB49: 74848000000 | BC49: 881786000000 | BD49: 235578000000 | BE49: 657271000000 | BF49: 44262900000 | BG49: 31989000000 | BH49: 379531000000 | BI49: 2.66794e+11 | BJ49: 117563000000 | BK49: 4681970000 | BL49: 2016000000 | BM49: 25000500000 | BN49: 18563000000 | BO49: 5886000000 | BP49: 44132600000 | BQ49: 282799800000 | BR49: 24330000000 | BS49: 224365000000 | BT49: 58244000000 | BU49: 7391660000 | BV49: 2755000000 | BW49: 46658100000 | BX49: 69138000000 | BY49: 12748000000 | BZ49: 66.4118 | CA49: 45.156 | CB49: 65.3639 | CC49: 105.1408 | CD49: 49.8779 | CE49: 1.13116 | CF49: -2930000000 | CG49: 8910000000 | CH49: 27270000000 | CI49: -9960000000 | CJ49: -4870000000 | CK49: 4.869341 | CL49: 4.352359 | CM49: 4.825922 | CN49: 4.814148 | CO49: 5.197898 | CP49: 4.14 | CQ49: 4.13 | CR49: 4.13 | CS49: 4.25 | CT49: 4.12 | CU49: 2.33 | CV49: 2.33 | CW49: 2.33 | CX49: 2.33 | CY49: 2.33
A50: =A49+1 -> 2004 | B50: 37987 | C50: 51150400000 | D50: 6022150000 | E50: 279806600000 | F50: 73616100000 | G50: 2.659154e+11 | H50: 45373000000 | I50: 86221000000 | J50: 21045000000 | K50: 29131000000 | L50: 6205000000 | M50: 43253700000 | N50: 6027000000 | O50: 2.60347e+11 | P50: 57887500000 | Q50: 35624000000 | R50: 233278900000 | S50: 85821000000 | T50: 16300000000 | U50: 4705000000 | V50: 27436000000 | W50: -1.888437 | X50: 3.906993 | Y50: -0.754032 | Z50: 1.119219 | AA50: 0.584492 | AB50: 118767800000 | AC50: 81495000000 | AD50: 855607000000 | AE50: 629663000000 | AF50: 227769000000 | AG50: 3.213193e+10 | AH50: 26926000000 | AI50: 187956700000 | AJ50: 185289000000 | AK50: 51395000000 | AL50: 35223890000 | AM50: 20987000000 | AN50: 2.588919e+11 | AO50: 199155000000 | AP50: 62566000000 | AQ50: 34461520000 | AR50: 17988000000 | AS50: 268979400000 | AT50: 173070000000 | AU50: 70581000000 | AV50: 2641950000 | AW50: 30122600000 | AX50: 0 | AY50: 3643000000 | AZ50: 5056000000 | BA50: 1.306538e+11 | BB50: 77979000000 | BC50: 915906000000 | BD50: 237470000000 | BE50: 680101000000 | BF50: 46048100000 | BG50: 3.3624e+10 | BH50: 394321000000 | BI50: 280686000000 | BJ50: 119681000000 | BK50: 4562770000 | BL50: 2017000000 | BM50: 24295900000 | BN50: 16890000000 | BO50: 6309000000 | BP50: 45349600000 | BQ50: 295514000000 | BR50: 25192000000 | BS50: 234595000000 | BT50: 59562000000 | BU50: 7343490000 | BV50: 2686000000 | BW50: 47510600000 | BX50: 6.6749e+10 | BY50: 12808000000 | BZ50: 65.9119 | CA50: 44.938 | CB50: 66.8794 | CC50: 104.7421 | CD50: 50.1645 | CE50: 1.243902 | CF50: -6450000000 | CG50: 6340000000 | CH50: 13640000000 | CI50: 4700000000 | CJ50: 140000000 | CK50: 4.796316 | CL50: 3.92071 | CM50: 4.480414 | CN50: 4.536656 | CO50: 4.987112 | CP50: 4.13 | CQ50: 4.11 | CR50: 4.1 | CS50: 4.26 | CT50: 4.1 | CU50: 2.11 | CV50: 2.11 | CW50: 2.11 | CX50: 2.11 | CY50: 2.11
A51: =A50+1 -> 2005 | B51: 38353 | C51: 51059500000 | D51: 7574100000 | E51: 296142900000 | F51: 78385000000 | G51: 277777700000 | H51: 47123000000 | I51: 90956000000 | J51: 21396000000 | K51: 31824000000 | L51: 5919000000 | M51: 44931500000 | N51: 7049390000 | O51: 274464000000 | P51: 60759600000 | Q51: 37509000000 | R51: 244183500000 | S51: 88843000000 | T51: 1.6912e+10 | U51: 5001000000 | V51: 29004000000 | W51: 0.677894 | X51: 4.270463 | Y51: -0.79205 | Z51: 0.385838 | AA51: 1.737953 | AB51: 123866500000 | AC51: 85096000000 | AD51: 894341000000 | AE51: 643925000000 | AF51: 237320000000 | AG51: 32372990000 | AH51: 27825000000 | AI51: 198857900000 | AJ51: 191001000000 | AK51: 55677000000 | AL51: 36145420000 | AM51: 21886000000 | AN51: 270940500000 | AO51: 208059000000 | AP51: 6.5808e+10 | AQ51: 35830910000 | AR51: 19108000000 | AS51: 279506800000 | AT51: 178585000000 | AU51: 71722000000 | AV51: 2249350000 | AW51: 31191800000 | AX51: 0 | AY51: 3471000000 | AZ51: 4992000000 | BA51: 1.303987e+11 | BB51: 80717000000 | BC51: 956143000000 | BD51: 240167000000 | BE51: 705365000000 | BF51: 49408500000 | BG51: 35250000000 | BH51: 409986500000 | BI51: 295313000000 | BJ51: 123401000000 | BK51: 4011590000 | BL51: 2.075e+09 | BM51: 24117800000 | BN51: 15830000000 | BO51: 6064000000 | BP51: 46484600000 | BQ51: 308724300000 | BR51: 25889000000 | BS51: 242245000000 | BT51: 59673000000 | BU51: 8.2429e+09 | BV51: 2653000000 | BW51: 47845100000 | BX51: 67224000000 | BY51: 12460000000 | BZ51: 69.4276 | CA51: 42.1441 | CB51: 68.186 | CC51: 106.1767 | CD51: 49.6451 | CE51: 1.24409 | CF51: 10130000000 | CG51: 2440000000 | CH51: 5320000000 | CI51: 3760000000 | CJ51: 5090000000 | CK51: 5.199069 | CL51: 3.719072 | CM51: 4.217854 | CN51: 4.403901 | CO51: 4.672599 | CP51: 3.39 | CQ51: 3.35 | CR51: 3.41 | CS51: 3.56 | CT51: 3.37 | CU51: 2.19 | CV51: 2.19 | CW51: 2.19 | CX51: 2.19 | CY51: 2.19
A52: =A51+1 -> 2006 | B52: 38718 | C52: 52855600000 | D52: 7858860000 | E52: 323360300000 | F52: 80877400000 | G52: 293141400000 | H52: 48847000000 | I52: 99056000000 | J52: 23776000000 | K52: 3.3581e+10 | L52: 5777000000 | M52: 46749000000 | N52: 7301830000 | O52: 291162600000 | P52: 63745200000 | Q52: 39662000000 | R52: 255575300000 | S52: 92764000000 | T52: 17676000000 | U52: 5259000000 | V52: 30430000000 | W52: 0.563945 | X52: 5.481283 | Y52: -0.054306 | Z52: 0.80975 | AA52: 2.114925 | AB52: 128476200000 | AC52: 89977000000 | AD52: 943178000000 | AE52: 685630000000 | AF52: 258423000000 | AG52: 33935100000 | AH52: 28966000000 | AI52: 217141500000 | AJ52: 213472000000 | AK52: 58657000000 | AL52: 37042360000 | AM52: 22840000000 | AN52: 281529000000 | AO52: 224967000000 | AP52: 70359000000 | AQ52: 37380810000 | AR52: 20505000000 | AS52: 295287600000 | AT52: 180870000000 | AU52: 81531000000 | AV52: 2189500000 | AW52: 31916800000 | AX52: 0 | AY52: 3549000000 | AZ52: 3881000000 | BA52: 1.354131e+11 | BB52: 83083000000 | BC52: 992241000000 | BD52: 258252000000 | BE52: 741870000000 | BF52: 51920100000 | BG52: 36835000000 | BH52: 423187500000 | BI52: 304957000000 | BJ52: 136316000000 | BK52: 4.18256e+09 | BL52: 2256000000 | BM52: 25294300000 | BN52: 17258000000 | BO52: 6193000000 | BP52: 48017300000 | BQ52: 323955400000 | BR52: 26460000000 | BS52: 252104000000 | BT52: 61140000000 | BU52: 8.43658e+09 | BV52: 2581000000 | BW52: 48060100000 | BX52: 68871000000 | BY52: 12253000000 | BZ52: 68.1766 | CA52: 40.2242 | CB52: 65.4008 | CC52: 106.2569 | CD52: 45.0208 | CE52: 1.255599 | CF52: -840000000 | CG52: 7030000000 | CH52: -43220000000 | CI52: 9560000000 | CJ52: -9960000000 | CK52: 4.815292 | CL52: 3.719181 | CM52: 4.000106 | CN52: 4.326973 | CO52: 4.462159 | CP52: 3.8 | CQ52: 3.78 | CR52: 3.8 | CS52: 4.05 | CT52: 3.78 | CU52: 3.08 | CV52: 3.08 | CW52: 3.08 | CX52: 3.08 | CY52: 3.08
A53: =A52+1 -> 2007 | B53: 39083 | C53: 56728400000 | D53: 8572860000 | E53: 352863200000 | F53: 84819900000 | G53: 305935600000 | H53: 50752000000 | I53: 119329000000 | J53: 24556000000 | K53: 38745000000 | L53: 6518000000 | M53: 49031300000 | N53: 7598410000 | O53: 307326300000 | P53: 6.68208e+10 | Q53: 41850000000 | R53: 267623700000 | S53: 97499000000 | T53: 18537000000 | U53: 5567000000 | V53: 32464000000 | W53: 1.81533 | X53: 6.528422 | Y53: -0.301387 | Z53: 3.402202 | AA53: 1.807555 | AB53: 1.364481e+11 | AC53: 96675000000 | AD53: 981352000000 | AE53: 734222000000 | AF53: 267848000000 | AG53: 37298580000 | AH53: 31779000000 | AI53: 226017100000 | AJ53: 233507000000 | AK53: 65128000000 | AL53: 39103670000 | AM53: 23625000000 | AN53: 291869900000 | AO53: 232258000000 | AP53: 72540000000 | AQ53: 39000480000 | AR53: 21612000000 | AS53: 305923700000 | AT53: 199278000000 | AU53: 81968000000 | AV53: 2177440000 | AW53: 33638500000 | AX53: 0 | AY53: 3889000000 | AZ53: 4.02e+09 | BA53: 140313100000 | BB53: 87113000000 | BC53: 1039288000000 | BD53: 269466000000 | BE53: 755725000000 | BF53: 53606100000 | BG53: 38843000000 | BH53: 438020200000 | BI53: 309847000000 | BJ53: 144773000000 | BK53: 4.15037e+09 | BL53: 2319000000 | BM53: 28471800000 | BN53: 17492000000 | BO53: 7398000000 | BP53: 49243600000 | BQ53: 338128100000 | BR53: 27080000000 | BS53: 2.64407e+11 | BT53: 62377000000 | BU53: 8988080000 | BV53: 2650000000 | BW53: 52095200000 | BX53: 76677000000 | BY53: 12875000000 | BZ53: 65.8131 | CA53: 35.9993 | CB53: 65.4768 | CC53: 103.4635 | CD53: 42.7996 | CE53: 1.370478 | CF53: 560000000 | CG53: 7370000000 | CH53: 3610000000 | CI53: -1080000000 | CJ53: 460000000 | CK53: 4.957453 | CL53: 3.811195 | CM53: 4.314972 | CN53: 4.626164 | CO53: 4.86819 | CP53: 4.3 | CQ53: 4.29 | CR53: 4.3 | CS53: 4.49 | CT53: 4.29 | CU53: 4.28 | CV53: 4.28 | CW53: 4.28 | CX53: 4.28 | CY53: 4.28
... A69: =A68+1 -> 2023 | B69: 44927 | C69: 100176100000 | D69: 17663220000 | E69: 532092500000 | F69: 119699400000 | G69: 412367800000 | H69: 67565000000 | I69: 180947000000 | J69: 33597000000 | K69: 52538000000 | L69: 11189000000 | M69: 99359500000 | N69: 13943050000 | O69: 528807100000 | P69: 107907000000 | Q69: 58451000000 | R69: 384228100000 | S69: 167048000000 | T69: 30853000000 | U69: 10222000000 | V69: 55555000000 | W69: -1.40195 | X69: -1.811703 | Y69: -3.496198 | Z69: -3.5878 | AA69: 0.326808 | AB69: 237093700000 | AC69: 144448000000 | AD69: 1455683000000 | AE69: 995682000000 | AF69: 457397000000 | AG69: 66045440000 | AH69: 43563000000 | AI69: 357078000000 | AJ69: 321787000000 | AK69: 156259000000 | AL69: 65417310000 | AM69: 37572000000 | AN69: 446580000000 | AO69: 291446000000 | AP69: 118832000000 | AQ69: 71740470000 | AR69: 33987000000 | AS69: 413490000000 | AT69: 2.63886e+11 | AU69: 129202000000 | AV69: 1528350000 | AW69: 48176000000 | AX69: 0 | AY69: 4271000000 | AZ69: 5439000000 | BA69: 249471200000 | BB69: 152592000000 | BC69: 1607392000000 | BD69: 461217000000 | BE69: 1149966000000 | BF69: 98315000000 | BG69: 70153000000 | BH69: 682143600000 | BI69: 382684000000 | BJ69: 264091000000 | BK69: 10798810000 | BL69: 2828000000 | BM69: 69952000000 | BN69: 38895000000 | BO69: 17985000000 | BP69: 87641300000 | BQ69: 5.296588e+11 | BR69: 49798000000 | BS69: 424484000000 | BT69: 109939000000 | BU69: 5743060000 | BV69: 3202000000 | BW69: 52887200000 | BX69: 77814000000 | BY69: 7309000000 | BZ69: 78.5079 | CA69: 77.5487 | CB69: 109.7646 | CC69: 134.6374 | CD69: 45.1694 | CE69: 1.081144 | CF69: 8010000000 | CG69: 6380000000 | CH69: -4810000000 | CI69: -48870000000 | CJ69: -2740000000 | CK69: 1.635587 | CL69: 1.625257 | CM69: 1.789366 | CN69: 2.815026 | CO69: 1.519085 | CP69: 3.08 | CQ69: 3.04 | CR69: 2.99 | CS69: 4.28 | CT69: 2.79 | CU69: 3.43 | CV69: 3.43 | CW69: 3.43 | CX69: 3.43 | CY69: 3.43
A70: =A69+1 -> 2024 | B70: 45292 | C70: 98622600000 | D70: 18646470000 | E70: 526001800000 | F70: 126084400000 | G70: 404281200000 | H70: 77208000000 | I70: 187684000000 | J70: 36113000000 | K70: 47278000000 | L70: 12139000000 | M70: 103579300000 | N70: 14691270000 | P70: 107907000000 | Q70: 62710000000 | R70: 389255000000 | S70: 178337100000 | T70: 32259000000 | U70: 10248000000 | V70: 56280050000 | W70: -3.150801 | X70: -2.830483 | Y70: -3.736291 | Z70: 0.439425 | AA70: -0.192485 | AB70: 248824800000 | AC70: 147025000000 | AD70: 1500636000000 | AE70: 1032867000000 | AF70: 487336000000 | AG70: 69284980000 | AH70: 44324000000 | AI70: 366049000000 | AJ70: 343185000000 | AK70: 168193000000 | AL70: 67517860000 | AM70: 38437000000 | AN70: 453679000000 | AO70: 309128000000 | AP70: 125593000000 | AQ70: 77504280000 | AR70: 32671000000 | AS70: 431065000000 | AT70: 275193000000 | AU70: 1.35341e+11 | AV70: 1544160000 | AW70: 51216000000 | AX70: 0 | AY70: 4418000000 | AZ70: 5894000000 | BA70: 271309300000 | BB70: 159184000000 | BC70: 1670208000000 | BD70: 497420000000 | BE70: 1108414000000 | BF70: 106766400000 | BG70: 71872000000 | BH70: 702498600000 | BI70: 400720000000 | BJ70: 289059000000 | BK70: 9581780000 | BL70: 3237000000 | BM70: 57670000000 | BN70: 36291000000 | BO70: 15393000000 | BP70: 97148900000 | BQ70: 561799800000 | BR70: 52177000000 | BS70: 446007000000 | BT70: 118188000000 | BU70: 7299480000 | BV70: 4342000000 | BW70: 60261200000 | BX70: 85180000000 | BY70: 7901000000 | BZ70: 81.7801 | CA70: 82.0869 | CB70: 112.9765 | CC70: 135.3262 | CD70: 43.3453 | CE70: 1.08238 | CF70: 130000000 | CG70: 3000000000 | CH70: 33170000000 | CI70: 21400000000 | CJ70: -730000000 | CK70: 1.964759 | CL70: 2.052577 | CM70: 1.942317 | CN70: 2.968309 | CO70: 1.638437 | CP70: 2.84 | CQ70: 2.85 | CR70: 2.97 | CS70: 3.71 | CT70: 2.62 | CU70: 3.57 | CV70: 3.57 | CW70: 3.57 | CX70: 3.57 | CY70: 3.57
A71: =A70+1 -> 2025 | B71: 45658 | C71: 97336000000 | D71: 19466910000 | E71: 5.279622e+11 | F71: 127932200000 | G71: 404698000000 | H71: 84675860000 | I71: 194593900000 | J71: 37986700000 | K71: 48096570000 | L71: 13892000000 | M71: 104791300000 | N71: 15132010000 | P71: 110604700000 | Q71: 6.45913e+10 | R71: 397731000000 | S71: 186854300000 | T71: 33963580000 | U71: 10248000000 | V71: 56924060000 | W71: -2.650498 | X71: -2.228994 | Y71: -3.110692 | Z71: 0.630015 | AA71: -1.373088 | AB71: 258550500000 | AC71: 152745400000 | AD71: 1556648000000 | AE71: 1076019000000 | AF71: 502232600000 | AG71: 69908540000 | AH71: 45919660000 | AI71: 384045300000 | AJ71: 342241700000 | AK71: 167961200000 | AL71: 72924790000 | AM71: 40265100000 | AN71: 470453400000 | AO71: 315293900000 | AP71: 131302200000 | AQ71: 81216740000 | AR71: 33977840000 | AS71: 443397200000 | AT71: 300230800000 | AU71: 143919400000 | AV71: 1626030000 | AW71: 52999250000 | AX71: 0 | AY71: 4819960000 | AZ71: 6098714000 | BA71: 280344800000 | BB71: 163332700000 | BC71: 1723587000000 | BD71: 527540700000 | BE71: 1149658000000 | BF71: 110863600000 | BG71: 73229520000 | BH71: 721908700000 | BI71: 413310300000 | BJ71: 305446100000 | BK71: 8931090000 | BL71: 3393618000 | BM71: 55448580000 | BN71: 29849960000 | BO71: 16815960000 | BP71: 103269200000 | BQ71: 580276000000 | BR71: 52855300000 | BS71: 460716600000 | BT71: 1.293068e+11 | BU71: 8613386000 | BV71: 4.259502e+09 | BW71: 73820990000 | BX71: 87852300000 | BY71: 8946850000 | BZ71: 84.037 | CA71: 85.5861 | CB71: 116.0325 | CC71: 136.6632 | CD71: 44.9593 | CE71: 1.11352 | CF71: 1990000000 | CG71: 5680000000 | CH71: 1220000000 | CI71: 43050000000 | CJ71: 18830000000 | CK71: 2.185412 | CL71: 1.878908 | CM71: 2.233422 | CN71: 2.961383 | CO71: 1.82
A72: =A71+1 -> 2026 | B72: 46023 | C72: 100388100000 | D72: 20498660000 | E72: 545198400000 | F72: 129007000000 | G72: 413922700000 | H72: 89625330000 | I72: 198395000000 | J72: 40389460000 | K72: 50805480000 | L72: 14128160000 | M72: 107149900000 | N72: 15495180000 | P72: 113369800000 | Q72: 6.652904e+10 | R72: 408468300000 | S72: 192047500000 | T72: 35916640000 | U72: 10248000000 | V72: 58207390000 | W72: -2.434735 | X72: -1.733156 | Y72: -2.776063 | Z72: 1.097933 | AA72: -1.950895 | AB72: 2.672318e+11 | AC72: 157047700000 | AD72: 1596379000000 | AE72: 1108859000000 | AF72: 525534800000 | AG72: 72145620000 | AH72: 47021740000 | AI72: 398791700000 | AJ72: 350582900000 | AK72: 175517800000 | AL72: 75629140000 | AM72: 42353830000 | AN72: 484973700000 | AO72: 322383100000 | AP72: 139857900000 | AQ72: 84108050000 | AR72: 34623420000 | AS72: 452291500000 | AT72: 308787600000 | AU72: 150120700000 | AV72: 1717054000 | AW72: 55006070000 | AX72: 0 | AY72: 4957330000 | AZ72: 6198916000 | BA72: 288943100000 | BB72: 167120600000 | BC72: 1771500000000 | BD72: 559486000000 | BE72: 1175609000000 | BF72: 113889600000 | BG72: 74282440000 | BH72: 744539800000 | BI72: 422835000000 | BJ72: 319920700000 | BK72: 8728280000 | BL72: 3425177000 | BM72: 55157330000 | BN72: 31839440000 | BO72: 17777980000 | BP72: 106780400000 | BQ72: 589508300000 | BR72: 54018120000 | BS72: 472075300000 | BT72: 135692500000 | BU72: 9216323000 | BV72: 5004915000 | BW72: 89643070000 | BX72: 92180900000 | BY72: 9794460000 | BZ72: 85.7643 | CA72: 87.5343 | CB72: 118.4478 | CC72: 138.1981 | CD72: 47.7665 | CE72: 1.13468 | CF72: 510000000 | CG72: 2920000000 | CH72: -1430000000 | CI72: 50930000000 | CJ72: 21790000000 | CK72: 2.205313 | CL72: 2.059924 | CM72: 2.58081 | CN72: 2.989693 | CO72: 1.828281

Sheet Sheet3
B4: France, DG ECFIN AMECO, General Government, Expenditure(ESA2010), Total Expenditure, Estimate, EUR
A5: 28491 | B5: 180064000000
A6: 28856 | B6: 203739000000
A7: 29221 | B7: 234311000000
A8: 29587 | B8: 271156000000
A9: 29952 | B9: 300263000000
A10: 30317 | B10: 319801000000
A11: 30682 | B11: 348755000000
A12: 31048 | B12: 382625000000
A13: 31413 | B13: 407853000000
A14: 31778 | B14: 415853000000
A15: 32143 | B15: 436808000000
A16: 32509 | B16: 460696000000
... A53: 46023 | B53: 1771500000000

Sheet Sheet2
B2: {=TRANSPOSE(Sheet1!C2:CY2)} -> Capital Formation & Saving, Gross Fixed Capital Formation, Private Sector, Current Prices, EUR | D2: {=_xlfn.UNIQUE(_xlfn.ANCHORARRAY(B2))} -> Capital Formation & Saving, Gross Fixed Capital Formation, Private Sector, Current Prices, EUR | E2: I_M_NOM
B3: Capital Formation & Saving, Gross Fixed Capital Formation, General Government, Current Prices, EUR | D3: Capital Formation & Saving, Gross Fixed Capital Formation, General Government, Current Prices, EUR | E3: I_G
B4: Capital Formation & Saving, Gross Fixed Capital Formation, Private Sector, Current Prices, EUR | D4: Capital Formation & Saving, Consumption of Fixed Capital, Total, Current Prices, EUR | E4: DEPR_TOTAL_NOM
B5: Capital Formation & Saving, Gross Fixed Capital Formation, General Government, Current Prices, EUR | D5: Capital Formation & Saving, Consumption of Fixed Capital, General Government, Current Prices, EUR | E5: DEPR_G_NOM
B6: Capital Formation & Saving, Gross Fixed Capital Formation, Private Sector, Current Prices, EUR | D6: General Government, Net Lending(ESA2010), Net Lending (+) or Net Borrowing (-) Excluding Interest, Percent of GDP (Excessive Deficit Procedure), Market Prices | E6: PB_RATIO
B7: Capital Formation & Saving, Gross Fixed Capital Formation, General Government, Current Prices, EUR | D7: General Government, Revenue(ESA2010), Total Revenue, EUR | E7: GR
B8: Capital Formation & Saving, Gross Fixed Capital Formation, Private Sector, Current Prices, EUR | D8: General Government, Revenue(ESA2010), Current Taxes on Income & Wealth, Direct Taxes, EUR | E8: taxes_income_wealth
B9: Capital Formation & Saving, Gross Fixed Capital Formation, General Government, Current Prices, EUR | D9: General Government, Revenue(ESA2010), Taxes Linked to Imports & Production, Indirect Taxes, EUR | E9: T_C
B10: Capital Formation & Saving, Gross Fixed Capital Formation, Private Sector, Current Prices, EUR | D10: General Government, Revenue(ESA2010), Actual Social Contributions Received, EUR | E10: SC_actual
B11: Capital Formation & Saving, Gross Fixed Capital Formation, General Government, Current Prices, EUR | D11: General Government, Revenue(ESA2010), Imputed Social Contributions, EUR | E11: SC_IMP
B12: Capital Formation & Saving, Consumption of Fixed Capital, Total, Current Prices, EUR | D12: General Government, Expenditure(ESA2010), Total Expenditure, EUR | E12: GE
B13: Capital Formation & Saving, Consumption of Fixed Capital, General Government, Current Prices, EUR | D13: General Government, Expenditure(ESA2010), Final Consumption Expenditure, EUR | E13: G
B14: Capital Formation & Saving, Consumption of Fixed Capital, Total, Current Prices, EUR | D14: General Government, Expenditure(ESA2010), Subsidies, EUR | E14: SUB
... B22: General Government, Net Lending(ESA2010), Net Lending (+) or Net Borrowing (-) Excluding Interest, Percent of GDP (Excessive Deficit Procedure), Market Prices | D22: Monetary Variables, Interest Rates, Nominal, Short-Term, Current Prices | E22: I_RATE
B23: General Government, Net Lending(ESA2010), Net Lending (+) or Net Borrowing (-) Excluding Interest, Percent of GDP (Excessive Deficit Procedure), Market Prices
B24: General Government, Net Lending(ESA2010), Net Lending (+) or Net Borrowing (-) Excluding Interest, Percent of GDP (Excessive Deficit Procedure), Market Prices
B25: General Government, Net Lending(ESA2010), Net Lending (+) or Net Borrowing (-) Excluding Interest, Percent of GDP (Excessive Deficit Procedure), Market Prices
B26: General Government, Net Lending(ESA2010), Net Lending (+) or Net Borrowing (-) Excluding Interest, Percent of GDP (Excessive Deficit Procedure), Market Prices
B27: General Government, Revenue(ESA2010), Total Revenue, EUR
B28: General Government, Revenue(ESA2010), Total Revenue, EUR
B29: General Government, Revenue(ESA2010), Total Revenue, EUR
B30: General Government, Revenue(ESA2010), Total Revenue, EUR
B31: General Government, Revenue(ESA2010), Total Revenue, EUR
B32: General Government, Revenue(ESA2010), Current Taxes on Income & Wealth, Direct Taxes, EUR
B33: General Government, Revenue(ESA2010), Current Taxes on Income & Wealth, Direct Taxes, EUR
B34: General Government, Revenue(ESA2010), Current Taxes on Income & Wealth, Direct Taxes, EUR
... B102: Monetary Variables, Interest Rates, Nominal, Short-Term, Current Prices
