Workbook

Sheet Sources
A1: Block | B1: Decription | C1: Variable / Parameter | D1: In Model? | E1: Source | F1: Notes | G1: Link
A2: Supply | B2: potential output, real | C2: Y_STAR | D2: 1 | E2: EUCAM | G2: https://circabc.europa.eu/ui/group/671d465b-0752-4a2e-906c-a3effd2340ba/library/b9482682-d5a0-47a1-9281-bc7d8a214629
B3: log TFP | C3: SR | D3: 0 | E3: calculated
B4: log trend TFP | C4: SR_TREND | D4: 1 | E4: estimated | F4: UCM, bayesian Kalman filter
B5: log trend TFP growth | C5: SR_SLOPE | D5: 1 | E5: estimated | F5: UCM, bayesian Kalman filter
B6: inertia / persistence in TFP growth | C6: RHO_SR | D6: 1 | E6: estimated | F6: UCM, bayesian Kalman filter
B7: long-term TFP growth | C7: OMEGA_SR | D7: 1 | E7: estimated | F7: UCM, bayesian Kalman filter
B8: capacity utilisation indicator | C8: CUBS | D8: 0 | E8: EUCAM | F8: relevant for TFP trend estimation | G8: https://circabc.europa.eu/ui/group/671d465b-0752-4a2e-906c-a3effd2340ba/library/b9482682-d5a0-47a1-9281-bc7d8a214626
B9: working age population EUCAM | C9: WP_EUCAM | D9: 0 | E9: EUCAM | G9: https://circabc.europa.eu/ui/group/671d465b-0752-4a2e-906c-a3effd2340ba/library/b9482682-d5a0-47a1-9281-bc7d8a214627
B10: working age population EU projections | C10: WP_PROJ | D10: 0 | E10: EUCAM | G10: https://circabc.europa.eu/ui/group/671d465b-0752-4a2e-906c-a3effd2340ba/library/b9482682-d5a0-47a1-9281-bc7d8a214628
B11: working age population (merged) | C11: WP | D11: 1 | E11: calculated | F11: starting 2029 forecasted based on EU projections | G11: https://circabc.europa.eu/ui/group/671d465b-0752-4a2e-906c-a3effd2340ba/library/b9482682-d5a0-47a1-9281-bc7d8a214629
B12: labour force participation rate | C12: LP | D12: 0 | E12: EUCAM | G12: https://circabc.europa.eu/ui/group/671d465b-0752-4a2e-906c-a3effd2340ba/library/b9482682-d5a0-47a1-9281-bc7d8a214630
B13: trend labour force participation rate | C13: LP_TREND | D13: 1 | E13: estimated | F13: UCM, MLE Kalman filter
B14: trend labour force participation rate growth | C14: LP_SLOPE | D14: 1 | E14: estimated | F14: UCM, MLE Kalman filter
B15: trend labour force participation rate; EUCAM values | C15: LP_TREND_EUCAM | D15: 0 | E15: EUCAM | G15: https://circabc.europa.eu/ui/group/671d465b-0752-4a2e-906c-a3effd2340ba/library/b9482682-d5a0-47a1-9281-bc7d8a214631
B16: AWG participation rate projections | C16: LP_AWG | D16: 1 | E16: AWG EU projections
B17: unemployment rate | C17: U | D17: 0 | E17: EUCAM | G17: https://circabc.europa.eu/ui/group/671d465b-0752-4a2e-906c-a3effd2340ba/library/b9482682-d5a0-47a1-9281-bc7d8a214632
B18: trend unemployment rate (NAWRU) | C18: U_TREND | D18: 1 | E18: estimated | F18: UCM, MLE Kalman filter
B19: trend unemployment rate growth | C19: U_SLOPE | D19: 1 | E19: estimated | F19: UCM, MLE Kalman filter
B20: NAWRU; EUCAM values | C20: U_TREND_EUCAM | D20: 0 | E20: EUCAM | G20: https://circabc.europa.eu/ui/group/671d465b-0752-4a2e-906c-a3effd2340ba/library/b9482682-d5a0-47a1-9281-bc7d8a214633
B21: Anchored NAWRU EUCAM estimates | C21: STRUCT_U_EUCAM | D21: 0 | E21: EUCAM
B22: productivity indicator? | C22: dlprod | D22: 0 | E22: EUCAM | F22: relevant for Germany NAWRU estimation | G22: https://circabc.europa.eu/ui/group/671d465b-0752-4a2e-906c-a3effd2340ba/library/b9482682-d5a0-47a1-9281-bc7d8a214634
B23: Terms of trade indicator? | C23: dpcegdp | D23: 0 | E23: EUCAM | F23: relevant for Germany NAWRU estimation | G23: https://circabc.europa.eu/ui/group/671d465b-0752-4a2e-906c-a3effd2340ba/library/b9482682-d5a0-47a1-9281-bc7d8a214635
B24: wage level/inflation indicator? | C24: endo_dwinf | D24: 0 | E24: EUCAM | F24: relevant for Germany NAWRU estimation | G24: https://circabc.europa.eu/ui/group/671d465b-0752-4a2e-906c-a3effd2340ba/library/b9482682-d5a0-47a1-9281-bc7d8a214636
B25: average hours worked | C25: H | D25: 0 | E25: EUCAM | F25: relevant for Germany NAWRU estimation | G25: https://circabc.europa.eu/ui/group/671d465b-0752-4a2e-906c-a3effd2340ba/library/b9482682-d5a0-47a1-9281-bc7d8a214634
B26: trend average hours worked | C26: H_TREND | D26: 1 | E26: estimated | F26: UCM, MLE Kalman filter
B27: trend average hours worked growth | C27: H_SLOPE | D27: 1 | E27: estimated | F27: UCM, MLE Kalman filter
B28: trend average hours worked; EUCAM values | C28: H_TREND_EUCAM | D28: 0 | E28: EUCAM | G28: https://circabc.europa.eu/ui/group/671d465b-0752-4a2e-906c-a3effd2340ba/library/b9482682-d5a0-47a1-9281-bc7d8a214635
B29: capital stock (total) | C29: K | D29: 0 | E29: EUCAM | G29: https://circabc.europa.eu/ui/group/671d465b-0752-4a2e-906c-a3effd2340ba/library/b9482682-d5a0-47a1-9281-bc7d8a214636
B30: total capital stock Eurostat | C30: K_EUROSTAT | D30: 0 | E30: Eurostat | G30: Saskia Link
B31: public capital stock eurostat | C31: K_G_EUROSTAT | D31: 0 | E31: Eurostat | G31: Saskia Link
B32: eurostat private/public capital split | C32: K_SPLIT | D32: 0 | E32: calculated | F32: K_G_EUROSTAT/K_EUROSTAT | G32: https://ec.europa.eu/eurostat/databrowser/view/nama_10_nfa_bs/default/table?lang=en
B33: public capital stock, real | C33: K_G | D33: 1 | E33: calculated (based on Eurostat, AMECO) | F33: initial values based on Eurostat private/public split; then calculated based on AMECO investment and depreciation data | G33: Macrobond, https://ec.europa.eu/eurostat/databrowser/view/nama_10_nfa_bs/default/table?lang=en
B34: public investment, real | C34: I_G_REAL | D34: 1 | E34: calculated (based on AMECO) | F34: nominal expenditure and GDP deflator
B35: public capital depreciation, nominal | C35: DEPR_G_NOM | D35: 0 | E35: AMECO | F35: AMECO Capital Formation & Saving, Consumption of Fixes Capital, General Government, Current Prices, EUR | G35: Macrobond
B36: public capital depreciation, real | C36: DEPR_G | D36: 0 | E36: calculated (based on AMECO) | F36: DEPR_G_NOM / P
B37: public capital depreciation rate | C37: DEPR_G_RATIO | D37: 1 | E37: calculated (based on AMECO) | F37: DEPR_G / K_G; projected based on historical average
B38: public capital depreciation rate | C38: DELTA_G | D38: 1 | E38: calibrated / calculated | F38: Historical average of DEPR_G_RATIO
B39: private capital stock, real | C39: K_M | D39: 1 | E39: calculated (based on Eurostat, AMECO) | F39: initial values based on Eurostat private/public split; then calculated based on AMECO investment and depreciation data | G39: Macrobond, https://ec.europa.eu/eurostat/databrowser/view/nama_10_nfa_bs/default/table?lang=en
B40: private investment, nominal | C40: I_M_NOM | D40: 0 | E40: AMECO | F40: AMECO Capital Formation & Saving, Gross Fixed Capital Formation, Private Sector, Current Prices, EUR | G40: Macrobond
B41: private investment, real | C41: I_M | D41: 1 | E41: calculated (based on AMECO) | F41: I_M_NOM / P
B42: total capital depreciation, nominal | C42: DEPR_TOTAL_NOM | D42: 0 | E42: AMECO | F42: AMECO Capital Formation & Saving, Consumption of Fixes Capital, Total, Current Prices, EUR | G42: Macrobond
B43: private capital depreciation, real | C43: DEPR_M | D43: 0 | E43: calculated (based on AMECO) | F43: (DEPR_TOTAL_NOM - DEPR_G_NOM) / P
B44: private capital depreciation rate | C44: DELTA_M | D44: 1 | E44: calibrated / calculated | F44: DEPR_M / K_M; projected based on last historical depreciation rate
B45: private investment rate | C45: IQ_M | D45: 1 | E45: calculated | F45: I_M / Y_STAR * 100
B46: AR(2) parameter for private investment rate (constant) | C46: PHI_IQ_M_0 | D46: 1 | E46: estimated | F46: Bayesian linear regression for private investment rate
B47: AR(2) parameter for private investment rate (1) | C47: PHI_IQ_M_1 | D47: 1 | E47: estimated | F47: Bayesian linear regression for private investment rate
B48: AR(2) parameter for private investment rate (2) | C48: PHI_IQ_M_2 | D48: 1 | E48: estimated | F48: Bayesian linear regression for private investment rate
B49: impact of change in LT interest rate on investment | C49: LAMBDA_IQ_M_1 | D49: 1 | E49: estimated | F49: Bayesian linear regression for private investment rate
B50: impact of change in struct. tax rate on firms on investment | C50: LAMBDA_IQ_M_2 | D50: 1 | E50: estimated | F50: Bayesian linear regression for private investment rate
B51: impact of change in struct. subsidies rate on investment | C51: LAMBDA_IQ_M_3 | D51: 1 | E51: estimated | F51: Bayesian linear regression for private investment rate
B52: impact of output gap on investment | C52: LAMBDA_IQ_M_4 | D52: 1 | E52: estimated | F52: Bayesian linear regression for private investment rate
A53: Demand | B53: aggregate demand (GDP), real | C53: Y_D | D53: 1 | E53: EUCAM | G53: https://circabc.europa.eu/ui/group/671d465b-0752-4a2e-906c-a3effd2340ba/library/b9482682-d5a0-47a1-9281-bc7d8a214636
B54: agreggate demand (GDP), nominal | C54: Y_D_NOM | D54: 1 | E54: EUCAM | G54: https://circabc.europa.eu/ui/group/671d465b-0752-4a2e-906c-a3effd2340ba/library/b9482682-d5a0-47a1-9281-bc7d8a214632
B55: output gap | C55: Y_GAP | D55: 1 | E55: EUCAM | G55: https://circabc.europa.eu/ui/group/671d465b-0752-4a2e-906c-a3effd2340ba/library/b9482682-d5a0-47a1-9281-bc7d8a214636
B56: output gap closure parameter | C56: BETA_D | D56: 1 | E56: estimated / calibrated | F56: Bayesian linear regression for demand equation
B57: impact of change in interest rate on aggregate demand | C57: LAMBDA_R | D57: 1 | E57: estimated | F57: Bayesian linear regression for demand equation
B58: fiscal multiplier: public inverstment | C58: LAMBDA_I_G | D58: 1 | E58: estimated / calibrated | F58: Bayesian linear regression for demand equation
B59: fiscal multiplier: government consumption | C59: LAMBDA_G | D59: 1 | E59: estimated | F59: Bayesian linear regression for demand equation
B60: fiscal multiplier: subsidies | C60: LAMBDA_S | D60: 1 | E60: estimated / calibrated | F60: Bayesian linear regression for demand equation
B61: fiscal multiplier: transfers | C61: LAMBDA_TR | D61: 1 | E61: estimated | F61: Bayesian linear regression for demand equation
B62: fiscal multiplier: taxes on households | C62: LAMBDA_T_HH | D62: 1 | E62: estimated / calibrated | F62: Bayesian linear regression for demand equation
B63: fiscal multiplier: taxes on firms | C63: LAMBDA_T_F | D63: 1 | E63: estimated | F63: Bayesian linear regression for demand equation
B64: fiscal multiplier: indirect taxes (taxes on consumption) | C64: LAMBDA_T_C | D64: 1 | E64: estimated / calibrated | F64: Bayesian linear regression for demand equation
A65: Fiscal | B65: primary balance, nominal | C65: PB | D65: 1 | E65: calculated | G65: Macrobond
B66: primary balance ratio as share of GDP | C66: PB_RATIO | D66: 1 | E66: AMECO | F66: AMECO General Government, Net Lending(ESA2010), Net Lending (+) or Net Borrowing (-), Excluding Interest, Percent of GDP | G66: Macrobond
B67: general government revenue, nominal | C67: GR | D67: 1 | E67: AMECO | F67: AMECO General Government, Revenue(ESA2010), Total Revenue, EUR | G67: Macrobond
B68: taxes on wealth and income, nominal | C68: taxes_income_wealth | D68: 0 | E68: AMECO | F68: AMECO General Government, Revenue(ESA2010), Taxes on Wealth and Income, EUR | G68: Macrobond
B69: direct taxes on households, nominal | C69: T_HH_ECB | D69: 0 | E69: ECB | F69: Quarterly; adjusted for annually | G69: https://data.ecb.europa.eu/data/datasets/QSA/QSA.Q.N.DE.W0.S1M.S1.N.D.D5._Z._Z._Z.XDC._T.S.V.N._T
B70: current taxes payable by non-financial corporations | C70: T_non-finan_corp | D70: 0 | E70: ECB | F70: Quarterly; adjusted for annually | G70: https://data.ecb.europa.eu/data/datasets/QSA/QSA.Q.N.DE.W0.S11.S1.N.D.D5._Z._Z._Z.XDC._T.S.V.N._T
B71: current taxes payable by non-financial corporations | C71: T_finan_corp | D71: 0 | E71: ECB | F71: Quarterly; adjusted for annually | G71: https://data.ecb.europa.eu/data/datasets/QSA/QSA.Q.N.DE.W0.S12.S1.N.D.D5._Z._Z._Z.XDC._T.S.V.N._T
B72: direct taxes on households, nominal, scaled | C72: T_HH | D72: 1 | E72: caclulated | F72: taxes_income_wealth * T_HH_ECB / (T_HH_ECB + T_non-finan_corp + T_finan_corp)
B73: direct taxes on firms, nominal, scaled | C73: T_F | D73: 1 | E73: caclulated | F73: taxes_income_wealth - T_HH
B74: indirect taxes on consumption, nominal | C74: T_C | D74: 1 | E74: AMECO | F74: AMECO General Government, Revenue(ESA2010), Indirect Taxes, EUR | G74: Macrobond
B75: actual social security contributions, nominal | C75: SC_actual | D75: 0 | E75: AMECO | F75: AMECO General Government, Revenue(ESA2010), Actual Social Contributions, EUR | G75: Macrobond
B76: social secutiry contributions from households, nominal | C76: SC_HH_ECB | D76: 0 | E76: ECB | F76: possibly scaled via AMECO total | G76: https://data.ecb.europa.eu/data/datasets/GFS/GFS.A.N.DE.W0.S13.S1.N.C.D613._Z._Z._Z.XDC._Z.S.V.N._T
B77: social secutiry contributions from firms, nominal | C77: SC_F_ECB | D77: 0 | E77: ECB | F77: possibly scaled via AMECO total | G77: https://data.ecb.europa.eu/data/datasets/GFS/GFS.A.N.DE.W0.S13.S1.N.C.D611._Z._Z._Z.XDC._Z.S.V.N._T
B78: social contribtuions from households, nominal, scaled | C78: T_HH | D78: 1 | E78: caclulated | F78: SC_actual * SC_HH_ECB / (SC_HH_ECB + SC_F_ECB)
B79: social contribtuions from firms, nominal, scaled | C79: T_F | D79: 1 | E79: caclulated | F79: SC_actual - SC_HH
B80: social secutiry contributions, imputed, nominal | C80: SC_IMP | D80: 1 | E80: AMECO | F80: AMECO General Government, Revenue(ESA2010), Imputed Social Contributions, EUR | G80: Macrobond
B81: other/non-tax revenues, nominal | C81: NonT | D81: 1 | E81: calculated
B82: total government expenditure, nominal | C82: GE | D82: 0 | E82: AMECO | F82: AMECO General Government, Expenditure(ESA2010), Total Expenditure, EUR | G82: Macrobond
B83: primary expenditure, nominal | C83: PE | D83: 1 | E83: calculated
B84: final consumption expenditure, nominal | C84: G | D84: 1 | E84: AMECO | F84: AMECO General Government, Expenditure(ESA2010), Final Consumption Expenditure, EUR | G84: Macrobond
B85: public investment, nominal | C85: I_G | D85: 1 | E85: AMECO | F85: AMECO Capital Formation & Saving, Gross Fixed Capital Formation, General Government, Current Prices, EUR | G85: Macrobond
B86: subsidies | C86: SUB | D86: 1 | E86: AMECO | F86: AMECO General Government, Expenditure(ESA2010), Subsidies, EUR | G86: Macrobond
B87: transfers | C87: TR | D87: 1 | E87: AMECO | F87: AMECO General Government, Expenditure(ESA2010), Social Benefits, EUR | G87: Macrobond
B88: interest payments | C88: INT | D88: 1 | E88: AMECO | F88: AMECO General Government, Expenditure(ESA2010), Interest, EUR | G88: Macrobond
B89: other primary expenditure | C89: OTHER_PE | D89: 1 | E89: calculated
B90: structural tax rate for households | C90: TAU_HH_STAR | D90: 1 | E90: kept constant as last caclulated value | F90: structural share = imputed share - semi-elasticity * output gap
B91: structural tax rate for firms | C91: TAU_F_STAR | D91: 1 | E91: kept constant as last caclulated value | F91: structural share = imputed share - semi-elasticity * output gap
B92: structural tax rate on indirect taxes (consumption) | C92: TAU_C_STAR | D92: 1 | E92: kept constant as last caclulated value | F92: structural share = imputed share - semi-elasticity * output gap
B93: structural rate of social security contributions by households | C93: TAU_SC_HH_STAR | D93: 1 | E93: kept constant as last caclulated value | F93: structural share = imputed share - semi-elasticity * output gap
B94: structural rate of social security contributions by firms | C94: TAU_SC_F_STAR | D94: 1 | E94: kept constant as last caclulated value | F94: structural share = imputed share - semi-elasticity * output gap
B95: structural rate of imputed social security contributions | C95: TAU_SC_IMP_STAR | D95: 1 | E95: kept constant as last caclulated value | F95: structural share = imputed share - semi-elasticity * output gap
B96: structural rate of non-tax revenue (acyclical) | C96: TAU_NON_T_STAR | D96: 1 | E96: kept constant as last caclulated value | F96: structural share = imputed share - semi-elasticity * output gap
B97: structural share of government consumption (acyclical) | C97: S_G_STAR | D97: 1 | E97: kept constant as last caclulated value | F97: structural share = imputed share - semi-elasticity * output gap
B98: structural share of public investment (acyclical) | C98: S_IG_STAR | D98: 1 | E98: kept constant as last caclulated value | F98: structural share = imputed share - semi-elasticity * output gap
B99: structural share of subsidies (acyclical) | C99: S_SUB_STAR | D99: 1 | E99: kept constant as last caclulated value | F99: structural share = imputed share - semi-elasticity * output gap
B100: structural share of transfers (cyclical) | C100: S_TR_STAR | D100: 1 | E100: kept constant as last caclulated value | F100: structural share = imputed share - semi-elasticity * output gap
...

Sheet Python Calculations
A1: Block | B1: Decription | C1: Variable / Parameter | D1: Calculation
A2: Supply | B2: log trend potential output, real | C2: Y_TREND | D2: log(Y_STAR)
B3: potential output, nominal | C3: Y_STAR_NOM | D3: Y_STAR * P
B4: PO growth, real | C4: G_Y_STAR | D4: (Y_STAR - Y_STAR(-1))/Y_STAR(-1) * 100
B5: pulbic investment lags | C5: THETA_KG_x | D5: add all thetas
B6: AWG participation rate growth | C6: LP_SLOPE_AWG | D6: LP_AWG(+1) - LP_AWG
A7: Demand | B7: log demand, real | C7: Y_D_LOG | D7: log(Y_D)
B8: GDP growth, real | C8: G_Y_D | D8: (Y_D - Y_D(-1))/Y_D * 100
B9: output gap closure mechanism | C9: BETA_D | D9: = 0
A10: Prices | B10: nominal potential output growth | C10: G_Y_STAR_NOM | D10: (Y_STAR_NOM - Y_STAR_NOM(-1)) / Y_STAR_NOM(-1) * 100
B11: nominal GDP growth | C11: G_Y_D_NOM | D11: (Y_D_NOM - Y_D_NOM(-1)) / Y_D_NOM(-1) * 100
A12: Financial | B12: short-term interest rate | C12: I_ST | D12: = I_RATE
B13: share of country GDP in euro area gdp | C13: OMEGA_DE | D13: Y_D / GDP_EA; kept constant
B14: neutral interest rate | C14: I_STAR | D14: kept constant; (I_RATE - THETA_I * I_RATE(-1)) / (1 - THETA_I) - OMEGA_DE * (SIGMA_I_1 * (PI - PI_T) + SIGMA_I_2 * Y_GAP) - (1 - OMEGA_DE) * (SIGMA_I_1 * (PI_EA - PI_T) + SIGMA_I_2 * Y_GAP_EA)
B15: term premium on long-term interest rate | C15: TERM | D15: I_LT - I_ST
B16: historical average / long-term term premium | C16: TERM_STAR | D16: average of term between 1999 and 2014
B17: risk premium | C17: RISK | D17: PHI_RISK * D_RATIO(-1) / D_RATIO_STAR
B18: short-term real interest rate | C18: R_ST | D18: I_ST - PI
B19: long-term real interest rate | C19: R_LT | D19: I_LT - PI
A20: Fiscal | B20: share of short term debt | C20: ALPHA_ST | D20: D_ST / D
B21: implicit long-term interest rate | C21: IIR_LT | D21: (IIR - ALPHA_ST(-1) * I_ST) / (1 - ALPHA_ST(-1))
B22: parameter: share of new debt issued as short-term debt | C22: D_SHARE_ST | D22: 3 year historical average of ALPHA_ST
B23: repayments, short-term | C23: REP_ST | D23: = D_ST(-1)
B24: repayments, long-term | C24: REP_LT | D24: D_residual_maturity_ST(-1) - D_ST(-1)
B25: repayments | C25: REP | D25: REP_ST + REP_LT
B26: new short-term debt | C26: D_STN | D26: = D_ST
B27: new long-term debt | C27: D_LTN | D27: D_LT - D_LT(-1) + REP_LT
B28: share of new debt in long-term debt | C28: BETA_LT | D28: D_LTN / D_LT
B29: parameter: long-term debt maturing share | C29: PHI_LT | D29: converges over 10 years from BETA_LT to 6 year historical average of BETA_LT
B30: gross financing needs | C30: GFN | D30: INT + REP - PB + SF
B31: parameter: share of stock flow adjustments | C31: SF_RATIO | D31: SF / GDP nominal * 100, 0 after 2025

Sheet Austria
A1: YEAR | B1: Y_STAR | C1: SR | D1: SR_TREND | E1: SR_SLOPE | F1: RHO_SR | G1: OMEGA_SR | H1: CUBS | I1: WP_EUCAM | J1: WP_PROJ | K1: WP | L1: LP | M1: LP_TREND | N1: LP_SLOPE | O1: LP_TREND_EUCAM | P1: LP_AWG_GROWTH_EUCAM | Q1: LP_AWG | R1: U | S1: U_TREND | T1: U_SLOPE | U1: U_TREND_EUCAM | V1: STRUCT_U_EUCAM | W1: dlprod | X1: dpcegdp | Y1: endo_dwinf | Z1: H | AA1: H_TREND | AB1: H_SLOPE | AC1: H_TREND_EUCAM | AD1: K | AE1: K_EUROSTAT | AF1: K_G_EUROSTAT | AG1: K_SPLIT | AH1: K_G | AI1: I_G_REAL | AJ1: DEPR_G_NOM | AK1: DEPR_G | AL1: DEPR_G_RATIO | AM1: DELTA_G | AN1: K_M | AO1: I_M_NOM | AP1: I_M | AQ1: DEPR_TOTAL_NOM | AR1: DEPR_M | AS1: DELTA_M | AT1: IQ_M | AU1: PHI_IQ_M_0 | AV1: PHI_IQ_M_1 | AW1: PHI_IQ_M_2 | AX1: LAMBDA_IQ_M_1 | AY1: LAMBDA_IQ_M_2 | AZ1: LAMBDA_IQ_M_3 | BA1: LAMBDA_IQ_M_4 | BB1: Y_D | BC1: Y_D_NOM | BD1: Y_GAP | BE1: BETA_D | BF1: LAMBDA_R | BG1: LAMBDA_I_G | BH1: LAMBDA_G | BI1: LAMBDA_S | BJ1: LAMBDA_TR | BK1: LAMBDA_T_HH | BL1: LAMBDA_T_F | BM1: LAMBDA_T_C | BN1: PB | BO1: PB_RATIO | BP1: GR | BQ1: taxes_income_wealth | BR1: T_HH_ECB | BS1: T_non-finan_corp | BT1: T_finan_corp | BU1: T_HH | BV1: T_F | BW1: T_C | BX1: SC_actual | BY1: SC_HH_ECB | BZ1: SC_F_ECB | CA1: SC_HH | CB1: SC_F | CC1: SC_IMP | CD1: NonT | CE1: GE | CF1: PE | CG1: G | CH1: I_G | CI1: SUB | CJ1: TR | CK1: INT | CL1: OTHER_PE | CM1: TAU_HH_STAR | CN1: TAU_F_STAR | CO1: TAU_C_STAR | CP1: TAU_SC_HH_STAR | CQ1: TAU_SC_F_STAR | CR1: TAU_SC_IMP_STAR | CS1: TAU_NON_T_STAR | CT1: S_G_STAR | CU1: S_IG_STAR | CV1: S_SUB_STAR | CW1: S_TR_STAR | CX1: S_OTHER_PE_STAR | CY1: ALPHA_HH | CZ1: ALPHA_F | DA1: ALPHA_C | DB1: ALPHA_SC_HH | DC1: ALPHA_SC_F | DD1: ALPHA_SC_IMP | DE1: ALPHA_NON_T | DF1: ALPHA_G | DG1: ALPHA_IG | DH1: ALPHA_SUB | DI1: ALPHA_TR | DJ1: ALPHA_OTHER_PE | DK1: D | DL1: D_RATIO | DM1: D_ST | DN1: D_LT | DO1: ALPHA_EUR | DP1: ALPHA_USD | DQ1: EXR_USD | DR1: SF | DS1: IIR | DT1: D_residual_maturity_ST | DU1: I_RATE | DV1: THETA_I | DW1: GDP_EA | DX1: SIGMA_I_1 | DY1: SIGMA_I_2 | DZ1: I_LT | EA1: PI_T | EB1: P_EA | EC1: PI_EA | ED1: Y_GAP_EA | EE1: I_LB | EF1: I_ST_10F | EG1: I_LT_10F | EH1: THETA_TERM | EI1: PHI_RISK | EJ1: D_RATIO_STAR | EK1: PI | EL1: BETA_PI_1 | EM1: BETA_PI_2 | EN1: P
A2: 1962 | W2: 0.020145346 | X2: 0.04762852 | AJ2: 248100000 | AM2: =AVERAGE($AL$35:$AL$63) -> 0.065166448 | AO2: 1619400000 | AQ2: 1002100000 | CH2: {=INDEX([1]Sheet1!$C$6:$CY$72,MATCH($A2,[1]Sheet1!$A$6:$A$72,0),MATCH(MID(CELL("filename",O1),FIND("]",CELL("filename",O1))+1,255) & CH$1,[1]Sheet1!$C$1:$CY$1 & [1]Sheet1!$C$3:$CY$3,0))} -> 418620000 | DQ2: 1.06981 | DR2: {=INDEX([1]Sheet1!$C$6:$CY$72,MATCH($A2,[1]Sheet1!$A$6:$A$72,0),MATCH(MID(CELL("filename",AZ1),FIND("]",CELL("filename",AZ1))+1,255) & DR$1,[1]Sheet1!$C$1:$CY$1 & [1]Sheet1!$C$3:$CY$3,0))} -> 0 | DS2: {=INDEX([1]Sheet1!$C$6:$CY$72,MATCH($A2,[1]Sheet1!$A$6:$A$72,0),MATCH(MID(CELL("filename",BA1),FIND("]",CELL("filename",BA1))+1,255) & DS$1,[1]Sheet1!$C$1:$CY$1 & [1]Sheet1!$C$3:$CY$3,0))} -> 0 | DU2: {=INDEX([1]Sheet1!$C$6:$CY$72,MATCH($A2,[1]Sheet1!$A$6:$A$72,0),MATCH(MID(CELL("filename",BC1),FIND("]",CELL("filename",BC1))+1,255) & DU$1,[1]Sheet1!$C$1:$CY$1 & [1]Sheet1!$C$3:$CY$3,0))} -> 0 | DV2: 0.5 | DX2: 1 | DY2: 0.5 | DZ2: {=INDEX([1]Sheet1!$C$6:$CY$72,MATCH($A2,[1]Sheet1!$A$6:$A$72,0),MATCH(MID(CELL("filename",BH1),FIND("]",CELL("filename",BH1))+1,255) & DZ$1,[1]Sheet1!$C$1:$CY$1 & [1]Sheet1!$C$3:$CY$3,0))} -> 0 | EA2: 2 | EH2: 0.75 | EI2: 0.05 | EJ2: 75
A3: 1963 | W3: 0.046661457 | X3: 0.038727325 | AJ3: 268220000 | AM3: =AVERAGE($AL$35:$AL$63) -> 0.065166448 | AO3: 1758600000 | AQ3: 1088700000 | CH3: {=INDEX([1]Sheet1!$C$6:$CY$72,MATCH($A3,[1]Sheet1!$A$6:$A$72,0),MATCH(MID(CELL("filename",O2),FIND("]",CELL("filename",O2))+1,255) & CH$1,[1]Sheet1!$C$1:$CY$1 & [1]Sheet1!$C$3:$CY$3,0))} -> 458510000 | DQ3: 1.06981 | DR3: {=INDEX([1]Sheet1!$C$6:$CY$72,MATCH($A3,[1]Sheet1!$A$6:$A$72,0),MATCH(MID(CELL("filename",AZ2),FIND("]",CELL("filename",AZ2))+1,255) & DR$1,[1]Sheet1!$C$1:$CY$1 & [1]Sheet1!$C$3:$CY$3,0))} -> 0 | DS3: {=INDEX([1]Sheet1!$C$6:$CY$72,MATCH($A3,[1]Sheet1!$A$6:$A$72,0),MATCH(MID(CELL("filename",BA2),FIND("]",CELL("filename",BA2))+1,255) & DS$1,[1]Sheet1!$C$1:$CY$1 & [1]Sheet1!$C$3:$CY$3,0))} -> 0 | DU3: {=INDEX([1]Sheet1!$C$6:$CY$72,MATCH($A3,[1]Sheet1!$A$6:$A$72,0),MATCH(MID(CELL("filename",BC2),FIND("]",CELL("filename",BC2))+1,255) & DU$1,[1]Sheet1!$C$1:$CY$1 & [1]Sheet1!$C$3:$CY$3,0))} -> 0 | DV3: 0.5 | DX3: 1 | DY3: 0.5 | DZ3: {=INDEX([1]Sheet1!$C$6:$CY$72,MATCH($A3,[1]Sheet1!$A$6:$A$72,0),MATCH(MID(CELL("filename",BH2),FIND("]",CELL("filename",BH2))+1,255) & DZ$1,[1]Sheet1!$C$1:$CY$1 & [1]Sheet1!$C$3:$CY$3,0))} -> 0 | EA3: 2 | EH3: 0.75 | EI3: 0.05 | EJ3: 75
A4: 1964 | W4: 0.061708767 | X4: 0.04327294 | AJ4: 283310000 | AM4: =AVERAGE($AL$35:$AL$63) -> 0.065166448 | AO4: 1938300000 | AQ4: 1181000000 | CH4: {=INDEX([1]Sheet1!$C$6:$CY$72,MATCH($A4,[1]Sheet1!$A$6:$A$72,0),MATCH(MID(CELL("filename",O3),FIND("]",CELL("filename",O3))+1,255) & CH$1,[1]Sheet1!$C$1:$CY$1 & [1]Sheet1!$C$3:$CY$3,0))} -> 5.3072e+08 | DQ4: 1.06981 | DR4: {=INDEX([1]Sheet1!$C$6:$CY$72,MATCH($A4,[1]Sheet1!$A$6:$A$72,0),MATCH(MID(CELL("filename",AZ3),FIND("]",CELL("filename",AZ3))+1,255) & DR$1,[1]Sheet1!$C$1:$CY$1 & [1]Sheet1!$C$3:$CY$3,0))} -> 0 | DS4: {=INDEX([1]Sheet1!$C$6:$CY$72,MATCH($A4,[1]Sheet1!$A$6:$A$72,0),MATCH(MID(CELL("filename",BA3),FIND("]",CELL("filename",BA3))+1,255) & DS$1,[1]Sheet1!$C$1:$CY$1 & [1]Sheet1!$C$3:$CY$3,0))} -> 0 | DU4: {=INDEX([1]Sheet1!$C$6:$CY$72,MATCH($A4,[1]Sheet1!$A$6:$A$72,0),MATCH(MID(CELL("filename",BC3),FIND("]",CELL("filename",BC3))+1,255) & DU$1,[1]Sheet1!$C$1:$CY$1 & [1]Sheet1!$C$3:$CY$3,0))} -> 0 | DV4: 0.5 | DX4: 1 | DY4: 0.5 | DZ4: {=INDEX([1]Sheet1!$C$6:$CY$72,MATCH($A4,[1]Sheet1!$A$6:$A$72,0),MATCH(MID(CELL("filename",BH3),FIND("]",CELL("filename",BH3))+1,255) & DZ$1,[1]Sheet1!$C$1:$CY$1 & [1]Sheet1!$C$3:$CY$3,0))} -> 0 | EA4: 2 | EH4: 0.75 | EI4: 0.05 | EJ4: 75
A5: 1965 | B5: =[2]EUCAM_output!$E2*10^9 -> 1.0364351e+11 | I5: =[2]EUCAM_output!$W2*10^3 -> 5250163 | K5: =IF(A5<2030,I5,K4*J5/J4) -> 5250163 | L5: =[2]EUCAM_output!$G2 -> 65.05291 | O5: =[2]EUCAM_output!$H2 -> 64.545558 | R5: =[2]EUCAM_output!$L2 -> 1.6 | U5: =[2]EUCAM_output!$K2 -> 1.3885506 | V5: 1.3885506 | W5: 0.035075862 | X5: 0.031476534 | Y5: =[2]EUCAM_output!$AI2 -> -0.0017574738 | Z5: =[2]EUCAM_output!$M2 -> 2005.2571 | AC5: =[2]EUCAM_output!$AL2 -> 2009.1425 | AD5: =[2]EUCAM_output!$T2*10^9 -> 2.992678e+11 | AJ5: 316840000 | AM5: =AVERAGE($AL$35:$AL$63) -> 0.065166448 | AO5: 2187000000 | AP5: =AO5/EN5 -> 2.3766215e+10 | AQ5: 1307400000 | AR5: =(AQ5-AJ5)/EN5 -> 1.0764455e+10 | BB5: 1.0200195e+11 | BC5: =[2]EUCAM_output!$AG2*10^9 -> 1.897354e+10 | BD5: =(BB5-B5)/B5*100 -> -1.5838576 | CH5: {=INDEX([1]Sheet1!$C$6:$CY$72,MATCH($A5,[1]Sheet1!$A$6:$A$72,0),MATCH(MID(CELL("filename",O4),FIND("]",CELL("filename",O4))+1,255) & CH$1,[1]Sheet1!$C$1:$CY$1 & [1]Sheet1!$C$3:$CY$3,0))} -> 588290000 | DQ5: 1.06981 | DR5: {=INDEX([1]Sheet1!$C$6:$CY$72,MATCH($A5,[1]Sheet1!$A$6:$A$72,0),MATCH(MID(CELL("filename",AZ4),FIND("]",CELL("filename",AZ4))+1,255) & DR$1,[1]Sheet1!$C$1:$CY$1 & [1]Sheet1!$C$3:$CY$3,0))} -> 0 | DS5: {=INDEX([1]Sheet1!$C$6:$CY$72,MATCH($A5,[1]Sheet1!$A$6:$A$72,0),MATCH(MID(CELL("filename",BA4),FIND("]",CELL("filename",BA4))+1,255) & DS$1,[1]Sheet1!$C$1:$CY$1 & [1]Sheet1!$C$3:$CY$3,0))} -> 0 | DU5: {=INDEX([1]Sheet1!$C$6:$CY$72,MATCH($A5,[1]Sheet1!$A$6:$A$72,0),MATCH(MID(CELL("filename",BC4),FIND("]",CELL("filename",BC4))+1,255) & DU$1,[1]Sheet1!$C$1:$CY$1 & [1]Sheet1!$C$3:$CY$3,0))} -> 0 | DV5: 0.5 | DW5: =Euro_Area_Data!V2*10^9 -> #N/A | DX5: 1 | DY5: 0.5 | DZ5: {=INDEX([1]Sheet1!$C$6:$CY$72,MATCH($A5,[1]Sheet1!$A$6:$A$72,0),MATCH(MID(CELL("filename",BH4),FIND("]",CELL("filename",BH4))+1,255) & DZ$1,[1]Sheet1!$C$1:$CY$1 & [1]Sheet1!$C$3:$CY$3,0))} -> 6.51 | EA5: 2 | EE5: -5 | EH5: 0.75 | EI5: 0.05 | EJ5: 75 | EN5: =[2]EUCAM_output!$AE2 -> 0.092021383
A6: 1966 | B6: =[2]EUCAM_output!$E3*10^9 -> 1.0826854e+11 | I6: =[2]EUCAM_output!$W3*10^3 -> 5265008.5 | K6: =IF(A6<2030,I6,K5*J6/J5) -> 5265008.5 | L6: =[2]EUCAM_output!$G3 -> 64.169299 | O6: =[2]EUCAM_output!$H3 -> 63.820409 | R6: =[2]EUCAM_output!$L3 -> 1.5 | U6: =[2]EUCAM_output!$K3 -> 1.3347745 | V6: 1.3347745 | W6: 0.066872852 | X6: 0.023475123 | Y6: =[2]EUCAM_output!$AI3 -> 0.0019316627 | Z6: =[2]EUCAM_output!$M3 -> 1995.9261 | AC6: =[2]EUCAM_output!$AL3 -> 1993.3413 | AD6: =[2]EUCAM_output!$T3*10^9 -> 3.1180181e+11 | AI6: =CH6/EN6 -> 6.6730047e+09 | AJ6: 336950000 | AK6: =AJ6/EN6 -> 3.5507935e+09 | AM6: =AVERAGE($AL$35:$AL$63) -> 0.065166448 | AO6: 2440800000 | AP6: =AO6/EN6 -> 2.5721254e+10 | AQ6: 1410600000 | AR6: =(AQ6-AJ6)/EN6 -> 1.1314169e+10 | BB6: 1.077579e+11 | BC6: =[2]EUCAM_output!$AG3*10^9 -> 2.0670067e+10 | BD6: =(BB6-B6)/B6*100 -> -0.47164484 | CH6: {=INDEX([1]Sheet1!$C$6:$CY$72,MATCH($A6,[1]Sheet1!$A$6:$A$72,0),MATCH(MID(CELL("filename",O5),FIND("]",CELL("filename",O5))+1,255) & CH$1,[1]Sheet1!$C$1:$CY$1 & [1]Sheet1!$C$3:$CY$3,0))} -> 633230000 | DQ6: 1.06981 | DR6: {=INDEX([1]Sheet1!$C$6:$CY$72,MATCH($A6,[1]Sheet1!$A$6:$A$72,0),MATCH(MID(CELL("filename",AZ5),FIND("]",CELL("filename",AZ5))+1,255) & DR$1,[1]Sheet1!$C$1:$CY$1 & [1]Sheet1!$C$3:$CY$3,0))} -> 0 | DS6: {=INDEX([1]Sheet1!$C$6:$CY$72,MATCH($A6,[1]Sheet1!$A$6:$A$72,0),MATCH(MID(CELL("filename",BA5),FIND("]",CELL("filename",BA5))+1,255) & DS$1,[1]Sheet1!$C$1:$CY$1 & [1]Sheet1!$C$3:$CY$3,0))} -> 0 | DU6: {=INDEX([1]Sheet1!$C$6:$CY$72,MATCH($A6,[1]Sheet1!$A$6:$A$72,0),MATCH(MID(CELL("filename",BC5),FIND("]",CELL("filename",BC5))+1,255) & DU$1,[1]Sheet1!$C$1:$CY$1 & [1]Sheet1!$C$3:$CY$3,0))} -> 0 | DV6: 0.5 | DW6: =Euro_Area_Data!V3*10^9 -> #N/A | DX6: 1 | DY6: 0.5 | DZ6: {=INDEX([1]Sheet1!$C$6:$CY$72,MATCH($A6,[1]Sheet1!$A$6:$A$72,0),MATCH(MID(CELL("filename",BH5),FIND("]",CELL("filename",BH5))+1,255) & DZ$1,[1]Sheet1!$C$1:$CY$1 & [1]Sheet1!$C$3:$CY$3,0))} -> 6.91 | EA6: 2 | EE6: -5 | EH6: 0.75 | EI6: 0.05 | EJ6: 75 | EK6: =(EN6-EN5)/EN5*100 -> 3.1219914 | EN6: =[2]EUCAM_output!$AE3 -> 0.094894283
A7: 1967 | B7: =[2]EUCAM_output!$E4*10^9 -> 1.129524e+11 | I7: =[2]EUCAM_output!$W4*10^3 -> 5282658.5 | K7: =IF(A7<2030,I7,K6*J7/J6) -> 5282658.5 | L7: =[2]EUCAM_output!$G4 -> 62.833244 | O7: =[2]EUCAM_output!$H4 -> 63.145994 | R7: =[2]EUCAM_output!$L4 -> 1.5 | U7: =[2]EUCAM_output!$K4 -> 1.280036 | V7: 1.280036 | W7: 0.048464971 | X7: 0.029641486 | Y7: =[2]EUCAM_output!$AI4 -> 0.0019664909 | Z7: =[2]EUCAM_output!$M4 -> 1986.1608 | AC7: =[2]EUCAM_output!$AL4 -> 1977.1517 | AD7: =[2]EUCAM_output!$T4*10^9 -> 3.2331192e+11 | AI7: =CH7/EN7 -> 7.426873e+09 | AJ7: 378950000 | AK7: =AJ7/EN7 -> 3.8497182e+09 | AM7: =AVERAGE($AL$35:$AL$63) -> 0.065166448 | AO7: 2428600000 | AP7: =AO7/EN7 -> 2.4671924e+10 | AQ7: 1566900000 | AR7: =(AQ7-AJ7)/EN7 -> 1.2068275e+10 | BB7: 1.109989e+11 | BC7: =[2]EUCAM_output!$AG4*10^9 -> 2.1983259e+10 | BD7: =(BB7-B7)/B7*100 -> -1.7294904 | CH7: {=INDEX([1]Sheet1!$C$6:$CY$72,MATCH($A7,[1]Sheet1!$A$6:$A$72,0),MATCH(MID(CELL("filename",O6),FIND("]",CELL("filename",O6))+1,255) & CH$1,[1]Sheet1!$C$1:$CY$1 & [1]Sheet1!$C$3:$CY$3,0))} -> 731070000 | DQ7: 1.064817 | DR7: {=INDEX([1]Sheet1!$C$6:$CY$72,MATCH($A7,[1]Sheet1!$A$6:$A$72,0),MATCH(MID(CELL("filename",AZ6),FIND("]",CELL("filename",AZ6))+1,255) & DR$1,[1]Sheet1!$C$1:$CY$1 & [1]Sheet1!$C$3:$CY$3,0))} -> 0 | DS7: {=INDEX([1]Sheet1!$C$6:$CY$72,MATCH($A7,[1]Sheet1!$A$6:$A$72,0),MATCH(MID(CELL("filename",BA6),FIND("]",CELL("filename",BA6))+1,255) & DS$1,[1]Sheet1!$C$1:$CY$1 & [1]Sheet1!$C$3:$CY$3,0))} -> 0 | DU7: {=INDEX([1]Sheet1!$C$6:$CY$72,MATCH($A7,[1]Sheet1!$A$6:$A$72,0),MATCH(MID(CELL("filename",BC6),FIND("]",CELL("filename",BC6))+1,255) & DU$1,[1]Sheet1!$C$1:$CY$1 & [1]Sheet1!$C$3:$CY$3,0))} -> 4.75 | DV7: 0.5 | DW7: =Euro_Area_Data!V4*10^9 -> #N/A | DX7: 1 | DY7: 0.5 | DZ7: {=INDEX([1]Sheet1!$C$6:$CY$72,MATCH($A7,[1]Sheet1!$A$6:$A$72,0),MATCH(MID(CELL("filename",BH6),FIND("]",CELL("filename",BH6))+1,255) & DZ$1,[1]Sheet1!$C$1:$CY$1 & [1]Sheet1!$C$3:$CY$3,0))} -> 7.22 | EA7: 2 | EE7: -5 | EH7: 0.75 | EI7: 0.05 | EJ7: 75 | EK7: =(EN7-EN6)/EN6*100 -> 3.7320395 | EN7: =[2]EUCAM_output!$AE4 -> 0.098435775
A8: 1968 | B8: =[2]EUCAM_output!$E5*10^9 -> 1.1768782e+11 | I8: =[2]EUCAM_output!$W5*10^3 -> 5289687 | K8: =IF(A8<2030,I8,K7*J8/J7) -> 5289687 | L8: =[2]EUCAM_output!$G5 -> 62.101917 | O8: =[2]EUCAM_output!$H5 -> 62.607938 | R8: =[2]EUCAM_output!$L5 -> 1.7 | U8: =[2]EUCAM_output!$K5 -> 1.22466 | V8: 1.22466 | W8: 0.057769949 | X8: 0.0260883 | Y8: =[2]EUCAM_output!$AI5 -> -0.022069905 | Z8: =[2]EUCAM_output!$M5 -> 1972.3733 | AC8: =[2]EUCAM_output!$AL5 -> 1960.4434 | AD8: =[2]EUCAM_output!$T5*10^9 -> 3.3480634e+11 | AI8: =CH8/EN8 -> 7.5226176e+09 | AJ8: 409620000 | AK8: =AJ8/EN8 -> 3.9099285e+09 | AM8: =AVERAGE($AL$35:$AL$63) -> 0.065166448 | AO8: 2604400000 | AP8: =AO8/EN8 -> 2.4859669e+10 | AQ8: 1703300000 | AR8: =(AQ8-AJ8)/EN8 -> 1.2348509e+10 | BB8: 1.1596319e+11 | BC8: =[2]EUCAM_output!$AG5*10^9 -> 2.3618205e+10 | BD8: =(BB8-B8)/B8*100 -> -1.4654245 | CH8: {=INDEX([1]Sheet1!$C$6:$CY$72,MATCH($A8,[1]Sheet1!$A$6:$A$72,0),MATCH(MID(CELL("filename",O7),FIND("]",CELL("filename",O7))+1,255) & CH$1,[1]Sheet1!$C$1:$CY$1 & [1]Sheet1!$C$3:$CY$3,0))} -> 788100000 | DQ8: 1.02889 | DR8: {=INDEX([1]Sheet1!$C$6:$CY$72,MATCH($A8,[1]Sheet1!$A$6:$A$72,0),MATCH(MID(CELL("filename",AZ7),FIND("]",CELL("filename",AZ7))+1,255) & DR$1,[1]Sheet1!$C$1:$CY$1 & [1]Sheet1!$C$3:$CY$3,0))} -> 0 | DS8: {=INDEX([1]Sheet1!$C$6:$CY$72,MATCH($A8,[1]Sheet1!$A$6:$A$72,0),MATCH(MID(CELL("filename",BA7),FIND("]",CELL("filename",BA7))+1,255) & DS$1,[1]Sheet1!$C$1:$CY$1 & [1]Sheet1!$C$3:$CY$3,0))} -> 0 | DU8: {=INDEX([1]Sheet1!$C$6:$CY$72,MATCH($A8,[1]Sheet1!$A$6:$A$72,0),MATCH(MID(CELL("filename",BC7),FIND("]",CELL("filename",BC7))+1,255) & DU$1,[1]Sheet1!$C$1:$CY$1 & [1]Sheet1!$C$3:$CY$3,0))} -> 4.14 | DV8: 0.5 | DW8: =Euro_Area_Data!V5*10^9 -> #N/A | DX8: 1 | DY8: 0.5 | DZ8: {=INDEX([1]Sheet1!$C$6:$CY$72,MATCH($A8,[1]Sheet1!$A$6:$A$72,0),MATCH(MID(CELL("filename",BH7),FIND("]",CELL("filename",BH7))+1,255) & DZ$1,[1]Sheet1!$C$1:$CY$1 & [1]Sheet1!$C$3:$CY$3,0))} -> 7.74 | EA8: 2 | EE8: -5 | EH8: 0.75 | EI8: 0.05 | EJ8: 75 | EK8: =(EN8-EN7)/EN7*100 -> 6.4288513 | EN8: =[2]EUCAM_output!$AE5 -> 0.10476406
A9: 1969 | B9: =[2]EUCAM_output!$E6*10^9 -> 1.2262414e+11 | I9: =[2]EUCAM_output!$W6*10^3 -> 5289343.5 | K9: =IF(A9<2030,I9,K8*J9/J8) -> 5289343.5 | L9: =[2]EUCAM_output!$G6 -> 62.044722 | O9: =[2]EUCAM_output!$H6 -> 62.260591 | R9: =[2]EUCAM_output!$L6 -> 1.7 | U9: =[2]EUCAM_output!$K6 -> 1.164066 | V9: 1.164066 | W9: 0.063810442 | X9: 0.031915588 | Y9: =[2]EUCAM_output!$AI6 -> 0.0098573205 | Z9: =[2]EUCAM_output!$M6 -> 1958.5649 | AC9: =[2]EUCAM_output!$AL6 -> 1943.9874 | AD9: =[2]EUCAM_output!$T6*10^9 -> 3.4687575e+11 | AI9: =CH9/EN9 -> 7.5859396e+09 | AJ9: 408790000 | AK9: =AJ9/EN9 -> 3.7734467e+09 | AM9: =AVERAGE($AL$35:$AL$63) -> 0.065166448 | AO9: 2808300000 | AP9: =AO9/EN9 -> 2.5922773e+10 | AQ9: 1853100000 | AR9: =(AQ9-AJ9)/EN9 -> 1.3332094e+10 | BB9: 1.2324123e+11 | BC9: =[2]EUCAM_output!$AG6*10^9 -> 2.5786588e+10 | BD9: =(BB9-B9)/B9*100 -> 0.50324034 | CH9: {=INDEX([1]Sheet1!$C$6:$CY$72,MATCH($A9,[1]Sheet1!$A$6:$A$72,0),MATCH(MID(CELL("filename",O8),FIND("]",CELL("filename",O8))+1,255) & CH$1,[1]Sheet1!$C$1:$CY$1 & [1]Sheet1!$C$3:$CY$3,0))} -> 821810000 | DQ9: 1.022187 | DR9: {=INDEX([1]Sheet1!$C$6:$CY$72,MATCH($A9,[1]Sheet1!$A$6:$A$72,0),MATCH(MID(CELL("filename",AZ8),FIND("]",CELL("filename",AZ8))+1,255) & DR$1,[1]Sheet1!$C$1:$CY$1 & [1]Sheet1!$C$3:$CY$3,0))} -> 0 | DS9: {=INDEX([1]Sheet1!$C$6:$CY$72,MATCH($A9,[1]Sheet1!$A$6:$A$72,0),MATCH(MID(CELL("filename",BA8),FIND("]",CELL("filename",BA8))+1,255) & DS$1,[1]Sheet1!$C$1:$CY$1 & [1]Sheet1!$C$3:$CY$3,0))} -> 0 | DU9: {=INDEX([1]Sheet1!$C$6:$CY$72,MATCH($A9,[1]Sheet1!$A$6:$A$72,0),MATCH(MID(CELL("filename",BC8),FIND("]",CELL("filename",BC8))+1,255) & DU$1,[1]Sheet1!$C$1:$CY$1 & [1]Sheet1!$C$3:$CY$3,0))} -> 4.49 | DV9: 0.5 | DW9: =Euro_Area_Data!V6*10^9 -> #N/A | DX9: 1 | DY9: 0.5 | DZ9: {=INDEX([1]Sheet1!$C$6:$CY$72,MATCH($A9,[1]Sheet1!$A$6:$A$72,0),MATCH(MID(CELL("filename",BH8),FIND("]",CELL("filename",BH8))+1,255) & DZ$1,[1]Sheet1!$C$1:$CY$1 & [1]Sheet1!$C$3:$CY$3,0))} -> 7.52 | EA9: 2 | EE9: -5 | EH9: 0.75 | EI9: 0.05 | EJ9: 75 | EK9: =(EN9-EN8)/EN8*100 -> 3.4069431 | EN9: =[2]EUCAM_output!$AE6 -> 0.10833332
A10: 1970 | B10: =[2]EUCAM_output!$E7*10^9 -> 1.281897e+11 | I10: =[2]EUCAM_output!$W7*10^3 -> 5297592 | K10: =IF(A10<2030,I10,K9*J10/J9) -> 5297592 | L10: =[2]EUCAM_output!$G7 -> 61.795088 | O10: =[2]EUCAM_output!$H7 -> 62.1077 | R10: =[2]EUCAM_output!$L7 -> 1.1 | U10: =[2]EUCAM_output!$K7 -> 1.093997 | V10: 1.093997 | W10: 0.067366127 | X10: 0.023764645 | Y10: =[2]EUCAM_output!$AI7 -> -0.0029240582 | Z10: =[2]EUCAM_output!$M7 -> 1897.1867 | AC10: =[2]EUCAM_output!$AL7 -> 1929.7474 | AD10: =[2]EUCAM_output!$T7*10^9 -> 3.6093085e+11 | AI10: =CH10/EN10 -> 8.1646164e+09 | AJ10: 456150000 | AK10: =AJ10/EN10 -> 4.0201312e+09 | AM10: =AVERAGE($AL$35:$AL$63) -> 0.065166448 | AO10: 3270100000 | AP10: =AO10/EN10 -> 2.8819974e+10 | AQ10: 2028400000 | AR10: =(AQ10-AJ10)/EN10 -> 1.3856519e+10 | BB10: 1.320195e+11 | BC10: =[2]EUCAM_output!$AG7*10^9 -> 2.8933321e+10 | BD10: =(BB10-B10)/B10*100 -> 2.9876053 | CH10: {=INDEX([1]Sheet1!$C$6:$CY$72,MATCH($A10,[1]Sheet1!$A$6:$A$72,0),MATCH(MID(CELL("filename",O9),FIND("]",CELL("filename",O9))+1,255) & CH$1,[1]Sheet1!$C$1:$CY$1 & [1]Sheet1!$C$3:$CY$3,0))} -> 926410000 | DQ10: 1.022227 | DR10: {=INDEX([1]Sheet1!$C$6:$CY$72,MATCH($A10,[1]Sheet1!$A$6:$A$72,0),MATCH(MID(CELL("filename",AZ9),FIND("]",CELL("filename",AZ9))+1,255) & DR$1,[1]Sheet1!$C$1:$CY$1 & [1]Sheet1!$C$3:$CY$3,0))} -> 0 | DS10: {=INDEX([1]Sheet1!$C$6:$CY$72,MATCH($A10,[1]Sheet1!$A$6:$A$72,0),MATCH(MID(CELL("filename",BA9),FIND("]",CELL("filename",BA9))+1,255) & DS$1,[1]Sheet1!$C$1:$CY$1 & [1]Sheet1!$C$3:$CY$3,0))} -> 0 | DU10: {=INDEX([1]Sheet1!$C$6:$CY$72,MATCH($A10,[1]Sheet1!$A$6:$A$72,0),MATCH(MID(CELL("filename",BC9),FIND("]",CELL("filename",BC9))+1,255) & DU$1,[1]Sheet1!$C$1:$CY$1 & [1]Sheet1!$C$3:$CY$3,0))} -> 5.62 | DV10: 0.5 | DW10: =Euro_Area_Data!V7*10^9 -> #N/A | DX10: 1 | DY10: 0.5 | DZ10: {=INDEX([1]Sheet1!$C$6:$CY$72,MATCH($A10,[1]Sheet1!$A$6:$A$72,0),MATCH(MID(CELL("filename",BH9),FIND("]",CELL("filename",BH9))+1,255) & DZ$1,[1]Sheet1!$C$1:$CY$1 & [1]Sheet1!$C$3:$CY$3,0))} -> 7.82 | EA10: 2 | EE10: -5 | EH10: 0.75 | EI10: 0.05 | EJ10: 75 | EK10: =(EN10-EN9)/EN9*100 -> 4.7382731 | EN10: =[2]EUCAM_output!$AE7 -> 0.11346645
A11: 1971 | B11: =[2]EUCAM_output!$E8*10^9 -> 1.3469051e+11 | I11: =[2]EUCAM_output!$W8*10^3 -> 5319969.5 | K11: =IF(A11<2030,I11,K10*J11/J10) -> 5319969.5 | L11: =[2]EUCAM_output!$G8 -> 62.178198 | O11: =[2]EUCAM_output!$H8 -> 62.131424 | R11: =[2]EUCAM_output!$L8 -> 1 | U11: =[2]EUCAM_output!$K8 -> 1.036013 | V11: 1.036013 | W11: 0.039209843 | X11: 0.012186416 | Y11: =[2]EUCAM_output!$AI8 -> 0.045715548 | Z11: =[2]EUCAM_output!$M8 -> 1891.4112 | AC11: =[2]EUCAM_output!$AL8 -> 1921.1451 | AD11: =[2]EUCAM_output!$T8*10^9 -> 3.7829696e+11 | AI11: =CH11/EN11 -> 9.2136534e+09 | AJ11: 537910000 | AK11: =AJ11/EN11 -> 4.3966434e+09 | AM11: =AVERAGE($AL$35:$AL$63) -> 0.065166448 | AO11: 3996800000 | AP11: =AO11/EN11 -> 3.2668113e+10 | AQ11: 2172300000 | AR11: =(AQ11-AJ11)/EN11 -> 1.3358796e+10 | BB11: 1.3876983e+11 | BC11: =[2]EUCAM_output!$AG8*10^9 -> 3.2300203e+10 | BD11: =(BB11-B11)/B11*100 -> 3.0286553 | CH11: {=INDEX([1]Sheet1!$C$6:$CY$72,MATCH($A11,[1]Sheet1!$A$6:$A$72,0),MATCH(MID(CELL("filename",O10),FIND("]",CELL("filename",O10))+1,255) & CH$1,[1]Sheet1!$C$1:$CY$1 & [1]Sheet1!$C$3:$CY$3,0))} -> 1127250000 | DQ11: 1.04776 | DR11: {=INDEX([1]Sheet1!$C$6:$CY$72,MATCH($A11,[1]Sheet1!$A$6:$A$72,0),MATCH(MID(CELL("filename",AZ10),FIND("]",CELL("filename",AZ10))+1,255) & DR$1,[1]Sheet1!$C$1:$CY$1 & [1]Sheet1!$C$3:$CY$3,0))} -> 0 | DS11: {=INDEX([1]Sheet1!$C$6:$CY$72,MATCH($A11,[1]Sheet1!$A$6:$A$72,0),MATCH(MID(CELL("filename",BA10),FIND("]",CELL("filename",BA10))+1,255) & DS$1,[1]Sheet1!$C$1:$CY$1 & [1]Sheet1!$C$3:$CY$3,0))} -> 0 | DU11: {=INDEX([1]Sheet1!$C$6:$CY$72,MATCH($A11,[1]Sheet1!$A$6:$A$72,0),MATCH(MID(CELL("filename",BC10),FIND("]",CELL("filename",BC10))+1,255) & DU$1,[1]Sheet1!$C$1:$CY$1 & [1]Sheet1!$C$3:$CY$3,0))} -> 4.39 | DV11: 0.5 | DW11: =Euro_Area_Data!V8*10^9 -> #N/A | DX11: 1 | DY11: 0.5 | DZ11: {=INDEX([1]Sheet1!$C$6:$CY$72,MATCH($A11,[1]Sheet1!$A$6:$A$72,0),MATCH(MID(CELL("filename",BH10),FIND("]",CELL("filename",BH10))+1,255) & DZ$1,[1]Sheet1!$C$1:$CY$1 & [1]Sheet1!$C$3:$CY$3,0))} -> 7.71 | EA11: 2 | EE11: -5 | EH11: 0.75 | EI11: 0.05 | EJ11: 75 | EK11: =(EN11-EN10)/EN10*100 -> 7.8253617 | EN11: =[2]EUCAM_output!$AE8 -> 0.12234561
A12: 1972 | B12: =[2]EUCAM_output!$E9*10^9 -> 1.4217231e+11 | I12: =[2]EUCAM_output!$W9*10^3 -> 5356960.5 | K12: =IF(A12<2030,I12,K11*J12/J11) -> 5356960.5 | L12: =[2]EUCAM_output!$G9 -> 62.126296 | O12: =[2]EUCAM_output!$H9 -> 62.282662 | R12: =[2]EUCAM_output!$L9 -> 0.9 | U12: =[2]EUCAM_output!$K9 -> 0.990719 | V12: 0.990719 | W12: 0.054560679 | X12: 0.0017830222 | Y12: =[2]EUCAM_output!$AI9 -> -0.015973066 | Z12: =[2]EUCAM_output!$M9 -> 1912.4208 | AC12: =[2]EUCAM_output!$AL9 -> 1918.346 | AD12: =[2]EUCAM_output!$T9*10^9 -> 3.9976557e+11 | AI12: =CH12/EN12 -> 1.0246063e+10 | AJ12: 609600000 | AK12: =AJ12/EN12 -> 4.5867111e+09 | AM12: =AVERAGE($AL$35:$AL$63) -> 0.065166448 | AO12: 5040000000 | AP12: =AO12/EN12 -> 3.7921627e+10 | AQ12: 2416300000 | AR12: =(AQ12-AJ12)/EN12 -> 1.359385e+10 | BB12: 1.4738446e+11 | BC12: =[2]EUCAM_output!$AG9*10^9 -> 3.6912538e+10 | BD12: =(BB12-B12)/B12*100 -> 3.6660849 | CH12: {=INDEX([1]Sheet1!$C$6:$CY$72,MATCH($A12,[1]Sheet1!$A$6:$A$72,0),MATCH(MID(CELL("filename",O11),FIND("]",CELL("filename",O11))+1,255) & CH$1,[1]Sheet1!$C$1:$CY$1 & [1]Sheet1!$C$3:$CY$3,0))} -> 1361760000 | DQ12: 1.12178 | DR12: {=INDEX([1]Sheet1!$C$6:$CY$72,MATCH($A12,[1]Sheet1!$A$6:$A$72,0),MATCH(MID(CELL("filename",AZ11),FIND("]",CELL("filename",AZ11))+1,255) & DR$1,[1]Sheet1!$C$1:$CY$1 & [1]Sheet1!$C$3:$CY$3,0))} -> 0 | DS12: {=INDEX([1]Sheet1!$C$6:$CY$72,MATCH($A12,[1]Sheet1!$A$6:$A$72,0),MATCH(MID(CELL("filename",BA11),FIND("]",CELL("filename",BA11))+1,255) & DS$1,[1]Sheet1!$C$1:$CY$1 & [1]Sheet1!$C$3:$CY$3,0))} -> 0 | DU12: {=INDEX([1]Sheet1!$C$6:$CY$72,MATCH($A12,[1]Sheet1!$A$6:$A$72,0),MATCH(MID(CELL("filename",BC11),FIND("]",CELL("filename",BC11))+1,255) & DU$1,[1]Sheet1!$C$1:$CY$1 & [1]Sheet1!$C$3:$CY$3,0))} -> 5.17 | DV12: 0.5 | DW12: =Euro_Area_Data!V9*10^9 -> #N/A | DX12: 1 | DY12: 0.5 | DZ12: {=INDEX([1]Sheet1!$C$6:$CY$72,MATCH($A12,[1]Sheet1!$A$6:$A$72,0),MATCH(MID(CELL("filename",BH11),FIND("]",CELL("filename",BH11))+1,255) & DZ$1,[1]Sheet1!$C$1:$CY$1 & [1]Sheet1!$C$3:$CY$3,0))} -> 7.38 | EA12: 2 | EE12: -5 | EH12: 0.75 | EI12: 0.05 | EJ12: 75 | EK12: =(EN12-EN11)/EN11*100 -> 8.6313549 | EN12: =[2]EUCAM_output!$AE9 -> 0.13290569
A13: 1973 | B13: =[2]EUCAM_output!$E10*10^9 -> 1.4967003e+11 | I13: =[2]EUCAM_output!$W10*10^3 -> 5399117 | K13: =IF(A13<2030,I13,K12*J13/J12) -> 5399117 | L13: =[2]EUCAM_output!$G10 -> 62.672532 | O13: =[2]EUCAM_output!$H10 -> 62.516991 | R13: =[2]EUCAM_output!$L10 -> 0.9 | U13: =[2]EUCAM_output!$K10 -> 0.970604 | V13: 0.970604 | W13: 0.03161307 | X13: -0.011905162 | Y13: =[2]EUCAM_output!$AI10 -> 0.022597137 | Z13: =[2]EUCAM_output!$M10 -> 1902.2121 | AC13: =[2]EUCAM_output!$AL10 -> 1918.5422 | AD13: =[2]EUCAM_output!$T10*10^9 -> 4.204903e+11 | AI13: =CH13/EN13 -> 1.0018456e+10 | AJ13: 732760000 | AK13: =AJ13/EN13 -> 4.745915e+09 | AM13: =AVERAGE($AL$35:$AL$63) -> 0.065166448 | AO13: 5809800000 | AP13: =AO13/EN13 -> 3.7628715e+10 | AQ13: 2770300000 | AR13: =(AQ13-AJ13)/EN13 -> 1.319667e+10 | BB13: 1.5458759e+11 | BC13: =[2]EUCAM_output!$AG10*10^9 -> 4.1832773e+10 | BD13: =(BB13-B13)/B13*100 -> 3.2856015 | CH13: {=INDEX([1]Sheet1!$C$6:$CY$72,MATCH($A13,[1]Sheet1!$A$6:$A$72,0),MATCH(MID(CELL("filename",O12),FIND("]",CELL("filename",O12))+1,255) & CH$1,[1]Sheet1!$C$1:$CY$1 & [1]Sheet1!$C$3:$CY$3,0))} -> 1546830000 | DQ13: 1.23173 | DR13: {=INDEX([1]Sheet1!$C$6:$CY$72,MATCH($A13,[1]Sheet1!$A$6:$A$72,0),MATCH(MID(CELL("filename",AZ12),FIND("]",CELL("filename",AZ12))+1,255) & DR$1,[1]Sheet1!$C$1:$CY$1 & [1]Sheet1!$C$3:$CY$3,0))} -> 0 | DS13: {=INDEX([1]Sheet1!$C$6:$CY$72,MATCH($A13,[1]Sheet1!$A$6:$A$72,0),MATCH(MID(CELL("filename",BA12),FIND("]",CELL("filename",BA12))+1,255) & DS$1,[1]Sheet1!$C$1:$CY$1 & [1]Sheet1!$C$3:$CY$3,0))} -> 0 | DU13: {=INDEX([1]Sheet1!$C$6:$CY$72,MATCH($A13,[1]Sheet1!$A$6:$A$72,0),MATCH(MID(CELL("filename",BC12),FIND("]",CELL("filename",BC12))+1,255) & DU$1,[1]Sheet1!$C$1:$CY$1 & [1]Sheet1!$C$3:$CY$3,0))} -> 6.94 | DV13: 0.5 | DW13: =Euro_Area_Data!V10*10^9 -> #N/A | DX13: 1 | DY13: 0.5 | DZ13: {=INDEX([1]Sheet1!$C$6:$CY$72,MATCH($A13,[1]Sheet1!$A$6:$A$72,0),MATCH(MID(CELL("filename",BH12),FIND("]",CELL("filename",BH12))+1,255) & DZ$1,[1]Sheet1!$C$1:$CY$1 & [1]Sheet1!$C$3:$CY$3,0))} -> 8.25 | EA13: 2 | EE13: -5 | EH13: 0.75 | EI13: 0.05 | EJ13: 75 | EK13: =(EN13-EN12)/EN12*100 -> 16.171134 | EN13: =[2]EUCAM_output!$AE10 -> 0.15439805
A14: 1974 | B14: =[2]EUCAM_output!$E11*10^9 -> 1.5662384e+11 | I14: =[2]EUCAM_output!$W11*10^3 -> 5422011.5 | K14: =IF(A14<2030,I14,K13*J14/J13) -> 5422011.5 | L14: =[2]EUCAM_output!$G11 -> 63.127778 | O14: =[2]EUCAM_output!$H11 -> 62.774351 | R14: =[2]EUCAM_output!$L11 -> 1.1 | U14: =[2]EUCAM_output!$K11 -> 0.985529 | V14: 0.985529 | W14: 0.029662229 | X14: -0.0072064351 | Y14: =[2]EUCAM_output!$AI11 -> 0.0063791865 | Z14: =[2]EUCAM_output!$M11 -> 1987.0916 | AC14: =[2]EUCAM_output!$AL11 -> 1918.3332 | AD14: =[2]EUCAM_output!$T11*10^9 -> 4.4178968e+11 | AI14: =CH14/EN14 -> 1.0864732e+10 | AJ14: 958160000 | AK14: =AJ14/EN14 -> 5.1461267e+09 | AM14: =AVERAGE($AL$35:$AL$63) -> 0.065166448 | AO14: 7184000000 | AP14: =AO14/EN14 -> 3.8584135e+10 | AQ14: 3174200000 | AR14: =(AQ14-AJ14)/EN14 -> 1.1902002e+10 | BB14: 1.6068413e+11 | BC14: =[2]EUCAM_output!$AG11*10^9 -> 4.7613587e+10 | BD14: =(BB14-B14)/B14*100 -> 2.5923869 | CH14: {=INDEX([1]Sheet1!$C$6:$CY$72,MATCH($A14,[1]Sheet1!$A$6:$A$72,0),MATCH(MID(CELL("filename",O13),FIND("]",CELL("filename",O13))+1,255) & CH$1,[1]Sheet1!$C$1:$CY$1 & [1]Sheet1!$C$3:$CY$3,0))} -> 2022910000 | DQ14: 1.1927 | DR14: {=INDEX([1]Sheet1!$C$6:$CY$72,MATCH($A14,[1]Sheet1!$A$6:$A$72,0),MATCH(MID(CELL("filename",AZ13),FIND("]",CELL("filename",AZ13))+1,255) & DR$1,[1]Sheet1!$C$1:$CY$1 & [1]Sheet1!$C$3:$CY$3,0))} -> 0 | DS14: {=INDEX([1]Sheet1!$C$6:$CY$72,MATCH($A14,[1]Sheet1!$A$6:$A$72,0),MATCH(MID(CELL("filename",BA13),FIND("]",CELL("filename",BA13))+1,255) & DS$1,[1]Sheet1!$C$1:$CY$1 & [1]Sheet1!$C$3:$CY$3,0))} -> 0 | DU14: {=INDEX([1]Sheet1!$C$6:$CY$72,MATCH($A14,[1]Sheet1!$A$6:$A$72,0),MATCH(MID(CELL("filename",BC13),FIND("]",CELL("filename",BC13))+1,255) & DU$1,[1]Sheet1!$C$1:$CY$1 & [1]Sheet1!$C$3:$CY$3,0))} -> 7.26 | DV14: 0.5 | DW14: =Euro_Area_Data!V11*10^9 -> #N/A | DX14: 1 | DY14: 0.5 | DZ14: {=INDEX([1]Sheet1!$C$6:$CY$72,MATCH($A14,[1]Sheet1!$A$6:$A$72,0),MATCH(MID(CELL("filename",BH13),FIND("]",CELL("filename",BH13))+1,255) & DZ$1,[1]Sheet1!$C$1:$CY$1 & [1]Sheet1!$C$3:$CY$3,0))} -> 9.74 | EA14: 2 | EE14: -5 | EH14: 0.75 | EI14: 0.05 | EJ14: 75 | EK14: =(EN14-EN13)/EN13*100 -> 20.59124 | EN14: =[2]EUCAM_output!$AE11 -> 0.18619052
A15: 1975 | B15: =[2]EUCAM_output!$E12*10^9 -> 1.6218392e+11 | I15: =[2]EUCAM_output!$W12*10^3 -> 5424049.5 | K15: =IF(A15<2030,I15,K14*J15/J14) -> 5424049.5 | L15: =[2]EUCAM_output!$G12 -> 62.998429 | O15: =[2]EUCAM_output!$H12 -> 63.010234 | R15: =[2]EUCAM_output!$L12 -> 1.4 | U15: =[2]EUCAM_output!$K12 -> 1.039544 | V15: 1.039544 | W15: 0.0010842606 | X15: 0.006122739 | Y15: =[2]EUCAM_output!$AI12 -> -0.01208226 | Z15: =[2]EUCAM_output!$M12 -> 1906.9313 | AC15: =[2]EUCAM_output!$AL12 -> 1912.6858 | AD15: =[2]EUCAM_output!$T12*10^9 -> 4.6005117e+11 | AI15: =CH15/EN15 -> 1.1076272e+10 | AJ15: 1.0712e+09 | AK15: =AJ15/EN15 -> 5.3173887e+09 | AM15: =AVERAGE($AL$35:$AL$63) -> 0.065166448 | AO15: 7124700000 | AP15: =AO15/EN15 -> 3.5366691e+10 | AQ15: 3787400000 | AR15: =(AQ15-AJ15)/EN15 -> 1.3483095e+10 | BB15: 1.6010197e+11 | BC15: =[2]EUCAM_output!$AG12*10^9 -> 5.0503994e+10 | BD15: =(BB15-B15)/B15*100 -> -1.2836977 | CH15: {=INDEX([1]Sheet1!$C$6:$CY$72,MATCH($A15,[1]Sheet1!$A$6:$A$72,0),MATCH(MID(CELL("filename",O14),FIND("]",CELL("filename",O14))+1,255) & CH$1,[1]Sheet1!$C$1:$CY$1 & [1]Sheet1!$C$3:$CY$3,0))} -> 2231340000 | DQ15: 1.24077 | DR15: {=INDEX([1]Sheet1!$C$6:$CY$72,MATCH($A15,[1]Sheet1!$A$6:$A$72,0),MATCH(MID(CELL("filename",AZ14),FIND("]",CELL("filename",AZ14))+1,255) & DR$1,[1]Sheet1!$C$1:$CY$1 & [1]Sheet1!$C$3:$CY$3,0))} -> 0 | DS15: {=INDEX([1]Sheet1!$C$6:$CY$72,MATCH($A15,[1]Sheet1!$A$6:$A$72,0),MATCH(MID(CELL("filename",BA14),FIND("]",CELL("filename",BA14))+1,255) & DS$1,[1]Sheet1!$C$1:$CY$1 & [1]Sheet1!$C$3:$CY$3,0))} -> 0 | DU15: {=INDEX([1]Sheet1!$C$6:$CY$72,MATCH($A15,[1]Sheet1!$A$6:$A$72,0),MATCH(MID(CELL("filename",BC14),FIND("]",CELL("filename",BC14))+1,255) & DU$1,[1]Sheet1!$C$1:$CY$1 & [1]Sheet1!$C$3:$CY$3,0))} -> 5.49 | DV15: 0.5 | DW15: =Euro_Area_Data!V12*10^9 -> #N/A | DX15: 1 | DY15: 0.5 | DZ15: {=INDEX([1]Sheet1!$C$6:$CY$72,MATCH($A15,[1]Sheet1!$A$6:$A$72,0),MATCH(MID(CELL("filename",BH14),FIND("]",CELL("filename",BH14))+1,255) & DZ$1,[1]Sheet1!$C$1:$CY$1 & [1]Sheet1!$C$3:$CY$3,0))} -> 9.61 | EA15: 2 | EE15: -5 | EH15: 0.75 | EI15: 0.05 | EJ15: 75 | EK15: =(EN15-EN14)/EN14*100 -> 8.1968454 | EN15: =[2]EUCAM_output!$AE12 -> 0.20145227
A16: 1976 | B16: =[2]EUCAM_output!$E13*10^9 -> 1.6759215e+11 | I16: =[2]EUCAM_output!$W13*10^3 -> 5440280.5 | K16: =IF(A16<2030,I16,K15*J16/J15) -> 5440280.5 | L16: =[2]EUCAM_output!$G13 -> 63.07227 | O16: =[2]EUCAM_output!$H13 -> 63.215479 | R16: =[2]EUCAM_output!$L13 -> 1.5 | U16: =[2]EUCAM_output!$K13 -> 1.138892 | V16: 1.138892 | W16: 0.042486602 | X16: 0.014742997 | Y16: =[2]EUCAM_output!$AI13 -> -0.03451953 | Z16: =[2]EUCAM_output!$M13 -> 1901.3918 | AC16: =[2]EUCAM_output!$AL13 -> 1903.4422 | AD16: =[2]EUCAM_output!$T13*10^9 -> 4.793181e+11 | AI16: =CH16/EN16 -> 1.0329929e+10 | AJ16: 1238180000 | AK16: =AJ16/EN16 -> 5.4104073e+09 | AM16: =AVERAGE($AL$35:$AL$63) -> 0.065166448 | AO16: 8441400000 | AP16: =AO16/EN16 -> 3.6885923e+10 | AQ16: 4779600000 | AR16: =(AQ16-AJ16)/EN16 -> 1.5474749e+10 | BB16: 1.6742984e+11 | BC16: =[2]EUCAM_output!$AG13*10^9 -> 5.5787551e+10 | BD16: =(BB16-B16)/B16*100 -> -0.096849894 | CH16: {=INDEX([1]Sheet1!$C$6:$CY$72,MATCH($A16,[1]Sheet1!$A$6:$A$72,0),MATCH(MID(CELL("filename",O15),FIND("]",CELL("filename",O15))+1,255) & CH$1,[1]Sheet1!$C$1:$CY$1 & [1]Sheet1!$C$3:$CY$3,0))} -> 2364020000 | DQ16: 1.11805 | DR16: {=INDEX([1]Sheet1!$C$6:$CY$72,MATCH($A16,[1]Sheet1!$A$6:$A$72,0),MATCH(MID(CELL("filename",AZ15),FIND("]",CELL("filename",AZ15))+1,255) & DR$1,[1]Sheet1!$C$1:$CY$1 & [1]Sheet1!$C$3:$CY$3,0))} -> 0 | DS16: {=INDEX([1]Sheet1!$C$6:$CY$72,MATCH($A16,[1]Sheet1!$A$6:$A$72,0),MATCH(MID(CELL("filename",BA15),FIND("]",CELL("filename",BA15))+1,255) & DS$1,[1]Sheet1!$C$1:$CY$1 & [1]Sheet1!$C$3:$CY$3,0))} -> 0 | DU16: {=INDEX([1]Sheet1!$C$6:$CY$72,MATCH($A16,[1]Sheet1!$A$6:$A$72,0),MATCH(MID(CELL("filename",BC15),FIND("]",CELL("filename",BC15))+1,255) & DU$1,[1]Sheet1!$C$1:$CY$1 & [1]Sheet1!$C$3:$CY$3,0))} -> 4.67 | DV16: 0.5 | DW16: =Euro_Area_Data!V13*10^9 -> #N/A | DX16: 1 | DY16: 0.5 | DZ16: {=INDEX([1]Sheet1!$C$6:$CY$72,MATCH($A16,[1]Sheet1!$A$6:$A$72,0),MATCH(MID(CELL("filename",BH15),FIND("]",CELL("filename",BH15))+1,255) & DZ$1,[1]Sheet1!$C$1:$CY$1 & [1]Sheet1!$C$3:$CY$3,0))} -> 8.75 | EA16: 2 | EE16: -5 | EH16: 0.75 | EI16: 0.05 | EJ16: 75 | EK16: =(EN16-EN15)/EN15*100 -> 13.600872 | EN16: =[2]EUCAM_output!$AE13 -> 0.22885153
A17: 1977 | B17: =[2]EUCAM_output!$E14*10^9 -> 1.7309417e+11 | I17: =[2]EUCAM_output!$W14*10^3 -> 5473782.5 | K17: =IF(A17<2030,I17,K16*J17/J16) -> 5473782.5 | L17: =[2]EUCAM_output!$G14 -> 63.51301 | O17: =[2]EUCAM_output!$H14 -> 63.37974 | R17: =[2]EUCAM_output!$L14 -> 1.6 | U17: =[2]EUCAM_output!$K14 -> 1.287983 | V17: 1.287983 | W17: 0.038175132 | X17: 0.017259586 | Y17: =[2]EUCAM_output!$AI14 -> -0.012670404 | Z17: =[2]EUCAM_output!$M14 -> 1906.5261 | AC17: =[2]EUCAM_output!$AL14 -> 1891.8695 | AD17: =[2]EUCAM_output!$T14*10^9 -> 5.0055777e+11 | AI17: =CH17/EN17 -> 1.0649621e+10 | AJ17: 1462370000 | AK17: =AJ17/EN17 -> 5.7126407e+09 | AM17: =AVERAGE($AL$35:$AL$63) -> 0.065166448 | AO17: 10345100000 | AP17: =AO17/EN17 -> 4.0412371e+10 | AQ17: 5262200000 | AR17: =(AQ17-AJ17)/EN17 -> 1.4843756e+10 | BB17: 1.7593524e+11 | BC17: =[2]EUCAM_output!$AG14*10^9 -> 6.1669109e+10 | BD17: =(BB17-B17)/B17*100 -> 1.6413398 | CH17: {=INDEX([1]Sheet1!$C$6:$CY$72,MATCH($A17,[1]Sheet1!$A$6:$A$72,0),MATCH(MID(CELL("filename",O16),FIND("]",CELL("filename",O16))+1,255) & CH$1,[1]Sheet1!$C$1:$CY$1 & [1]Sheet1!$C$3:$CY$3,0))} -> 2726180000 | DQ17: 1.14112 | DR17: {=INDEX([1]Sheet1!$C$6:$CY$72,MATCH($A17,[1]Sheet1!$A$6:$A$72,0),MATCH(MID(CELL("filename",AZ16),FIND("]",CELL("filename",AZ16))+1,255) & DR$1,[1]Sheet1!$C$1:$CY$1 & [1]Sheet1!$C$3:$CY$3,0))} -> 0 | DS17: {=INDEX([1]Sheet1!$C$6:$CY$72,MATCH($A17,[1]Sheet1!$A$6:$A$72,0),MATCH(MID(CELL("filename",BA16),FIND("]",CELL("filename",BA16))+1,255) & DS$1,[1]Sheet1!$C$1:$CY$1 & [1]Sheet1!$C$3:$CY$3,0))} -> 0 | DU17: {=INDEX([1]Sheet1!$C$6:$CY$72,MATCH($A17,[1]Sheet1!$A$6:$A$72,0),MATCH(MID(CELL("filename",BC16),FIND("]",CELL("filename",BC16))+1,255) & DU$1,[1]Sheet1!$C$1:$CY$1 & [1]Sheet1!$C$3:$CY$3,0))} -> 7.49 | DV17: 0.5 | DW17: =Euro_Area_Data!V14*10^9 -> #N/A | DX17: 1 | DY17: 0.5 | DZ17: {=INDEX([1]Sheet1!$C$6:$CY$72,MATCH($A17,[1]Sheet1!$A$6:$A$72,0),MATCH(MID(CELL("filename",BH16),FIND("]",CELL("filename",BH16))+1,255) & DZ$1,[1]Sheet1!$C$1:$CY$1 & [1]Sheet1!$C$3:$CY$3,0))} -> 8.73 | EA17: 2 | EE17: -5 | EH17: 0.75 | EI17: 0.05 | EJ17: 75 | EK17: =(EN17-EN16)/EN16*100 -> 11.857868 | EN17: =[2]EUCAM_output!$AE14 -> 0.25598844
... A30: 1990 | B30: =[2]EUCAM_output!$E27*10^9 -> 2.316421e+11 | I30: =[2]EUCAM_output!$W27*10^3 -> 5801920.5 | K30: =IF(A30<2030,I30,K29*J30/J29) -> 5801920.5 | L30: =[2]EUCAM_output!$G27 -> 63.654158 | O30: =[2]EUCAM_output!$H27 -> 63.051071 | R30: =[2]EUCAM_output!$L27 -> 3.6 | U30: =[2]EUCAM_output!$K27 -> 3.726822 | V30: 3.726822 | W30: 0.022677997 | X30: -0.012026614 | Y30: =[2]EUCAM_output!$AI27 -> 0.0088977438 | Z30: =[2]EUCAM_output!$M27 -> 1824.9736 | AC30: =[2]EUCAM_output!$AL27 -> 1818.378 | AD30: =[2]EUCAM_output!$T27*10^9 -> 7.161258e+11 | AI30: =CH30/EN30 -> 9.1836521e+09 | AJ30: 4.00048e+09 | AK30: =AJ30/EN30 -> 7.2009754e+09 | AM30: =AVERAGE($AL$35:$AL$63) -> 0.065166448 | AO30: 28511400000 | AP30: =AO30/EN30 -> 5.1321314e+10 | AQ30: 19017800000 | AR30: =(AQ30-AJ30)/EN30 -> 2.7031594e+10 | BB30: 2.3501469e+11 | BC30: =[2]EUCAM_output!$AG27*10^9 -> 1.3700994e+11 | BD30: =(BB30-B30)/B30*100 -> 1.4559506 | CH30: {=INDEX([1]Sheet1!$C$6:$CY$72,MATCH($A30,[1]Sheet1!$A$6:$A$72,0),MATCH(MID(CELL("filename",O29),FIND("]",CELL("filename",O29))+1,255) & CH$1,[1]Sheet1!$C$1:$CY$1 & [1]Sheet1!$C$3:$CY$3,0))} -> 5101950000 | DQ30: 1.27343 | DR30: {=INDEX([1]Sheet1!$C$6:$CY$72,MATCH($A30,[1]Sheet1!$A$6:$A$72,0),MATCH(MID(CELL("filename",AZ29),FIND("]",CELL("filename",AZ29))+1,255) & DR$1,[1]Sheet1!$C$1:$CY$1 & [1]Sheet1!$C$3:$CY$3,0))} -> 0 | DS30: {=INDEX([1]Sheet1!$C$6:$CY$72,MATCH($A30,[1]Sheet1!$A$6:$A$72,0),MATCH(MID(CELL("filename",BA29),FIND("]",CELL("filename",BA29))+1,255) & DS$1,[1]Sheet1!$C$1:$CY$1 & [1]Sheet1!$C$3:$CY$3,0))} -> 0 | DU30: {=INDEX([1]Sheet1!$C$6:$CY$72,MATCH($A30,[1]Sheet1!$A$6:$A$72,0),MATCH(MID(CELL("filename",BC29),FIND("]",CELL("filename",BC29))+1,255) & DU$1,[1]Sheet1!$C$1:$CY$1 & [1]Sheet1!$C$3:$CY$3,0))} -> 8.53 | DV30: 0.5 | DW30: =Euro_Area_Data!V27*10^9 -> #N/A | DX30: 1 | DY30: 0.5 | DZ30: {=INDEX([1]Sheet1!$C$6:$CY$72,MATCH($A30,[1]Sheet1!$A$6:$A$72,0),MATCH(MID(CELL("filename",BH29),FIND("]",CELL("filename",BH29))+1,255) & DZ$1,[1]Sheet1!$C$1:$CY$1 & [1]Sheet1!$C$3:$CY$3,0))} -> 8.77 | EA30: 2 | EE30: -5 | EH30: 0.75 | EI30: 0.05 | EJ30: 75 | EK30: =(EN30-EN29)/EN29*100 -> 3.9241089 | EN30: =[2]EUCAM_output!$AE27 -> 0.55554696
A31: 1991 | B31: =[2]EUCAM_output!$E28*10^9 -> 2.3915635e+11 | I31: =[2]EUCAM_output!$W28*10^3 -> 5873311.5 | K31: =IF(A31<2030,I31,K30*J31/J30) -> 5873311.5 | L31: =[2]EUCAM_output!$G28 -> 63.855685 | O31: =[2]EUCAM_output!$H28 -> 63.08808 | R31: =[2]EUCAM_output!$L28 -> 3.9 | U31: =[2]EUCAM_output!$K28 -> 3.802161 | V31: 3.802161 | W31: 0.021797768 | X31: -0.016651225 | Y31: =[2]EUCAM_output!$AI28 -> 0.012151225 | Z31: =[2]EUCAM_output!$M28 -> 1835.3923 | AC31: =[2]EUCAM_output!$AL28 -> 1815.4316 | AD31: =[2]EUCAM_output!$T28*10^9 -> 7.4025744e+11 | AI31: =CH31/EN31 -> 9.6280171e+09 | AJ31: 4.25255e+09 | AK31: =AJ31/EN31 -> 7.3811263e+09 | AM31: =AVERAGE($AL$35:$AL$63) -> 0.065166448 | AO31: 32009000000 | AP31: =AO31/EN31 -> 5.5557835e+10 | AQ31: 20402500000 | AR31: =(AQ31-AJ31)/EN31 -> 2.8031374e+10 | AT31: =AP31/B31*100 -> 23.230758 | BB31: 2.4310303e+11 | BC31: =[2]EUCAM_output!$AG28*10^9 -> 1.4688677e+11 | BD31: =(BB31-B31)/B31*100 -> 1.650247 | CH31: {=INDEX([1]Sheet1!$C$6:$CY$72,MATCH($A31,[1]Sheet1!$A$6:$A$72,0),MATCH(MID(CELL("filename",O30),FIND("]",CELL("filename",O30))+1,255) & CH$1,[1]Sheet1!$C$1:$CY$1 & [1]Sheet1!$C$3:$CY$3,0))} -> 5547070000 | DQ31: 1.23916 | DR31: {=INDEX([1]Sheet1!$C$6:$CY$72,MATCH($A31,[1]Sheet1!$A$6:$A$72,0),MATCH(MID(CELL("filename",AZ30),FIND("]",CELL("filename",AZ30))+1,255) & DR$1,[1]Sheet1!$C$1:$CY$1 & [1]Sheet1!$C$3:$CY$3,0))} -> 0 | DS31: {=INDEX([1]Sheet1!$C$6:$CY$72,MATCH($A31,[1]Sheet1!$A$6:$A$72,0),MATCH(MID(CELL("filename",BA30),FIND("]",CELL("filename",BA30))+1,255) & DS$1,[1]Sheet1!$C$1:$CY$1 & [1]Sheet1!$C$3:$CY$3,0))} -> 0 | DU31: {=INDEX([1]Sheet1!$C$6:$CY$72,MATCH($A31,[1]Sheet1!$A$6:$A$72,0),MATCH(MID(CELL("filename",BC30),FIND("]",CELL("filename",BC30))+1,255) & DU$1,[1]Sheet1!$C$1:$CY$1 & [1]Sheet1!$C$3:$CY$3,0))} -> 9.1 | DV31: 0.5 | DW31: =Euro_Area_Data!V28*10^9 -> #N/A | DX31: 1 | DY31: 0.5 | DZ31: {=INDEX([1]Sheet1!$C$6:$CY$72,MATCH($A31,[1]Sheet1!$A$6:$A$72,0),MATCH(MID(CELL("filename",BH30),FIND("]",CELL("filename",BH30))+1,255) & DZ$1,[1]Sheet1!$C$1:$CY$1 & [1]Sheet1!$C$3:$CY$3,0))} -> 8.56 | EA31: 2 | EE31: -5 | EH31: 0.75 | EI31: 0.05 | EJ31: 75 | EK31: =(EN31-EN30)/EN30*100 -> 3.7065091 | EN31: =[2]EUCAM_output!$AE28 -> 0.57613836
A32: 1992 | B32: =[2]EUCAM_output!$E29*10^9 -> 2.4625608e+11 | I32: =[2]EUCAM_output!$W29*10^3 -> 5950880.5 | K32: =IF(A32<2030,I32,K31*J32/J31) -> 5950880.5 | L32: =[2]EUCAM_output!$G29 -> 63.241038 | O32: =[2]EUCAM_output!$H29 -> 63.001847 | R32: =[2]EUCAM_output!$L29 -> 3.8 | U32: =[2]EUCAM_output!$K29 -> 3.871702 | V32: 3.871702 | W32: 0.016363086 | X32: -0.017672754 | Y32: =[2]EUCAM_output!$AI29 -> -0.0049583809 | Z32: =[2]EUCAM_output!$M29 -> 1803.8884 | AC32: =[2]EUCAM_output!$AL29 -> 1810.5278 | AD32: =[2]EUCAM_output!$T29*10^9 -> 7.6295222e+11 | AI32: =CH32/EN32 -> 9.8506862e+09 | AJ32: 4574640000 | AK32: =AJ32/EN32 -> 7.5594289e+09 | AM32: =AVERAGE($AL$35:$AL$63) -> 0.065166448 | AO32: 33706100000 | AP32: =AO32/EN32 -> 5.5698124e+10 | AQ32: 21956400000 | AR32: =(AQ32-AJ32)/EN32 -> 2.8722736e+10 | AT32: =AP32/B32*100 -> 22.617969 | BB32: 2.4819244e+11 | BC32: =[2]EUCAM_output!$AG29*10^9 -> 1.5517919e+11 | BD32: =(BB32-B32)/B32*100 -> 0.78632005 | CH32: {=INDEX([1]Sheet1!$C$6:$CY$72,MATCH($A32,[1]Sheet1!$A$6:$A$72,0),MATCH(MID(CELL("filename",O31),FIND("]",CELL("filename",O31))+1,255) & CH$1,[1]Sheet1!$C$1:$CY$1 & [1]Sheet1!$C$3:$CY$3,0))} -> 5961210000 | DQ32: 1.2981 | DR32: {=INDEX([1]Sheet1!$C$6:$CY$72,MATCH($A32,[1]Sheet1!$A$6:$A$72,0),MATCH(MID(CELL("filename",AZ31),FIND("]",CELL("filename",AZ31))+1,255) & DR$1,[1]Sheet1!$C$1:$CY$1 & [1]Sheet1!$C$3:$CY$3,0))} -> 0 | DS32: {=INDEX([1]Sheet1!$C$6:$CY$72,MATCH($A32,[1]Sheet1!$A$6:$A$72,0),MATCH(MID(CELL("filename",BA31),FIND("]",CELL("filename",BA31))+1,255) & DS$1,[1]Sheet1!$C$1:$CY$1 & [1]Sheet1!$C$3:$CY$3,0))} -> 0 | DU32: {=INDEX([1]Sheet1!$C$6:$CY$72,MATCH($A32,[1]Sheet1!$A$6:$A$72,0),MATCH(MID(CELL("filename",BC31),FIND("]",CELL("filename",BC31))+1,255) & DU$1,[1]Sheet1!$C$1:$CY$1 & [1]Sheet1!$C$3:$CY$3,0))} -> 9.32 | DV32: 0.5 | DW32: =Euro_Area_Data!V29*10^9 -> #N/A | DX32: 1 | DY32: 0.5 | DZ32: {=INDEX([1]Sheet1!$C$6:$CY$72,MATCH($A32,[1]Sheet1!$A$6:$A$72,0),MATCH(MID(CELL("filename",BH31),FIND("]",CELL("filename",BH31))+1,255) & DZ$1,[1]Sheet1!$C$1:$CY$1 & [1]Sheet1!$C$3:$CY$3,0))} -> 7.37 | EA32: 2 | EE32: -5 | EH32: 0.75 | EI32: 0.05 | EJ32: 75 | EK32: =(EN32-EN31)/EN31*100 -> 5.0367183 | EN32: =[2]EUCAM_output!$AE29 -> 0.60515683
A33: 1993 | B33: =[2]EUCAM_output!$E30*10^9 -> 2.5240638e+11 | I33: =[2]EUCAM_output!$W30*10^3 -> 6012349.5 | K33: =IF(A33<2030,I33,K32*J33/J32) -> 6012349.5 | L33: =[2]EUCAM_output!$G30 -> 62.581201 | O33: =[2]EUCAM_output!$H30 -> 62.858964 | R33: =[2]EUCAM_output!$L30 -> 4.3 | U33: =[2]EUCAM_output!$K30 -> 3.951558 | V33: 3.951558 | W33: 0.01073464 | X33: -0.014854452 | Y33: =[2]EUCAM_output!$AI30 -> -0.014813454 | Z33: =[2]EUCAM_output!$M30 -> 1801.25 | AC33: =[2]EUCAM_output!$AL30 -> 1805.4742 | AD33: =[2]EUCAM_output!$T30*10^9 -> 7.8362222e+11 | AI33: =CH33/EN33 -> 1.0491379e+10 | AJ33: 5051970000 | AK33: =AJ33/EN33 -> 7.7852832e+09 | AM33: =AVERAGE($AL$35:$AL$63) -> 0.065166448 | AO33: 35208200000 | AP33: =AO33/EN33 -> 5.4257212e+10 | AQ33: 23614800000 | AR33: =(AQ33-AJ33)/EN33 -> 2.8606046e+10 | AT33: =AP33/B33*100 -> 21.495975 | BB33: 2.4949994e+11 | BC33: =[2]EUCAM_output!$AG30*10^9 -> 1.6029765e+11 | BD33: =(BB33-B33)/B33*100 -> -1.1514924 | CH33: {=INDEX([1]Sheet1!$C$6:$CY$72,MATCH($A33,[1]Sheet1!$A$6:$A$72,0),MATCH(MID(CELL("filename",O32),FIND("]",CELL("filename",O32))+1,255) & CH$1,[1]Sheet1!$C$1:$CY$1 & [1]Sheet1!$C$3:$CY$3,0))} -> 6807990000 | DQ33: 1.171 | DR33: {=INDEX([1]Sheet1!$C$6:$CY$72,MATCH($A33,[1]Sheet1!$A$6:$A$72,0),MATCH(MID(CELL("filename",AZ32),FIND("]",CELL("filename",AZ32))+1,255) & DR$1,[1]Sheet1!$C$1:$CY$1 & [1]Sheet1!$C$3:$CY$3,0))} -> 0 | DS33: {=INDEX([1]Sheet1!$C$6:$CY$72,MATCH($A33,[1]Sheet1!$A$6:$A$72,0),MATCH(MID(CELL("filename",BA32),FIND("]",CELL("filename",BA32))+1,255) & DS$1,[1]Sheet1!$C$1:$CY$1 & [1]Sheet1!$C$3:$CY$3,0))} -> 0 | DU33: {=INDEX([1]Sheet1!$C$6:$CY$72,MATCH($A33,[1]Sheet1!$A$6:$A$72,0),MATCH(MID(CELL("filename",BC32),FIND("]",CELL("filename",BC32))+1,255) & DU$1,[1]Sheet1!$C$1:$CY$1 & [1]Sheet1!$C$3:$CY$3,0))} -> 7.23 | DV33: 0.5 | DW33: =Euro_Area_Data!V30*10^9 -> #N/A | DX33: 1 | DY33: 0.5 | DZ33: {=INDEX([1]Sheet1!$C$6:$CY$72,MATCH($A33,[1]Sheet1!$A$6:$A$72,0),MATCH(MID(CELL("filename",BH32),FIND("]",CELL("filename",BH32))+1,255) & DZ$1,[1]Sheet1!$C$1:$CY$1 & [1]Sheet1!$C$3:$CY$3,0))} -> 6.7 | EA33: 2 | EE33: -5 | EH33: 0.75 | EI33: 0.05 | EJ33: 75 | EK33: =(EN33-EN32)/EN32*100 -> 7.2305198 | EN33: =[2]EUCAM_output!$AE30 -> 0.64891281
A34: 1994 | B34: =[2]EUCAM_output!$E31*10^9 -> 2.5815899e+11 | I34: =[2]EUCAM_output!$W31*10^3 -> 6040309 | K34: =IF(A34<2030,I34,K33*J34/J33) -> 6040309 | L34: =[2]EUCAM_output!$G31 -> 62.474675 | O34: =[2]EUCAM_output!$H31 -> 62.749943 | R34: =[2]EUCAM_output!$L31 -> 4.6 | U34: =[2]EUCAM_output!$K31 -> 4.025289 | V34: 4.025289 | W34: 0.024229901 | X34: -0.017311854 | Y34: =[2]EUCAM_output!$AI31 -> -0.0054187832 | Z34: =[2]EUCAM_output!$M31 -> 1799.508 | AC34: =[2]EUCAM_output!$AL31 -> 1801.4142 | AD34: =[2]EUCAM_output!$T31*10^9 -> 8.0660424e+11 | AI34: =CH34/EN34 -> 1.0785486e+10 | AJ34: 5317520000 | AK34: =AJ34/EN34 -> 7.9432973e+09 | AM34: =AVERAGE($AL$35:$AL$63) -> 0.065166448 | AO34: 38255100000 | AP34: =AO34/EN34 -> 5.7145367e+10 | AQ34: 25827200000 | AR34: =(AQ34-AJ34)/EN34 -> 3.0637306e+10 | AT34: =AP34/B34*100 -> 22.135726 | BB34: 2.5549323e+11 | BC34: =[2]EUCAM_output!$AG31*10^9 -> 1.6829284e+11 | BD34: =(BB34-B34)/B34*100 -> -1.032604 | CH34: {=INDEX([1]Sheet1!$C$6:$CY$72,MATCH($A34,[1]Sheet1!$A$6:$A$72,0),MATCH(MID(CELL("filename",O33),FIND("]",CELL("filename",O33))+1,255) & CH$1,[1]Sheet1!$C$1:$CY$1 & [1]Sheet1!$C$3:$CY$3,0))} -> 7220180000 | DQ34: 1.18952 | DR34: {=INDEX([1]Sheet1!$C$6:$CY$72,MATCH($A34,[1]Sheet1!$A$6:$A$72,0),MATCH(MID(CELL("filename",AZ33),FIND("]",CELL("filename",AZ33))+1,255) & DR$1,[1]Sheet1!$C$1:$CY$1 & [1]Sheet1!$C$3:$CY$3,0))} -> 0 | DS34: {=INDEX([1]Sheet1!$C$6:$CY$72,MATCH($A34,[1]Sheet1!$A$6:$A$72,0),MATCH(MID(CELL("filename",BA33),FIND("]",CELL("filename",BA33))+1,255) & DS$1,[1]Sheet1!$C$1:$CY$1 & [1]Sheet1!$C$3:$CY$3,0))} -> 0 | DU34: {=INDEX([1]Sheet1!$C$6:$CY$72,MATCH($A34,[1]Sheet1!$A$6:$A$72,0),MATCH(MID(CELL("filename",BC33),FIND("]",CELL("filename",BC33))+1,255) & DU$1,[1]Sheet1!$C$1:$CY$1 & [1]Sheet1!$C$3:$CY$3,0))} -> 5.04 | DV34: 0.5 | DW34: =Euro_Area_Data!V31*10^9 -> #N/A | DX34: 1 | DY34: 0.5 | DZ34: {=INDEX([1]Sheet1!$C$6:$CY$72,MATCH($A34,[1]Sheet1!$A$6:$A$72,0),MATCH(MID(CELL("filename",BH33),FIND("]",CELL("filename",BH33))+1,255) & DZ$1,[1]Sheet1!$C$1:$CY$1 & [1]Sheet1!$C$3:$CY$3,0))} -> 7.03 | EA34: 2 | EE34: -5 | EH34: 0.75 | EI34: 0.05 | EJ34: 75 | EK34: =(EN34-EN33)/EN33*100 -> 3.1625255 | EN34: =[2]EUCAM_output!$AE31 -> 0.66943484
A35: 1995 | B35: =[2]EUCAM_output!$E32*10^9 -> 2.6367523e+11 | I35: =[2]EUCAM_output!$W32*10^3 -> 6044081.5 | K35: =IF(A35<2030,I35,K34*J35/J34) -> 6044081.5 | L35: =[2]EUCAM_output!$G32 -> 62.151753 | O35: =[2]EUCAM_output!$H32 -> 62.737519 | R35: =[2]EUCAM_output!$L32 -> 4.5 | U35: =[2]EUCAM_output!$K32 -> 4.082081 | V35: 4.082081 | W35: 0.030290046 | X35: -0.013291292 | Y35: =[2]EUCAM_output!$AI32 -> -0.0061220823 | Z35: =[2]EUCAM_output!$M32 -> 1773.4306 | AC35: =[2]EUCAM_output!$AL32 -> 1799.069 | AD35: =[2]EUCAM_output!$T32*10^9 -> 8.2878681e+11 | AE35: {=INDEX('[3]Sheet 1'!$B$12:$M$61,MATCH($A35,'[3]Sheet 1'!$A$12:$A$61,0),MATCH(MID(CELL("filename",A34),FIND("]",CELL("filename",A34))+1,255)&AE$1,'[3]Sheet 1'!$B$9:$M$9&'[3]Sheet 1'!$B$8:$M$8,0))*10^6} -> 601483200000 | AF35: {=INDEX('[3]Sheet 1'!$B$12:$M$61,MATCH($A35,'[3]Sheet 1'!$A$12:$A$61,0),MATCH(MID(CELL("filename",B34),FIND("]",CELL("filename",B34))+1,255)&AF$1,'[3]Sheet 1'!$B$9:$M$9&'[3]Sheet 1'!$B$8:$M$8,0))*10^6} -> 112354200000 | AG35: =AF35/AE35 -> 0.18679524 | AH35: =AD35*AG35 -> 1.5481343e+11 | AI35: =CH35/EN35 -> 1.0300875e+10 | AJ35: 5756000000 | AK35: =AJ35/EN35 -> 8.2223126e+09 | AL35: =AK35/AH35 -> 0.053111106 | AM35: =AVERAGE($AL$35:$AL$63) -> 0.065166448 | AN35: =AD35-AH35 -> 6.7397338e+11 | AO35: 39947500000 | AP35: =AO35/EN35 -> 5.7064078e+10 | AQ35: 28433600000 | AR35: =(AQ35-AJ35)/EN35 -> 3.2394426e+10 | AS35: =AR35/AN35 -> 0.048064845 | AT35: =AP35/B35*100 -> 21.641805 | BB35: 2.6230975e+11 | BC35: =[2]EUCAM_output!$AG32*10^9 -> 175917000000 | BD35: =(BB35-B35)/B35*100 -> -0.51786479 | BN35: =BP35-CF35 -> -3952360000 | BO35: {=INDEX([1]Sheet1!$C$6:$CY$72,MATCH($A35,[1]Sheet1!$A$6:$A$72,0),MATCH(MID(CELL("filename",A34),FIND("]",CELL("filename",A34))+1,255) & BO$1,[1]Sheet1!$C$1:$CY$1 & [1]Sheet1!$C$3:$CY$3,0))} -> -2.152362 | BP35: {=INDEX([1]Sheet1!$C$6:$CY$72,MATCH($A35,[1]Sheet1!$A$6:$A$72,0),MATCH(MID(CELL("filename",B34),FIND("]",CELL("filename",B34))+1,255) & BP$1,[1]Sheet1!$C$1:$CY$1 & [1]Sheet1!$C$3:$CY$3,0))} -> 91559100000 | BQ35: {=INDEX([1]Sheet1!$C$6:$CY$72,MATCH($A35,[1]Sheet1!$A$6:$A$72,0),MATCH(MID(CELL("filename",C34),FIND("]",CELL("filename",C34))+1,255) & BQ$1,[1]Sheet1!$C$1:$CY$1 & [1]Sheet1!$C$3:$CY$3,0))} -> 22029370000 | BW35: {=INDEX([1]Sheet1!$C$6:$CY$72,MATCH($A35,[1]Sheet1!$A$6:$A$72,0),MATCH(MID(CELL("filename",F34),FIND("]",CELL("filename",F34))+1,255) & BW$1,[1]Sheet1!$C$1:$CY$1 & [1]Sheet1!$C$3:$CY$3,0))} -> 26897520000 | BX35: {=INDEX([1]Sheet1!$C$6:$CY$72,MATCH($A35,[1]Sheet1!$A$6:$A$72,0),MATCH(MID(CELL("filename",G34),FIND("]",CELL("filename",G34))+1,255) & BX$1,[1]Sheet1!$C$1:$CY$1 & [1]Sheet1!$C$3:$CY$3,0))} -> 27526260000 | BY35: {=INDEX([4]DATA!$C$18:$N$51,MATCH($A35,[4]DATA!$B$18:$B$51,0),MATCH(MID(CELL("filename",F2),FIND("]",CELL("filename",F2))+1,255) & BY$1,[4]DATA!$C$15:$N$15&[4]DATA!$C$16:$N$16,0)) * 10^6} -> 13578000000 | BZ35: {=INDEX([4]DATA!$C$18:$N$51,MATCH($A35,[4]DATA!$B$18:$B$51,0),MATCH(MID(CELL("filename",G2),FIND("]",CELL("filename",G2))+1,255) & BZ$1,[4]DATA!$C$15:$N$15&[4]DATA!$C$16:$N$16,0)) * 10^6} -> 12792000000 | CA35: =$BX35*BY35/SUM($BY35:$BZ35) -> 1.4173362e+10 | CB35: =BX35-CA35 -> 1.3352898e+10 | CC35: {=INDEX([1]Sheet1!$C$6:$CY$72,MATCH($A35,[1]Sheet1!$A$6:$A$72,0),MATCH(MID(CELL("filename",J34),FIND("]",CELL("filename",J34))+1,255) & CC$1,[1]Sheet1!$C$1:$CY$1 & [1]Sheet1!$C$3:$CY$3,0))} -> 2258084000 | CD35: =BP35-BQ35-BW35-BX35-CC35 -> 12847866000 | CE35: {=INDEX([1]Sheet1!$C$6:$CY$72,MATCH($A35,[1]Sheet1!$A$6:$A$72,0),MATCH(MID(CELL("filename",L34),FIND("]",CELL("filename",L34))+1,255) & CE$1,[1]Sheet1!$C$1:$CY$1 & [1]Sheet1!$C$3:$CY$3,0))} -> 102891400000 | CF35: =CE35-CK35 -> 95511460000 | CG35: {=INDEX([1]Sheet1!$C$6:$CY$72,MATCH($A35,[1]Sheet1!$A$6:$A$72,0),MATCH(MID(CELL("filename",N34),FIND("]",CELL("filename",N34))+1,255) & CG$1,[1]Sheet1!$C$1:$CY$1 & [1]Sheet1!$C$3:$CY$3,0))} -> 36567300000 | CH35: {=INDEX([1]Sheet1!$C$6:$CY$72,MATCH($A35,[1]Sheet1!$A$6:$A$72,0),MATCH(MID(CELL("filename",O34),FIND("]",CELL("filename",O34))+1,255) & CH$1,[1]Sheet1!$C$1:$CY$1 & [1]Sheet1!$C$3:$CY$3,0))} -> 7211090000 | CI35: {=INDEX([1]Sheet1!$C$6:$CY$72,MATCH($A35,[1]Sheet1!$A$6:$A$72,0),MATCH(MID(CELL("filename",P34),FIND("]",CELL("filename",P34))+1,255) & CI$1,[1]Sheet1!$C$1:$CY$1 & [1]Sheet1!$C$3:$CY$3,0))} -> 4726430000 | CJ35: {=INDEX([1]Sheet1!$C$6:$CY$72,MATCH($A35,[1]Sheet1!$A$6:$A$72,0),MATCH(MID(CELL("filename",R34),FIND("]",CELL("filename",R34))+1,255) & CJ$1,[1]Sheet1!$C$1:$CY$1 & [1]Sheet1!$C$3:$CY$3,0))} -> 36683000000 | CK35: {=INDEX([1]Sheet1!$C$6:$CY$72,MATCH($A35,[1]Sheet1!$A$6:$A$72,0),MATCH(MID(CELL("filename",S34),FIND("]",CELL("filename",S34))+1,255) & CK$1,[1]Sheet1!$C$1:$CY$1 & [1]Sheet1!$C$3:$CY$3,0))} -> 7379940000 | CL35: =CF35-CG35-CH35-CI35-CJ35 -> 10323640000 | DK35: =DL35/100*BC35 -> 120650035695 | DL35: {=INDEX([1]Sheet1!$C$6:$CY$72,MATCH($A35,[1]Sheet1!$A$6:$A$72,0),MATCH(MID(CELL("filename",AT34),FIND("]",CELL("filename",AT34))+1,255) & DL$1,[1]Sheet1!$C$1:$CY$1 & [1]Sheet1!$C$3:$CY$3,0))} -> 68.5835 | DM35: {=INDEX([5]DATA!$C$18:$T$51,MATCH($A35,[5]DATA!$B$18:$B$51,0),MATCH(MID(CELL("filename",AU2),FIND("]",CELL("filename",AU2))+1,255) & DM$1,[5]DATA!$C$15:$T$15&[5]DATA!$C$16:$T$16,0)) * 10^6} -> 1634000000 | DN35: {=INDEX([5]DATA!$C$18:$T$51,MATCH($A35,[5]DATA!$B$18:$B$51,0),MATCH(MID(CELL("filename",AV2),FIND("]",CELL("filename",AV2))+1,255) & DN$1,[5]DATA!$C$15:$T$15&[5]DATA!$C$16:$T$16,0)) * 10^6} -> 119016000000 | DQ35: 1.30801 | DR35: {=INDEX([1]Sheet1!$C$6:$CY$72,MATCH($A35,[1]Sheet1!$A$6:$A$72,0),MATCH(MID(CELL("filename",AZ34),FIND("]",CELL("filename",AZ34))+1,255) & DR$1,[1]Sheet1!$C$1:$CY$1 & [1]Sheet1!$C$3:$CY$3,0))} -> 0 | DS35: {=INDEX([1]Sheet1!$C$6:$CY$72,MATCH($A35,[1]Sheet1!$A$6:$A$72,0),MATCH(MID(CELL("filename",BA34),FIND("]",CELL("filename",BA34))+1,255) & DS$1,[1]Sheet1!$C$1:$CY$1 & [1]Sheet1!$C$3:$CY$3,0))} -> 0 | DT35: {=INDEX([5]DATA!$C$18:$T$51,MATCH($A35,[5]DATA!$B$18:$B$51,0),MATCH(MID(CELL("filename",BB2),FIND("]",CELL("filename",BB2))+1,255) & DT$1,[5]DATA!$C$15:$T$15&[5]DATA!$C$16:$T$16,0)) * 10^6} -> 10067000000 | DU35: {=INDEX([1]Sheet1!$C$6:$CY$72,MATCH($A35,[1]Sheet1!$A$6:$A$72,0),MATCH(MID(CELL("filename",BC34),FIND("]",CELL("filename",BC34))+1,255) & DU$1,[1]Sheet1!$C$1:$CY$1 & [1]Sheet1!$C$3:$CY$3,0))} -> 4.52 | DV35: 0.5 | DW35: =Euro_Area_Data!V32*10^9 -> 8.4301981e+12 | DX35: 1 | DY35: 0.5 | DZ35: {=INDEX([1]Sheet1!$C$6:$CY$72,MATCH($A35,[1]Sheet1!$A$6:$A$72,0),MATCH(MID(CELL("filename",BH34),FIND("]",CELL("filename",BH34))+1,255) & DZ$1,[1]Sheet1!$C$1:$CY$1 & [1]Sheet1!$C$3:$CY$3,0))} -> 7.14 | EA35: 2 | EB35: =SUMPRODUCT(Euro_Area_Data!C32:U32,Euro_Area_Data!Z32:AR32)/SUM(Euro_Area_Data!C32:U32) -> 0.6828828 | EE35: -5 | EH35: 0.75 | EI35: 0.05 | EJ35: 75 | EK35: =(EN35-EN34)/EN34*100 -> 4.5727401 | EN35: =[2]EUCAM_output!$AE32 -> 0.70004636
A36: 1996 | B36: =[2]EUCAM_output!$E33*10^9 -> 2.6969103e+11 | H36: =[2]EUCAM_output!$AK33 -> 0.0042463918 | I36: =[2]EUCAM_output!$W33*10^3 -> 6044990.5 | K36: =IF(A36<2030,I36,K35*J36/J35) -> 6044990.5 | L36: =[2]EUCAM_output!$G33 -> 62.646966 | O36: =[2]EUCAM_output!$H33 -> 62.856901 | R36: =[2]EUCAM_output!$L33 -> 4.9 | U36: =[2]EUCAM_output!$K33 -> 4.133896 | V36: 4.133896 | W36: 0.018189866 | X36: -0.01019482 | Y36: =[2]EUCAM_output!$AI33 -> -0.02106268 | Z36: =[2]EUCAM_output!$M33 -> 1805.8816 | AC36: =[2]EUCAM_output!$AL33 -> 1798.9691 | AD36: =[2]EUCAM_output!$T33*10^9 -> 8.5200258e+11 | AE36: {=INDEX('[3]Sheet 1'!$B$12:$M$61,MATCH($A36,'[3]Sheet 1'!$A$12:$A$61,0),MATCH(MID(CELL("filename",A35),FIND("]",CELL("filename",A35))+1,255)&AE$1,'[3]Sheet 1'!$B$9:$M$9&'[3]Sheet 1'!$B$8:$M$8,0))*10^6} -> 614567000000 | AF36: {=INDEX('[3]Sheet 1'!$B$12:$M$61,MATCH($A36,'[3]Sheet 1'!$A$12:$A$61,0),MATCH(MID(CELL("filename",B35),FIND("]",CELL("filename",B35))+1,255)&AF$1,'[3]Sheet 1'!$B$9:$M$9&'[3]Sheet 1'!$B$8:$M$8,0))*10^6} -> 113815800000 | AG36: =AF36/AE36 -> 0.18519673 | AH36: =AD36*AG36 -> 1.5778809e+11 | AI36: =CH36/EN36 -> 9.9469039e+09 | AJ36: 5831840000 | AK36: =AJ36/EN36 -> 8.4091983e+09 | AL36: =AK36/AH36 -> 0.053294251 | AM36: =AVERAGE($AL$35:$AL$63) -> 0.065166448 | AN36: =AD36-AH36 -> 6.9421449e+11 | AO36: 41408700000 | AP36: =AO36/EN36 -> 5.9709109e+10 | AQ36: 29954400000 | AR36: =(AQ36-AJ36)/EN36 -> 3.4783429e+10 | AS36: =AR36/AN36 -> 0.050104729 | AT36: =AP36/B36*100 -> 22.13982 | BB36: 2.6812191e+11 | BC36: =[2]EUCAM_output!$AG33*10^9 -> 181541920000 | BD36: =(BB36-B36)/B36*100 -> -0.58182117 | BN36: =BP36-CF36 -> -1143649000 | BO36: {=INDEX([1]Sheet1!$C$6:$CY$72,MATCH($A36,[1]Sheet1!$A$6:$A$72,0),MATCH(MID(CELL("filename",A35),FIND("]",CELL("filename",A35))+1,255) & BO$1,[1]Sheet1!$C$1:$CY$1 & [1]Sheet1!$C$3:$CY$3,0))} -> -0.615015 | BP36: {=INDEX([1]Sheet1!$C$6:$CY$72,MATCH($A36,[1]Sheet1!$A$6:$A$72,0),MATCH(MID(CELL("filename",B35),FIND("]",CELL("filename",B35))+1,255) & BP$1,[1]Sheet1!$C$1:$CY$1 & [1]Sheet1!$C$3:$CY$3,0))} -> 95557400000 | BQ36: {=INDEX([1]Sheet1!$C$6:$CY$72,MATCH($A36,[1]Sheet1!$A$6:$A$72,0),MATCH(MID(CELL("filename",C35),FIND("]",CELL("filename",C35))+1,255) & BQ$1,[1]Sheet1!$C$1:$CY$1 & [1]Sheet1!$C$3:$CY$3,0))} -> 24167680000 | BW36: {=INDEX([1]Sheet1!$C$6:$CY$72,MATCH($A36,[1]Sheet1!$A$6:$A$72,0),MATCH(MID(CELL("filename",F35),FIND("]",CELL("filename",F35))+1,255) & BW$1,[1]Sheet1!$C$1:$CY$1 & [1]Sheet1!$C$3:$CY$3,0))} -> 27895500000 | BX36: {=INDEX([1]Sheet1!$C$6:$CY$72,MATCH($A36,[1]Sheet1!$A$6:$A$72,0),MATCH(MID(CELL("filename",G35),FIND("]",CELL("filename",G35))+1,255) & BX$1,[1]Sheet1!$C$1:$CY$1 & [1]Sheet1!$C$3:$CY$3,0))} -> 28049650000 | BY36: {=INDEX([4]DATA!$C$18:$N$51,MATCH($A36,[4]DATA!$B$18:$B$51,0),MATCH(MID(CELL("filename",F3),FIND("]",CELL("filename",F3))+1,255) & BY$1,[4]DATA!$C$15:$N$15&[4]DATA!$C$16:$N$16,0)) * 10^6} -> 14133000000 | BZ36: {=INDEX([4]DATA!$C$18:$N$51,MATCH($A36,[4]DATA!$B$18:$B$51,0),MATCH(MID(CELL("filename",G3),FIND("]",CELL("filename",G3))+1,255) & BZ$1,[4]DATA!$C$15:$N$15&[4]DATA!$C$16:$N$16,0)) * 10^6} -> 13252000000 | CA36: =$BX36*BY36/SUM($BY36:$BZ36) -> 1.4476016e+10 | CB36: =BX36-CA36 -> 1.3573634e+10 | CC36: {=INDEX([1]Sheet1!$C$6:$CY$72,MATCH($A36,[1]Sheet1!$A$6:$A$72,0),MATCH(MID(CELL("filename",J35),FIND("]",CELL("filename",J35))+1,255) & CC$1,[1]Sheet1!$C$1:$CY$1 & [1]Sheet1!$C$3:$CY$3,0))} -> 2385819000 | CD36: =BP36-BQ36-BW36-BX36-CC36 -> 13058751000 | CE36: {=INDEX([1]Sheet1!$C$6:$CY$72,MATCH($A36,[1]Sheet1!$A$6:$A$72,0),MATCH(MID(CELL("filename",L35),FIND("]",CELL("filename",L35))+1,255) & CE$1,[1]Sheet1!$C$1:$CY$1 & [1]Sheet1!$C$3:$CY$3,0))} -> 104061900000 | CF36: =CE36-CK36 -> 96701049000 | CG36: {=INDEX([1]Sheet1!$C$6:$CY$72,MATCH($A36,[1]Sheet1!$A$6:$A$72,0),MATCH(MID(CELL("filename",N35),FIND("]",CELL("filename",N35))+1,255) & CG$1,[1]Sheet1!$C$1:$CY$1 & [1]Sheet1!$C$3:$CY$3,0))} -> 37040100000 | CH36: {=INDEX([1]Sheet1!$C$6:$CY$72,MATCH($A36,[1]Sheet1!$A$6:$A$72,0),MATCH(MID(CELL("filename",O35),FIND("]",CELL("filename",O35))+1,255) & CH$1,[1]Sheet1!$C$1:$CY$1 & [1]Sheet1!$C$3:$CY$3,0))} -> 6898250000 | CI36: {=INDEX([1]Sheet1!$C$6:$CY$72,MATCH($A36,[1]Sheet1!$A$6:$A$72,0),MATCH(MID(CELL("filename",P35),FIND("]",CELL("filename",P35))+1,255) & CI$1,[1]Sheet1!$C$1:$CY$1 & [1]Sheet1!$C$3:$CY$3,0))} -> 4302200000 | CJ36: {=INDEX([1]Sheet1!$C$6:$CY$72,MATCH($A36,[1]Sheet1!$A$6:$A$72,0),MATCH(MID(CELL("filename",R35),FIND("]",CELL("filename",R35))+1,255) & CJ$1,[1]Sheet1!$C$1:$CY$1 & [1]Sheet1!$C$3:$CY$3,0))} -> 37054400000 | CK36: {=INDEX([1]Sheet1!$C$6:$CY$72,MATCH($A36,[1]Sheet1!$A$6:$A$72,0),MATCH(MID(CELL("filename",S35),FIND("]",CELL("filename",S35))+1,255) & CK$1,[1]Sheet1!$C$1:$CY$1 & [1]Sheet1!$C$3:$CY$3,0))} -> 7360851000 | CL36: =CF36-CG36-CH36-CI36-CJ36 -> 11406099000 | DK36: =DL36/100*BC36 -> 1.2459658e+11 | DL36: {=INDEX([1]Sheet1!$C$6:$CY$72,MATCH($A36,[1]Sheet1!$A$6:$A$72,0),MATCH(MID(CELL("filename",AT35),FIND("]",CELL("filename",AT35))+1,255) & DL$1,[1]Sheet1!$C$1:$CY$1 & [1]Sheet1!$C$3:$CY$3,0))} -> 68.6324 | DM36: {=INDEX([5]DATA!$C$18:$T$51,MATCH($A36,[5]DATA!$B$18:$B$51,0),MATCH(MID(CELL("filename",AU3),FIND("]",CELL("filename",AU3))+1,255) & DM$1,[5]DATA!$C$15:$T$15&[5]DATA!$C$16:$T$16,0)) * 10^6} -> 1797000000 | DN36: {=INDEX([5]DATA!$C$18:$T$51,MATCH($A36,[5]DATA!$B$18:$B$51,0),MATCH(MID(CELL("filename",AV3),FIND("]",CELL("filename",AV3))+1,255) & DN$1,[5]DATA!$C$15:$T$15&[5]DATA!$C$16:$T$16,0)) * 10^6} -> 122800000000 | DQ36: 1.26975 | DR36: {=INDEX([1]Sheet1!$C$6:$CY$72,MATCH($A36,[1]Sheet1!$A$6:$A$72,0),MATCH(MID(CELL("filename",AZ35),FIND("]",CELL("filename",AZ35))+1,255) & DR$1,[1]Sheet1!$C$1:$CY$1 & [1]Sheet1!$C$3:$CY$3,0))} -> -8570000000 | DS36: {=INDEX([1]Sheet1!$C$6:$CY$72,MATCH($A36,[1]Sheet1!$A$6:$A$72,0),MATCH(MID(CELL("filename",BA35),FIND("]",CELL("filename",BA35))+1,255) & DS$1,[1]Sheet1!$C$1:$CY$1 & [1]Sheet1!$C$3:$CY$3,0))} -> 5.956544 | DT36: {=INDEX([5]DATA!$C$18:$T$51,MATCH($A36,[5]DATA!$B$18:$B$51,0),MATCH(MID(CELL("filename",BB3),FIND("]",CELL("filename",BB3))+1,255) & DT$1,[5]DATA!$C$15:$T$15&[5]DATA!$C$16:$T$16,0)) * 10^6} -> 10712000000 | DU36: {=INDEX([1]Sheet1!$C$6:$CY$72,MATCH($A36,[1]Sheet1!$A$6:$A$72,0),MATCH(MID(CELL("filename",BC35),FIND("]",CELL("filename",BC35))+1,255) & DU$1,[1]Sheet1!$C$1:$CY$1 & [1]Sheet1!$C$3:$CY$3,0))} -> 3.34 | DV36: 0.5 | DW36: =Euro_Area_Data!V33*10^9 -> 8.5771589e+12 | DX36: 1 | DY36: 0.5 | DZ36: {=INDEX([1]Sheet1!$C$6:$CY$72,MATCH($A36,[1]Sheet1!$A$6:$A$72,0),MATCH(MID(CELL("filename",BH35),FIND("]",CELL("filename",BH35))+1,255) & DZ$1,[1]Sheet1!$C$1:$CY$1 & [1]Sheet1!$C$3:$CY$3,0))} -> 6.32 | EA36: 2 | EB36: =SUMPRODUCT(Euro_Area_Data!C33:U33,Euro_Area_Data!Z33:AR33)/SUM(Euro_Area_Data!C33:U33) -> 0.70048799 | EC36: =(EB36-EB35)/EB35*100 -> 2.5780691 | EE36: -5 | EH36: 0.75 | EI36: 0.05 | EJ36: 75 | EK36: =(EN36-EN35)/EN35*100 -> -0.93409635 | EN36: =[2]EUCAM_output!$AE33 -> 0.69350725
A37: 1997 | B37: =[2]EUCAM_output!$E34*10^9 -> 2.7617804e+11 | H37: =[2]EUCAM_output!$AK34 -> 0.0071154456 | I37: =[2]EUCAM_output!$W34*10^3 -> 6047578 | K37: =IF(A37<2030,I37,K36*J37/J36) -> 6047578 | L37: =[2]EUCAM_output!$G34 -> 63.077976 | O37: =[2]EUCAM_output!$H34 -> 63.08472 | R37: =[2]EUCAM_output!$L34 -> 4.9 | U37: =[2]EUCAM_output!$K34 -> 4.167054 | V37: 4.167054 | W37: 0.014044723 | X37: -0.0075341587 | Y37: =[2]EUCAM_output!$AI34 -> -0.0056197968 | Z37: =[2]EUCAM_output!$M34 -> 1814.336 | AC37: =[2]EUCAM_output!$AL34 -> 1799.081 | AD37: =[2]EUCAM_output!$T34*10^9 -> 8.7427589e+11 | AE37: {=INDEX('[3]Sheet 1'!$B$12:$M$61,MATCH($A37,'[3]Sheet 1'!$A$12:$A$61,0),MATCH(MID(CELL("filename",A36),FIND("]",CELL("filename",A36))+1,255)&AE$1,'[3]Sheet 1'!$B$9:$M$9&'[3]Sheet 1'!$B$8:$M$8,0))*10^6} -> 621027200000 | AF37: {=INDEX('[3]Sheet 1'!$B$12:$M$61,MATCH($A37,'[3]Sheet 1'!$A$12:$A$61,0),MATCH(MID(CELL("filename",B36),FIND("]",CELL("filename",B36))+1,255)&AF$1,'[3]Sheet 1'!$B$9:$M$9&'[3]Sheet 1'!$B$8:$M$8,0))*10^6} -> 84536300000 | AG37: =AF37/AE37 -> 0.13612335 | AH37: =AD37*AG37 -> 1.1900936e+11 | AI37: =CH37/EN37 -> 8.1944962e+09 | AJ37: 4914780000 | AK37: =AJ37/EN37 -> 7.2013923e+09 | AL37: =AK37/AH37 -> 0.060511142 | AM37: =AVERAGE($AL$35:$AL$63) -> 0.065166448 | AN37: =AD37-AH37 -> 7.5526653e+11 | AO37: 42147100000 | AP37: =AO37/EN37 -> 6.1756131e+10 | AQ37: 31688000000 | AR37: =(AQ37-AJ37)/EN37 -> 3.922952e+10 | AS37: =AR37/AN37 -> 0.051941292 | AT37: =AP37/B37*100 -> 22.360986 | BB37: 2.7387537e+11 | BC37: =[2]EUCAM_output!$AG34*10^9 -> 187778740000 | BD37: =(BB37-B37)/B37*100 -> -0.83376098 | BN37: =BP37-CF37 -> 1845148000 | BO37: {=INDEX([1]Sheet1!$C$6:$CY$72,MATCH($A37,[1]Sheet1!$A$6:$A$72,0),MATCH(MID(CELL("filename",A36),FIND("]",CELL("filename",A36))+1,255) & BO$1,[1]Sheet1!$C$1:$CY$1 & [1]Sheet1!$C$3:$CY$3,0))} -> 0.987146 | BP37: {=INDEX([1]Sheet1!$C$6:$CY$72,MATCH($A37,[1]Sheet1!$A$6:$A$72,0),MATCH(MID(CELL("filename",B36),FIND("]",CELL("filename",B36))+1,255) & BP$1,[1]Sheet1!$C$1:$CY$1 & [1]Sheet1!$C$3:$CY$3,0))} -> 93563700000 | BQ37: {=INDEX([1]Sheet1!$C$6:$CY$72,MATCH($A37,[1]Sheet1!$A$6:$A$72,0),MATCH(MID(CELL("filename",C36),FIND("]",CELL("filename",C36))+1,255) & BQ$1,[1]Sheet1!$C$1:$CY$1 & [1]Sheet1!$C$3:$CY$3,0))} -> 25389520000 | BW37: {=INDEX([1]Sheet1!$C$6:$CY$72,MATCH($A37,[1]Sheet1!$A$6:$A$72,0),MATCH(MID(CELL("filename",F36),FIND("]",CELL("filename",F36))+1,255) & BW$1,[1]Sheet1!$C$1:$CY$1 & [1]Sheet1!$C$3:$CY$3,0))} -> 28522830000 | BX37: {=INDEX([1]Sheet1!$C$6:$CY$72,MATCH($A37,[1]Sheet1!$A$6:$A$72,0),MATCH(MID(CELL("filename",G36),FIND("]",CELL("filename",G36))+1,255) & BX$1,[1]Sheet1!$C$1:$CY$1 & [1]Sheet1!$C$3:$CY$3,0))} -> 28009980000 | BY37: {=INDEX([4]DATA!$C$18:$N$51,MATCH($A37,[4]DATA!$B$18:$B$51,0),MATCH(MID(CELL("filename",F4),FIND("]",CELL("filename",F4))+1,255) & BY$1,[4]DATA!$C$15:$N$15&[4]DATA!$C$16:$N$16,0)) * 10^6} -> 14547000000 | BZ37: {=INDEX([4]DATA!$C$18:$N$51,MATCH($A37,[4]DATA!$B$18:$B$51,0),MATCH(MID(CELL("filename",G4),FIND("]",CELL("filename",G4))+1,255) & BZ$1,[4]DATA!$C$15:$N$15&[4]DATA!$C$16:$N$16,0)) * 10^6} -> 13593000000 | CA37: =$BX37*BY37/SUM($BY37:$BZ37) -> 1.4479786e+10 | CB37: =BX37-CA37 -> 1.3530194e+10 | CC37: {=INDEX([1]Sheet1!$C$6:$CY$72,MATCH($A37,[1]Sheet1!$A$6:$A$72,0),MATCH(MID(CELL("filename",J36),FIND("]",CELL("filename",J36))+1,255) & CC$1,[1]Sheet1!$C$1:$CY$1 & [1]Sheet1!$C$3:$CY$3,0))} -> 2334354000 | CD37: =BP37-BQ37-BW37-BX37-CC37 -> 9307016000 | CE37: {=INDEX([1]Sheet1!$C$6:$CY$72,MATCH($A37,[1]Sheet1!$A$6:$A$72,0),MATCH(MID(CELL("filename",L36),FIND("]",CELL("filename",L36))+1,255) & CE$1,[1]Sheet1!$C$1:$CY$1 & [1]Sheet1!$C$3:$CY$3,0))} -> 98465300000 | CF37: =CE37-CK37 -> 91718552000 | CG37: {=INDEX([1]Sheet1!$C$6:$CY$72,MATCH($A37,[1]Sheet1!$A$6:$A$72,0),MATCH(MID(CELL("filename",N36),FIND("]",CELL("filename",N36))+1,255) & CG$1,[1]Sheet1!$C$1:$CY$1 & [1]Sheet1!$C$3:$CY$3,0))} -> 37209800000 | CH37: {=INDEX([1]Sheet1!$C$6:$CY$72,MATCH($A37,[1]Sheet1!$A$6:$A$72,0),MATCH(MID(CELL("filename",O36),FIND("]",CELL("filename",O36))+1,255) & CH$1,[1]Sheet1!$C$1:$CY$1 & [1]Sheet1!$C$3:$CY$3,0))} -> 5592550000 | CI37: {=INDEX([1]Sheet1!$C$6:$CY$72,MATCH($A37,[1]Sheet1!$A$6:$A$72,0),MATCH(MID(CELL("filename",P36),FIND("]",CELL("filename",P36))+1,255) & CI$1,[1]Sheet1!$C$1:$CY$1 & [1]Sheet1!$C$3:$CY$3,0))} -> 4048990000 | CJ37: {=INDEX([1]Sheet1!$C$6:$CY$72,MATCH($A37,[1]Sheet1!$A$6:$A$72,0),MATCH(MID(CELL("filename",R36),FIND("]",CELL("filename",R36))+1,255) & CJ$1,[1]Sheet1!$C$1:$CY$1 & [1]Sheet1!$C$3:$CY$3,0))} -> 36042600000 | CK37: {=INDEX([1]Sheet1!$C$6:$CY$72,MATCH($A37,[1]Sheet1!$A$6:$A$72,0),MATCH(MID(CELL("filename",S36),FIND("]",CELL("filename",S36))+1,255) & CK$1,[1]Sheet1!$C$1:$CY$1 & [1]Sheet1!$C$3:$CY$3,0))} -> 6746748000 | CL37: =CF37-CG37-CH37-CI37-CJ37 -> 8824612000 | DK37: =DL37/100*BC37 -> 1.1999794e+11 | DL37: {=INDEX([1]Sheet1!$C$6:$CY$72,MATCH($A37,[1]Sheet1!$A$6:$A$72,0),MATCH(MID(CELL("filename",AT36),FIND("]",CELL("filename",AT36))+1,255) & DL$1,[1]Sheet1!$C$1:$CY$1 & [1]Sheet1!$C$3:$CY$3,0))} -> 63.9039 | DM37: {=INDEX([5]DATA!$C$18:$T$51,MATCH($A37,[5]DATA!$B$18:$B$51,0),MATCH(MID(CELL("filename",AU4),FIND("]",CELL("filename",AU4))+1,255) & DM$1,[5]DATA!$C$15:$T$15&[5]DATA!$C$16:$T$16,0)) * 10^6} -> 2851000000 | DN37: {=INDEX([5]DATA!$C$18:$T$51,MATCH($A37,[5]DATA!$B$18:$B$51,0),MATCH(MID(CELL("filename",AV4),FIND("]",CELL("filename",AV4))+1,255) & DN$1,[5]DATA!$C$15:$T$15&[5]DATA!$C$16:$T$16,0)) * 10^6} -> 117147000000 | DQ37: 1.13404 | DR37: {=INDEX([1]Sheet1!$C$6:$CY$72,MATCH($A37,[1]Sheet1!$A$6:$A$72,0),MATCH(MID(CELL("filename",AZ36),FIND("]",CELL("filename",AZ36))+1,255) & DR$1,[1]Sheet1!$C$1:$CY$1 & [1]Sheet1!$C$3:$CY$3,0))} -> -11300000000 | DS37: {=INDEX([1]Sheet1!$C$6:$CY$72,MATCH($A37,[1]Sheet1!$A$6:$A$72,0),MATCH(MID(CELL("filename",BA36),FIND("]",CELL("filename",BA36))+1,255) & DS$1,[1]Sheet1!$C$1:$CY$1 & [1]Sheet1!$C$3:$CY$3,0))} -> 5.43994 | DT37: {=INDEX([5]DATA!$C$18:$T$51,MATCH($A37,[5]DATA!$B$18:$B$51,0),MATCH(MID(CELL("filename",BB4),FIND("]",CELL("filename",BB4))+1,255) & DT$1,[5]DATA!$C$15:$T$15&[5]DATA!$C$16:$T$16,0)) * 10^6} -> 12846000000 | DU37: {=INDEX([1]Sheet1!$C$6:$CY$72,MATCH($A37,[1]Sheet1!$A$6:$A$72,0),MATCH(MID(CELL("filename",BC36),FIND("]",CELL("filename",BC36))+1,255) & DU$1,[1]Sheet1!$C$1:$CY$1 & [1]Sheet1!$C$3:$CY$3,0))} -> 3.51 | DV37: 0.5 | DW37: =Euro_Area_Data!V34*10^9 -> 8.8141556e+12 | DX37: 1 | DY37: 0.5 | DZ37: {=INDEX([1]Sheet1!$C$6:$CY$72,MATCH($A37,[1]Sheet1!$A$6:$A$72,0),MATCH(MID(CELL("filename",BH36),FIND("]",CELL("filename",BH36))+1,255) & DZ$1,[1]Sheet1!$C$1:$CY$1 & [1]Sheet1!$C$3:$CY$3,0))} -> 5.68 | EA37: 2 | EB37: =SUMPRODUCT(Euro_Area_Data!C34:U34,Euro_Area_Data!Z34:AR34)/SUM(Euro_Area_Data!C34:U34) -> 0.6986876 | EC37: =(EB37-EB36)/EB36*100 -> -0.25701867 | EE37: -5 | EH37: 0.75 | EI37: 0.05 | EJ37: 75 | EK37: =(EN37-EN36)/EN36*100 -> -1.5905945 | EN37: =[2]EUCAM_output!$AE34 -> 0.68247636
A38: 1998 | B38: =[2]EUCAM_output!$E35*10^9 -> 2.83262e+11 | H38: =[2]EUCAM_output!$AK35 -> 0.029514827 | I38: =[2]EUCAM_output!$W35*10^3 -> 6051531 | K38: =IF(A38<2030,I38,K37*J38/J37) -> 6051531 | L38: =[2]EUCAM_output!$G35 -> 63.540328 | O38: =[2]EUCAM_output!$H35 -> 63.376616 | R38: =[2]EUCAM_output!$L35 -> 4.7 | U38: =[2]EUCAM_output!$K35 -> 4.191592 | V38: 4.191592 | W38: 0.024572284 | X38: -0.010418019 | Y38: =[2]EUCAM_output!$AI35 -> 0.018226737 | Z38: =[2]EUCAM_output!$M35 -> 1792.7671 | AC38: =[2]EUCAM_output!$AL35 -> 1798.0627 | AD38: =[2]EUCAM_output!$T35*10^9 -> 8.9739999e+11 | AE38: {=INDEX('[3]Sheet 1'!$B$12:$M$61,MATCH($A38,'[3]Sheet 1'!$A$12:$A$61,0),MATCH(MID(CELL("filename",A37),FIND("]",CELL("filename",A37))+1,255)&AE$1,'[3]Sheet 1'!$B$9:$M$9&'[3]Sheet 1'!$B$8:$M$8,0))*10^6} -> 640582100000 | AF38: {=INDEX('[3]Sheet 1'!$B$12:$M$61,MATCH($A38,'[3]Sheet 1'!$A$12:$A$61,0),MATCH(MID(CELL("filename",B37),FIND("]",CELL("filename",B37))+1,255)&AF$1,'[3]Sheet 1'!$B$9:$M$9&'[3]Sheet 1'!$B$8:$M$8,0))*10^6} -> 85665600000 | AG38: =AF38/AE38 -> 0.13373087 | AH38: =AD38*AG38 -> 1.2001008e+11 | AI38: =CH38/EN38 -> 8.3467515e+09 | AJ38: 5046740000 | AK38: =AJ38/EN38 -> 7.3755077e+09 | AL38: =AK38/AH38 -> 0.061457402 | AM38: =AVERAGE($AL$35:$AL$63) -> 0.065166448 | AN38: =AD38-AH38 -> 7.7738991e+11 | AO38: 43905800000 | AP38: =AO38/EN38 -> 6.4165692e+10 | AQ38: 3.22582e+10 | AR38: =(AQ38-AJ38)/EN38 -> 3.9767916e+10 | AS38: =AR38/AN38 -> 0.051155688 | AT38: =AP38/B38*100 -> 22.652418 | BB38: 2.8344151e+11 | BC38: =[2]EUCAM_output!$AG35*10^9 -> 195274450000 | BD38: =(BB38-B38)/B38*100 -> 0.063372221 | BN38: =BP38-CF38 -> 1634289000 | BO38: {=INDEX([1]Sheet1!$C$6:$CY$72,MATCH($A38,[1]Sheet1!$A$6:$A$72,0),MATCH(MID(CELL("filename",A37),FIND("]",CELL("filename",A37))+1,255) & BO$1,[1]Sheet1!$C$1:$CY$1 & [1]Sheet1!$C$3:$CY$3,0))} -> 0.842629 | BP38: {=INDEX([1]Sheet1!$C$6:$CY$72,MATCH($A38,[1]Sheet1!$A$6:$A$72,0),MATCH(MID(CELL("filename",B37),FIND("]",CELL("filename",B37))+1,255) & BP$1,[1]Sheet1!$C$1:$CY$1 & [1]Sheet1!$C$3:$CY$3,0))} -> 96767400000 | BQ38: {=INDEX([1]Sheet1!$C$6:$CY$72,MATCH($A38,[1]Sheet1!$A$6:$A$72,0),MATCH(MID(CELL("filename",C37),FIND("]",CELL("filename",C37))+1,255) & BQ$1,[1]Sheet1!$C$1:$CY$1 & [1]Sheet1!$C$3:$CY$3,0))} -> 26662500000 | BW38: {=INDEX([1]Sheet1!$C$6:$CY$72,MATCH($A38,[1]Sheet1!$A$6:$A$72,0),MATCH(MID(CELL("filename",F37),FIND("]",CELL("filename",F37))+1,255) & BW$1,[1]Sheet1!$C$1:$CY$1 & [1]Sheet1!$C$3:$CY$3,0))} -> 29414720000 | BX38: {=INDEX([1]Sheet1!$C$6:$CY$72,MATCH($A38,[1]Sheet1!$A$6:$A$72,0),MATCH(MID(CELL("filename",G37),FIND("]",CELL("filename",G37))+1,255) & BX$1,[1]Sheet1!$C$1:$CY$1 & [1]Sheet1!$C$3:$CY$3,0))} -> 28902660000 | BY38: {=INDEX([4]DATA!$C$18:$N$51,MATCH($A38,[4]DATA!$B$18:$B$51,0),MATCH(MID(CELL("filename",F5),FIND("]",CELL("filename",F5))+1,255) & BY$1,[4]DATA!$C$15:$N$15&[4]DATA!$C$16:$N$16,0)) * 10^6} -> 15280000000 | BZ38: {=INDEX([4]DATA!$C$18:$N$51,MATCH($A38,[4]DATA!$B$18:$B$51,0),MATCH(MID(CELL("filename",G5),FIND("]",CELL("filename",G5))+1,255) & BZ$1,[4]DATA!$C$15:$N$15&[4]DATA!$C$16:$N$16,0)) * 10^6} -> 13821000000 | CA38: =$BX38*BY38/SUM($BY38:$BZ38) -> 1.5175858e+10 | CB38: =BX38-CA38 -> 1.3726802e+10 | CC38: {=INDEX([1]Sheet1!$C$6:$CY$72,MATCH($A38,[1]Sheet1!$A$6:$A$72,0),MATCH(MID(CELL("filename",J37),FIND("]",CELL("filename",J37))+1,255) & CC$1,[1]Sheet1!$C$1:$CY$1 & [1]Sheet1!$C$3:$CY$3,0))} -> 2382172000 | CD38: =BP38-BQ38-BW38-BX38-CC38 -> 9405348000 | CE38: {=INDEX([1]Sheet1!$C$6:$CY$72,MATCH($A38,[1]Sheet1!$A$6:$A$72,0),MATCH(MID(CELL("filename",L37),FIND("]",CELL("filename",L37))+1,255) & CE$1,[1]Sheet1!$C$1:$CY$1 & [1]Sheet1!$C$3:$CY$3,0))} -> 102108300000 | CF38: =CE38-CK38 -> 95133111000 | CG38: {=INDEX([1]Sheet1!$C$6:$CY$72,MATCH($A38,[1]Sheet1!$A$6:$A$72,0),MATCH(MID(CELL("filename",N37),FIND("]",CELL("filename",N37))+1,255) & CG$1,[1]Sheet1!$C$1:$CY$1 & [1]Sheet1!$C$3:$CY$3,0))} -> 38557800000 | CH38: {=INDEX([1]Sheet1!$C$6:$CY$72,MATCH($A38,[1]Sheet1!$A$6:$A$72,0),MATCH(MID(CELL("filename",O37),FIND("]",CELL("filename",O37))+1,255) & CH$1,[1]Sheet1!$C$1:$CY$1 & [1]Sheet1!$C$3:$CY$3,0))} -> 5711320000 | CI38: {=INDEX([1]Sheet1!$C$6:$CY$72,MATCH($A38,[1]Sheet1!$A$6:$A$72,0),MATCH(MID(CELL("filename",P37),FIND("]",CELL("filename",P37))+1,255) & CI$1,[1]Sheet1!$C$1:$CY$1 & [1]Sheet1!$C$3:$CY$3,0))} -> 4656670000 | CJ38: {=INDEX([1]Sheet1!$C$6:$CY$72,MATCH($A38,[1]Sheet1!$A$6:$A$72,0),MATCH(MID(CELL("filename",R37),FIND("]",CELL("filename",R37))+1,255) & CJ$1,[1]Sheet1!$C$1:$CY$1 & [1]Sheet1!$C$3:$CY$3,0))} -> 36655800000 | CK38: {=INDEX([1]Sheet1!$C$6:$CY$72,MATCH($A38,[1]Sheet1!$A$6:$A$72,0),MATCH(MID(CELL("filename",S37),FIND("]",CELL("filename",S37))+1,255) & CK$1,[1]Sheet1!$C$1:$CY$1 & [1]Sheet1!$C$3:$CY$3,0))} -> 6975189000 | CL38: =CF38-CG38-CH38-CI38-CJ38 -> 9551521000 | DK38: =DL38/100*BC38 -> 1.2565013e+11 | DL38: {=INDEX([1]Sheet1!$C$6:$CY$72,MATCH($A38,[1]Sheet1!$A$6:$A$72,0),MATCH(MID(CELL("filename",AT37),FIND("]",CELL("filename",AT37))+1,255) & DL$1,[1]Sheet1!$C$1:$CY$1 & [1]Sheet1!$C$3:$CY$3,0))} -> 64.3454 | DM38: {=INDEX([5]DATA!$C$18:$T$51,MATCH($A38,[5]DATA!$B$18:$B$51,0),MATCH(MID(CELL("filename",AU5),FIND("]",CELL("filename",AU5))+1,255) & DM$1,[5]DATA!$C$15:$T$15&[5]DATA!$C$16:$T$16,0)) * 10^6} -> 722000000 | DN38: {=INDEX([5]DATA!$C$18:$T$51,MATCH($A38,[5]DATA!$B$18:$B$51,0),MATCH(MID(CELL("filename",AV5),FIND("]",CELL("filename",AV5))+1,255) & DN$1,[5]DATA!$C$15:$T$15&[5]DATA!$C$16:$T$16,0)) * 10^6} -> 124929000000 | DQ38: 1.12109 | DR38: {=INDEX([1]Sheet1!$C$6:$CY$72,MATCH($A38,[1]Sheet1!$A$6:$A$72,0),MATCH(MID(CELL("filename",AZ37),FIND("]",CELL("filename",AZ37))+1,255) & DR$1,[1]Sheet1!$C$1:$CY$1 & [1]Sheet1!$C$3:$CY$3,0))} -> 1530000000 | DS38: {=INDEX([1]Sheet1!$C$6:$CY$72,MATCH($A38,[1]Sheet1!$A$6:$A$72,0),MATCH(MID(CELL("filename",BA37),FIND("]",CELL("filename",BA37))+1,255) & DS$1,[1]Sheet1!$C$1:$CY$1 & [1]Sheet1!$C$3:$CY$3,0))} -> 5.852548 | DT38: {=INDEX([5]DATA!$C$18:$T$51,MATCH($A38,[5]DATA!$B$18:$B$51,0),MATCH(MID(CELL("filename",BB5),FIND("]",CELL("filename",BB5))+1,255) & DT$1,[5]DATA!$C$15:$T$15&[5]DATA!$C$16:$T$16,0)) * 10^6} -> 12207000000 | DU38: {=INDEX([1]Sheet1!$C$6:$CY$72,MATCH($A38,[1]Sheet1!$A$6:$A$72,0),MATCH(MID(CELL("filename",BC37),FIND("]",CELL("filename",BC37))+1,255) & DU$1,[1]Sheet1!$C$1:$CY$1 & [1]Sheet1!$C$3:$CY$3,0))} -> 3.58 | DV38: 0.5 | DW38: =Euro_Area_Data!V35*10^9 -> 9.0783722e+12 | DX38: 1 | DY38: 0.5 | DZ38: {=INDEX([1]Sheet1!$C$6:$CY$72,MATCH($A38,[1]Sheet1!$A$6:$A$72,0),MATCH(MID(CELL("filename",BH37),FIND("]",CELL("filename",BH37))+1,255) & DZ$1,[1]Sheet1!$C$1:$CY$1 & [1]Sheet1!$C$3:$CY$3,0))} -> 4.71 | EA38: 2 | EB38: =SUMPRODUCT(Euro_Area_Data!C35:U35,Euro_Area_Data!Z35:AR35)/SUM(Euro_Area_Data!C35:U35) -> 0.70611013 | EC38: =(EB38-EB37)/EB37*100 -> 1.0623532 | EE38: -5 | EH38: 0.75 | EI38: 0.05 | EJ38: 60 | EK38: =(EN38-EN37)/EN37*100 -> 0.26085345 | EN38: =[2]EUCAM_output!$AE35 -> 0.68425663
A39: 1999 | B39: =[2]EUCAM_output!$E36*10^9 -> 2.9060144e+11 | H39: =[2]EUCAM_output!$AK36 -> 0.012727421 | I39: =[2]EUCAM_output!$W36*10^3 -> 6062468 | K39: =IF(A39<2030,I39,K38*J39/J38) -> 6062468 | L39: =[2]EUCAM_output!$G36 -> 63.91752 | O39: =[2]EUCAM_output!$H36 -> 63.687551 | R39: =[2]EUCAM_output!$L36 -> 4 | U39: =[2]EUCAM_output!$K36 -> 4.215855 | V39: 4.215855 | W39: 0.022127364 | X39: -0.012799093 | Y39: =[2]EUCAM_output!$AI36 -> -0.0071317162 | Z39: =[2]EUCAM_output!$M36 -> 1796.4866 | AC39: =[2]EUCAM_output!$AL36 -> 1796.0975 | AD39: =[2]EUCAM_output!$T36*10^9 -> 9.1982962e+11 | AE39: {=INDEX('[3]Sheet 1'!$B$12:$M$61,MATCH($A39,'[3]Sheet 1'!$A$12:$A$61,0),MATCH(MID(CELL("filename",A38),FIND("]",CELL("filename",A38))+1,255)&AE$1,'[3]Sheet 1'!$B$9:$M$9&'[3]Sheet 1'!$B$8:$M$8,0))*10^6} -> 668729000000 | AF39: {=INDEX('[3]Sheet 1'!$B$12:$M$61,MATCH($A39,'[3]Sheet 1'!$A$12:$A$61,0),MATCH(MID(CELL("filename",B38),FIND("]",CELL("filename",B38))+1,255)&AF$1,'[3]Sheet 1'!$B$9:$M$9&'[3]Sheet 1'!$B$8:$M$8,0))*10^6} -> 87926200000 | AG39: =AF39/AE39 -> 0.13148256 | AH39: =AD39*AG39 -> 1.2094155e+11 | AI39: =CH39/EN39 -> 8.4771e+09 | AJ39: 5229660000 | AK39: =AJ39/EN39 -> 7.5742566e+09 | AL39: =AK39/AH39 -> 0.062627413 | AM39: =AVERAGE($AL$35:$AL$63) -> 0.065166448 | AN39: =AD39-AH39 -> 7.9888807e+11 | AO39: 45073900000 | AP39: =AO39/EN39 -> 6.5281736e+10 | AQ39: 32596700000 | AR39: =(AQ39-AJ39)/EN39 -> 3.9636417e+10 | AS39: =AR39/AN39 -> 0.049614481 | AT39: =AP39/B39*100 -> 22.464354 | BB39: 2.9410436e+11 | BC39: =[2]EUCAM_output!$AG36*10^9 -> 203064920000 | BD39: =(BB39-B39)/B39*100 -> 1.2054029 | BN39: =BP39-CF39 -> 1671750000 | BO39: {=INDEX([1]Sheet1!$C$6:$CY$72,MATCH($A39,[1]Sheet1!$A$6:$A$72,0),MATCH(MID(CELL("filename",A38),FIND("]",CELL("filename",A38))+1,255) & BO$1,[1]Sheet1!$C$1:$CY$1 & [1]Sheet1!$C$3:$CY$3,0))} -> 0.823234 | BP39: {=INDEX([1]Sheet1!$C$6:$CY$72,MATCH($A39,[1]Sheet1!$A$6:$A$72,0),MATCH(MID(CELL("filename",B38),FIND("]",CELL("filename",B38))+1,255) & BP$1,[1]Sheet1!$C$1:$CY$1 & [1]Sheet1!$C$3:$CY$3,0))} -> 101085000000 | BQ39: {=INDEX([1]Sheet1!$C$6:$CY$72,MATCH($A39,[1]Sheet1!$A$6:$A$72,0),MATCH(MID(CELL("filename",C38),FIND("]",CELL("filename",C38))+1,255) & BQ$1,[1]Sheet1!$C$1:$CY$1 & [1]Sheet1!$C$3:$CY$3,0))} -> 27016490000 | BR39: {=INDEX([6]Annual!$C$5:$T$30,MATCH($A39,[6]Annual!$B$5:$B$30,0),MATCH(MID(CELL("filename",$F$2),FIND("]",CELL("filename",$F$2))+1,255) & BR$1,[6]Annual!$C$3:$T$3 & [6]Annual!$C$4:$T$4,0))} -> 23194700000 | BS39: {=INDEX([6]Annual!$C$5:$T$30,MATCH($A39,[6]Annual!$B$5:$B$30,0),MATCH(MID(CELL("filename",$F$2),FIND("]",CELL("filename",$F$2))+1,255) & BS$1,[6]Annual!$C$3:$T$3 & [6]Annual!$C$4:$T$4,0))} -> 2.9798e+09 | BT39: {=INDEX([6]Annual!$C$5:$T$30,MATCH($A39,[6]Annual!$B$5:$B$30,0),MATCH(MID(CELL("filename",$F$2),FIND("]",CELL("filename",$F$2))+1,255) & BT$1,[6]Annual!$C$3:$T$3 & [6]Annual!$C$4:$T$4,0))} -> 863400000 | BU39: =BQ39*BR39/SUM($BR39:$BT39) -> 2.3176333e+10 | BV39: =BQ39-BU39 -> 3.8401568e+09 | BW39: {=INDEX([1]Sheet1!$C$6:$CY$72,MATCH($A39,[1]Sheet1!$A$6:$A$72,0),MATCH(MID(CELL("filename",F38),FIND("]",CELL("filename",F38))+1,255) & BW$1,[1]Sheet1!$C$1:$CY$1 & [1]Sheet1!$C$3:$CY$3,0))} -> 30965230000 | BX39: {=INDEX([1]Sheet1!$C$6:$CY$72,MATCH($A39,[1]Sheet1!$A$6:$A$72,0),MATCH(MID(CELL("filename",G38),FIND("]",CELL("filename",G38))+1,255) & BX$1,[1]Sheet1!$C$1:$CY$1 & [1]Sheet1!$C$3:$CY$3,0))} -> 30124590000 | BY39: {=INDEX([4]DATA!$C$18:$N$51,MATCH($A39,[4]DATA!$B$18:$B$51,0),MATCH(MID(CELL("filename",F6),FIND("]",CELL("filename",F6))+1,255) & BY$1,[4]DATA!$C$15:$N$15&[4]DATA!$C$16:$N$16,0)) * 10^6} -> 15820000000 | BZ39: {=INDEX([4]DATA!$C$18:$N$51,MATCH($A39,[4]DATA!$B$18:$B$51,0),MATCH(MID(CELL("filename",G6),FIND("]",CELL("filename",G6))+1,255) & BZ$1,[4]DATA!$C$15:$N$15&[4]DATA!$C$16:$N$16,0)) * 10^6} -> 14304000000 | CA39: =$BX39*BY39/SUM($BY39:$BZ39) -> 1.582031e+10 | CB39: =BX39-CA39 -> 1.430428e+10 | CC39: {=INDEX([1]Sheet1!$C$6:$CY$72,MATCH($A39,[1]Sheet1!$A$6:$A$72,0),MATCH(MID(CELL("filename",J38),FIND("]",CELL("filename",J38))+1,255) & CC$1,[1]Sheet1!$C$1:$CY$1 & [1]Sheet1!$C$3:$CY$3,0))} -> 2507970000 | CD39: =BP39-BQ39-BW39-BX39-CC39 -> 10470720000 | CE39: {=INDEX([1]Sheet1!$C$6:$CY$72,MATCH($A39,[1]Sheet1!$A$6:$A$72,0),MATCH(MID(CELL("filename",L38),FIND("]",CELL("filename",L38))+1,255) & CE$1,[1]Sheet1!$C$1:$CY$1 & [1]Sheet1!$C$3:$CY$3,0))} -> 106429100000 | CF39: =CE39-CK39 -> 99413250000 | CG39: {=INDEX([1]Sheet1!$C$6:$CY$72,MATCH($A39,[1]Sheet1!$A$6:$A$72,0),MATCH(MID(CELL("filename",N38),FIND("]",CELL("filename",N38))+1,255) & CG$1,[1]Sheet1!$C$1:$CY$1 & [1]Sheet1!$C$3:$CY$3,0))} -> 40881300000 | CH39: {=INDEX([1]Sheet1!$C$6:$CY$72,MATCH($A39,[1]Sheet1!$A$6:$A$72,0),MATCH(MID(CELL("filename",O38),FIND("]",CELL("filename",O38))+1,255) & CH$1,[1]Sheet1!$C$1:$CY$1 & [1]Sheet1!$C$3:$CY$3,0))} -> 5853030000 | CI39: {=INDEX([1]Sheet1!$C$6:$CY$72,MATCH($A39,[1]Sheet1!$A$6:$A$72,0),MATCH(MID(CELL("filename",P38),FIND("]",CELL("filename",P38))+1,255) & CI$1,[1]Sheet1!$C$1:$CY$1 & [1]Sheet1!$C$3:$CY$3,0))} -> 4530720000 | CJ39: {=INDEX([1]Sheet1!$C$6:$CY$72,MATCH($A39,[1]Sheet1!$A$6:$A$72,0),MATCH(MID(CELL("filename",R38),FIND("]",CELL("filename",R38))+1,255) & CJ$1,[1]Sheet1!$C$1:$CY$1 & [1]Sheet1!$C$3:$CY$3,0))} -> 38429800000 | CK39: {=INDEX([1]Sheet1!$C$6:$CY$72,MATCH($A39,[1]Sheet1!$A$6:$A$72,0),MATCH(MID(CELL("filename",S38),FIND("]",CELL("filename",S38))+1,255) & CK$1,[1]Sheet1!$C$1:$CY$1 & [1]Sheet1!$C$3:$CY$3,0))} -> 7015850000 | CL39: =CF39-CG39-CH39-CI39-CJ39 -> 9718400000 | DK39: =DL39/100*BC39 -> 1.3621615e+11 | DL39: {=INDEX([1]Sheet1!$C$6:$CY$72,MATCH($A39,[1]Sheet1!$A$6:$A$72,0),MATCH(MID(CELL("filename",AT38),FIND("]",CELL("filename",AT38))+1,255) & DL$1,[1]Sheet1!$C$1:$CY$1 & [1]Sheet1!$C$3:$CY$3,0))} -> 67.0801 | DM39: {=INDEX([5]DATA!$C$18:$T$51,MATCH($A39,[5]DATA!$B$18:$B$51,0),MATCH(MID(CELL("filename",AU6),FIND("]",CELL("filename",AU6))+1,255) & DM$1,[5]DATA!$C$15:$T$15&[5]DATA!$C$16:$T$16,0)) * 10^6} -> 5679000000 | DN39: {=INDEX([5]DATA!$C$18:$T$51,MATCH($A39,[5]DATA!$B$18:$B$51,0),MATCH(MID(CELL("filename",AV6),FIND("]",CELL("filename",AV6))+1,255) & DN$1,[5]DATA!$C$15:$T$15&[5]DATA!$C$16:$T$16,0)) * 10^6} -> 130537000000 | DQ39: 1.065776 | DR39: {=INDEX([1]Sheet1!$C$6:$CY$72,MATCH($A39,[1]Sheet1!$A$6:$A$72,0),MATCH(MID(CELL("filename",AZ38),FIND("]",CELL("filename",AZ38))+1,255) & DR$1,[1]Sheet1!$C$1:$CY$1 & [1]Sheet1!$C$3:$CY$3,0))} -> 5220000000 | DS39: {=INDEX([1]Sheet1!$C$6:$CY$72,MATCH($A39,[1]Sheet1!$A$6:$A$72,0),MATCH(MID(CELL("filename",BA38),FIND("]",CELL("filename",BA38))+1,255) & DS$1,[1]Sheet1!$C$1:$CY$1 & [1]Sheet1!$C$3:$CY$3,0))} -> 5.583636 | DT39: {=INDEX([5]DATA!$C$18:$T$51,MATCH($A39,[5]DATA!$B$18:$B$51,0),MATCH(MID(CELL("filename",BB6),FIND("]",CELL("filename",BB6))+1,255) & DT$1,[5]DATA!$C$15:$T$15&[5]DATA!$C$16:$T$16,0)) * 10^6} -> 12031000000 | DU39: {=INDEX([1]Sheet1!$C$6:$CY$72,MATCH($A39,[1]Sheet1!$A$6:$A$72,0),MATCH(MID(CELL("filename",BC38),FIND("]",CELL("filename",BC38))+1,255) & DU$1,[1]Sheet1!$C$1:$CY$1 & [1]Sheet1!$C$3:$CY$3,0))} -> 2.96 | DV39: 0.5 | DW39: =Euro_Area_Data!V36*10^9 -> 9.3514721e+12 | DX39: 1 | DY39: 0.5 | DZ39: {=INDEX([1]Sheet1!$C$6:$CY$72,MATCH($A39,[1]Sheet1!$A$6:$A$72,0),MATCH(MID(CELL("filename",BH38),FIND("]",CELL("filename",BH38))+1,255) & DZ$1,[1]Sheet1!$C$1:$CY$1 & [1]Sheet1!$C$3:$CY$3,0))} -> 4.68 | EA39: 2 | EB39: =SUMPRODUCT(Euro_Area_Data!C36:U36,Euro_Area_Data!Z36:AR36)/SUM(Euro_Area_Data!C36:U36) -> 0.71777776 | EC39: =(EB39-EB38)/EB38*100 -> 1.6523804 | EE39: -5 | EH39: 0.75 | EI39: 0.05 | EJ39: 60 | EK39: =(EN39-EN38)/EN38*100 -> 0.90540522 | EN39: =[2]EUCAM_output!$AE36 -> 0.69045192
A40: 2000 | B40: =[2]EUCAM_output!$E37*10^9 -> 2.981603e+11 | H40: =[2]EUCAM_output!$AK37 -> 0.035967766 | I40: =[2]EUCAM_output!$W37*10^3 -> 6078397.5 | K40: =IF(A40<2030,I40,K39*J40/J39) -> 6078397.5 | L40: =[2]EUCAM_output!$G37 -> 64.222529 | O40: =[2]EUCAM_output!$H37 -> 63.988861 | R40: =[2]EUCAM_output!$L37 -> 3.8 | U40: =[2]EUCAM_output!$K37 -> 4.272902 | V40: 4.272902 | W40: 0.022173539 | X40: -0.0060918076 | Y40: =[2]EUCAM_output!$AI37 -> 0.0035074731 | Z40: =[2]EUCAM_output!$M37 -> 1797.3227 | AC40: =[2]EUCAM_output!$AL37 -> 1792.8394 | AD40: =[2]EUCAM_output!$T37*10^9 -> 9.4451717e+11 | AE40: {=INDEX('[3]Sheet 1'!$B$12:$M$61,MATCH($A40,'[3]Sheet 1'!$A$12:$A$61,0),MATCH(MID(CELL("filename",A39),FIND("]",CELL("filename",A39))+1,255)&AE$1,'[3]Sheet 1'!$B$9:$M$9&'[3]Sheet 1'!$B$8:$M$8,0))*10^6} -> 696587100000 | AF40: {=INDEX('[3]Sheet 1'!$B$12:$M$61,MATCH($A40,'[3]Sheet 1'!$A$12:$A$61,0),MATCH(MID(CELL("filename",B39),FIND("]",CELL("filename",B39))+1,255)&AF$1,'[3]Sheet 1'!$B$9:$M$9&'[3]Sheet 1'!$B$8:$M$8,0))*10^6} -> 89306200000 | AG40: =AF40/AE40 -> 0.12820536 | AH40: =AD40*AG40 -> 1.2109216e+11 | AI40: =CH40/EN40 -> 8.2001302e+09 | AJ40: 5408590000 | AK40: =AJ40/EN40 -> 7.7277434e+09 | AL40: =AK40/AH40 -> 0.06381704 | AM40: =AVERAGE($AL$35:$AL$63) -> 0.065166448 | AN40: =AD40-AH40 -> 8.23425e+11 | AO40: 48862200000 | AP40: =AO40/EN40 -> 6.9813859e+10 | AQ40: 33807100000 | AR40: =(AQ40-AJ40)/EN40 -> 4.0575528e+10 | AS40: =AR40/AN40 -> 0.049276532 | AT40: =AP40/B40*100 -> 23.414874 | BB40: 3.0348489e+11 | BC40: =[2]EUCAM_output!$AG37*10^9 -> 212406810000 | BD40: =(BB40-B40)/B40*100 -> 1.7858129 | BN40: =BP40-CF40 -> 2499230000 | BO40: {=INDEX([1]Sheet1!$C$6:$CY$72,MATCH($A40,[1]Sheet1!$A$6:$A$72,0),MATCH(MID(CELL("filename",A39),FIND("]",CELL("filename",A39))+1,255) & BO$1,[1]Sheet1!$C$1:$CY$1 & [1]Sheet1!$C$3:$CY$3,0))} -> 1.176629 | BP40: {=INDEX([1]Sheet1!$C$6:$CY$72,MATCH($A40,[1]Sheet1!$A$6:$A$72,0),MATCH(MID(CELL("filename",B39),FIND("]",CELL("filename",B39))+1,255) & BP$1,[1]Sheet1!$C$1:$CY$1 & [1]Sheet1!$C$3:$CY$3,0))} -> 104170500000 | BQ40: {=INDEX([1]Sheet1!$C$6:$CY$72,MATCH($A40,[1]Sheet1!$A$6:$A$72,0),MATCH(MID(CELL("filename",C39),FIND("]",CELL("filename",C39))+1,255) & BQ$1,[1]Sheet1!$C$1:$CY$1 & [1]Sheet1!$C$3:$CY$3,0))} -> 28046400000 | BR40: {=INDEX([6]Annual!$C$5:$T$30,MATCH($A40,[6]Annual!$B$5:$B$30,0),MATCH(MID(CELL("filename",$F$2),FIND("]",CELL("filename",$F$2))+1,255) & BR$1,[6]Annual!$C$3:$T$3 & [6]Annual!$C$4:$T$4,0))} -> 23594800000 | BS40: {=INDEX([6]Annual!$C$5:$T$30,MATCH($A40,[6]Annual!$B$5:$B$30,0),MATCH(MID(CELL("filename",$F$2),FIND("]",CELL("filename",$F$2))+1,255) & BS$1,[6]Annual!$C$3:$T$3 & [6]Annual!$C$4:$T$4,0))} -> 3440500000 | BT40: {=INDEX([6]Annual!$C$5:$T$30,MATCH($A40,[6]Annual!$B$5:$B$30,0),MATCH(MID(CELL("filename",$F$2),FIND("]",CELL("filename",$F$2))+1,255) & BT$1,[6]Annual!$C$3:$T$3 & [6]Annual!$C$4:$T$4,0))} -> 1.0637e+09 | BU40: =BQ40*BR40/SUM($BR40:$BT40) -> 2.3550632e+10 | BV40: =BQ40-BU40 -> 4.4957684e+09 | BW40: {=INDEX([1]Sheet1!$C$6:$CY$72,MATCH($A40,[1]Sheet1!$A$6:$A$72,0),MATCH(MID(CELL("filename",F39),FIND("]",CELL("filename",F39))+1,255) & BW$1,[1]Sheet1!$C$1:$CY$1 & [1]Sheet1!$C$3:$CY$3,0))} -> 31563930000 | BX40: {=INDEX([1]Sheet1!$C$6:$CY$72,MATCH($A40,[1]Sheet1!$A$6:$A$72,0),MATCH(MID(CELL("filename",G39),FIND("]",CELL("filename",G39))+1,255) & BX$1,[1]Sheet1!$C$1:$CY$1 & [1]Sheet1!$C$3:$CY$3,0))} -> 30940370000 | BY40: {=INDEX([4]DATA!$C$18:$N$51,MATCH($A40,[4]DATA!$B$18:$B$51,0),MATCH(MID(CELL("filename",F7),FIND("]",CELL("filename",F7))+1,255) & BY$1,[4]DATA!$C$15:$N$15&[4]DATA!$C$16:$N$16,0)) * 10^6} -> 16289000000 | BZ40: {=INDEX([4]DATA!$C$18:$N$51,MATCH($A40,[4]DATA!$B$18:$B$51,0),MATCH(MID(CELL("filename",G7),FIND("]",CELL("filename",G7))+1,255) & BZ$1,[4]DATA!$C$15:$N$15&[4]DATA!$C$16:$N$16,0)) * 10^6} -> 14651000000 | CA40: =$BX40*BY40/SUM($BY40:$BZ40) -> 1.6289195e+10 | CB40: =BX40-CA40 -> 1.4651175e+10 | CC40: {=INDEX([1]Sheet1!$C$6:$CY$72,MATCH($A40,[1]Sheet1!$A$6:$A$72,0),MATCH(MID(CELL("filename",J39),FIND("]",CELL("filename",J39))+1,255) & CC$1,[1]Sheet1!$C$1:$CY$1 & [1]Sheet1!$C$3:$CY$3,0))} -> 2484540000 | CD40: =BP40-BQ40-BW40-BX40-CC40 -> 11135260000 | CE40: {=INDEX([1]Sheet1!$C$6:$CY$72,MATCH($A40,[1]Sheet1!$A$6:$A$72,0),MATCH(MID(CELL("filename",L39),FIND("]",CELL("filename",L39))+1,255) & CE$1,[1]Sheet1!$C$1:$CY$1 & [1]Sheet1!$C$3:$CY$3,0))} -> 109281900000 | CF40: =CE40-CK40 -> 101671270000 | CG40: {=INDEX([1]Sheet1!$C$6:$CY$72,MATCH($A40,[1]Sheet1!$A$6:$A$72,0),MATCH(MID(CELL("filename",N39),FIND("]",CELL("filename",N39))+1,255) & CG$1,[1]Sheet1!$C$1:$CY$1 & [1]Sheet1!$C$3:$CY$3,0))} -> 41486200000 | CH40: {=INDEX([1]Sheet1!$C$6:$CY$72,MATCH($A40,[1]Sheet1!$A$6:$A$72,0),MATCH(MID(CELL("filename",O39),FIND("]",CELL("filename",O39))+1,255) & CH$1,[1]Sheet1!$C$1:$CY$1 & [1]Sheet1!$C$3:$CY$3,0))} -> 5739210000 | CI40: {=INDEX([1]Sheet1!$C$6:$CY$72,MATCH($A40,[1]Sheet1!$A$6:$A$72,0),MATCH(MID(CELL("filename",P39),FIND("]",CELL("filename",P39))+1,255) & CI$1,[1]Sheet1!$C$1:$CY$1 & [1]Sheet1!$C$3:$CY$3,0))} -> 4454270000 | CJ40: {=INDEX([1]Sheet1!$C$6:$CY$72,MATCH($A40,[1]Sheet1!$A$6:$A$72,0),MATCH(MID(CELL("filename",R39),FIND("]",CELL("filename",R39))+1,255) & CJ$1,[1]Sheet1!$C$1:$CY$1 & [1]Sheet1!$C$3:$CY$3,0))} -> 39876900000 | CK40: {=INDEX([1]Sheet1!$C$6:$CY$72,MATCH($A40,[1]Sheet1!$A$6:$A$72,0),MATCH(MID(CELL("filename",S39),FIND("]",CELL("filename",S39))+1,255) & CK$1,[1]Sheet1!$C$1:$CY$1 & [1]Sheet1!$C$3:$CY$3,0))} -> 7610630000 | CL40: =CF40-CG40-CH40-CI40-CJ40 -> 10114690000 | DK40: =DL40/100*BC40 -> 1.4154323e+11 | DL40: {=INDEX([1]Sheet1!$C$6:$CY$72,MATCH($A40,[1]Sheet1!$A$6:$A$72,0),MATCH(MID(CELL("filename",AT39),FIND("]",CELL("filename",AT39))+1,255) & DL$1,[1]Sheet1!$C$1:$CY$1 & [1]Sheet1!$C$3:$CY$3,0))} -> 66.6378 | DM40: {=INDEX([5]DATA!$C$18:$T$51,MATCH($A40,[5]DATA!$B$18:$B$51,0),MATCH(MID(CELL("filename",AU7),FIND("]",CELL("filename",AU7))+1,255) & DM$1,[5]DATA!$C$15:$T$15&[5]DATA!$C$16:$T$16,0)) * 10^6} -> 7820000000 | DN40: {=INDEX([5]DATA!$C$18:$T$51,MATCH($A40,[5]DATA!$B$18:$B$51,0),MATCH(MID(CELL("filename",AV7),FIND("]",CELL("filename",AV7))+1,255) & DN$1,[5]DATA!$C$15:$T$15&[5]DATA!$C$16:$T$16,0)) * 10^6} -> 133724000000 | DQ40: 0.923613 | DR40: {=INDEX([1]Sheet1!$C$6:$CY$72,MATCH($A40,[1]Sheet1!$A$6:$A$72,0),MATCH(MID(CELL("filename",AZ39),FIND("]",CELL("filename",AZ39))+1,255) & DR$1,[1]Sheet1!$C$1:$CY$1 & [1]Sheet1!$C$3:$CY$3,0))} -> 220000000 | DS40: {=INDEX([1]Sheet1!$C$6:$CY$72,MATCH($A40,[1]Sheet1!$A$6:$A$72,0),MATCH(MID(CELL("filename",BA39),FIND("]",CELL("filename",BA39))+1,255) & DS$1,[1]Sheet1!$C$1:$CY$1 & [1]Sheet1!$C$3:$CY$3,0))} -> 5.587174 | DT40: {=INDEX([5]DATA!$C$18:$T$51,MATCH($A40,[5]DATA!$B$18:$B$51,0),MATCH(MID(CELL("filename",BB7),FIND("]",CELL("filename",BB7))+1,255) & DT$1,[5]DATA!$C$15:$T$15&[5]DATA!$C$16:$T$16,0)) * 10^6} -> 13154000000 | DU40: {=INDEX([1]Sheet1!$C$6:$CY$72,MATCH($A40,[1]Sheet1!$A$6:$A$72,0),MATCH(MID(CELL("filename",BC39),FIND("]",CELL("filename",BC39))+1,255) & DU$1,[1]Sheet1!$C$1:$CY$1 & [1]Sheet1!$C$3:$CY$3,0))} -> 4.39 | DV40: 0.5 | DW40: =Euro_Area_Data!V37*10^9 -> 9.7148429e+12 | DX40: 1 | DY40: 0.5 | DZ40: {=INDEX([1]Sheet1!$C$6:$CY$72,MATCH($A40,[1]Sheet1!$A$6:$A$72,0),MATCH(MID(CELL("filename",BH39),FIND("]",CELL("filename",BH39))+1,255) & DZ$1,[1]Sheet1!$C$1:$CY$1 & [1]Sheet1!$C$3:$CY$3,0))} -> 5.56 | EA40: 2 | EB40: =SUMPRODUCT(Euro_Area_Data!C37:U37,Euro_Area_Data!Z37:AR37)/SUM(Euro_Area_Data!C37:U37) -> 0.72764869 | EC40: =(EB40-EB39)/EB39*100 -> 1.3752078 | EE40: -5 | EH40: 0.75 | EI40: 0.05 | EJ40: 60 | EK40: =(EN40-EN39)/EN39*100 -> 1.3673112 | EN40: =[2]EUCAM_output!$AE37 -> 0.69989255
A41: 2001 | B41: =[2]EUCAM_output!$E38*10^9 -> 3.0542853e+11 | H41: =[2]EUCAM_output!$AK38 -> -0.00066469886 | I41: =[2]EUCAM_output!$W38*10^3 -> 6105352 | K41: =IF(A41<2030,I41,K40*J41/J40) -> 6105352 | L41: =[2]EUCAM_output!$G38 -> 64.464857 | O41: =[2]EUCAM_output!$H38 -> 64.274879 | R41: =[2]EUCAM_output!$L38 -> 3.9 | U41: =[2]EUCAM_output!$K38 -> 4.36708 | V41: 4.36708 | W41: 0.0059507834 | X41: -0.0019457469 | Y41: =[2]EUCAM_output!$AI38 -> -0.0078627679 | Z41: =[2]EUCAM_output!$M38 -> 1783.7594 | AC41: =[2]EUCAM_output!$AL38 -> 1787.981 | AD41: =[2]EUCAM_output!$T38*10^9 -> 9.6663305e+11 | AE41: {=INDEX('[3]Sheet 1'!$B$12:$M$61,MATCH($A41,'[3]Sheet 1'!$A$12:$A$61,0),MATCH(MID(CELL("filename",A40),FIND("]",CELL("filename",A40))+1,255)&AE$1,'[3]Sheet 1'!$B$9:$M$9&'[3]Sheet 1'!$B$8:$M$8,0))*10^6} -> 717465800000 | AF41: {=INDEX('[3]Sheet 1'!$B$12:$M$61,MATCH($A41,'[3]Sheet 1'!$A$12:$A$61,0),MATCH(MID(CELL("filename",B40),FIND("]",CELL("filename",B40))+1,255)&AF$1,'[3]Sheet 1'!$B$9:$M$9&'[3]Sheet 1'!$B$8:$M$8,0))*10^6} -> 89094500000 | AG41: =AF41/AE41 -> 0.12417944 | AH41: =AD41*AG41 -> 1.2003595e+11 | AI41: =CH41/EN41 -> 7.5817072e+09 | AJ41: 5517590000 | AK41: =AJ41/EN41 -> 7.7336587e+09 | AL41: =AK41/AH41 -> 0.064427855 | AM41: =AVERAGE($AL$35:$AL$63) -> 0.065166448 | AN41: =AD41-AH41 -> 8.465971e+11 | AO41: 49276000000 | AP41: =AO41/EN41 -> 6.9067069e+10 | AQ41: 35405800000 | AR41: =(AQ41-AJ41)/EN41 -> 4.1892423e+10 | AS41: =AR41/AN41 -> 0.049483306 | AT41: =AP41/B41*100 -> 22.613168 | BB41: 3.0748175e+11 | BC41: =[2]EUCAM_output!$AG38*10^9 -> 219373300000 | BD41: =(BB41-B41)/B41*100 -> 0.67224106 | BN41: =BP41-CF41 -> 6401290000 | BO41: {=INDEX([1]Sheet1!$C$6:$CY$72,MATCH($A41,[1]Sheet1!$A$6:$A$72,0),MATCH(MID(CELL("filename",A40),FIND("]",CELL("filename",A40))+1,255) & BO$1,[1]Sheet1!$C$1:$CY$1 & [1]Sheet1!$C$3:$CY$3,0))} -> 2.91799 | BP41: {=INDEX([1]Sheet1!$C$6:$CY$72,MATCH($A41,[1]Sheet1!$A$6:$A$72,0),MATCH(MID(CELL("filename",B40),FIND("]",CELL("filename",B40))+1,255) & BP$1,[1]Sheet1!$C$1:$CY$1 & [1]Sheet1!$C$3:$CY$3,0))} -> 112105900000 | BQ41: {=INDEX([1]Sheet1!$C$6:$CY$72,MATCH($A41,[1]Sheet1!$A$6:$A$72,0),MATCH(MID(CELL("filename",C40),FIND("]",CELL("filename",C40))+1,255) & BQ$1,[1]Sheet1!$C$1:$CY$1 & [1]Sheet1!$C$3:$CY$3,0))} -> 3.256023e+10 | BR41: {=INDEX([6]Annual!$C$5:$T$30,MATCH($A41,[6]Annual!$B$5:$B$30,0),MATCH(MID(CELL("filename",$F$2),FIND("]",CELL("filename",$F$2))+1,255) & BR$1,[6]Annual!$C$3:$T$3 & [6]Annual!$C$4:$T$4,0))} -> 25701800000 | BS41: {=INDEX([6]Annual!$C$5:$T$30,MATCH($A41,[6]Annual!$B$5:$B$30,0),MATCH(MID(CELL("filename",$F$2),FIND("]",CELL("filename",$F$2))+1,255) & BS$1,[6]Annual!$C$3:$T$3 & [6]Annual!$C$4:$T$4,0))} -> 5.6834e+09 | BT41: {=INDEX([6]Annual!$C$5:$T$30,MATCH($A41,[6]Annual!$B$5:$B$30,0),MATCH(MID(CELL("filename",$F$2),FIND("]",CELL("filename",$F$2))+1,255) & BT$1,[6]Annual!$C$3:$T$3 & [6]Annual!$C$4:$T$4,0))} -> 1.2096e+09 | BU41: =BQ41*BR41/SUM($BR41:$BT41) -> 2.5674541e+10 | BV41: =BQ41-BU41 -> 6.8856893e+09 | BW41: {=INDEX([1]Sheet1!$C$6:$CY$72,MATCH($A41,[1]Sheet1!$A$6:$A$72,0),MATCH(MID(CELL("filename",F40),FIND("]",CELL("filename",F40))+1,255) & BW$1,[1]Sheet1!$C$1:$CY$1 & [1]Sheet1!$C$3:$CY$3,0))} -> 32470830000 | BX41: {=INDEX([1]Sheet1!$C$6:$CY$72,MATCH($A41,[1]Sheet1!$A$6:$A$72,0),MATCH(MID(CELL("filename",G40),FIND("]",CELL("filename",G40))+1,255) & BX$1,[1]Sheet1!$C$1:$CY$1 & [1]Sheet1!$C$3:$CY$3,0))} -> 31843730000 | BY41: {=INDEX([4]DATA!$C$18:$N$51,MATCH($A41,[4]DATA!$B$18:$B$51,0),MATCH(MID(CELL("filename",F8),FIND("]",CELL("filename",F8))+1,255) & BY$1,[4]DATA!$C$15:$N$15&[4]DATA!$C$16:$N$16,0)) * 10^6} -> 17013000000 | BZ41: {=INDEX([4]DATA!$C$18:$N$51,MATCH($A41,[4]DATA!$B$18:$B$51,0),MATCH(MID(CELL("filename",G8),FIND("]",CELL("filename",G8))+1,255) & BZ$1,[4]DATA!$C$15:$N$15&[4]DATA!$C$16:$N$16,0)) * 10^6} -> 14831000000 | CA41: =$BX41*BY41/SUM($BY41:$BZ41) -> 1.7012856e+10 | CB41: =BX41-CA41 -> 1.4830874e+10 | CC41: {=INDEX([1]Sheet1!$C$6:$CY$72,MATCH($A41,[1]Sheet1!$A$6:$A$72,0),MATCH(MID(CELL("filename",J40),FIND("]",CELL("filename",J40))+1,255) & CC$1,[1]Sheet1!$C$1:$CY$1 & [1]Sheet1!$C$3:$CY$3,0))} -> 2599120000 | CD41: =BP41-BQ41-BW41-BX41-CC41 -> 12631990000 | CE41: {=INDEX([1]Sheet1!$C$6:$CY$72,MATCH($A41,[1]Sheet1!$A$6:$A$72,0),MATCH(MID(CELL("filename",L40),FIND("]",CELL("filename",L40))+1,255) & CE$1,[1]Sheet1!$C$1:$CY$1 & [1]Sheet1!$C$3:$CY$3,0))} -> 113669200000 | CF41: =CE41-CK41 -> 105704610000 | CG41: {=INDEX([1]Sheet1!$C$6:$CY$72,MATCH($A41,[1]Sheet1!$A$6:$A$72,0),MATCH(MID(CELL("filename",N40),FIND("]",CELL("filename",N40))+1,255) & CG$1,[1]Sheet1!$C$1:$CY$1 & [1]Sheet1!$C$3:$CY$3,0))} -> 42238800000 | CH41: {=INDEX([1]Sheet1!$C$6:$CY$72,MATCH($A41,[1]Sheet1!$A$6:$A$72,0),MATCH(MID(CELL("filename",O40),FIND("]",CELL("filename",O40))+1,255) & CH$1,[1]Sheet1!$C$1:$CY$1 & [1]Sheet1!$C$3:$CY$3,0))} -> 5409180000 | CI41: {=INDEX([1]Sheet1!$C$6:$CY$72,MATCH($A41,[1]Sheet1!$A$6:$A$72,0),MATCH(MID(CELL("filename",P40),FIND("]",CELL("filename",P40))+1,255) & CI$1,[1]Sheet1!$C$1:$CY$1 & [1]Sheet1!$C$3:$CY$3,0))} -> 4.28302e+09 | CJ41: {=INDEX([1]Sheet1!$C$6:$CY$72,MATCH($A41,[1]Sheet1!$A$6:$A$72,0),MATCH(MID(CELL("filename",R40),FIND("]",CELL("filename",R40))+1,255) & CJ$1,[1]Sheet1!$C$1:$CY$1 & [1]Sheet1!$C$3:$CY$3,0))} -> 40825400000 | CK41: {=INDEX([1]Sheet1!$C$6:$CY$72,MATCH($A41,[1]Sheet1!$A$6:$A$72,0),MATCH(MID(CELL("filename",S40),FIND("]",CELL("filename",S40))+1,255) & CK$1,[1]Sheet1!$C$1:$CY$1 & [1]Sheet1!$C$3:$CY$3,0))} -> 7964590000 | CL41: =CF41-CG41-CH41-CI41-CJ41 -> 12948210000 | DK41: =DL41/100*BC41 -> 1.4750244e+11 | DL41: {=INDEX([1]Sheet1!$C$6:$CY$72,MATCH($A41,[1]Sheet1!$A$6:$A$72,0),MATCH(MID(CELL("filename",AT40),FIND("]",CELL("filename",AT40))+1,255) & DL$1,[1]Sheet1!$C$1:$CY$1 & [1]Sheet1!$C$3:$CY$3,0))} -> 67.2381 | DM41: {=INDEX([5]DATA!$C$18:$T$51,MATCH($A41,[5]DATA!$B$18:$B$51,0),MATCH(MID(CELL("filename",AU8),FIND("]",CELL("filename",AU8))+1,255) & DM$1,[5]DATA!$C$15:$T$15&[5]DATA!$C$16:$T$16,0)) * 10^6} -> 5899000000 | DN41: {=INDEX([5]DATA!$C$18:$T$51,MATCH($A41,[5]DATA!$B$18:$B$51,0),MATCH(MID(CELL("filename",AV8),FIND("]",CELL("filename",AV8))+1,255) & DN$1,[5]DATA!$C$15:$T$15&[5]DATA!$C$16:$T$16,0)) * 10^6} -> 141603000000 | DQ41: 0.89563 | DR41: {=INDEX([1]Sheet1!$C$6:$CY$72,MATCH($A41,[1]Sheet1!$A$6:$A$72,0),MATCH(MID(CELL("filename",AZ40),FIND("]",CELL("filename",AZ40))+1,255) & DR$1,[1]Sheet1!$C$1:$CY$1 & [1]Sheet1!$C$3:$CY$3,0))} -> 4400000000 | DS41: {=INDEX([1]Sheet1!$C$6:$CY$72,MATCH($A41,[1]Sheet1!$A$6:$A$72,0),MATCH(MID(CELL("filename",BA40),FIND("]",CELL("filename",BA40))+1,255) & DS$1,[1]Sheet1!$C$1:$CY$1 & [1]Sheet1!$C$3:$CY$3,0))} -> 5.626968 | DT41: {=INDEX([5]DATA!$C$18:$T$51,MATCH($A41,[5]DATA!$B$18:$B$51,0),MATCH(MID(CELL("filename",BB8),FIND("]",CELL("filename",BB8))+1,255) & DT$1,[5]DATA!$C$15:$T$15&[5]DATA!$C$16:$T$16,0)) * 10^6} -> 15757000000 | DU41: {=INDEX([1]Sheet1!$C$6:$CY$72,MATCH($A41,[1]Sheet1!$A$6:$A$72,0),MATCH(MID(CELL("filename",BC40),FIND("]",CELL("filename",BC40))+1,255) & DU$1,[1]Sheet1!$C$1:$CY$1 & [1]Sheet1!$C$3:$CY$3,0))} -> 4.26 | DV41: 0.5 | DW41: =Euro_Area_Data!V38*10^9 -> 9.9262806e+12 | DX41: 1 | DY41: 0.5 | DZ41: {=INDEX([1]Sheet1!$C$6:$CY$72,MATCH($A41,[1]Sheet1!$A$6:$A$72,0),MATCH(MID(CELL("filename",BH40),FIND("]",CELL("filename",BH40))+1,255) & DZ$1,[1]Sheet1!$C$1:$CY$1 & [1]Sheet1!$C$3:$CY$3,0))} -> 5.08 | EA41: 2 | EB41: =SUMPRODUCT(Euro_Area_Data!C38:U38,Euro_Area_Data!Z38:AR38)/SUM(Euro_Area_Data!C38:U38) -> 0.74594369 | EC41: =(EB41-EB40)/EB40*100 -> 2.514262 | ED41: =SUMPRODUCT(Euro_Area_Data!C38:U38,Euro_Area_Data!AW38:BO38)/SUM(Euro_Area_Data!C38:U38) -> 2.0404606 | EE41: -5 | EH41: 0.75 | EI41: 0.05 | EJ41: 60 | EK41: =(EN41-EN40)/EN40*100 -> 1.937283 | EN41: =[2]EUCAM_output!$AE38 -> 0.71345145
A42: 2002 | B42: =[2]EUCAM_output!$E39*10^9 -> 3.1231484e+11 | H42: =[2]EUCAM_output!$AK39 -> -0.012571784 | I42: =[2]EUCAM_output!$W39*10^3 -> 6141756.5 | K42: =IF(A42<2030,I42,K41*J42/J41) -> 6141756.5 | L42: =[2]EUCAM_output!$G39 -> 64.291561 | O42: =[2]EUCAM_output!$H39 -> 64.563303 | R42: =[2]EUCAM_output!$L39 -> 4.3 | U42: =[2]EUCAM_output!$K39 -> 4.498002 | V42: 4.498002 | W42: 0.015775588 | X42: -0.0024592104 | Y42: =[2]EUCAM_output!$AI39 -> 0.0058208239 | Z42: =[2]EUCAM_output!$M39 -> 1781.0435 | AC42: =[2]EUCAM_output!$AL39 -> 1781.6635 | AD42: =[2]EUCAM_output!$T39*10^9 -> 9.8467386e+11 | AE42: {=INDEX('[3]Sheet 1'!$B$12:$M$61,MATCH($A42,'[3]Sheet 1'!$A$12:$A$61,0),MATCH(MID(CELL("filename",A41),FIND("]",CELL("filename",A41))+1,255)&AE$1,'[3]Sheet 1'!$B$9:$M$9&'[3]Sheet 1'!$B$8:$M$8,0))*10^6} -> 735841700000 | AF42: {=INDEX('[3]Sheet 1'!$B$12:$M$61,MATCH($A42,'[3]Sheet 1'!$A$12:$A$61,0),MATCH(MID(CELL("filename",B41),FIND("]",CELL("filename",B41))+1,255)&AF$1,'[3]Sheet 1'!$B$9:$M$9&'[3]Sheet 1'!$B$8:$M$8,0))*10^6} -> 90709100000 | AG42: =AF42/AE42 -> 0.12327257 | AH42: =AD42*AG42 -> 1.2138328e+11 | AI42: =CH42/EN42 -> 8.4757522e+09 | AJ42: 5621400000 | AK42: =AJ42/EN42 -> 7.7931099e+09 | AL42: =AK42/AH42 -> 0.064202498 | AM42: =AVERAGE($AL$35:$AL$63) -> 0.065166448 | AN42: =AD42-AH42 -> 8.6329058e+11 | AO42: 47058900000 | AP42: =AO42/EN42 -> 6.5239118e+10 | AQ42: 37239500000 | AR42: =(AQ42-AJ42)/EN42 -> 4.3833089e+10 | AS42: =AR42/AN42 -> 0.050774432 | AT42: =AP42/B42*100 -> 20.888894 | BB42: 3.1204591e+11 | BC42: =[2]EUCAM_output!$AG39*10^9 -> 225087920000 | BD42: =(BB42-B42)/B42*100 -> -0.086109047 | BN42: =BP42-CF42 -> 4619330000 | BO42: {=INDEX([1]Sheet1!$C$6:$CY$72,MATCH($A42,[1]Sheet1!$A$6:$A$72,0),MATCH(MID(CELL("filename",A41),FIND("]",CELL("filename",A41))+1,255) & BO$1,[1]Sheet1!$C$1:$CY$1 & [1]Sheet1!$C$3:$CY$3,0))} -> 2.052216 | BP42: {=INDEX([1]Sheet1!$C$6:$CY$72,MATCH($A42,[1]Sheet1!$A$6:$A$72,0),MATCH(MID(CELL("filename",B41),FIND("]",CELL("filename",B41))+1,255) & BP$1,[1]Sheet1!$C$1:$CY$1 & [1]Sheet1!$C$3:$CY$3,0))} -> 112963800000 | BQ42: {=INDEX([1]Sheet1!$C$6:$CY$72,MATCH($A42,[1]Sheet1!$A$6:$A$72,0),MATCH(MID(CELL("filename",C41),FIND("]",CELL("filename",C41))+1,255) & BQ$1,[1]Sheet1!$C$1:$CY$1 & [1]Sheet1!$C$3:$CY$3,0))} -> 30963810000 | BR42: {=INDEX([6]Annual!$C$5:$T$30,MATCH($A42,[6]Annual!$B$5:$B$30,0),MATCH(MID(CELL("filename",$F$2),FIND("]",CELL("filename",$F$2))+1,255) & BR$1,[6]Annual!$C$3:$T$3 & [6]Annual!$C$4:$T$4,0))} -> 25779300000 | BS42: {=INDEX([6]Annual!$C$5:$T$30,MATCH($A42,[6]Annual!$B$5:$B$30,0),MATCH(MID(CELL("filename",$F$2),FIND("]",CELL("filename",$F$2))+1,255) & BS$1,[6]Annual!$C$3:$T$3 & [6]Annual!$C$4:$T$4,0))} -> 4111200000 | BT42: {=INDEX([6]Annual!$C$5:$T$30,MATCH($A42,[6]Annual!$B$5:$B$30,0),MATCH(MID(CELL("filename",$F$2),FIND("]",CELL("filename",$F$2))+1,255) & BT$1,[6]Annual!$C$3:$T$3 & [6]Annual!$C$4:$T$4,0))} -> 1121800000 | BU42: =BQ42*BR42/SUM($BR42:$BT42) -> 2.5738992e+10 | BV42: =BQ42-BU42 -> 5.2248178e+09 | BW42: {=INDEX([1]Sheet1!$C$6:$CY$72,MATCH($A42,[1]Sheet1!$A$6:$A$72,0),MATCH(MID(CELL("filename",F41),FIND("]",CELL("filename",F41))+1,255) & BW$1,[1]Sheet1!$C$1:$CY$1 & [1]Sheet1!$C$3:$CY$3,0))} -> 33658830000 | BX42: {=INDEX([1]Sheet1!$C$6:$CY$72,MATCH($A42,[1]Sheet1!$A$6:$A$72,0),MATCH(MID(CELL("filename",G41),FIND("]",CELL("filename",G41))+1,255) & BX$1,[1]Sheet1!$C$1:$CY$1 & [1]Sheet1!$C$3:$CY$3,0))} -> 3.232943e+10 | BY42: {=INDEX([4]DATA!$C$18:$N$51,MATCH($A42,[4]DATA!$B$18:$B$51,0),MATCH(MID(CELL("filename",F9),FIND("]",CELL("filename",F9))+1,255) & BY$1,[4]DATA!$C$15:$N$15&[4]DATA!$C$16:$N$16,0)) * 10^6} -> 17297000000 | BZ42: {=INDEX([4]DATA!$C$18:$N$51,MATCH($A42,[4]DATA!$B$18:$B$51,0),MATCH(MID(CELL("filename",G9),FIND("]",CELL("filename",G9))+1,255) & BZ$1,[4]DATA!$C$15:$N$15&[4]DATA!$C$16:$N$16,0)) * 10^6} -> 15033000000 | CA42: =$BX42*BY42/SUM($BY42:$BZ42) -> 1.7296695e+10 | CB42: =BX42-CA42 -> 1.5032735e+10 | CC42: {=INDEX([1]Sheet1!$C$6:$CY$72,MATCH($A42,[1]Sheet1!$A$6:$A$72,0),MATCH(MID(CELL("filename",J41),FIND("]",CELL("filename",J41))+1,255) & CC$1,[1]Sheet1!$C$1:$CY$1 & [1]Sheet1!$C$3:$CY$3,0))} -> 2626140000 | CD42: =BP42-BQ42-BW42-BX42-CC42 -> 1.338559e+10 | CE42: {=INDEX([1]Sheet1!$C$6:$CY$72,MATCH($A42,[1]Sheet1!$A$6:$A$72,0),MATCH(MID(CELL("filename",L41),FIND("]",CELL("filename",L41))+1,255) & CE$1,[1]Sheet1!$C$1:$CY$1 & [1]Sheet1!$C$3:$CY$3,0))} -> 116171900000 | CF42: =CE42-CK42 -> 108344470000 | CG42: {=INDEX([1]Sheet1!$C$6:$CY$72,MATCH($A42,[1]Sheet1!$A$6:$A$72,0),MATCH(MID(CELL("filename",N41),FIND("]",CELL("filename",N41))+1,255) & CG$1,[1]Sheet1!$C$1:$CY$1 & [1]Sheet1!$C$3:$CY$3,0))} -> 42972700000 | CH42: {=INDEX([1]Sheet1!$C$6:$CY$72,MATCH($A42,[1]Sheet1!$A$6:$A$72,0),MATCH(MID(CELL("filename",O41),FIND("]",CELL("filename",O41))+1,255) & CH$1,[1]Sheet1!$C$1:$CY$1 & [1]Sheet1!$C$3:$CY$3,0))} -> 6113810000 | CI42: {=INDEX([1]Sheet1!$C$6:$CY$72,MATCH($A42,[1]Sheet1!$A$6:$A$72,0),MATCH(MID(CELL("filename",P41),FIND("]",CELL("filename",P41))+1,255) & CI$1,[1]Sheet1!$C$1:$CY$1 & [1]Sheet1!$C$3:$CY$3,0))} -> 4.23375e+09 | CJ42: {=INDEX([1]Sheet1!$C$6:$CY$72,MATCH($A42,[1]Sheet1!$A$6:$A$72,0),MATCH(MID(CELL("filename",R41),FIND("]",CELL("filename",R41))+1,255) & CJ$1,[1]Sheet1!$C$1:$CY$1 & [1]Sheet1!$C$3:$CY$3,0))} -> 42514200000 | CK42: {=INDEX([1]Sheet1!$C$6:$CY$72,MATCH($A42,[1]Sheet1!$A$6:$A$72,0),MATCH(MID(CELL("filename",S41),FIND("]",CELL("filename",S41))+1,255) & CK$1,[1]Sheet1!$C$1:$CY$1 & [1]Sheet1!$C$3:$CY$3,0))} -> 7827430000 | CL42: =CF42-CG42-CH42-CI42-CJ42 -> 12510010000 | DK42: =DL42/100*BC42 -> 1.5179997e+11 | DL42: {=INDEX([1]Sheet1!$C$6:$CY$72,MATCH($A42,[1]Sheet1!$A$6:$A$72,0),MATCH(MID(CELL("filename",AT41),FIND("]",CELL("filename",AT41))+1,255) & DL$1,[1]Sheet1!$C$1:$CY$1 & [1]Sheet1!$C$3:$CY$3,0))} -> 67.4403 | DM42: {=INDEX([5]DATA!$C$18:$T$51,MATCH($A42,[5]DATA!$B$18:$B$51,0),MATCH(MID(CELL("filename",AU9),FIND("]",CELL("filename",AU9))+1,255) & DM$1,[5]DATA!$C$15:$T$15&[5]DATA!$C$16:$T$16,0)) * 10^6} -> 4125000000 | DN42: {=INDEX([5]DATA!$C$18:$T$51,MATCH($A42,[5]DATA!$B$18:$B$51,0),MATCH(MID(CELL("filename",AV9),FIND("]",CELL("filename",AV9))+1,255) & DN$1,[5]DATA!$C$15:$T$15&[5]DATA!$C$16:$T$16,0)) * 10^6} -> 147675000000 | DQ42: 0.945574 | DR42: {=INDEX([1]Sheet1!$C$6:$CY$72,MATCH($A42,[1]Sheet1!$A$6:$A$72,0),MATCH(MID(CELL("filename",AZ41),FIND("]",CELL("filename",AZ41))+1,255) & DR$1,[1]Sheet1!$C$1:$CY$1 & [1]Sheet1!$C$3:$CY$3,0))} -> 1090000000 | DS42: {=INDEX([1]Sheet1!$C$6:$CY$72,MATCH($A42,[1]Sheet1!$A$6:$A$72,0),MATCH(MID(CELL("filename",BA41),FIND("]",CELL("filename",BA41))+1,255) & DS$1,[1]Sheet1!$C$1:$CY$1 & [1]Sheet1!$C$3:$CY$3,0))} -> 5.306642 | DT42: {=INDEX([5]DATA!$C$18:$T$51,MATCH($A42,[5]DATA!$B$18:$B$51,0),MATCH(MID(CELL("filename",BB9),FIND("]",CELL("filename",BB9))+1,255) & DT$1,[5]DATA!$C$15:$T$15&[5]DATA!$C$16:$T$16,0)) * 10^6} -> 18695000000 | DU42: {=INDEX([1]Sheet1!$C$6:$CY$72,MATCH($A42,[1]Sheet1!$A$6:$A$72,0),MATCH(MID(CELL("filename",BC41),FIND("]",CELL("filename",BC41))+1,255) & DU$1,[1]Sheet1!$C$1:$CY$1 & [1]Sheet1!$C$3:$CY$3,0))} -> 3.32 | DV42: 0.5 | DW42: =Euro_Area_Data!V39*10^9 -> 1.0019063e+13 | DX42: 1 | DY42: 0.5 | DZ42: {=INDEX([1]Sheet1!$C$6:$CY$72,MATCH($A42,[1]Sheet1!$A$6:$A$72,0),MATCH(MID(CELL("filename",BH41),FIND("]",CELL("filename",BH41))+1,255) & DZ$1,[1]Sheet1!$C$1:$CY$1 & [1]Sheet1!$C$3:$CY$3,0))} -> 4.96 | EA42: 2 | EB42: =SUMPRODUCT(Euro_Area_Data!C39:U39,Euro_Area_Data!Z39:AR39)/SUM(Euro_Area_Data!C39:U39) -> 0.76474674 | EC42: =(EB42-EB41)/EB41*100 -> 2.5207061 | ED42: =SUMPRODUCT(Euro_Area_Data!C39:U39,Euro_Area_Data!AW39:BO39)/SUM(Euro_Area_Data!C39:U39) -> 0.98780046 | EE42: -5 | EH42: 0.75 | EI42: 0.05 | EJ42: 60 | EK42: =(EN42-EN41)/EN41*100 -> 1.1042159 | EN42: =[2]EUCAM_output!$AE39 -> 0.72132949
A43: 2003 | B43: =[2]EUCAM_output!$E40*10^9 -> 3.192792e+11 | H43: =[2]EUCAM_output!$AK40 -> -0.0014809456 | I43: =[2]EUCAM_output!$W40*10^3 -> 6179838.5 | K43: =IF(A43<2030,I43,K42*J43/J42) -> 6179838.5 | L43: =[2]EUCAM_output!$G40 -> 64.515944 | O43: =[2]EUCAM_output!$H40 -> 64.89083 | R43: =[2]EUCAM_output!$L40 -> 4.6 | U43: =[2]EUCAM_output!$K40 -> 4.646428 | V43: 4.646428 | W43: 0.0048369789 | X43: -0.00018339433 | Y43: =[2]EUCAM_output!$AI40 -> -0.0036037643 | Z43: =[2]EUCAM_output!$M40 -> 1772.4473 | AC43: =[2]EUCAM_output!$AL40 -> 1773.6057 | AD43: =[2]EUCAM_output!$T40*10^9 -> 1.0041682e+12 | AE43: {=INDEX('[3]Sheet 1'!$B$12:$M$61,MATCH($A43,'[3]Sheet 1'!$A$12:$A$61,0),MATCH(MID(CELL("filename",A42),FIND("]",CELL("filename",A42))+1,255)&AE$1,'[3]Sheet 1'!$B$9:$M$9&'[3]Sheet 1'!$B$8:$M$8,0))*10^6} -> 763714000000 | AF43: {=INDEX('[3]Sheet 1'!$B$12:$M$61,MATCH($A43,'[3]Sheet 1'!$A$12:$A$61,0),MATCH(MID(CELL("filename",B42),FIND("]",CELL("filename",B42))+1,255)&AF$1,'[3]Sheet 1'!$B$9:$M$9&'[3]Sheet 1'!$B$8:$M$8,0))*10^6} -> 94048900000 | AG43: =AF43/AE43 -> 0.12314675 | AH43: =AD43*AG43 -> 1.2366006e+11 | AI43: =CH43/EN43 -> 8.1983519e+09 | AJ43: 5842300000 | AK43: =AJ43/EN43 -> 7.9980148e+09 | AL43: =AK43/AH43 -> 0.06467743 | AM43: =AVERAGE($AL$35:$AL$63) -> 0.065166448 | AN43: =AD43-AH43 -> 8.8050818e+11 | AO43: 49788900000 | AP43: =AO43/EN43 -> 6.8160204e+10 | AQ43: 38949500000 | AR43: =(AQ43-AJ43)/EN43 -> 4.5323225e+10 | AS43: =AR43/AN43 -> 0.051473939 | AT43: =AP43/B43*100 -> 21.34815 | BB43: 3.1560811e+11 | BC43: =[2]EUCAM_output!$AG40*10^9 -> 230541870000 | BD43: =(BB43-B43)/B43*100 -> -1.149804 | BN43: =BP43-CF43 -> 3152360000 | BO43: {=INDEX([1]Sheet1!$C$6:$CY$72,MATCH($A43,[1]Sheet1!$A$6:$A$72,0),MATCH(MID(CELL("filename",A42),FIND("]",CELL("filename",A42))+1,255) & BO$1,[1]Sheet1!$C$1:$CY$1 & [1]Sheet1!$C$3:$CY$3,0))} -> 1.367374 | BP43: {=INDEX([1]Sheet1!$C$6:$CY$72,MATCH($A43,[1]Sheet1!$A$6:$A$72,0),MATCH(MID(CELL("filename",B42),FIND("]",CELL("filename",B42))+1,255) & BP$1,[1]Sheet1!$C$1:$CY$1 & [1]Sheet1!$C$3:$CY$3,0))} -> 115095100000 | BQ43: {=INDEX([1]Sheet1!$C$6:$CY$72,MATCH($A43,[1]Sheet1!$A$6:$A$72,0),MATCH(MID(CELL("filename",C42),FIND("]",CELL("filename",C42))+1,255) & BQ$1,[1]Sheet1!$C$1:$CY$1 & [1]Sheet1!$C$3:$CY$3,0))} -> 31239400000 | BR43: {=INDEX([6]Annual!$C$5:$T$30,MATCH($A43,[6]Annual!$B$5:$B$30,0),MATCH(MID(CELL("filename",$F$2),FIND("]",CELL("filename",$F$2))+1,255) & BR$1,[6]Annual!$C$3:$T$3 & [6]Annual!$C$4:$T$4,0))} -> 2.6103e+10 | BS43: {=INDEX([6]Annual!$C$5:$T$30,MATCH($A43,[6]Annual!$B$5:$B$30,0),MATCH(MID(CELL("filename",$F$2),FIND("]",CELL("filename",$F$2))+1,255) & BS$1,[6]Annual!$C$3:$T$3 & [6]Annual!$C$4:$T$4,0))} -> 4297000000 | BT43: {=INDEX([6]Annual!$C$5:$T$30,MATCH($A43,[6]Annual!$B$5:$B$30,0),MATCH(MID(CELL("filename",$F$2),FIND("]",CELL("filename",$F$2))+1,255) & BT$1,[6]Annual!$C$3:$T$3 & [6]Annual!$C$4:$T$4,0))} -> 892900000 | BU43: =BQ43*BR43/SUM($BR43:$BT43) -> 2.6058373e+10 | BV43: =BQ43-BU43 -> 5.1810271e+09 | BW43: {=INDEX([1]Sheet1!$C$6:$CY$72,MATCH($A43,[1]Sheet1!$A$6:$A$72,0),MATCH(MID(CELL("filename",F42),FIND("]",CELL("filename",F42))+1,255) & BW$1,[1]Sheet1!$C$1:$CY$1 & [1]Sheet1!$C$3:$CY$3,0))} -> 3.412024e+10 | BX43: {=INDEX([1]Sheet1!$C$6:$CY$72,MATCH($A43,[1]Sheet1!$A$6:$A$72,0),MATCH(MID(CELL("filename",G42),FIND("]",CELL("filename",G42))+1,255) & BX$1,[1]Sheet1!$C$1:$CY$1 & [1]Sheet1!$C$3:$CY$3,0))} -> 3.313909e+10 | BY43: {=INDEX([4]DATA!$C$18:$N$51,MATCH($A43,[4]DATA!$B$18:$B$51,0),MATCH(MID(CELL("filename",F10),FIND("]",CELL("filename",F10))+1,255) & BY$1,[4]DATA!$C$15:$N$15&[4]DATA!$C$16:$N$16,0)) * 10^6} -> 17752000000 | BZ43: {=INDEX([4]DATA!$C$18:$N$51,MATCH($A43,[4]DATA!$B$18:$B$51,0),MATCH(MID(CELL("filename",G10),FIND("]",CELL("filename",G10))+1,255) & BZ$1,[4]DATA!$C$15:$N$15&[4]DATA!$C$16:$N$16,0)) * 10^6} -> 15387000000 | CA43: =$BX43*BY43/SUM($BY43:$BZ43) -> 1.7752048e+10 | CB43: =BX43-CA43 -> 1.5387042e+10 | CC43: {=INDEX([1]Sheet1!$C$6:$CY$72,MATCH($A43,[1]Sheet1!$A$6:$A$72,0),MATCH(MID(CELL("filename",J42),FIND("]",CELL("filename",J42))+1,255) & CC$1,[1]Sheet1!$C$1:$CY$1 & [1]Sheet1!$C$3:$CY$3,0))} -> 2635330000 | CD43: =BP43-BQ43-BW43-BX43-CC43 -> 1.396104e+10 | CE43: {=INDEX([1]Sheet1!$C$6:$CY$72,MATCH($A43,[1]Sheet1!$A$6:$A$72,0),MATCH(MID(CELL("filename",L42),FIND("]",CELL("filename",L42))+1,255) & CE$1,[1]Sheet1!$C$1:$CY$1 & [1]Sheet1!$C$3:$CY$3,0))} -> 119334400000 | CF43: =CE43-CK43 -> 111942740000 | CG43: {=INDEX([1]Sheet1!$C$6:$CY$72,MATCH($A43,[1]Sheet1!$A$6:$A$72,0),MATCH(MID(CELL("filename",N42),FIND("]",CELL("filename",N42))+1,255) & CG$1,[1]Sheet1!$C$1:$CY$1 & [1]Sheet1!$C$3:$CY$3,0))} -> 44262900000 | CH43: {=INDEX([1]Sheet1!$C$6:$CY$72,MATCH($A43,[1]Sheet1!$A$6:$A$72,0),MATCH(MID(CELL("filename",O42),FIND("]",CELL("filename",O42))+1,255) & CH$1,[1]Sheet1!$C$1:$CY$1 & [1]Sheet1!$C$3:$CY$3,0))} -> 5988640000 | CI43: {=INDEX([1]Sheet1!$C$6:$CY$72,MATCH($A43,[1]Sheet1!$A$6:$A$72,0),MATCH(MID(CELL("filename",P42),FIND("]",CELL("filename",P42))+1,255) & CI$1,[1]Sheet1!$C$1:$CY$1 & [1]Sheet1!$C$3:$CY$3,0))} -> 4681970000 | CJ43: {=INDEX([1]Sheet1!$C$6:$CY$72,MATCH($A43,[1]Sheet1!$A$6:$A$72,0),MATCH(MID(CELL("filename",R42),FIND("]",CELL("filename",R42))+1,255) & CJ$1,[1]Sheet1!$C$1:$CY$1 & [1]Sheet1!$C$3:$CY$3,0))} -> 44132600000 | CK43: {=INDEX([1]Sheet1!$C$6:$CY$72,MATCH($A43,[1]Sheet1!$A$6:$A$72,0),MATCH(MID(CELL("filename",S42),FIND("]",CELL("filename",S42))+1,255) & CK$1,[1]Sheet1!$C$1:$CY$1 & [1]Sheet1!$C$3:$CY$3,0))} -> 7391660000 | CL43: =CF43-CG43-CH43-CI43-CJ43 -> 12876630000 | DK43: =DL43/100*BC43 -> 1.5310701e+11 | DL43: {=INDEX([1]Sheet1!$C$6:$CY$72,MATCH($A43,[1]Sheet1!$A$6:$A$72,0),MATCH(MID(CELL("filename",AT42),FIND("]",CELL("filename",AT42))+1,255) & DL$1,[1]Sheet1!$C$1:$CY$1 & [1]Sheet1!$C$3:$CY$3,0))} -> 66.4118 | DM43: {=INDEX([5]DATA!$C$18:$T$51,MATCH($A43,[5]DATA!$B$18:$B$51,0),MATCH(MID(CELL("filename",AU10),FIND("]",CELL("filename",AU10))+1,255) & DM$1,[5]DATA!$C$15:$T$15&[5]DATA!$C$16:$T$16,0)) * 10^6} -> 3644000000 | DN43: {=INDEX([5]DATA!$C$18:$T$51,MATCH($A43,[5]DATA!$B$18:$B$51,0),MATCH(MID(CELL("filename",AV10),FIND("]",CELL("filename",AV10))+1,255) & DN$1,[5]DATA!$C$15:$T$15&[5]DATA!$C$16:$T$16,0)) * 10^6} -> 149463000000 | DQ43: 1.13116 | DR43: {=INDEX([1]Sheet1!$C$6:$CY$72,MATCH($A43,[1]Sheet1!$A$6:$A$72,0),MATCH(MID(CELL("filename",AZ42),FIND("]",CELL("filename",AZ42))+1,255) & DR$1,[1]Sheet1!$C$1:$CY$1 & [1]Sheet1!$C$3:$CY$3,0))} -> -2930000000 | DS43: {=INDEX([1]Sheet1!$C$6:$CY$72,MATCH($A43,[1]Sheet1!$A$6:$A$72,0),MATCH(MID(CELL("filename",BA42),FIND("]",CELL("filename",BA42))+1,255) & DS$1,[1]Sheet1!$C$1:$CY$1 & [1]Sheet1!$C$3:$CY$3,0))} -> 4.869341 | DT43: {=INDEX([5]DATA!$C$18:$T$51,MATCH($A43,[5]DATA!$B$18:$B$51,0),MATCH(MID(CELL("filename",BB10),FIND("]",CELL("filename",BB10))+1,255) & DT$1,[5]DATA!$C$15:$T$15&[5]DATA!$C$16:$T$16,0)) * 10^6} -> 18834000000 | DU43: {=INDEX([1]Sheet1!$C$6:$CY$72,MATCH($A43,[1]Sheet1!$A$6:$A$72,0),MATCH(MID(CELL("filename",BC42),FIND("]",CELL("filename",BC42))+1,255) & DU$1,[1]Sheet1!$C$1:$CY$1 & [1]Sheet1!$C$3:$CY$3,0))} -> 2.33 | DV43: 0.5 | DW43: =Euro_Area_Data!V40*10^9 -> 1.0093114e+13 | DX43: 1 | DY43: 0.5 | DZ43: {=INDEX([1]Sheet1!$C$6:$CY$72,MATCH($A43,[1]Sheet1!$A$6:$A$72,0),MATCH(MID(CELL("filename",BH42),FIND("]",CELL("filename",BH42))+1,255) & DZ$1,[1]Sheet1!$C$1:$CY$1 & [1]Sheet1!$C$3:$CY$3,0))} -> 4.14 | EA43: 2 | EB43: =SUMPRODUCT(Euro_Area_Data!C40:U40,Euro_Area_Data!Z40:AR40)/SUM(Euro_Area_Data!C40:U40) -> 0.78190074 | EC43: =(EB43-EB42)/EB42*100 -> 2.2430956 | ED43: =SUMPRODUCT(Euro_Area_Data!C40:U40,Euro_Area_Data!AW40:BO40)/SUM(Euro_Area_Data!C40:U40) -> -0.17911686 | EE43: -5 | EH43: 0.75 | EI43: 0.05 | EJ43: 60 | EK43: =(EN43-EN42)/EN42*100 -> 1.2670044 | EN43: =[2]EUCAM_output!$AE40 -> 0.73046877
A44: 2004 | B44: =[2]EUCAM_output!$E41*10^9 -> 3.2660582e+11 | H44: =[2]EUCAM_output!$AK41 -> 0.016655533 | I44: =[2]EUCAM_output!$W41*10^3 -> 6226946.5 | K44: =IF(A44<2030,I44,K43*J44/J43) -> 6226946.5 | L44: =[2]EUCAM_output!$G41 -> 65.320983 | O44: =[2]EUCAM_output!$H41 -> 65.266983 | R44: =[2]EUCAM_output!$L41 -> 5.9 | U44: =[2]EUCAM_output!$K41 -> 4.807228 | V44: 4.807228 | W44: 0.019237413 | X44: -0.00044234671 | Y44: =[2]EUCAM_output!$AI41 -> 0.0032302736 | Z44: =[2]EUCAM_output!$M41 -> 1774.8585 | AC44: =[2]EUCAM_output!$AL41 -> 1763.4646 | AD44: =[2]EUCAM_output!$T41*10^9 -> 1.0232128e+12 | AE44: {=INDEX('[3]Sheet 1'!$B$12:$M$61,MATCH($A44,'[3]Sheet 1'!$A$12:$A$61,0),MATCH(MID(CELL("filename",A43),FIND("]",CELL("filename",A43))+1,255)&AE$1,'[3]Sheet 1'!$B$9:$M$9&'[3]Sheet 1'!$B$8:$M$8,0))*10^6} -> 794059900000 | AF44: {=INDEX('[3]Sheet 1'!$B$12:$M$61,MATCH($A44,'[3]Sheet 1'!$A$12:$A$61,0),MATCH(MID(CELL("filename",B43),FIND("]",CELL("filename",B43))+1,255)&AF$1,'[3]Sheet 1'!$B$9:$M$9&'[3]Sheet 1'!$B$8:$M$8,0))*10^6} -> 95915300000 | AG44: =AF44/AE44 -> 0.12079101 | AH44: =AD44*AG44 -> 1.2359491e+11 | AI44: =CH44/EN44 -> 8.1041891e+09 | AJ44: 6027000000 | AK44: =AJ44/EN44 -> 8.1107159e+09 | AL44: =AK44/AH44 -> 0.065623382 | AM44: =AVERAGE($AL$35:$AL$63) -> 0.065166448 | AN44: =AD44-AH44 -> 8.9961787e+11 | AO44: 51150400000 | AP44: =AO44/EN44 -> 6.8834638e+10 | AQ44: 40282200000 | AR44: =(AQ44-AJ44)/EN44 -> 4.6098257e+10 | AS44: =AR44/AN44 -> 0.051242043 | AT44: =AP44/B44*100 -> 21.075754 | BB44: 3.2370427e+11 | BC44: =[2]EUCAM_output!$AG41*10^9 -> 240541730000 | BD44: =(BB44-B44)/B44*100 -> -0.88839416 | BN44: =BP44-CF44 -> -4.54251e+09 | BO44: {=INDEX([1]Sheet1!$C$6:$CY$72,MATCH($A44,[1]Sheet1!$A$6:$A$72,0),MATCH(MID(CELL("filename",A43),FIND("]",CELL("filename",A43))+1,255) & BO$1,[1]Sheet1!$C$1:$CY$1 & [1]Sheet1!$C$3:$CY$3,0))} -> -1.888437 | BP44: {=INDEX([1]Sheet1!$C$6:$CY$72,MATCH($A44,[1]Sheet1!$A$6:$A$72,0),MATCH(MID(CELL("filename",B43),FIND("]",CELL("filename",B43))+1,255) & BP$1,[1]Sheet1!$C$1:$CY$1 & [1]Sheet1!$C$3:$CY$3,0))} -> 118767800000 | BQ44: {=INDEX([1]Sheet1!$C$6:$CY$72,MATCH($A44,[1]Sheet1!$A$6:$A$72,0),MATCH(MID(CELL("filename",C43),FIND("]",CELL("filename",C43))+1,255) & BQ$1,[1]Sheet1!$C$1:$CY$1 & [1]Sheet1!$C$3:$CY$3,0))} -> 3.213193e+10 | BR44: {=INDEX([6]Annual!$C$5:$T$30,MATCH($A44,[6]Annual!$B$5:$B$30,0),MATCH(MID(CELL("filename",$F$2),FIND("]",CELL("filename",$F$2))+1,255) & BR$1,[6]Annual!$C$3:$T$3 & [6]Annual!$C$4:$T$4,0))} -> 2.65846e+10 | BS44: {=INDEX([6]Annual!$C$5:$T$30,MATCH($A44,[6]Annual!$B$5:$B$30,0),MATCH(MID(CELL("filename",$F$2),FIND("]",CELL("filename",$F$2))+1,255) & BS$1,[6]Annual!$C$3:$T$3 & [6]Annual!$C$4:$T$4,0))} -> 4727700000 | BT44: {=INDEX([6]Annual!$C$5:$T$30,MATCH($A44,[6]Annual!$B$5:$B$30,0),MATCH(MID(CELL("filename",$F$2),FIND("]",CELL("filename",$F$2))+1,255) & BT$1,[6]Annual!$C$3:$T$3 & [6]Annual!$C$4:$T$4,0))} -> 874800000 | BU44: =BQ44*BR44/SUM($BR44:$BT44) -> 2.6539033e+10 | BV44: =BQ44-BU44 -> 5.5928971e+09 | BW44: {=INDEX([1]Sheet1!$C$6:$CY$72,MATCH($A44,[1]Sheet1!$A$6:$A$72,0),MATCH(MID(CELL("filename",F43),FIND("]",CELL("filename",F43))+1,255) & BW$1,[1]Sheet1!$C$1:$CY$1 & [1]Sheet1!$C$3:$CY$3,0))} -> 35223890000 | BX44: {=INDEX([1]Sheet1!$C$6:$CY$72,MATCH($A44,[1]Sheet1!$A$6:$A$72,0),MATCH(MID(CELL("filename",G43),FIND("]",CELL("filename",G43))+1,255) & BX$1,[1]Sheet1!$C$1:$CY$1 & [1]Sheet1!$C$3:$CY$3,0))} -> 34461520000 | BY44: {=INDEX([4]DATA!$C$18:$N$51,MATCH($A44,[4]DATA!$B$18:$B$51,0),MATCH(MID(CELL("filename",F11),FIND("]",CELL("filename",F11))+1,255) & BY$1,[4]DATA!$C$15:$N$15&[4]DATA!$C$16:$N$16,0)) * 10^6} -> 18602000000 | BZ44: {=INDEX([4]DATA!$C$18:$N$51,MATCH($A44,[4]DATA!$B$18:$B$51,0),MATCH(MID(CELL("filename",G11),FIND("]",CELL("filename",G11))+1,255) & BZ$1,[4]DATA!$C$15:$N$15&[4]DATA!$C$16:$N$16,0)) * 10^6} -> 15860000000 | CA44: =$BX44*BY44/SUM($BY44:$BZ44) -> 1.8601741e+10 | CB44: =BX44-CA44 -> 1.5859779e+10 | CC44: {=INDEX([1]Sheet1!$C$6:$CY$72,MATCH($A44,[1]Sheet1!$A$6:$A$72,0),MATCH(MID(CELL("filename",J43),FIND("]",CELL("filename",J43))+1,255) & CC$1,[1]Sheet1!$C$1:$CY$1 & [1]Sheet1!$C$3:$CY$3,0))} -> 2641950000 | CD44: =BP44-BQ44-BW44-BX44-CC44 -> 14308510000 | CE44: {=INDEX([1]Sheet1!$C$6:$CY$72,MATCH($A44,[1]Sheet1!$A$6:$A$72,0),MATCH(MID(CELL("filename",L43),FIND("]",CELL("filename",L43))+1,255) & CE$1,[1]Sheet1!$C$1:$CY$1 & [1]Sheet1!$C$3:$CY$3,0))} -> 1.306538e+11 | CF44: =CE44-CK44 -> 1.2331031e+11 | CG44: {=INDEX([1]Sheet1!$C$6:$CY$72,MATCH($A44,[1]Sheet1!$A$6:$A$72,0),MATCH(MID(CELL("filename",N43),FIND("]",CELL("filename",N43))+1,255) & CG$1,[1]Sheet1!$C$1:$CY$1 & [1]Sheet1!$C$3:$CY$3,0))} -> 46048100000 | CH44: {=INDEX([1]Sheet1!$C$6:$CY$72,MATCH($A44,[1]Sheet1!$A$6:$A$72,0),MATCH(MID(CELL("filename",O43),FIND("]",CELL("filename",O43))+1,255) & CH$1,[1]Sheet1!$C$1:$CY$1 & [1]Sheet1!$C$3:$CY$3,0))} -> 6022150000 | CI44: {=INDEX([1]Sheet1!$C$6:$CY$72,MATCH($A44,[1]Sheet1!$A$6:$A$72,0),MATCH(MID(CELL("filename",P43),FIND("]",CELL("filename",P43))+1,255) & CI$1,[1]Sheet1!$C$1:$CY$1 & [1]Sheet1!$C$3:$CY$3,0))} -> 4562770000 | CJ44: {=INDEX([1]Sheet1!$C$6:$CY$72,MATCH($A44,[1]Sheet1!$A$6:$A$72,0),MATCH(MID(CELL("filename",R43),FIND("]",CELL("filename",R43))+1,255) & CJ$1,[1]Sheet1!$C$1:$CY$1 & [1]Sheet1!$C$3:$CY$3,0))} -> 45349600000 | CK44: {=INDEX([1]Sheet1!$C$6:$CY$72,MATCH($A44,[1]Sheet1!$A$6:$A$72,0),MATCH(MID(CELL("filename",S43),FIND("]",CELL("filename",S43))+1,255) & CK$1,[1]Sheet1!$C$1:$CY$1 & [1]Sheet1!$C$3:$CY$3,0))} -> 7343490000 | CL44: =CF44-CG44-CH44-CI44-CJ44 -> 2.132769e+10 | DK44: =DL44/100*BC44 -> 1.5854562e+11 | DL44: {=INDEX([1]Sheet1!$C$6:$CY$72,MATCH($A44,[1]Sheet1!$A$6:$A$72,0),MATCH(MID(CELL("filename",AT43),FIND("]",CELL("filename",AT43))+1,255) & DL$1,[1]Sheet1!$C$1:$CY$1 & [1]Sheet1!$C$3:$CY$3,0))} -> 65.9119 | DM44: {=INDEX([5]DATA!$C$18:$T$51,MATCH($A44,[5]DATA!$B$18:$B$51,0),MATCH(MID(CELL("filename",AU11),FIND("]",CELL("filename",AU11))+1,255) & DM$1,[5]DATA!$C$15:$T$15&[5]DATA!$C$16:$T$16,0)) * 10^6} -> 4653000000 | DN44: {=INDEX([5]DATA!$C$18:$T$51,MATCH($A44,[5]DATA!$B$18:$B$51,0),MATCH(MID(CELL("filename",AV11),FIND("]",CELL("filename",AV11))+1,255) & DN$1,[5]DATA!$C$15:$T$15&[5]DATA!$C$16:$T$16,0)) * 10^6} -> 153893000000 | DQ44: 1.243902 | DR44: {=INDEX([1]Sheet1!$C$6:$CY$72,MATCH($A44,[1]Sheet1!$A$6:$A$72,0),MATCH(MID(CELL("filename",AZ43),FIND("]",CELL("filename",AZ43))+1,255) & DR$1,[1]Sheet1!$C$1:$CY$1 & [1]Sheet1!$C$3:$CY$3,0))} -> -6450000000 | DS44: {=INDEX([1]Sheet1!$C$6:$CY$72,MATCH($A44,[1]Sheet1!$A$6:$A$72,0),MATCH(MID(CELL("filename",BA43),FIND("]",CELL("filename",BA43))+1,255) & DS$1,[1]Sheet1!$C$1:$CY$1 & [1]Sheet1!$C$3:$CY$3,0))} -> 4.796316 | DT44: {=INDEX([5]DATA!$C$18:$T$51,MATCH($A44,[5]DATA!$B$18:$B$51,0),MATCH(MID(CELL("filename",BB11),FIND("]",CELL("filename",BB11))+1,255) & DT$1,[5]DATA!$C$15:$T$15&[5]DATA!$C$16:$T$16,0)) * 10^6} -> 19581000000 | DU44: {=INDEX([1]Sheet1!$C$6:$CY$72,MATCH($A44,[1]Sheet1!$A$6:$A$72,0),MATCH(MID(CELL("filename",BC43),FIND("]",CELL("filename",BC43))+1,255) & DU$1,[1]Sheet1!$C$1:$CY$1 & [1]Sheet1!$C$3:$CY$3,0))} -> 2.11 | DV44: 0.5 | DW44: =Euro_Area_Data!V41*10^9 -> 1.0325521e+13 | DX44: 1 | DY44: 0.5 | DZ44: {=INDEX([1]Sheet1!$C$6:$CY$72,MATCH($A44,[1]Sheet1!$A$6:$A$72,0),MATCH(MID(CELL("filename",BH43),FIND("]",CELL("filename",BH43))+1,255) & DZ$1,[1]Sheet1!$C$1:$CY$1 & [1]Sheet1!$C$3:$CY$3,0))} -> 4.13 | EA44: 2 | EB44: =SUMPRODUCT(Euro_Area_Data!C41:U41,Euro_Area_Data!Z41:AR41)/SUM(Euro_Area_Data!C41:U41) -> 0.79719367 | EC44: =(EB44-EB43)/EB43*100 -> 1.9558657 | ED44: =SUMPRODUCT(Euro_Area_Data!C41:U41,Euro_Area_Data!AW41:BO41)/SUM(Euro_Area_Data!C41:U41) -> 0.2126194 | EE44: -5 | EH44: 0.75 | EI44: 0.05 | EJ44: 60 | EK44: =(EN44-EN43)/EN43*100 -> 1.7279629 | EN44: =[2]EUCAM_output!$AE41 -> 0.743091
A45: 2005 | B45: =[2]EUCAM_output!$E42*10^9 -> 3.3406541e+11 | H45: =[2]EUCAM_output!$AK42 -> 0.001181651 | I45: =[2]EUCAM_output!$W42*10^3 -> 6278368 | K45: =IF(A45<2030,I45,K44*J45/J44) -> 6278368 | L45: =[2]EUCAM_output!$G42 -> 65.635366 | O45: =[2]EUCAM_output!$H42 -> 65.663795 | R45: =[2]EUCAM_output!$L42 -> 6 | U45: =[2]EUCAM_output!$K42 -> 4.920672 | V45: 4.920672 | W45: 0.01103693 | X45: -0.0016955631 | Y45: =[2]EUCAM_output!$AI42 -> -0.000264614 | Z45: =[2]EUCAM_output!$M42 -> 1750.1815 | AC45: =[2]EUCAM_output!$AL42 -> 1750.7813 | AD45: =[2]EUCAM_output!$T42*10^9 -> 1.0415649e+12 | AE45: {=INDEX('[3]Sheet 1'!$B$12:$M$61,MATCH($A45,'[3]Sheet 1'!$A$12:$A$61,0),MATCH(MID(CELL("filename",A44),FIND("]",CELL("filename",A44))+1,255)&AE$1,'[3]Sheet 1'!$B$9:$M$9&'[3]Sheet 1'!$B$8:$M$8,0))*10^6} -> 826964000000 | AF45: {=INDEX('[3]Sheet 1'!$B$12:$M$61,MATCH($A45,'[3]Sheet 1'!$A$12:$A$61,0),MATCH(MID(CELL("filename",B44),FIND("]",CELL("filename",B44))+1,255)&AF$1,'[3]Sheet 1'!$B$9:$M$9&'[3]Sheet 1'!$B$8:$M$8,0))*10^6} -> 118063800000 | AG45: =AF45/AE45 -> 0.14276776 | AH45: =AD45*AG45 -> 1.4870189e+11 | AI45: =CH45/EN45 -> 9.9409926e+09 | AJ45: 7049390000 | AK45: =AJ45/EN45 -> 9.2523117e+09 | AL45: =AK45/AH45 -> 0.062220538 | AM45: =AVERAGE($AL$35:$AL$63) -> 0.065166448 | AN45: =AD45-AH45 -> 8.9286302e+11 | AO45: 51059500000 | AP45: =AO45/EN45 -> 6.7015502e+10 | AQ45: 41718000000 | AR45: =(AQ45-AJ45)/EN45 -> 4.5502488e+10 | AS45: =AR45/AN45 -> 0.050962452 | AT45: =AP45/B45*100 -> 20.060593 | BB45: 3.3121539e+11 | BC45: =[2]EUCAM_output!$AG42*10^9 -> 252354930000 | BD45: =(BB45-B45)/B45*100 -> -0.85313162 | BN45: =BP45-CF45 -> 1.7107e+09 | BO45: {=INDEX([1]Sheet1!$C$6:$CY$72,MATCH($A45,[1]Sheet1!$A$6:$A$72,0),MATCH(MID(CELL("filename",A44),FIND("]",CELL("filename",A44))+1,255) & BO$1,[1]Sheet1!$C$1:$CY$1 & [1]Sheet1!$C$3:$CY$3,0))} -> 0.677894 | BP45: {=INDEX([1]Sheet1!$C$6:$CY$72,MATCH($A45,[1]Sheet1!$A$6:$A$72,0),MATCH(MID(CELL("filename",B44),FIND("]",CELL("filename",B44))+1,255) & BP$1,[1]Sheet1!$C$1:$CY$1 & [1]Sheet1!$C$3:$CY$3,0))} -> 123866500000 | BQ45: {=INDEX([1]Sheet1!$C$6:$CY$72,MATCH($A45,[1]Sheet1!$A$6:$A$72,0),MATCH(MID(CELL("filename",C44),FIND("]",CELL("filename",C44))+1,255) & BQ$1,[1]Sheet1!$C$1:$CY$1 & [1]Sheet1!$C$3:$CY$3,0))} -> 32372990000 | BR45: {=INDEX([6]Annual!$C$5:$T$30,MATCH($A45,[6]Annual!$B$5:$B$30,0),MATCH(MID(CELL("filename",$F$2),FIND("]",CELL("filename",$F$2))+1,255) & BR$1,[6]Annual!$C$3:$T$3 & [6]Annual!$C$4:$T$4,0))} -> 26659900000 | BS45: {=INDEX([6]Annual!$C$5:$T$30,MATCH($A45,[6]Annual!$B$5:$B$30,0),MATCH(MID(CELL("filename",$F$2),FIND("]",CELL("filename",$F$2))+1,255) & BS$1,[6]Annual!$C$3:$T$3 & [6]Annual!$C$4:$T$4,0))} -> 4.8562e+09 | BT45: {=INDEX([6]Annual!$C$5:$T$30,MATCH($A45,[6]Annual!$B$5:$B$30,0),MATCH(MID(CELL("filename",$F$2),FIND("]",CELL("filename",$F$2))+1,255) & BT$1,[6]Annual!$C$3:$T$3 & [6]Annual!$C$4:$T$4,0))} -> 865900000 | BU45: =BQ45*BR45/SUM($BR45:$BT45) -> 2.6652482e+10 | BV45: =BQ45-BU45 -> 5.7205079e+09 | BW45: {=INDEX([1]Sheet1!$C$6:$CY$72,MATCH($A45,[1]Sheet1!$A$6:$A$72,0),MATCH(MID(CELL("filename",F44),FIND("]",CELL("filename",F44))+1,255) & BW$1,[1]Sheet1!$C$1:$CY$1 & [1]Sheet1!$C$3:$CY$3,0))} -> 36145420000 | BX45: {=INDEX([1]Sheet1!$C$6:$CY$72,MATCH($A45,[1]Sheet1!$A$6:$A$72,0),MATCH(MID(CELL("filename",G44),FIND("]",CELL("filename",G44))+1,255) & BX$1,[1]Sheet1!$C$1:$CY$1 & [1]Sheet1!$C$3:$CY$3,0))} -> 35830910000 | BY45: {=INDEX([4]DATA!$C$18:$N$51,MATCH($A45,[4]DATA!$B$18:$B$51,0),MATCH(MID(CELL("filename",F12),FIND("]",CELL("filename",F12))+1,255) & BY$1,[4]DATA!$C$15:$N$15&[4]DATA!$C$16:$N$16,0)) * 10^6} -> 19268000000 | BZ45: {=INDEX([4]DATA!$C$18:$N$51,MATCH($A45,[4]DATA!$B$18:$B$51,0),MATCH(MID(CELL("filename",G12),FIND("]",CELL("filename",G12))+1,255) & BZ$1,[4]DATA!$C$15:$N$15&[4]DATA!$C$16:$N$16,0)) * 10^6} -> 16562000000 | CA45: =$BX45*BY45/SUM($BY45:$BZ45) -> 1.9268489e+10 | CB45: =BX45-CA45 -> 1.6562421e+10 | CC45: {=INDEX([1]Sheet1!$C$6:$CY$72,MATCH($A45,[1]Sheet1!$A$6:$A$72,0),MATCH(MID(CELL("filename",J44),FIND("]",CELL("filename",J44))+1,255) & CC$1,[1]Sheet1!$C$1:$CY$1 & [1]Sheet1!$C$3:$CY$3,0))} -> 2249350000 | CD45: =BP45-BQ45-BW45-BX45-CC45 -> 17267830000 | CE45: {=INDEX([1]Sheet1!$C$6:$CY$72,MATCH($A45,[1]Sheet1!$A$6:$A$72,0),MATCH(MID(CELL("filename",L44),FIND("]",CELL("filename",L44))+1,255) & CE$1,[1]Sheet1!$C$1:$CY$1 & [1]Sheet1!$C$3:$CY$3,0))} -> 1.303987e+11 | CF45: =CE45-CK45 -> 1.221558e+11 | CG45: {=INDEX([1]Sheet1!$C$6:$CY$72,MATCH($A45,[1]Sheet1!$A$6:$A$72,0),MATCH(MID(CELL("filename",N44),FIND("]",CELL("filename",N44))+1,255) & CG$1,[1]Sheet1!$C$1:$CY$1 & [1]Sheet1!$C$3:$CY$3,0))} -> 49408500000 | CH45: {=INDEX([1]Sheet1!$C$6:$CY$72,MATCH($A45,[1]Sheet1!$A$6:$A$72,0),MATCH(MID(CELL("filename",O44),FIND("]",CELL("filename",O44))+1,255) & CH$1,[1]Sheet1!$C$1:$CY$1 & [1]Sheet1!$C$3:$CY$3,0))} -> 7574100000 | CI45: {=INDEX([1]Sheet1!$C$6:$CY$72,MATCH($A45,[1]Sheet1!$A$6:$A$72,0),MATCH(MID(CELL("filename",P44),FIND("]",CELL("filename",P44))+1,255) & CI$1,[1]Sheet1!$C$1:$CY$1 & [1]Sheet1!$C$3:$CY$3,0))} -> 4011590000 | CJ45: {=INDEX([1]Sheet1!$C$6:$CY$72,MATCH($A45,[1]Sheet1!$A$6:$A$72,0),MATCH(MID(CELL("filename",R44),FIND("]",CELL("filename",R44))+1,255) & CJ$1,[1]Sheet1!$C$1:$CY$1 & [1]Sheet1!$C$3:$CY$3,0))} -> 46484600000 | CK45: {=INDEX([1]Sheet1!$C$6:$CY$72,MATCH($A45,[1]Sheet1!$A$6:$A$72,0),MATCH(MID(CELL("filename",S44),FIND("]",CELL("filename",S44))+1,255) & CK$1,[1]Sheet1!$C$1:$CY$1 & [1]Sheet1!$C$3:$CY$3,0))} -> 8.2429e+09 | CL45: =CF45-CG45-CH45-CI45-CJ45 -> 1.467701e+10 | DK45: =DL45/100*BC45 -> 1.7520397e+11 | DL45: {=INDEX([1]Sheet1!$C$6:$CY$72,MATCH($A45,[1]Sheet1!$A$6:$A$72,0),MATCH(MID(CELL("filename",AT44),FIND("]",CELL("filename",AT44))+1,255) & DL$1,[1]Sheet1!$C$1:$CY$1 & [1]Sheet1!$C$3:$CY$3,0))} -> 69.4276 | DM45: {=INDEX([5]DATA!$C$18:$T$51,MATCH($A45,[5]DATA!$B$18:$B$51,0),MATCH(MID(CELL("filename",AU12),FIND("]",CELL("filename",AU12))+1,255) & DM$1,[5]DATA!$C$15:$T$15&[5]DATA!$C$16:$T$16,0)) * 10^6} -> 5537000000 | DN45: {=INDEX([5]DATA!$C$18:$T$51,MATCH($A45,[5]DATA!$B$18:$B$51,0),MATCH(MID(CELL("filename",AV12),FIND("]",CELL("filename",AV12))+1,255) & DN$1,[5]DATA!$C$15:$T$15&[5]DATA!$C$16:$T$16,0)) * 10^6} -> 169667000000 | DQ45: 1.24409 | DR45: {=INDEX([1]Sheet1!$C$6:$CY$72,MATCH($A45,[1]Sheet1!$A$6:$A$72,0),MATCH(MID(CELL("filename",AZ44),FIND("]",CELL("filename",AZ44))+1,255) & DR$1,[1]Sheet1!$C$1:$CY$1 & [1]Sheet1!$C$3:$CY$3,0))} -> 10130000000 | DS45: {=INDEX([1]Sheet1!$C$6:$CY$72,MATCH($A45,[1]Sheet1!$A$6:$A$72,0),MATCH(MID(CELL("filename",BA44),FIND("]",CELL("filename",BA44))+1,255) & DS$1,[1]Sheet1!$C$1:$CY$1 & [1]Sheet1!$C$3:$CY$3,0))} -> 5.199069 | DT45: {=INDEX([5]DATA!$C$18:$T$51,MATCH($A45,[5]DATA!$B$18:$B$51,0),MATCH(MID(CELL("filename",BB12),FIND("]",CELL("filename",BB12))+1,255) & DT$1,[5]DATA!$C$15:$T$15&[5]DATA!$C$16:$T$16,0)) * 10^6} -> 19681000000 | DU45: {=INDEX([1]Sheet1!$C$6:$CY$72,MATCH($A45,[1]Sheet1!$A$6:$A$72,0),MATCH(MID(CELL("filename",BC44),FIND("]",CELL("filename",BC44))+1,255) & DU$1,[1]Sheet1!$C$1:$CY$1 & [1]Sheet1!$C$3:$CY$3,0))} -> 2.19 | DV45: 0.5 | DW45: =Euro_Area_Data!V42*10^9 -> 1.0508347e+13 | DX45: 1 | DY45: 0.5 | DZ45: {=INDEX([1]Sheet1!$C$6:$CY$72,MATCH($A45,[1]Sheet1!$A$6:$A$72,0),MATCH(MID(CELL("filename",BH44),FIND("]",CELL("filename",BH44))+1,255) & DZ$1,[1]Sheet1!$C$1:$CY$1 & [1]Sheet1!$C$3:$CY$3,0))} -> 3.39 | EA45: 2 | EB45: =SUMPRODUCT(Euro_Area_Data!C42:U42,Euro_Area_Data!Z42:AR42)/SUM(Euro_Area_Data!C42:U42) -> 0.81235194 | EC45: =(EB45-EB44)/EB44*100 -> 1.9014542 | ED45: =SUMPRODUCT(Euro_Area_Data!C42:U42,Euro_Area_Data!AW42:BO42)/SUM(Euro_Area_Data!C42:U42) -> 0.19366839 | EE45: -5 | EH45: 0.75 | EI45: 0.05 | EJ45: 60 | EK45: =(EN45-EN44)/EN44*100 -> 2.5319656 | EN45: =[2]EUCAM_output!$AE42 -> 0.76190581
A46: 2006 | B46: =[2]EUCAM_output!$E43*10^9 -> 3.4102138e+11 | H46: =[2]EUCAM_output!$AK43 -> 0.032595565 | I46: =[2]EUCAM_output!$W43*10^3 -> 6321135.5 | K46: =IF(A46<2030,I46,K45*J46/J45) -> 6321135.5 | L46: =[2]EUCAM_output!$G43 -> 66.120146 | O46: =[2]EUCAM_output!$H43 -> 66.058701 | R46: =[2]EUCAM_output!$L43 -> 5.7 | U46: =[2]EUCAM_output!$K43 -> 4.991092 | V46: 4.991092 | W46: 0.014946915 | X46: -0.00094676495 | Y46: =[2]EUCAM_output!$AI43 -> 0.01063998 | Z46: =[2]EUCAM_output!$M43 -> 1733.39 | AC46: =[2]EUCAM_output!$AL43 -> 1736.2362 | AD46: =[2]EUCAM_output!$T43*10^9 -> 1.0598696e+12 | AE46: {=INDEX('[3]Sheet 1'!$B$12:$M$61,MATCH($A46,'[3]Sheet 1'!$A$12:$A$61,0),MATCH(MID(CELL("filename",A45),FIND("]",CELL("filename",A45))+1,255)&AE$1,'[3]Sheet 1'!$B$9:$M$9&'[3]Sheet 1'!$B$8:$M$8,0))*10^6} -> 867016100000 | AF46: {=INDEX('[3]Sheet 1'!$B$12:$M$61,MATCH($A46,'[3]Sheet 1'!$A$12:$A$61,0),MATCH(MID(CELL("filename",B45),FIND("]",CELL("filename",B45))+1,255)&AF$1,'[3]Sheet 1'!$B$9:$M$9&'[3]Sheet 1'!$B$8:$M$8,0))*10^6} -> 122319300000 | AG46: =AF46/AE46 -> 0.14108077 | AH46: =AD46*AG46 -> 1.4952722e+11 | AI46: =CH46/EN46 -> 1.0108068e+10 | AJ46: 7301830000 | AK46: =AJ46/EN46 -> 9.391616e+09 | AL46: =AK46/AH46 -> 0.06280874 | AM46: =AVERAGE($AL$35:$AL$63) -> 0.065166448 | AN46: =AD46-AH46 -> 9.1034236e+11 | AO46: 52855600000 | AP46: =AO46/EN46 -> 6.7982889e+10 | AQ46: 43253700000 | AR46: =(AQ46-AJ46)/EN46 -> 4.6241306e+10 | AS46: =AR46/AN46 -> 0.050795512 | AT46: =AP46/B46*100 -> 19.935081 | BB46: 3.4204394e+11 | BC46: =[2]EUCAM_output!$AG43*10^9 -> 265933650000 | BD46: =(BB46-B46)/B46*100 -> 0.29985264 | BN46: =BP46-CF46 -> 1.49968e+09 | BO46: {=INDEX([1]Sheet1!$C$6:$CY$72,MATCH($A46,[1]Sheet1!$A$6:$A$72,0),MATCH(MID(CELL("filename",A45),FIND("]",CELL("filename",A45))+1,255) & BO$1,[1]Sheet1!$C$1:$CY$1 & [1]Sheet1!$C$3:$CY$3,0))} -> 0.563945 | BP46: {=INDEX([1]Sheet1!$C$6:$CY$72,MATCH($A46,[1]Sheet1!$A$6:$A$72,0),MATCH(MID(CELL("filename",B45),FIND("]",CELL("filename",B45))+1,255) & BP$1,[1]Sheet1!$C$1:$CY$1 & [1]Sheet1!$C$3:$CY$3,0))} -> 128476200000 | BQ46: {=INDEX([1]Sheet1!$C$6:$CY$72,MATCH($A46,[1]Sheet1!$A$6:$A$72,0),MATCH(MID(CELL("filename",C45),FIND("]",CELL("filename",C45))+1,255) & BQ$1,[1]Sheet1!$C$1:$CY$1 & [1]Sheet1!$C$3:$CY$3,0))} -> 33935100000 | BR46: {=INDEX([6]Annual!$C$5:$T$30,MATCH($A46,[6]Annual!$B$5:$B$30,0),MATCH(MID(CELL("filename",$F$2),FIND("]",CELL("filename",$F$2))+1,255) & BR$1,[6]Annual!$C$3:$T$3 & [6]Annual!$C$4:$T$4,0))} -> 2.80274e+10 | BS46: {=INDEX([6]Annual!$C$5:$T$30,MATCH($A46,[6]Annual!$B$5:$B$30,0),MATCH(MID(CELL("filename",$F$2),FIND("]",CELL("filename",$F$2))+1,255) & BS$1,[6]Annual!$C$3:$T$3 & [6]Annual!$C$4:$T$4,0))} -> 5098600000 | BT46: {=INDEX([6]Annual!$C$5:$T$30,MATCH($A46,[6]Annual!$B$5:$B$30,0),MATCH(MID(CELL("filename",$F$2),FIND("]",CELL("filename",$F$2))+1,255) & BT$1,[6]Annual!$C$3:$T$3 & [6]Annual!$C$4:$T$4,0))} -> 825400000 | BU46: =BQ46*BR46/SUM($BR46:$BT46) -> 2.8013944e+10 | BV46: =BQ46-BU46 -> 5.9211559e+09 | BW46: {=INDEX([1]Sheet1!$C$6:$CY$72,MATCH($A46,[1]Sheet1!$A$6:$A$72,0),MATCH(MID(CELL("filename",F45),FIND("]",CELL("filename",F45))+1,255) & BW$1,[1]Sheet1!$C$1:$CY$1 & [1]Sheet1!$C$3:$CY$3,0))} -> 37042360000 | BX46: {=INDEX([1]Sheet1!$C$6:$CY$72,MATCH($A46,[1]Sheet1!$A$6:$A$72,0),MATCH(MID(CELL("filename",G45),FIND("]",CELL("filename",G45))+1,255) & BX$1,[1]Sheet1!$C$1:$CY$1 & [1]Sheet1!$C$3:$CY$3,0))} -> 37380810000 | BY46: {=INDEX([4]DATA!$C$18:$N$51,MATCH($A46,[4]DATA!$B$18:$B$51,0),MATCH(MID(CELL("filename",F13),FIND("]",CELL("filename",F13))+1,255) & BY$1,[4]DATA!$C$15:$N$15&[4]DATA!$C$16:$N$16,0)) * 10^6} -> 20120000000 | BZ46: {=INDEX([4]DATA!$C$18:$N$51,MATCH($A46,[4]DATA!$B$18:$B$51,0),MATCH(MID(CELL("filename",G13),FIND("]",CELL("filename",G13))+1,255) & BZ$1,[4]DATA!$C$15:$N$15&[4]DATA!$C$16:$N$16,0)) * 10^6} -> 17261000000 | CA46: =$BX46*BY46/SUM($BY46:$BZ46) -> 2.0119898e+10 | CB46: =BX46-CA46 -> 1.7260912e+10 | CC46: {=INDEX([1]Sheet1!$C$6:$CY$72,MATCH($A46,[1]Sheet1!$A$6:$A$72,0),MATCH(MID(CELL("filename",J45),FIND("]",CELL("filename",J45))+1,255) & CC$1,[1]Sheet1!$C$1:$CY$1 & [1]Sheet1!$C$3:$CY$3,0))} -> 2189500000 | CD46: =BP46-BQ46-BW46-BX46-CC46 -> 17928430000 | CE46: {=INDEX([1]Sheet1!$C$6:$CY$72,MATCH($A46,[1]Sheet1!$A$6:$A$72,0),MATCH(MID(CELL("filename",L45),FIND("]",CELL("filename",L45))+1,255) & CE$1,[1]Sheet1!$C$1:$CY$1 & [1]Sheet1!$C$3:$CY$3,0))} -> 1.354131e+11 | CF46: =CE46-CK46 -> 1.2697652e+11 | CG46: {=INDEX([1]Sheet1!$C$6:$CY$72,MATCH($A46,[1]Sheet1!$A$6:$A$72,0),MATCH(MID(CELL("filename",N45),FIND("]",CELL("filename",N45))+1,255) & CG$1,[1]Sheet1!$C$1:$CY$1 & [1]Sheet1!$C$3:$CY$3,0))} -> 51920100000 | CH46: {=INDEX([1]Sheet1!$C$6:$CY$72,MATCH($A46,[1]Sheet1!$A$6:$A$72,0),MATCH(MID(CELL("filename",O45),FIND("]",CELL("filename",O45))+1,255) & CH$1,[1]Sheet1!$C$1:$CY$1 & [1]Sheet1!$C$3:$CY$3,0))} -> 7858860000 | CI46: {=INDEX([1]Sheet1!$C$6:$CY$72,MATCH($A46,[1]Sheet1!$A$6:$A$72,0),MATCH(MID(CELL("filename",P45),FIND("]",CELL("filename",P45))+1,255) & CI$1,[1]Sheet1!$C$1:$CY$1 & [1]Sheet1!$C$3:$CY$3,0))} -> 4.18256e+09 | CJ46: {=INDEX([1]Sheet1!$C$6:$CY$72,MATCH($A46,[1]Sheet1!$A$6:$A$72,0),MATCH(MID(CELL("filename",R45),FIND("]",CELL("filename",R45))+1,255) & CJ$1,[1]Sheet1!$C$1:$CY$1 & [1]Sheet1!$C$3:$CY$3,0))} -> 48017300000 | CK46: {=INDEX([1]Sheet1!$C$6:$CY$72,MATCH($A46,[1]Sheet1!$A$6:$A$72,0),MATCH(MID(CELL("filename",S45),FIND("]",CELL("filename",S45))+1,255) & CK$1,[1]Sheet1!$C$1:$CY$1 & [1]Sheet1!$C$3:$CY$3,0))} -> 8.43658e+09 | CL46: =CF46-CG46-CH46-CI46-CJ46 -> 1.49977e+10 | DK46: =DL46/100*BC46 -> 1.8130452e+11 | DL46: {=INDEX([1]Sheet1!$C$6:$CY$72,MATCH($A46,[1]Sheet1!$A$6:$A$72,0),MATCH(MID(CELL("filename",AT45),FIND("]",CELL("filename",AT45))+1,255) & DL$1,[1]Sheet1!$C$1:$CY$1 & [1]Sheet1!$C$3:$CY$3,0))} -> 68.1766 | DM46: {=INDEX([5]DATA!$C$18:$T$51,MATCH($A46,[5]DATA!$B$18:$B$51,0),MATCH(MID(CELL("filename",AU13),FIND("]",CELL("filename",AU13))+1,255) & DM$1,[5]DATA!$C$15:$T$15&[5]DATA!$C$16:$T$16,0)) * 10^6} -> 6130000000 | DN46: {=INDEX([5]DATA!$C$18:$T$51,MATCH($A46,[5]DATA!$B$18:$B$51,0),MATCH(MID(CELL("filename",AV13),FIND("]",CELL("filename",AV13))+1,255) & DN$1,[5]DATA!$C$15:$T$15&[5]DATA!$C$16:$T$16,0)) * 10^6} -> 175174000000 | DQ46: 1.255599 | DR46: {=INDEX([1]Sheet1!$C$6:$CY$72,MATCH($A46,[1]Sheet1!$A$6:$A$72,0),MATCH(MID(CELL("filename",AZ45),FIND("]",CELL("filename",AZ45))+1,255) & DR$1,[1]Sheet1!$C$1:$CY$1 & [1]Sheet1!$C$3:$CY$3,0))} -> -840000000 | DS46: {=INDEX([1]Sheet1!$C$6:$CY$72,MATCH($A46,[1]Sheet1!$A$6:$A$72,0),MATCH(MID(CELL("filename",BA45),FIND("]",CELL("filename",BA45))+1,255) & DS$1,[1]Sheet1!$C$1:$CY$1 & [1]Sheet1!$C$3:$CY$3,0))} -> 4.815292 | DT46: {=INDEX([5]DATA!$C$18:$T$51,MATCH($A46,[5]DATA!$B$18:$B$51,0),MATCH(MID(CELL("filename",BB13),FIND("]",CELL("filename",BB13))+1,255) & DT$1,[5]DATA!$C$15:$T$15&[5]DATA!$C$16:$T$16,0)) * 10^6} -> 23218000000 | DU46: {=INDEX([1]Sheet1!$C$6:$CY$72,MATCH($A46,[1]Sheet1!$A$6:$A$72,0),MATCH(MID(CELL("filename",BC45),FIND("]",CELL("filename",BC45))+1,255) & DU$1,[1]Sheet1!$C$1:$CY$1 & [1]Sheet1!$C$3:$CY$3,0))} -> 3.08 | DV46: 0.5 | DW46: =Euro_Area_Data!V43*10^9 -> 1.0857529e+13 | DX46: 1 | DY46: 0.5 | DZ46: {=INDEX([1]Sheet1!$C$6:$CY$72,MATCH($A46,[1]Sheet1!$A$6:$A$72,0),MATCH(MID(CELL("filename",BH45),FIND("]",CELL("filename",BH45))+1,255) & DZ$1,[1]Sheet1!$C$1:$CY$1 & [1]Sheet1!$C$3:$CY$3,0))} -> 3.8 | EA46: 2 | EB46: =SUMPRODUCT(Euro_Area_Data!C43:U43,Euro_Area_Data!Z43:AR43)/SUM(Euro_Area_Data!C43:U43) -> 0.82880914 | EC46: =(EB46-EB45)/EB45*100 -> 2.0258714 | ED46: =SUMPRODUCT(Euro_Area_Data!C43:U43,Euro_Area_Data!AW43:BO43)/SUM(Euro_Area_Data!C43:U43) -> 1.6394196 | EE46: -5 | EH46: 0.75 | EI46: 0.05 | EJ46: 60 | EK46: =(EN46-EN45)/EN45*100 -> 2.0446187 | EN46: =[2]EUCAM_output!$AE43 -> 0.77748387
A47: 2007 | B47: =[2]EUCAM_output!$E44*10^9 -> 3.4743932e+11 | H47: =[2]EUCAM_output!$AK44 -> 0.034530668 | I47: =[2]EUCAM_output!$W44*10^3 -> 6355779 | K47: =IF(A47<2030,I47,K46*J47/J46) -> 6355779 | L47: =[2]EUCAM_output!$G44 -> 66.677381 | O47: =[2]EUCAM_output!$H44 -> 66.426291 | R47: =[2]EUCAM_output!$L44 -> 5.3 | U47: =[2]EUCAM_output!$K44 -> 5.031521 | V47: 5.031521 | W47: 0.019147346 | X47: 0.0014022415 | Y47: =[2]EUCAM_output!$AI44 -> -0.0012133938 | Z47: =[2]EUCAM_output!$M44 -> 1723.0521 | AC47: =[2]EUCAM_output!$AL44 -> 1720.4498 | AD47: =[2]EUCAM_output!$T44*10^9 -> 1.0805899e+12 | AE47: {=INDEX('[3]Sheet 1'!$B$12:$M$61,MATCH($A47,'[3]Sheet 1'!$A$12:$A$61,0),MATCH(MID(CELL("filename",A46),FIND("]",CELL("filename",A46))+1,255)&AE$1,'[3]Sheet 1'!$B$9:$M$9&'[3]Sheet 1'!$B$8:$M$8,0))*10^6} -> 918088900000 | AF47: {=INDEX('[3]Sheet 1'!$B$12:$M$61,MATCH($A47,'[3]Sheet 1'!$A$12:$A$61,0),MATCH(MID(CELL("filename",B46),FIND("]",CELL("filename",B46))+1,255)&AF$1,'[3]Sheet 1'!$B$9:$M$9&'[3]Sheet 1'!$B$8:$M$8,0))*10^6} -> 128182100000 | AG47: =AF47/AE47 -> 0.1396184 | AH47: =AD47*AG47 -> 1.5087022e+11 | AI47: =CH47/EN47 -> 1.0782802e+10 | AJ47: 7598410000 | AK47: =AJ47/EN47 -> 9.5571551e+09 | AL47: =AK47/AH47 -> 0.063346861 | AM47: =AVERAGE($AL$35:$AL$63) -> 0.065166448 | AN47: =AD47-AH47 -> 9.2971964e+11 | AO47: 56728400000 | AP47: =AO47/EN47 -> 7.1352048e+10 | AQ47: 44931500000 | AR47: =(AQ47-AJ47)/EN47 -> 4.6956946e+10 | AS47: =AR47/AN47 -> 0.050506566 | AT47: =AP47/B47*100 -> 20.53655 | BB47: 3.5495687e+11 | BC47: =[2]EUCAM_output!$AG44*10^9 -> 282208230000 | BD47: =(BB47-B47)/B47*100 -> 2.1637021 | BN47: =BP47-CF47 -> 5.12308e+09 | BO47: {=INDEX([1]Sheet1!$C$6:$CY$72,MATCH($A47,[1]Sheet1!$A$6:$A$72,0),MATCH(MID(CELL("filename",A46),FIND("]",CELL("filename",A46))+1,255) & BO$1,[1]Sheet1!$C$1:$CY$1 & [1]Sheet1!$C$3:$CY$3,0))} -> 1.81533 | BP47: {=INDEX([1]Sheet1!$C$6:$CY$72,MATCH($A47,[1]Sheet1!$A$6:$A$72,0),MATCH(MID(CELL("filename",B46),FIND("]",CELL("filename",B46))+1,255) & BP$1,[1]Sheet1!$C$1:$CY$1 & [1]Sheet1!$C$3:$CY$3,0))} -> 1.364481e+11 | BQ47: {=INDEX([1]Sheet1!$C$6:$CY$72,MATCH($A47,[1]Sheet1!$A$6:$A$72,0),MATCH(MID(CELL("filename",C46),FIND("]",CELL("filename",C46))+1,255) & BQ$1,[1]Sheet1!$C$1:$CY$1 & [1]Sheet1!$C$3:$CY$3,0))} -> 37298580000 | BR47: {=INDEX([6]Annual!$C$5:$T$30,MATCH($A47,[6]Annual!$B$5:$B$30,0),MATCH(MID(CELL("filename",$F$2),FIND("]",CELL("filename",$F$2))+1,255) & BR$1,[6]Annual!$C$3:$T$3 & [6]Annual!$C$4:$T$4,0))} -> 3.02809e+10 | BS47: {=INDEX([6]Annual!$C$5:$T$30,MATCH($A47,[6]Annual!$B$5:$B$30,0),MATCH(MID(CELL("filename",$F$2),FIND("]",CELL("filename",$F$2))+1,255) & BS$1,[6]Annual!$C$3:$T$3 & [6]Annual!$C$4:$T$4,0))} -> 6069800000 | BT47: {=INDEX([6]Annual!$C$5:$T$30,MATCH($A47,[6]Annual!$B$5:$B$30,0),MATCH(MID(CELL("filename",$F$2),FIND("]",CELL("filename",$F$2))+1,255) & BT$1,[6]Annual!$C$3:$T$3 & [6]Annual!$C$4:$T$4,0))} -> 966500000 | BU47: =BQ47*BR47/SUM($BR47:$BT47) -> 3.0265791e+10 | BV47: =BQ47-BU47 -> 7.0327891e+09 | BW47: {=INDEX([1]Sheet1!$C$6:$CY$72,MATCH($A47,[1]Sheet1!$A$6:$A$72,0),MATCH(MID(CELL("filename",F46),FIND("]",CELL("filename",F46))+1,255) & BW$1,[1]Sheet1!$C$1:$CY$1 & [1]Sheet1!$C$3:$CY$3,0))} -> 39103670000 | BX47: {=INDEX([1]Sheet1!$C$6:$CY$72,MATCH($A47,[1]Sheet1!$A$6:$A$72,0),MATCH(MID(CELL("filename",G46),FIND("]",CELL("filename",G46))+1,255) & BX$1,[1]Sheet1!$C$1:$CY$1 & [1]Sheet1!$C$3:$CY$3,0))} -> 39000480000 | BY47: {=INDEX([4]DATA!$C$18:$N$51,MATCH($A47,[4]DATA!$B$18:$B$51,0),MATCH(MID(CELL("filename",F14),FIND("]",CELL("filename",F14))+1,255) & BY$1,[4]DATA!$C$15:$N$15&[4]DATA!$C$16:$N$16,0)) * 10^6} -> 20909000000 | BZ47: {=INDEX([4]DATA!$C$18:$N$51,MATCH($A47,[4]DATA!$B$18:$B$51,0),MATCH(MID(CELL("filename",G14),FIND("]",CELL("filename",G14))+1,255) & BZ$1,[4]DATA!$C$15:$N$15&[4]DATA!$C$16:$N$16,0)) * 10^6} -> 18091000000 | CA47: =$BX47*BY47/SUM($BY47:$BZ47) -> 2.0909257e+10 | CB47: =BX47-CA47 -> 1.8091223e+10 | CC47: {=INDEX([1]Sheet1!$C$6:$CY$72,MATCH($A47,[1]Sheet1!$A$6:$A$72,0),MATCH(MID(CELL("filename",J46),FIND("]",CELL("filename",J46))+1,255) & CC$1,[1]Sheet1!$C$1:$CY$1 & [1]Sheet1!$C$3:$CY$3,0))} -> 2177440000 | CD47: =BP47-BQ47-BW47-BX47-CC47 -> 1.886793e+10 | CE47: {=INDEX([1]Sheet1!$C$6:$CY$72,MATCH($A47,[1]Sheet1!$A$6:$A$72,0),MATCH(MID(CELL("filename",L46),FIND("]",CELL("filename",L46))+1,255) & CE$1,[1]Sheet1!$C$1:$CY$1 & [1]Sheet1!$C$3:$CY$3,0))} -> 140313100000 | CF47: =CE47-CK47 -> 131325020000 | CG47: {=INDEX([1]Sheet1!$C$6:$CY$72,MATCH($A47,[1]Sheet1!$A$6:$A$72,0),MATCH(MID(CELL("filename",N46),FIND("]",CELL("filename",N46))+1,255) & CG$1,[1]Sheet1!$C$1:$CY$1 & [1]Sheet1!$C$3:$CY$3,0))} -> 53606100000 | CH47: {=INDEX([1]Sheet1!$C$6:$CY$72,MATCH($A47,[1]Sheet1!$A$6:$A$72,0),MATCH(MID(CELL("filename",O46),FIND("]",CELL("filename",O46))+1,255) & CH$1,[1]Sheet1!$C$1:$CY$1 & [1]Sheet1!$C$3:$CY$3,0))} -> 8572860000 | CI47: {=INDEX([1]Sheet1!$C$6:$CY$72,MATCH($A47,[1]Sheet1!$A$6:$A$72,0),MATCH(MID(CELL("filename",P46),FIND("]",CELL("filename",P46))+1,255) & CI$1,[1]Sheet1!$C$1:$CY$1 & [1]Sheet1!$C$3:$CY$3,0))} -> 4.15037e+09 | CJ47: {=INDEX([1]Sheet1!$C$6:$CY$72,MATCH($A47,[1]Sheet1!$A$6:$A$72,0),MATCH(MID(CELL("filename",R46),FIND("]",CELL("filename",R46))+1,255) & CJ$1,[1]Sheet1!$C$1:$CY$1 & [1]Sheet1!$C$3:$CY$3,0))} -> 49243600000 | CK47: {=INDEX([1]Sheet1!$C$6:$CY$72,MATCH($A47,[1]Sheet1!$A$6:$A$72,0),MATCH(MID(CELL("filename",S46),FIND("]",CELL("filename",S46))+1,255) & CK$1,[1]Sheet1!$C$1:$CY$1 & [1]Sheet1!$C$3:$CY$3,0))} -> 8988080000 | CL47: =CF47-CG47-CH47-CI47-CJ47 -> 15752090000 | DK47: =DL47/100*BC47 -> 1.8572998e+11 | DL47: {=INDEX([1]Sheet1!$C$6:$CY$72,MATCH($A47,[1]Sheet1!$A$6:$A$72,0),MATCH(MID(CELL("filename",AT46),FIND("]",CELL("filename",AT46))+1,255) & DL$1,[1]Sheet1!$C$1:$CY$1 & [1]Sheet1!$C$3:$CY$3,0))} -> 65.8131 | DM47: {=INDEX([5]DATA!$C$18:$T$51,MATCH($A47,[5]DATA!$B$18:$B$51,0),MATCH(MID(CELL("filename",AU14),FIND("]",CELL("filename",AU14))+1,255) & DM$1,[5]DATA!$C$15:$T$15&[5]DATA!$C$16:$T$16,0)) * 10^6} -> 6646000000 | DN47: {=INDEX([5]DATA!$C$18:$T$51,MATCH($A47,[5]DATA!$B$18:$B$51,0),MATCH(MID(CELL("filename",AV14),FIND("]",CELL("filename",AV14))+1,255) & DN$1,[5]DATA!$C$15:$T$15&[5]DATA!$C$16:$T$16,0)) * 10^6} -> 179084000000 | DQ47: 1.370478 | DR47: {=INDEX([1]Sheet1!$C$6:$CY$72,MATCH($A47,[1]Sheet1!$A$6:$A$72,0),MATCH(MID(CELL("filename",AZ46),FIND("]",CELL("filename",AZ46))+1,255) & DR$1,[1]Sheet1!$C$1:$CY$1 & [1]Sheet1!$C$3:$CY$3,0))} -> 560000000 | DS47: {=INDEX([1]Sheet1!$C$6:$CY$72,MATCH($A47,[1]Sheet1!$A$6:$A$72,0),MATCH(MID(CELL("filename",BA46),FIND("]",CELL("filename",BA46))+1,255) & DS$1,[1]Sheet1!$C$1:$CY$1 & [1]Sheet1!$C$3:$CY$3,0))} -> 4.957453 | DT47: {=INDEX([5]DATA!$C$18:$T$51,MATCH($A47,[5]DATA!$B$18:$B$51,0),MATCH(MID(CELL("filename",BB14),FIND("]",CELL("filename",BB14))+1,255) & DT$1,[5]DATA!$C$15:$T$15&[5]DATA!$C$16:$T$16,0)) * 10^6} -> 10395000000 | DU47: {=INDEX([1]Sheet1!$C$6:$CY$72,MATCH($A47,[1]Sheet1!$A$6:$A$72,0),MATCH(MID(CELL("filename",BC46),FIND("]",CELL("filename",BC46))+1,255) & DU$1,[1]Sheet1!$C$1:$CY$1 & [1]Sheet1!$C$3:$CY$3,0))} -> 4.28 | DV47: 0.5 | DW47: =Euro_Area_Data!V44*10^9 -> 1.1185188e+13 | DX47: 1 | DY47: 0.5 | DZ47: {=INDEX([1]Sheet1!$C$6:$CY$72,MATCH($A47,[1]Sheet1!$A$6:$A$72,0),MATCH(MID(CELL("filename",BH46),FIND("]",CELL("filename",BH46))+1,255) & DZ$1,[1]Sheet1!$C$1:$CY$1 & [1]Sheet1!$C$3:$CY$3,0))} -> 4.3 | EA47: 2 | EB47: =SUMPRODUCT(Euro_Area_Data!C44:U44,Euro_Area_Data!Z44:AR44)/SUM(Euro_Area_Data!C44:U44) -> 0.84932642 | EC47: =(EB47-EB46)/EB46*100 -> 2.4755132 | ED47: =SUMPRODUCT(Euro_Area_Data!C44:U44,Euro_Area_Data!AW44:BO44)/SUM(Euro_Area_Data!C44:U44) -> 2.769167 | EE47: -5 | EH47: 0.75 | EI47: 0.05 | EJ47: 60 | EK47: =(EN47-EN46)/EN46*100 -> 2.2592731 | EN47: =[2]EUCAM_output!$AE44 -> 0.79504936
A48: 2008 | B48: =[2]EUCAM_output!$E45*10^9 -> 3.5285816e+11 | H48: =[2]EUCAM_output!$AK45 -> -0.0024193751 | I48: =[2]EUCAM_output!$W45*10^3 -> 6390972 | K48: =IF(A48<2030,I48,K47*J48/J47) -> 6390972 | L48: =[2]EUCAM_output!$G45 -> 66.93297 | O48: =[2]EUCAM_output!$H45 -> 66.747302 | R48: =[2]EUCAM_output!$L45 -> 4.4 | U48: =[2]EUCAM_output!$K45 -> 5.052949 | V48: 5.052949 | W48: -0.0043685868 | X48: 0.0024891241 | Y48: =[2]EUCAM_output!$AI45 -> 0.00685907 | Z48: =[2]EUCAM_output!$M45 -> 1716.147 | AC48: =[2]EUCAM_output!$AL45 -> 1703.758 | AD48: =[2]EUCAM_output!$T45*10^9 -> 1.1015066e+12 | AE48: {=INDEX('[3]Sheet 1'!$B$12:$M$61,MATCH($A48,'[3]Sheet 1'!$A$12:$A$61,0),MATCH(MID(CELL("filename",A47),FIND("]",CELL("filename",A47))+1,255)&AE$1,'[3]Sheet 1'!$B$9:$M$9&'[3]Sheet 1'!$B$8:$M$8,0))*10^6} -> 965235800000 | AF48: {=INDEX('[3]Sheet 1'!$B$12:$M$61,MATCH($A48,'[3]Sheet 1'!$A$12:$A$61,0),MATCH(MID(CELL("filename",B47),FIND("]",CELL("filename",B47))+1,255)&AF$1,'[3]Sheet 1'!$B$9:$M$9&'[3]Sheet 1'!$B$8:$M$8,0))*10^6} -> 1.342338e+11 | AG48: =AF48/AE48 -> 0.1390684 | AH48: =AD48*AG48 -> 1.5318476e+11 | AI48: =CH48/EN48 -> 1.1918046e+10 | AJ48: 8.01029e+09 | AK48: =AJ48/EN48 -> 9.8840737e+09 | AL48: =AK48/AH48 -> 0.064523872 | AM48: =AVERAGE($AL$35:$AL$63) -> 0.065166448 | AN48: =AD48-AH48 -> 9.483218e+11 | AO48: 59023800000 | AP48: =AO48/EN48 -> 7.283077e+10 | AQ48: 46749000000 | AR48: =(AQ48-AJ48)/EN48 -> 4.780055e+10 | AS48: =AR48/AN48 -> 0.05040541 | AT48: =AP48/B48*100 -> 20.64024 | BB48: 3.6011547e+11 | BC48: =[2]EUCAM_output!$AG45*10^9 -> 291846200000 | BD48: =(BB48-B48)/B48*100 -> 2.056721 | BN48: =BP48-CF48 -> 4097000000 | BO48: {=INDEX([1]Sheet1!$C$6:$CY$72,MATCH($A48,[1]Sheet1!$A$6:$A$72,0),MATCH(MID(CELL("filename",A47),FIND("]",CELL("filename",A47))+1,255) & BO$1,[1]Sheet1!$C$1:$CY$1 & [1]Sheet1!$C$3:$CY$3,0))} -> 1.403801 | BP48: {=INDEX([1]Sheet1!$C$6:$CY$72,MATCH($A48,[1]Sheet1!$A$6:$A$72,0),MATCH(MID(CELL("filename",B47),FIND("]",CELL("filename",B47))+1,255) & BP$1,[1]Sheet1!$C$1:$CY$1 & [1]Sheet1!$C$3:$CY$3,0))} -> 142516600000 | BQ48: {=INDEX([1]Sheet1!$C$6:$CY$72,MATCH($A48,[1]Sheet1!$A$6:$A$72,0),MATCH(MID(CELL("filename",C47),FIND("]",CELL("filename",C47))+1,255) & BQ$1,[1]Sheet1!$C$1:$CY$1 & [1]Sheet1!$C$3:$CY$3,0))} -> 40284800000 | BR48: {=INDEX([6]Annual!$C$5:$T$30,MATCH($A48,[6]Annual!$B$5:$B$30,0),MATCH(MID(CELL("filename",$F$2),FIND("]",CELL("filename",$F$2))+1,255) & BR$1,[6]Annual!$C$3:$T$3 & [6]Annual!$C$4:$T$4,0))} -> 32858600000 | BS48: {=INDEX([6]Annual!$C$5:$T$30,MATCH($A48,[6]Annual!$B$5:$B$30,0),MATCH(MID(CELL("filename",$F$2),FIND("]",CELL("filename",$F$2))+1,255) & BS$1,[6]Annual!$C$3:$T$3 & [6]Annual!$C$4:$T$4,0))} -> 6503900000 | BT48: {=INDEX([6]Annual!$C$5:$T$30,MATCH($A48,[6]Annual!$B$5:$B$30,0),MATCH(MID(CELL("filename",$F$2),FIND("]",CELL("filename",$F$2))+1,255) & BT$1,[6]Annual!$C$3:$T$3 & [6]Annual!$C$4:$T$4,0))} -> 9.602e+08 | BU48: =BQ48*BR48/SUM($BR48:$BT48) -> 3.2827716e+10 | BV48: =BQ48-BU48 -> 7.4570844e+09 | BW48: {=INDEX([1]Sheet1!$C$6:$CY$72,MATCH($A48,[1]Sheet1!$A$6:$A$72,0),MATCH(MID(CELL("filename",F47),FIND("]",CELL("filename",F47))+1,255) & BW$1,[1]Sheet1!$C$1:$CY$1 & [1]Sheet1!$C$3:$CY$3,0))} -> 40717240000 | BX48: {=INDEX([1]Sheet1!$C$6:$CY$72,MATCH($A48,[1]Sheet1!$A$6:$A$72,0),MATCH(MID(CELL("filename",G47),FIND("]",CELL("filename",G47))+1,255) & BX$1,[1]Sheet1!$C$1:$CY$1 & [1]Sheet1!$C$3:$CY$3,0))} -> 40756800000 | BY48: {=INDEX([4]DATA!$C$18:$N$51,MATCH($A48,[4]DATA!$B$18:$B$51,0),MATCH(MID(CELL("filename",F15),FIND("]",CELL("filename",F15))+1,255) & BY$1,[4]DATA!$C$15:$N$15&[4]DATA!$C$16:$N$16,0)) * 10^6} -> 21902000000 | BZ48: {=INDEX([4]DATA!$C$18:$N$51,MATCH($A48,[4]DATA!$B$18:$B$51,0),MATCH(MID(CELL("filename",G15),FIND("]",CELL("filename",G15))+1,255) & BZ$1,[4]DATA!$C$15:$N$15&[4]DATA!$C$16:$N$16,0)) * 10^6} -> 18855000000 | CA48: =$BX48*BY48/SUM($BY48:$BZ48) -> 2.1901893e+10 | CB48: =BX48-CA48 -> 1.8854907e+10 | CC48: {=INDEX([1]Sheet1!$C$6:$CY$72,MATCH($A48,[1]Sheet1!$A$6:$A$72,0),MATCH(MID(CELL("filename",J47),FIND("]",CELL("filename",J47))+1,255) & CC$1,[1]Sheet1!$C$1:$CY$1 & [1]Sheet1!$C$3:$CY$3,0))} -> 2160130000 | CD48: =BP48-BQ48-BW48-BX48-CC48 -> 18597630000 | CE48: {=INDEX([1]Sheet1!$C$6:$CY$72,MATCH($A48,[1]Sheet1!$A$6:$A$72,0),MATCH(MID(CELL("filename",L47),FIND("]",CELL("filename",L47))+1,255) & CE$1,[1]Sheet1!$C$1:$CY$1 & [1]Sheet1!$C$3:$CY$3,0))} -> 147103100000 | CF48: =CE48-CK48 -> 138419600000 | CG48: {=INDEX([1]Sheet1!$C$6:$CY$72,MATCH($A48,[1]Sheet1!$A$6:$A$72,0),MATCH(MID(CELL("filename",N47),FIND("]",CELL("filename",N47))+1,255) & CG$1,[1]Sheet1!$C$1:$CY$1 & [1]Sheet1!$C$3:$CY$3,0))} -> 57057300000 | CH48: {=INDEX([1]Sheet1!$C$6:$CY$72,MATCH($A48,[1]Sheet1!$A$6:$A$72,0),MATCH(MID(CELL("filename",O47),FIND("]",CELL("filename",O47))+1,255) & CH$1,[1]Sheet1!$C$1:$CY$1 & [1]Sheet1!$C$3:$CY$3,0))} -> 9658670000 | CI48: {=INDEX([1]Sheet1!$C$6:$CY$72,MATCH($A48,[1]Sheet1!$A$6:$A$72,0),MATCH(MID(CELL("filename",P47),FIND("]",CELL("filename",P47))+1,255) & CI$1,[1]Sheet1!$C$1:$CY$1 & [1]Sheet1!$C$3:$CY$3,0))} -> 4445710000 | CJ48: {=INDEX([1]Sheet1!$C$6:$CY$72,MATCH($A48,[1]Sheet1!$A$6:$A$72,0),MATCH(MID(CELL("filename",R47),FIND("]",CELL("filename",R47))+1,255) & CJ$1,[1]Sheet1!$C$1:$CY$1 & [1]Sheet1!$C$3:$CY$3,0))} -> 51510400000 | CK48: {=INDEX([1]Sheet1!$C$6:$CY$72,MATCH($A48,[1]Sheet1!$A$6:$A$72,0),MATCH(MID(CELL("filename",S47),FIND("]",CELL("filename",S47))+1,255) & CK$1,[1]Sheet1!$C$1:$CY$1 & [1]Sheet1!$C$3:$CY$3,0))} -> 8683500000 | CL48: =CF48-CG48-CH48-CI48-CJ48 -> 15747520000 | DK48: =DL48/100*BC48 -> 202914825936 | DL48: {=INDEX([1]Sheet1!$C$6:$CY$72,MATCH($A48,[1]Sheet1!$A$6:$A$72,0),MATCH(MID(CELL("filename",AT47),FIND("]",CELL("filename",AT47))+1,255) & DL$1,[1]Sheet1!$C$1:$CY$1 & [1]Sheet1!$C$3:$CY$3,0))} -> 69.528 | DM48: {=INDEX([5]DATA!$C$18:$T$51,MATCH($A48,[5]DATA!$B$18:$B$51,0),MATCH(MID(CELL("filename",AU15),FIND("]",CELL("filename",AU15))+1,255) & DM$1,[5]DATA!$C$15:$T$15&[5]DATA!$C$16:$T$16,0)) * 10^6} -> 12625000000 | DN48: {=INDEX([5]DATA!$C$18:$T$51,MATCH($A48,[5]DATA!$B$18:$B$51,0),MATCH(MID(CELL("filename",AV15),FIND("]",CELL("filename",AV15))+1,255) & DN$1,[5]DATA!$C$15:$T$15&[5]DATA!$C$16:$T$16,0)) * 10^6} -> 190290000000 | DQ48: 1.470755 | DR48: {=INDEX([1]Sheet1!$C$6:$CY$72,MATCH($A48,[1]Sheet1!$A$6:$A$72,0),MATCH(MID(CELL("filename",AZ47),FIND("]",CELL("filename",AZ47))+1,255) & DR$1,[1]Sheet1!$C$1:$CY$1 & [1]Sheet1!$C$3:$CY$3,0))} -> 12600000000 | DS48: {=INDEX([1]Sheet1!$C$6:$CY$72,MATCH($A48,[1]Sheet1!$A$6:$A$72,0),MATCH(MID(CELL("filename",BA47),FIND("]",CELL("filename",BA47))+1,255) & DS$1,[1]Sheet1!$C$1:$CY$1 & [1]Sheet1!$C$3:$CY$3,0))} -> 4.675335 | DT48: {=INDEX([5]DATA!$C$18:$T$51,MATCH($A48,[5]DATA!$B$18:$B$51,0),MATCH(MID(CELL("filename",BB15),FIND("]",CELL("filename",BB15))+1,255) & DT$1,[5]DATA!$C$15:$T$15&[5]DATA!$C$16:$T$16,0)) * 10^6} -> 25929000000 | DU48: {=INDEX([1]Sheet1!$C$6:$CY$72,MATCH($A48,[1]Sheet1!$A$6:$A$72,0),MATCH(MID(CELL("filename",BC47),FIND("]",CELL("filename",BC47))+1,255) & DU$1,[1]Sheet1!$C$1:$CY$1 & [1]Sheet1!$C$3:$CY$3,0))} -> 4.63 | DV48: 0.5 | DW48: =Euro_Area_Data!V45*10^9 -> 1.1232956e+13 | DX48: 1 | DY48: 0.5 | DZ48: {=INDEX([1]Sheet1!$C$6:$CY$72,MATCH($A48,[1]Sheet1!$A$6:$A$72,0),MATCH(MID(CELL("filename",BH47),FIND("]",CELL("filename",BH47))+1,255) & DZ$1,[1]Sheet1!$C$1:$CY$1 & [1]Sheet1!$C$3:$CY$3,0))} -> 4.36 | EA48: 2 | EB48: =SUMPRODUCT(Euro_Area_Data!C45:U45,Euro_Area_Data!Z45:AR45)/SUM(Euro_Area_Data!C45:U45) -> 0.86716332 | EC48: =(EB48-EB47)/EB47*100 -> 2.1001225 | ED48: =SUMPRODUCT(Euro_Area_Data!C45:U45,Euro_Area_Data!AW45:BO45)/SUM(Euro_Area_Data!C45:U45) -> 1.6472344 | EE48: -5 | EH48: 0.75 | EI48: 0.05 | EJ48: 60 | EK48: =(EN48-EN47)/EN47*100 -> 1.9337898 | EN48: =[2]EUCAM_output!$AE45 -> 0.81042394
A49: 2009 | B49: =[2]EUCAM_output!$E46*10^9 -> 3.5625576e+11 | H49: =[2]EUCAM_output!$AK46 -> -0.081001013 | I49: =[2]EUCAM_output!$W46*10^3 -> 6423371.5 | K49: =IF(A49<2030,I49,K48*J49/J48) -> 6423371.5 | L49: =[2]EUCAM_output!$G46 -> 67.150888 | O49: =[2]EUCAM_output!$H46 -> 67.027578 | R49: =[2]EUCAM_output!$L46 -> 5.7 | U49: =[2]EUCAM_output!$K46 -> 5.116061 | V49: 5.116061 | W49: -0.030657348 | X49: -0.01166711 | Y49: =[2]EUCAM_output!$AI46 -> -0.02414553 | Z49: =[2]EUCAM_output!$M46 -> 1669.5377 | AC49: =[2]EUCAM_output!$AL46 -> 1686.7568 | AD49: =[2]EUCAM_output!$T46*10^9 -> 1.1154367e+12 | AE49: {=INDEX('[3]Sheet 1'!$B$12:$M$61,MATCH($A49,'[3]Sheet 1'!$A$12:$A$61,0),MATCH(MID(CELL("filename",A48),FIND("]",CELL("filename",A48))+1,255)&AE$1,'[3]Sheet 1'!$B$9:$M$9&'[3]Sheet 1'!$B$8:$M$8,0))*10^6} -> 998938000000 | AF49: {=INDEX('[3]Sheet 1'!$B$12:$M$61,MATCH($A49,'[3]Sheet 1'!$A$12:$A$61,0),MATCH(MID(CELL("filename",B48),FIND("]",CELL("filename",B48))+1,255)&AF$1,'[3]Sheet 1'!$B$9:$M$9&'[3]Sheet 1'!$B$8:$M$8,0))*10^6} -> 139264000000 | AG49: =AF49/AE49 -> 0.13941206 | AH49: =AD49*AG49 -> 1.5550533e+11 | AI49: =CH49/EN49 -> 1.1893362e+10 | AJ49: 8323350000 | AK49: =AJ49/EN49 -> 1.0094777e+10 | AL49: =AK49/AH49 -> 0.064915958 | AM49: =AVERAGE($AL$35:$AL$63) -> 0.065166448 | AN49: =AD49-AH49 -> 9.5993142e+11 | AO49: 55074000000 | AP49: =AO49/EN49 -> 6.6795193e+10 | AQ49: 49031300000 | AR49: =(AQ49-AJ49)/EN49 -> 4.9371671e+10 | AS49: =AR49/AN49 -> 0.051432498 | AT49: =AP49/B49*100 -> 18.749225 | BB49: 3.4720078e+11 | BC49: =[2]EUCAM_output!$AG46*10^9 -> 286274130000 | BD49: =(BB49-B49)/B49*100 -> -2.5417065 | BN49: =BP49-CF49 -> -6214010000 | BO49: {=INDEX([1]Sheet1!$C$6:$CY$72,MATCH($A49,[1]Sheet1!$A$6:$A$72,0),MATCH(MID(CELL("filename",A48),FIND("]",CELL("filename",A48))+1,255) & BO$1,[1]Sheet1!$C$1:$CY$1 & [1]Sheet1!$C$3:$CY$3,0))} -> -2.170654 | BP49: {=INDEX([1]Sheet1!$C$6:$CY$72,MATCH($A49,[1]Sheet1!$A$6:$A$72,0),MATCH(MID(CELL("filename",B48),FIND("]",CELL("filename",B48))+1,255) & BP$1,[1]Sheet1!$C$1:$CY$1 & [1]Sheet1!$C$3:$CY$3,0))} -> 140893900000 | BQ49: {=INDEX([1]Sheet1!$C$6:$CY$72,MATCH($A49,[1]Sheet1!$A$6:$A$72,0),MATCH(MID(CELL("filename",C48),FIND("]",CELL("filename",C48))+1,255) & BQ$1,[1]Sheet1!$C$1:$CY$1 & [1]Sheet1!$C$3:$CY$3,0))} -> 35916860000 | BR49: {=INDEX([6]Annual!$C$5:$T$30,MATCH($A49,[6]Annual!$B$5:$B$30,0),MATCH(MID(CELL("filename",$F$2),FIND("]",CELL("filename",$F$2))+1,255) & BR$1,[6]Annual!$C$3:$T$3 & [6]Annual!$C$4:$T$4,0))} -> 30839000000 | BS49: {=INDEX([6]Annual!$C$5:$T$30,MATCH($A49,[6]Annual!$B$5:$B$30,0),MATCH(MID(CELL("filename",$F$2),FIND("]",CELL("filename",$F$2))+1,255) & BS$1,[6]Annual!$C$3:$T$3 & [6]Annual!$C$4:$T$4,0))} -> 4392100000 | BT49: {=INDEX([6]Annual!$C$5:$T$30,MATCH($A49,[6]Annual!$B$5:$B$30,0),MATCH(MID(CELL("filename",$F$2),FIND("]",CELL("filename",$F$2))+1,255) & BT$1,[6]Annual!$C$3:$T$3 & [6]Annual!$C$4:$T$4,0))} -> 694100000 | BU49: =BQ49*BR49/SUM($BR49:$BT49) -> 3.0831841e+10 | BV49: =BQ49-BU49 -> 5.0850192e+09 | BW49: {=INDEX([1]Sheet1!$C$6:$CY$72,MATCH($A49,[1]Sheet1!$A$6:$A$72,0),MATCH(MID(CELL("filename",F48),FIND("]",CELL("filename",F48))+1,255) & BW$1,[1]Sheet1!$C$1:$CY$1 & [1]Sheet1!$C$3:$CY$3,0))} -> 41196770000 | BX49: {=INDEX([1]Sheet1!$C$6:$CY$72,MATCH($A49,[1]Sheet1!$A$6:$A$72,0),MATCH(MID(CELL("filename",G48),FIND("]",CELL("filename",G48))+1,255) & BX$1,[1]Sheet1!$C$1:$CY$1 & [1]Sheet1!$C$3:$CY$3,0))} -> 41266430000 | BY49: {=INDEX([4]DATA!$C$18:$N$51,MATCH($A49,[4]DATA!$B$18:$B$51,0),MATCH(MID(CELL("filename",F16),FIND("]",CELL("filename",F16))+1,255) & BY$1,[4]DATA!$C$15:$N$15&[4]DATA!$C$16:$N$16,0)) * 10^6} -> 22319000000 | BZ49: {=INDEX([4]DATA!$C$18:$N$51,MATCH($A49,[4]DATA!$B$18:$B$51,0),MATCH(MID(CELL("filename",G16),FIND("]",CELL("filename",G16))+1,255) & BZ$1,[4]DATA!$C$15:$N$15&[4]DATA!$C$16:$N$16,0)) * 10^6} -> 18947000000 | CA49: =$BX49*BY49/SUM($BY49:$BZ49) -> 2.2319233e+10 | CB49: =BX49-CA49 -> 1.8947197e+10 | CC49: {=INDEX([1]Sheet1!$C$6:$CY$72,MATCH($A49,[1]Sheet1!$A$6:$A$72,0),MATCH(MID(CELL("filename",J48),FIND("]",CELL("filename",J48))+1,255) & CC$1,[1]Sheet1!$C$1:$CY$1 & [1]Sheet1!$C$3:$CY$3,0))} -> 2129400000 | CD49: =BP49-BQ49-BW49-BX49-CC49 -> 20384440000 | CE49: {=INDEX([1]Sheet1!$C$6:$CY$72,MATCH($A49,[1]Sheet1!$A$6:$A$72,0),MATCH(MID(CELL("filename",L48),FIND("]",CELL("filename",L48))+1,255) & CE$1,[1]Sheet1!$C$1:$CY$1 & [1]Sheet1!$C$3:$CY$3,0))} -> 156298200000 | CF49: =CE49-CK49 -> 147107910000 | CG49: {=INDEX([1]Sheet1!$C$6:$CY$72,MATCH($A49,[1]Sheet1!$A$6:$A$72,0),MATCH(MID(CELL("filename",N48),FIND("]",CELL("filename",N48))+1,255) & CG$1,[1]Sheet1!$C$1:$CY$1 & [1]Sheet1!$C$3:$CY$3,0))} -> 59668000000 | CH49: {=INDEX([1]Sheet1!$C$6:$CY$72,MATCH($A49,[1]Sheet1!$A$6:$A$72,0),MATCH(MID(CELL("filename",O48),FIND("]",CELL("filename",O48))+1,255) & CH$1,[1]Sheet1!$C$1:$CY$1 & [1]Sheet1!$C$3:$CY$3,0))} -> 9806320000 | CI49: {=INDEX([1]Sheet1!$C$6:$CY$72,MATCH($A49,[1]Sheet1!$A$6:$A$72,0),MATCH(MID(CELL("filename",P48),FIND("]",CELL("filename",P48))+1,255) & CI$1,[1]Sheet1!$C$1:$CY$1 & [1]Sheet1!$C$3:$CY$3,0))} -> 4466130000 | CJ49: {=INDEX([1]Sheet1!$C$6:$CY$72,MATCH($A49,[1]Sheet1!$A$6:$A$72,0),MATCH(MID(CELL("filename",R48),FIND("]",CELL("filename",R48))+1,255) & CJ$1,[1]Sheet1!$C$1:$CY$1 & [1]Sheet1!$C$3:$CY$3,0))} -> 54683800000 | CK49: {=INDEX([1]Sheet1!$C$6:$CY$72,MATCH($A49,[1]Sheet1!$A$6:$A$72,0),MATCH(MID(CELL("filename",S48),FIND("]",CELL("filename",S48))+1,255) & CK$1,[1]Sheet1!$C$1:$CY$1 & [1]Sheet1!$C$3:$CY$3,0))} -> 9190290000 | CL49: =CF49-CG49-CH49-CI49-CJ49 -> 18483660000 | DK49: =DL49/100*BC49 -> 2.3117266e+11 | DL49: {=INDEX([1]Sheet1!$C$6:$CY$72,MATCH($A49,[1]Sheet1!$A$6:$A$72,0),MATCH(MID(CELL("filename",AT48),FIND("]",CELL("filename",AT48))+1,255) & DL$1,[1]Sheet1!$C$1:$CY$1 & [1]Sheet1!$C$3:$CY$3,0))} -> 80.7522 | DM49: {=INDEX([5]DATA!$C$18:$T$51,MATCH($A49,[5]DATA!$B$18:$B$51,0),MATCH(MID(CELL("filename",AU16),FIND("]",CELL("filename",AU16))+1,255) & DM$1,[5]DATA!$C$15:$T$15&[5]DATA!$C$16:$T$16,0)) * 10^6} -> 12350000000 | DN49: {=INDEX([5]DATA!$C$18:$T$51,MATCH($A49,[5]DATA!$B$18:$B$51,0),MATCH(MID(CELL("filename",AV16),FIND("]",CELL("filename",AV16))+1,255) & DN$1,[5]DATA!$C$15:$T$15&[5]DATA!$C$16:$T$16,0)) * 10^6} -> 218822000000 | DQ49: 1.394782 | DR49: {=INDEX([1]Sheet1!$C$6:$CY$72,MATCH($A49,[1]Sheet1!$A$6:$A$72,0),MATCH(MID(CELL("filename",AZ48),FIND("]",CELL("filename",AZ48))+1,255) & DR$1,[1]Sheet1!$C$1:$CY$1 & [1]Sheet1!$C$3:$CY$3,0))} -> 12850000000 | DS49: {=INDEX([1]Sheet1!$C$6:$CY$72,MATCH($A49,[1]Sheet1!$A$6:$A$72,0),MATCH(MID(CELL("filename",BA48),FIND("]",CELL("filename",BA48))+1,255) & DS$1,[1]Sheet1!$C$1:$CY$1 & [1]Sheet1!$C$3:$CY$3,0))} -> 4.52914 | DT49: {=INDEX([5]DATA!$C$18:$T$51,MATCH($A49,[5]DATA!$B$18:$B$51,0),MATCH(MID(CELL("filename",BB16),FIND("]",CELL("filename",BB16))+1,255) & DT$1,[5]DATA!$C$15:$T$15&[5]DATA!$C$16:$T$16,0)) * 10^6} -> 20148000000 | DU49: {=INDEX([1]Sheet1!$C$6:$CY$72,MATCH($A49,[1]Sheet1!$A$6:$A$72,0),MATCH(MID(CELL("filename",BC48),FIND("]",CELL("filename",BC48))+1,255) & DU$1,[1]Sheet1!$C$1:$CY$1 & [1]Sheet1!$C$3:$CY$3,0))} -> 1.22 | DV49: 0.5 | DW49: =Euro_Area_Data!V46*10^9 -> 1.0728706e+13 | DX49: 1 | DY49: 0.5 | DZ49: {=INDEX([1]Sheet1!$C$6:$CY$72,MATCH($A49,[1]Sheet1!$A$6:$A$72,0),MATCH(MID(CELL("filename",BH48),FIND("]",CELL("filename",BH48))+1,255) & DZ$1,[1]Sheet1!$C$1:$CY$1 & [1]Sheet1!$C$3:$CY$3,0))} -> 3.94 | EA49: 2 | EB49: =SUMPRODUCT(Euro_Area_Data!C46:U46,Euro_Area_Data!Z46:AR46)/SUM(Euro_Area_Data!C46:U46) -> 0.87617213 | EC49: =(EB49-EB48)/EB48*100 -> 1.0388833 | ED49: =SUMPRODUCT(Euro_Area_Data!C46:U46,Euro_Area_Data!AW46:BO46)/SUM(Euro_Area_Data!C46:U46) -> -3.6561982 | EE49: -5 | EH49: 0.75 | EI49: 0.05 | EJ49: 60 | EK49: =(EN49-EN48)/EN48*100 -> 1.7393941 | EN49: =[2]EUCAM_output!$AE46 -> 0.82452041
A50: 2010 | B50: =[2]EUCAM_output!$E47*10^9 -> 3.5899699e+11 | H50: =[2]EUCAM_output!$AK47 -> -0.016137451 | I50: =[2]EUCAM_output!$W47*10^3 -> 6452508.5 | K50: =IF(A50<2030,I50,K49*J50/J49) -> 6452508.5 | L50: =[2]EUCAM_output!$G47 -> 66.997625 | O50: =[2]EUCAM_output!$H47 -> 67.29153 | R50: =[2]EUCAM_output!$L47 -> 5.2 | U50: =[2]EUCAM_output!$K47 -> 5.164527 | V50: 5.164527 | W50: 0.01045333 | X50: -0.0033060679 | Y50: =[2]EUCAM_output!$AI47 -> -0.0015592728 | Z50: =[2]EUCAM_output!$M47 -> 1662.8666 | AC50: =[2]EUCAM_output!$AL47 -> 1671.2814 | AD50: =[2]EUCAM_output!$T47*10^9 -> 1.126623e+12 | AE50: {=INDEX('[3]Sheet 1'!$B$12:$M$61,MATCH($A50,'[3]Sheet 1'!$A$12:$A$61,0),MATCH(MID(CELL("filename",A49),FIND("]",CELL("filename",A49))+1,255)&AE$1,'[3]Sheet 1'!$B$9:$M$9&'[3]Sheet 1'!$B$8:$M$8,0))*10^6} -> 1036044200000 | AF50: {=INDEX('[3]Sheet 1'!$B$12:$M$61,MATCH($A50,'[3]Sheet 1'!$A$12:$A$61,0),MATCH(MID(CELL("filename",B49),FIND("]",CELL("filename",B49))+1,255)&AF$1,'[3]Sheet 1'!$B$9:$M$9&'[3]Sheet 1'!$B$8:$M$8,0))*10^6} -> 144668900000 | AG50: =AF50/AE50 -> 0.13963584 | AH50: =AD50*AG50 -> 1.5731695e+11 | AI50: =CH50/EN50 -> 1.1629033e+10 | AJ50: 8664320000 | AK50: =AJ50/EN50 -> 1.0415478e+10 | AL50: =AK50/AH50 -> 0.066206963 | AM50: =AVERAGE($AL$35:$AL$63) -> 0.065166448 | AN50: =AD50-AH50 -> 9.6930608e+11 | AO50: 54609000000 | AP50: =AO50/EN50 -> 6.5646099e+10 | AQ50: 51708400000 | AR50: =(AQ50-AJ50)/EN50 -> 5.1743778e+10 | AS50: =AR50/AN50 -> 0.05338229 | AT50: =AP50/B50*100 -> 18.285975 | BB50: 3.5348158e+11 | BC50: =[2]EUCAM_output!$AG47*10^9 -> 294050610000 | BD50: =(BB50-B50)/B50*100 -> -1.536339 | BN50: =BP50-CF50 -> -4413300000 | BO50: {=INDEX([1]Sheet1!$C$6:$CY$72,MATCH($A50,[1]Sheet1!$A$6:$A$72,0),MATCH(MID(CELL("filename",A49),FIND("]",CELL("filename",A49))+1,255) & BO$1,[1]Sheet1!$C$1:$CY$1 & [1]Sheet1!$C$3:$CY$3,0))} -> -1.500881 | BP50: {=INDEX([1]Sheet1!$C$6:$CY$72,MATCH($A50,[1]Sheet1!$A$6:$A$72,0),MATCH(MID(CELL("filename",B49),FIND("]",CELL("filename",B49))+1,255) & BP$1,[1]Sheet1!$C$1:$CY$1 & [1]Sheet1!$C$3:$CY$3,0))} -> 143769100000 | BQ50: {=INDEX([1]Sheet1!$C$6:$CY$72,MATCH($A50,[1]Sheet1!$A$6:$A$72,0),MATCH(MID(CELL("filename",C49),FIND("]",CELL("filename",C49))+1,255) & BQ$1,[1]Sheet1!$C$1:$CY$1 & [1]Sheet1!$C$3:$CY$3,0))} -> 37145150000 | BR50: {=INDEX([6]Annual!$C$5:$T$30,MATCH($A50,[6]Annual!$B$5:$B$30,0),MATCH(MID(CELL("filename",$F$2),FIND("]",CELL("filename",$F$2))+1,255) & BR$1,[6]Annual!$C$3:$T$3 & [6]Annual!$C$4:$T$4,0))} -> 3.13477e+10 | BS50: {=INDEX([6]Annual!$C$5:$T$30,MATCH($A50,[6]Annual!$B$5:$B$30,0),MATCH(MID(CELL("filename",$F$2),FIND("]",CELL("filename",$F$2))+1,255) & BS$1,[6]Annual!$C$3:$T$3 & [6]Annual!$C$4:$T$4,0))} -> 4963400000 | BT50: {=INDEX([6]Annual!$C$5:$T$30,MATCH($A50,[6]Annual!$B$5:$B$30,0),MATCH(MID(CELL("filename",$F$2),FIND("]",CELL("filename",$F$2))+1,255) & BT$1,[6]Annual!$C$3:$T$3 & [6]Annual!$C$4:$T$4,0))} -> 8.084e+08 | BU50: =BQ50*BR50/SUM($BR50:$BT50) -> 3.1369362e+10 | BV50: =BQ50-BU50 -> 5.7757884e+09 | BW50: {=INDEX([1]Sheet1!$C$6:$CY$72,MATCH($A50,[1]Sheet1!$A$6:$A$72,0),MATCH(MID(CELL("filename",F49),FIND("]",CELL("filename",F49))+1,255) & BW$1,[1]Sheet1!$C$1:$CY$1 & [1]Sheet1!$C$3:$CY$3,0))} -> 42474330000 | BX50: {=INDEX([1]Sheet1!$C$6:$CY$72,MATCH($A50,[1]Sheet1!$A$6:$A$72,0),MATCH(MID(CELL("filename",G49),FIND("]",CELL("filename",G49))+1,255) & BX$1,[1]Sheet1!$C$1:$CY$1 & [1]Sheet1!$C$3:$CY$3,0))} -> 42102460000 | BY50: {=INDEX([4]DATA!$C$18:$N$51,MATCH($A50,[4]DATA!$B$18:$B$51,0),MATCH(MID(CELL("filename",F17),FIND("]",CELL("filename",F17))+1,255) & BY$1,[4]DATA!$C$15:$N$15&[4]DATA!$C$16:$N$16,0)) * 10^6} -> 22681000000 | BZ50: {=INDEX([4]DATA!$C$18:$N$51,MATCH($A50,[4]DATA!$B$18:$B$51,0),MATCH(MID(CELL("filename",G17),FIND("]",CELL("filename",G17))+1,255) & BZ$1,[4]DATA!$C$15:$N$15&[4]DATA!$C$16:$N$16,0)) * 10^6} -> 19421000000 | CA50: =$BX50*BY50/SUM($BY50:$BZ50) -> 2.2681248e+10 | CB50: =BX50-CA50 -> 1.9421212e+10 | CC50: {=INDEX([1]Sheet1!$C$6:$CY$72,MATCH($A50,[1]Sheet1!$A$6:$A$72,0),MATCH(MID(CELL("filename",J49),FIND("]",CELL("filename",J49))+1,255) & CC$1,[1]Sheet1!$C$1:$CY$1 & [1]Sheet1!$C$3:$CY$3,0))} -> 2106360000 | CD50: =BP50-BQ50-BW50-BX50-CC50 -> 19940800000 | CE50: {=INDEX([1]Sheet1!$C$6:$CY$72,MATCH($A50,[1]Sheet1!$A$6:$A$72,0),MATCH(MID(CELL("filename",L49),FIND("]",CELL("filename",L49))+1,255) & CE$1,[1]Sheet1!$C$1:$CY$1 & [1]Sheet1!$C$3:$CY$3,0))} -> 156896500000 | CF50: =CE50-CK50 -> 148182400000 | CG50: {=INDEX([1]Sheet1!$C$6:$CY$72,MATCH($A50,[1]Sheet1!$A$6:$A$72,0),MATCH(MID(CELL("filename",N49),FIND("]",CELL("filename",N49))+1,255) & CG$1,[1]Sheet1!$C$1:$CY$1 & [1]Sheet1!$C$3:$CY$3,0))} -> 60872700000 | CH50: {=INDEX([1]Sheet1!$C$6:$CY$72,MATCH($A50,[1]Sheet1!$A$6:$A$72,0),MATCH(MID(CELL("filename",O49),FIND("]",CELL("filename",O49))+1,255) & CH$1,[1]Sheet1!$C$1:$CY$1 & [1]Sheet1!$C$3:$CY$3,0))} -> 9673840000 | CI50: {=INDEX([1]Sheet1!$C$6:$CY$72,MATCH($A50,[1]Sheet1!$A$6:$A$72,0),MATCH(MID(CELL("filename",P49),FIND("]",CELL("filename",P49))+1,255) & CI$1,[1]Sheet1!$C$1:$CY$1 & [1]Sheet1!$C$3:$CY$3,0))} -> 4360780000 | CJ50: {=INDEX([1]Sheet1!$C$6:$CY$72,MATCH($A50,[1]Sheet1!$A$6:$A$72,0),MATCH(MID(CELL("filename",R49),FIND("]",CELL("filename",R49))+1,255) & CJ$1,[1]Sheet1!$C$1:$CY$1 & [1]Sheet1!$C$3:$CY$3,0))} -> 56577500000 | CK50: {=INDEX([1]Sheet1!$C$6:$CY$72,MATCH($A50,[1]Sheet1!$A$6:$A$72,0),MATCH(MID(CELL("filename",S49),FIND("]",CELL("filename",S49))+1,255) & CK$1,[1]Sheet1!$C$1:$CY$1 & [1]Sheet1!$C$3:$CY$3,0))} -> 8714100000 | CL50: =CF50-CG50-CH50-CI50-CJ50 -> 16697580000 | DK50: =DL50/100*BC50 -> 2.4598539e+11 | DL50: {=INDEX([1]Sheet1!$C$6:$CY$72,MATCH($A50,[1]Sheet1!$A$6:$A$72,0),MATCH(MID(CELL("filename",AT49),FIND("]",CELL("filename",AT49))+1,255) & DL$1,[1]Sheet1!$C$1:$CY$1 & [1]Sheet1!$C$3:$CY$3,0))} -> 83.6541 | DM50: {=INDEX([5]DATA!$C$18:$T$51,MATCH($A50,[5]DATA!$B$18:$B$51,0),MATCH(MID(CELL("filename",AU17),FIND("]",CELL("filename",AU17))+1,255) & DM$1,[5]DATA!$C$15:$T$15&[5]DATA!$C$16:$T$16,0)) * 10^6} -> 12215000000 | DN50: {=INDEX([5]DATA!$C$18:$T$51,MATCH($A50,[5]DATA!$B$18:$B$51,0),MATCH(MID(CELL("filename",AV17),FIND("]",CELL("filename",AV17))+1,255) & DN$1,[5]DATA!$C$15:$T$15&[5]DATA!$C$16:$T$16,0)) * 10^6} -> 233770000000 | DQ50: 1.324353 | DR50: {=INDEX([1]Sheet1!$C$6:$CY$72,MATCH($A50,[1]Sheet1!$A$6:$A$72,0),MATCH(MID(CELL("filename",AZ49),FIND("]",CELL("filename",AZ49))+1,255) & DR$1,[1]Sheet1!$C$1:$CY$1 & [1]Sheet1!$C$3:$CY$3,0))} -> 1690000000 | DS50: {=INDEX([1]Sheet1!$C$6:$CY$72,MATCH($A50,[1]Sheet1!$A$6:$A$72,0),MATCH(MID(CELL("filename",BA49),FIND("]",CELL("filename",BA49))+1,255) & DS$1,[1]Sheet1!$C$1:$CY$1 & [1]Sheet1!$C$3:$CY$3,0))} -> 3.76952 | DT50: {=INDEX([5]DATA!$C$18:$T$51,MATCH($A50,[5]DATA!$B$18:$B$51,0),MATCH(MID(CELL("filename",BB17),FIND("]",CELL("filename",BB17))+1,255) & DT$1,[5]DATA!$C$15:$T$15&[5]DATA!$C$16:$T$16,0)) * 10^6} -> 17652000000 | DU50: {=INDEX([1]Sheet1!$C$6:$CY$72,MATCH($A50,[1]Sheet1!$A$6:$A$72,0),MATCH(MID(CELL("filename",BC49),FIND("]",CELL("filename",BC49))+1,255) & DU$1,[1]Sheet1!$C$1:$CY$1 & [1]Sheet1!$C$3:$CY$3,0))} -> 0.81 | DV50: 0.5 | DW50: =Euro_Area_Data!V47*10^9 -> 1.0958819e+13 | DX50: 1 | DY50: 0.5 | DZ50: {=INDEX([1]Sheet1!$C$6:$CY$72,MATCH($A50,[1]Sheet1!$A$6:$A$72,0),MATCH(MID(CELL("filename",BH49),FIND("]",CELL("filename",BH49))+1,255) & DZ$1,[1]Sheet1!$C$1:$CY$1 & [1]Sheet1!$C$3:$CY$3,0))} -> 3.23 | EA50: 2 | EB50: =SUMPRODUCT(Euro_Area_Data!C47:U47,Euro_Area_Data!Z47:AR47)/SUM(Euro_Area_Data!C47:U47) -> 0.88169303 | EC50: =(EB50-EB49)/EB49*100 -> 0.63011544 | ED50: =SUMPRODUCT(Euro_Area_Data!C47:U47,Euro_Area_Data!AW47:BO47)/SUM(Euro_Area_Data!C47:U47) -> -2.1954247 | EE50: -5 | EH50: 0.75 | EI50: 0.05 | EJ50: 60 | EK50: =(EN50-EN49)/EN49*100 -> 0.89133936 | EN50: =[2]EUCAM_output!$AE47 -> 0.83186968
A51: 2011 | B51: =[2]EUCAM_output!$E48*10^9 -> 3.6226325e+11 | H51: =[2]EUCAM_output!$AK48 -> -0.0017137637 | I51: =[2]EUCAM_output!$W48*10^3 -> 6486372 | K51: =IF(A51<2030,I51,K50*J51/J50) -> 6486372 | L51: =[2]EUCAM_output!$G48 -> 67.470587 | O51: =[2]EUCAM_output!$H48 -> 67.575901 | R51: =[2]EUCAM_output!$L48 -> 4.9 | U51: =[2]EUCAM_output!$K48 -> 5.230479 | V51: 5.230479 | W51: 0.013516337 | X51: 0.0092928395 | Y51: =[2]EUCAM_output!$AI48 -> 0.0104044 | Z51: =[2]EUCAM_output!$M48 -> 1669.0017 | AC51: =[2]EUCAM_output!$AL48 -> 1657.4447 | AD51: =[2]EUCAM_output!$T48*10^9 -> 1.1417296e+12 | AE51: {=INDEX('[3]Sheet 1'!$B$12:$M$61,MATCH($A51,'[3]Sheet 1'!$A$12:$A$61,0),MATCH(MID(CELL("filename",A50),FIND("]",CELL("filename",A50))+1,255)&AE$1,'[3]Sheet 1'!$B$9:$M$9&'[3]Sheet 1'!$B$8:$M$8,0))*10^6} -> 1.0808726e+12 | AF51: {=INDEX('[3]Sheet 1'!$B$12:$M$61,MATCH($A51,'[3]Sheet 1'!$A$12:$A$61,0),MATCH(MID(CELL("filename",B50),FIND("]",CELL("filename",B50))+1,255)&AF$1,'[3]Sheet 1'!$B$9:$M$9&'[3]Sheet 1'!$B$8:$M$8,0))*10^6} -> 149901900000 | AG51: =AF51/AE51 -> 0.138686 | AH51: =AD51*AG51 -> 1.5834192e+11 | AI51: =CH51/EN51 -> 1.1090245e+10 | AJ51: 8956110000 | AK51: =AJ51/EN51 -> 1.0573805e+10 | AL51: =AK51/AH51 -> 0.066778305 | AM51: =AVERAGE($AL$35:$AL$63) -> 0.065166448 | AN51: =AD51-AH51 -> 9.833877e+11 | AO51: 60583100000 | AP51: =AO51/EN51 -> 7.1525905e+10 | AQ51: 53391300000 | AR51: =(AQ51-AJ51)/EN51 -> 5.2461283e+10 | AS51: =AR51/AN51 -> 0.053347508 | AT51: =AP51/B51*100 -> 19.744179 | BB51: 3.6382964e+11 | BC51: =[2]EUCAM_output!$AG48*10^9 -> 308167050000 | BD51: =(BB51-B51)/B51*100 -> 0.43238855 | BN51: =BP51-CF51 -> 1113520000 | BO51: {=INDEX([1]Sheet1!$C$6:$CY$72,MATCH($A51,[1]Sheet1!$A$6:$A$72,0),MATCH(MID(CELL("filename",A50),FIND("]",CELL("filename",A50))+1,255) & BO$1,[1]Sheet1!$C$1:$CY$1 & [1]Sheet1!$C$3:$CY$3,0))} -> 0.36135 | BP51: {=INDEX([1]Sheet1!$C$6:$CY$72,MATCH($A51,[1]Sheet1!$A$6:$A$72,0),MATCH(MID(CELL("filename",B50),FIND("]",CELL("filename",B50))+1,255) & BP$1,[1]Sheet1!$C$1:$CY$1 & [1]Sheet1!$C$3:$CY$3,0))} -> 150567600000 | BQ51: {=INDEX([1]Sheet1!$C$6:$CY$72,MATCH($A51,[1]Sheet1!$A$6:$A$72,0),MATCH(MID(CELL("filename",C50),FIND("]",CELL("filename",C50))+1,255) & BQ$1,[1]Sheet1!$C$1:$CY$1 & [1]Sheet1!$C$3:$CY$3,0))} -> 39188980000 | BR51: {=INDEX([6]Annual!$C$5:$T$30,MATCH($A51,[6]Annual!$B$5:$B$30,0),MATCH(MID(CELL("filename",$F$2),FIND("]",CELL("filename",$F$2))+1,255) & BR$1,[6]Annual!$C$3:$T$3 & [6]Annual!$C$4:$T$4,0))} -> 32733900000 | BS51: {=INDEX([6]Annual!$C$5:$T$30,MATCH($A51,[6]Annual!$B$5:$B$30,0),MATCH(MID(CELL("filename",$F$2),FIND("]",CELL("filename",$F$2))+1,255) & BS$1,[6]Annual!$C$3:$T$3 & [6]Annual!$C$4:$T$4,0))} -> 5556100000 | BT51: {=INDEX([6]Annual!$C$5:$T$30,MATCH($A51,[6]Annual!$B$5:$B$30,0),MATCH(MID(CELL("filename",$F$2),FIND("]",CELL("filename",$F$2))+1,255) & BT$1,[6]Annual!$C$3:$T$3 & [6]Annual!$C$4:$T$4,0))} -> 890300000 | BU51: =BQ51*BR51/SUM($BR51:$BT51) -> 3.2741152e+10 | BV51: =BQ51-BU51 -> 6.4478281e+09 | BW51: {=INDEX([1]Sheet1!$C$6:$CY$72,MATCH($A51,[1]Sheet1!$A$6:$A$72,0),MATCH(MID(CELL("filename",F50),FIND("]",CELL("filename",F50))+1,255) & BW$1,[1]Sheet1!$C$1:$CY$1 & [1]Sheet1!$C$3:$CY$3,0))} -> 44690520000 | BX51: {=INDEX([1]Sheet1!$C$6:$CY$72,MATCH($A51,[1]Sheet1!$A$6:$A$72,0),MATCH(MID(CELL("filename",G50),FIND("]",CELL("filename",G50))+1,255) & BX$1,[1]Sheet1!$C$1:$CY$1 & [1]Sheet1!$C$3:$CY$3,0))} -> 44036640000 | BY51: {=INDEX([4]DATA!$C$18:$N$51,MATCH($A51,[4]DATA!$B$18:$B$51,0),MATCH(MID(CELL("filename",F18),FIND("]",CELL("filename",F18))+1,255) & BY$1,[4]DATA!$C$15:$N$15&[4]DATA!$C$16:$N$16,0)) * 10^6} -> 23735000000 | BZ51: {=INDEX([4]DATA!$C$18:$N$51,MATCH($A51,[4]DATA!$B$18:$B$51,0),MATCH(MID(CELL("filename",G18),FIND("]",CELL("filename",G18))+1,255) & BZ$1,[4]DATA!$C$15:$N$15&[4]DATA!$C$16:$N$16,0)) * 10^6} -> 20302000000 | CA51: =$BX51*BY51/SUM($BY51:$BZ51) -> 2.3734806e+10 | CB51: =BX51-CA51 -> 2.0301834e+10 | CC51: {=INDEX([1]Sheet1!$C$6:$CY$72,MATCH($A51,[1]Sheet1!$A$6:$A$72,0),MATCH(MID(CELL("filename",J50),FIND("]",CELL("filename",J50))+1,255) & CC$1,[1]Sheet1!$C$1:$CY$1 & [1]Sheet1!$C$3:$CY$3,0))} -> 2071100000 | CD51: =BP51-BQ51-BW51-BX51-CC51 -> 20580360000 | CE51: {=INDEX([1]Sheet1!$C$6:$CY$72,MATCH($A51,[1]Sheet1!$A$6:$A$72,0),MATCH(MID(CELL("filename",L50),FIND("]",CELL("filename",L50))+1,255) & CE$1,[1]Sheet1!$C$1:$CY$1 & [1]Sheet1!$C$3:$CY$3,0))} -> 158215200000 | CF51: =CE51-CK51 -> 149454080000 | CG51: {=INDEX([1]Sheet1!$C$6:$CY$72,MATCH($A51,[1]Sheet1!$A$6:$A$72,0),MATCH(MID(CELL("filename",N50),FIND("]",CELL("filename",N50))+1,255) & CG$1,[1]Sheet1!$C$1:$CY$1 & [1]Sheet1!$C$3:$CY$3,0))} -> 62022000000 | CH51: {=INDEX([1]Sheet1!$C$6:$CY$72,MATCH($A51,[1]Sheet1!$A$6:$A$72,0),MATCH(MID(CELL("filename",O50),FIND("]",CELL("filename",O50))+1,255) & CH$1,[1]Sheet1!$C$1:$CY$1 & [1]Sheet1!$C$3:$CY$3,0))} -> 9393540000 | CI51: {=INDEX([1]Sheet1!$C$6:$CY$72,MATCH($A51,[1]Sheet1!$A$6:$A$72,0),MATCH(MID(CELL("filename",P50),FIND("]",CELL("filename",P50))+1,255) & CI$1,[1]Sheet1!$C$1:$CY$1 & [1]Sheet1!$C$3:$CY$3,0))} -> 4294900000 | CJ51: {=INDEX([1]Sheet1!$C$6:$CY$72,MATCH($A51,[1]Sheet1!$A$6:$A$72,0),MATCH(MID(CELL("filename",R50),FIND("]",CELL("filename",R50))+1,255) & CJ$1,[1]Sheet1!$C$1:$CY$1 & [1]Sheet1!$C$3:$CY$3,0))} -> 57202600000 | CK51: {=INDEX([1]Sheet1!$C$6:$CY$72,MATCH($A51,[1]Sheet1!$A$6:$A$72,0),MATCH(MID(CELL("filename",S50),FIND("]",CELL("filename",S50))+1,255) & CK$1,[1]Sheet1!$C$1:$CY$1 & [1]Sheet1!$C$3:$CY$3,0))} -> 8761120000 | CL51: =CF51-CG51-CH51-CI51-CJ51 -> 16541040000 | DK51: =DL51/100*BC51 -> 2.5687603e+11 | DL51: {=INDEX([1]Sheet1!$C$6:$CY$72,MATCH($A51,[1]Sheet1!$A$6:$A$72,0),MATCH(MID(CELL("filename",AT50),FIND("]",CELL("filename",AT50))+1,255) & DL$1,[1]Sheet1!$C$1:$CY$1 & [1]Sheet1!$C$3:$CY$3,0))} -> 83.3561 | DM51: {=INDEX([5]DATA!$C$18:$T$51,MATCH($A51,[5]DATA!$B$18:$B$51,0),MATCH(MID(CELL("filename",AU18),FIND("]",CELL("filename",AU18))+1,255) & DM$1,[5]DATA!$C$15:$T$15&[5]DATA!$C$16:$T$16,0)) * 10^6} -> 10736000000 | DN51: {=INDEX([5]DATA!$C$18:$T$51,MATCH($A51,[5]DATA!$B$18:$B$51,0),MATCH(MID(CELL("filename",AV18),FIND("]",CELL("filename",AV18))+1,255) & DN$1,[5]DATA!$C$15:$T$15&[5]DATA!$C$16:$T$16,0)) * 10^6} -> 246140000000 | DQ51: 1.39119 | DR51: {=INDEX([1]Sheet1!$C$6:$CY$72,MATCH($A51,[1]Sheet1!$A$6:$A$72,0),MATCH(MID(CELL("filename",AZ50),FIND("]",CELL("filename",AZ50))+1,255) & DR$1,[1]Sheet1!$C$1:$CY$1 & [1]Sheet1!$C$3:$CY$3,0))} -> 3240000000 | DS51: {=INDEX([1]Sheet1!$C$6:$CY$72,MATCH($A51,[1]Sheet1!$A$6:$A$72,0),MATCH(MID(CELL("filename",BA50),FIND("]",CELL("filename",BA50))+1,255) & DS$1,[1]Sheet1!$C$1:$CY$1 & [1]Sheet1!$C$3:$CY$3,0))} -> 3.561642 | DT51: {=INDEX([5]DATA!$C$18:$T$51,MATCH($A51,[5]DATA!$B$18:$B$51,0),MATCH(MID(CELL("filename",BB18),FIND("]",CELL("filename",BB18))+1,255) & DT$1,[5]DATA!$C$15:$T$15&[5]DATA!$C$16:$T$16,0)) * 10^6} -> 23708000000 | DU51: {=INDEX([1]Sheet1!$C$6:$CY$72,MATCH($A51,[1]Sheet1!$A$6:$A$72,0),MATCH(MID(CELL("filename",BC50),FIND("]",CELL("filename",BC50))+1,255) & DU$1,[1]Sheet1!$C$1:$CY$1 & [1]Sheet1!$C$3:$CY$3,0))} -> 1.39 | DV51: 0.5 | DW51: =Euro_Area_Data!V48*10^9 -> 1.1157242e+13 | DX51: 1 | DY51: 0.5 | DZ51: {=INDEX([1]Sheet1!$C$6:$CY$72,MATCH($A51,[1]Sheet1!$A$6:$A$72,0),MATCH(MID(CELL("filename",BH50),FIND("]",CELL("filename",BH50))+1,255) & DZ$1,[1]Sheet1!$C$1:$CY$1 & [1]Sheet1!$C$3:$CY$3,0))} -> 3.32 | EA51: 2 | EB51: =SUMPRODUCT(Euro_Area_Data!C48:U48,Euro_Area_Data!Z48:AR48)/SUM(Euro_Area_Data!C48:U48) -> 0.89066655 | EC51: =(EB51-EB50)/EB50*100 -> 1.0177602 | ED51: =SUMPRODUCT(Euro_Area_Data!C48:U48,Euro_Area_Data!AW48:BO48)/SUM(Euro_Area_Data!C48:U48) -> -1.1172335 | EE51: -5 | EH51: 0.75 | EI51: 0.05 | EJ51: 60 | EK51: =(EN51-EN50)/EN50*100 -> 1.819939 | EN51: =[2]EUCAM_output!$AE48 -> 0.8470092
